Workbook
Name APP: 人物卡!$BZ$11
Name APPA: 人物卡!$BZ$12
Name apple: 人物卡!#REF!
Name arti: 人物卡!$CM$57
Name arting: 人物卡!$CA$57
Name blast: 人物卡!$BQ$39
Name Blasting: 人物卡!$BE$39
Name BMI: 附表!$I$63
Name CON: 人物卡!$BT$11
Name CONA: 人物卡!$BT$12
Name dbf: 人物卡!$BQ$63
Name dbfg: 人物卡!$BG$63
Name dbfi: 人物卡!$BQ$64
Name dbfig: 人物卡!$BG$64
Name dbo: 人物卡!$BQ$60
Name dbog: 人物卡!$BG$60
Name dbt: 人物卡!$BQ$61
Name dbtg: 人物卡!$BG$61
Name dbth: 人物卡!$BQ$62
Name dbthg: 人物卡!$BG$62
Name DEX: 人物卡!$BZ$9
Name DEXA: 人物卡!$BZ$10
Name EDU: 人物卡!$CF$11
Name EDUA: 人物卡!$CF$12
Name elmaing: 人物卡!$BE$36
Name fight: 人物卡!$BQ$59
Name fighting: 人物卡!$BG$59
Name hp: 人物卡!$BD$19
Name INT: 人物卡!$BZ$13
Name INTA: 人物卡!$BZ$14
Name Luck: 人物卡!$CF$13
Name LuckA: 人物卡!$CF$14
Name mema: 人物卡!$BQ$35
Name memaing: 人物卡!$BE$35
Name MP: 人物卡!$BV$19
Name pistol: 人物卡!$CM$59
Name pistoling: 人物卡!$CC$59
Name POW: 人物卡!$CF$9
Name POWA: 人物卡!$CF$10
Name SAN: 人物卡!$BM$19
Name shf: 人物卡!$CM$63
Name shfg: 人物卡!$CC$63
Name shfi: 人物卡!$CM$64
Name shfig: 人物卡!$CC$64
Name sho: 人物卡!$CM$60
Name shog: 人物卡!$CC$60
Name sht: 人物卡!$CM$61
Name shtg: 人物卡!$CC$61
Name shth: 人物卡!$CM$62
Name shthg: 人物卡!$CC$62
Name SIZ: 人物卡!$BT$13
Name SIZA: 人物卡!$BT$14
Name STR: 人物卡!$BT$9
Name STRA: 人物卡!$BT$10
Name throw: 人物卡!$CM$58
Name throwing: 人物卡!$CA$58
Name 阿尔巴尼亚: 附表!$BI$109:$EJ$109
Name 阿尔及利亚: 附表!$BI$136:$EJ$136
Name 阿富汗: 附表!$BI$48:$EJ$48
Name 阿根廷: 附表!$BI$220:$EJ$220

Sheet 人物卡
BA1: 玩家 | BC1: 姓名 | BH1: 关系 | BM1: 地点 | BS1: 模组 | BY1: 联系人 | CA1: 姓名 | CF1: 关系 | CK1: 地点 | CQ1: 模组
BC2: 例：辛永梅 | BH2: =_xlfn.XLOOKUP(BC2,成长经历!B34:B71,成长经历!K34:K71) -> 好友 | BM2: =_xlfn.XLOOKUP(BC2,成长经历!B34:B71,成长经历!F34:F71) -> 中国上海电车 | BS2: =_xlfn.XLOOKUP(BC2,成长经历!B34:B71,成长经历!U34:U71) -> 兴海之路（常暗） | CA2: 例：比尔·季默李 | CF2: =_xlfn.XLOOKUP(CA2,成长经历!AA34:AA71,成长经历!AJ34:AJ71) -> 信仰启发者 | CK2: =_xlfn.XLOOKUP(CA2,成长经历!AA34:AA71,成长经历!AE34:AE71) -> 美国牡丹丘 | CQ2: =_xlfn.XLOOKUP(CA2,成长经历!AA34:AA71,成长经历!AT34:AT71) -> 牡丹丘之泪···
BA3: 神话/可憎 | BD3: 伪名 | BH3: 实名 | BL3: SC检定 | BP3: SC减免 | BR3: 免疫 | BT3: 初次目击 | BY3: 旧日/外神 | CB3: 称号 | CF3: 名讳 | CJ3: SC检定 | CN3: SC减免 | CP3: 免疫 | CR3: 初次目击
BH4: =IF(BD4="","",_xlfn.XLOOKUP(BD4,成长经历!B77:B113,成长经历!G77:G113)) | BL4: =IF(BD4="","",_xlfn.XLOOKUP(BD4,成长经历!B77:B113,成长经历!L77:L113)) | BP4: =IF(BD4="","",_xlfn.XLOOKUP(BD4,成长经历!B77:B113,成长经历!Q77:Q113)) | BR4: =_xlfn.XLOOKUP(BD4,成长经历!B77:B113,成长经历!S77:S113) -> ☐ | BT4: =IF(BD4="","",_xlfn.XLOOKUP(BD4,成长经历!B77:B113,成长经历!U77:U113)) | CF4: =IF(CB4="","",_xlfn.XLOOKUP(CB4,成长经历!AB77:AB113,成长经历!AG77:AG113)) | CJ4: =IF(CB4="","",_xlfn.XLOOKUP(CB4,成长经历!AB77:AB113,成长经历!AL77:AL113)) | CN4: =IF(CB4="","",_xlfn.XLOOKUP(CB4,成长经历!AB77:AB113,成长经历!AQ77:AQ113)) | CP4: =_xlfn.XLOOKUP(CB4,成长经历!AB77:AB113,成长经历!AS77:AS113) -> ☐ | CR4: =IF(CB4="","",_xlfn.XLOOKUP(CB4,成长经历!AB77:AB113,成长经历!AU77:AU113))
BA5: 博览 群书 | BC5: 书名 | BF5: 实名 | BI5: 类别 | BK5: 技能 | BM5: 等级 | BO5: 耗时 | BQ5: 消耗 | BT5: 受益 | BV5: 语言 | BY5: 非凡 能力 | CA5: 别名 | CD5: 实名 | CG5: 分类 | CJ5: 消耗 | CN5: 用时 | CQ5: 条件
BF6: =IF(BC6="","",_xlfn.XLOOKUP(BC6,成长经历!B119:B155,成长经历!F119:F155)) | BI6: =IF(BC6="","",_xlfn.XLOOKUP(BC6,成长经历!B119:B155,成长经历!J119:J155)) | BK6: =IF(BC6="","",_xlfn.XLOOKUP(BC6,成长经历!B119:B155,成长经历!M119:M155)) | BM6: =IF(BC6="","",_xlfn.XLOOKUP(BC6,成长经历!B119:B155,成长经历!O119:O155)) | BO6: =IF(BC6="","",_xlfn.XLOOKUP(BC6,成长经历!B119:B155,成长经历!R119:R155)) | BQ6: =IF(BC6="","",_xlfn.XLOOKUP(BC6,成长经历!B119:B155,成长经历!U119:U155)) | BT6: =IF(AD134="","",XLOOKUP(AD134,成长经历!BA32:BA68,成长经历!BW32:BW68) | BV6: =IF(BC6="","",_xlfn.XLOOKUP(BC6,成长经历!B119:B155,成长经历!AC119:AC155)) | CD6: =IF(CA6="","",_xlfn.XLOOKUP(CA6,成长经历!BA35:BA71,成长经历!BE35:BE71,"")) | CG6: =IF(CA6="","",_xlfn.XLOOKUP(CA6,成长经历!BA35:BA71,成长经历!BI35:BI71,"")) | CJ6: =IF(CA6="","",_xlfn.XLOOKUP(CA6,成长经历!BA35:BA71,成长经历!BE35:BE71,"")) | CN6: =IF(CA6="","",_xlfn.XLOOKUP(CA6,成长经历!BA35:BA71,成长经历!BK35:BK71,"")) | CQ6: =IF(CA6="","",_xlfn.XLOOKUP(CA6,成长经历!BA35:BA71,成长经历!BT35:BT71,""))
BA7: 电脑推荐使用excel2010及以后版本或WPS打开本卡，使用横轴滚动条可以看见更多东西
A8: 行/列可以取消隐藏,手机版点击"行/列"字母，选择"行列操作"，之后选择"管理隐藏行列"，最后展开第一栏。 | BA8: 调查员信息 | BI8: =附表!BB53 -> 基本信息未填写！ | BR8: 年龄补正： | BU8: =附表!D37 -> 请和kp商议 | BZ8: 属性 | CB8: 含运 | CD8: =BT9+BT11+BT13+BZ9+BZ11+BZ13+CF9+CF11+CF13 -> 0 | CF8: 不含 | CH8: =CD8-CF13 -> 0 | CK8: 调查员肖像 | CT8: =SUM(AR12:AS22) -> 0 | DB8: =SUM(AR25:AS104) -> 0
BA9: 姓名 | BR9: 力量 STR | BV9: =IFERROR(INT(STRA/2),0) -> 0 | BX9: 敏捷 DEX | CB9: =IFERROR(INT(DEXA/2),0) -> 0 | CD9: 意志 POW | CH9: =IFERROR(INT(POWA/2),0) -> 0 | CT9: 您的角色可能（只是可能！）
BA10: 玩家 | BI10: 时代 | BL10: 1920s | BT10: =IF(STR="","未填写",AT12) -> 未填写 | BV10: =IFERROR(INT(STRA/5),0) -> 0 | BZ10: =IF(DEX="","未填写",AT15) -> 未填写 | CB10: =IFERROR(INT(DEXA/5),0) -> 0 | CF10: =IF(POW="","未填写",AT18) -> 未填写 | CH10: =IFERROR(INT(POWA/5),0) -> 0 | CT10: =IF(OR(SIZ=0,STR=0,DEX=0),"","BMI:"&BMI&" "&附表!I64) | DB10: =IF(OR(SIZ=0,STR=0,DEX=0),"","身高："&附表!L63&"米") | DJ10: =IF(OR(SIZ=0,STR=0,DEX=0),"","体重："&附表!K63&"千克")
B11: 模组名 | E11: 模组名 | H11: 模组名 | K11: 模组名 | N11: 模组名 | Q11: 模组名 | T11: 模组名 | W11: 模组名 | Z11: 模组名 | AC11: 模组名 | AF11: 模组名 | AI11: 模组名 | AL11: 模组名 | AO11: 模组名 | AR11: 成长 | AT11: 总计 | AV11: 属性 | AY11: 修正 | BA11: 职业 | BI11: 职业序号 | BR11: 体质 CON | BV11: =IFERROR(INT(CONA/2),0) -> 0 | BX11: 外貌 APP | CB11: =IFERROR(INT(APPA/2),0) -> 0 | CD11: 教育 知识 | CH11: =IFERROR(INT(EDUA/2),0) -> 0
C12: - | F12: - | I12: - | L12: - | O12: - | R12: - | U12: - | X12: - | AA12: - | AD12: - | AG12: - | AJ12: - | AM12: - | AP12: - | AR12: =SUM(AO12,AL12,AI12,AF12,AC12,Z12,W12,T12,Q12,N12,K12,H12,E12,B12)-SUM(AQ12,AN12,AK12,AH12,AE12,AB12,Y12,V12,S12,P12,M12,J12,G12,D12) -> 0 | AT12: =AR12+STR -> 0 | AV12: 力量 | AY12: =IF(AR12>0,"强身",IF(AR12<0,"衰弱","")) | BA12: 年龄 | BD12: =CQ92 -> 时间未填 | BI12: 性别 | BT12: =IF(CON="","未填写",AT13) -> 未填写 | BV12: =IFERROR(INT(CONA/5),0) -> 0 | BZ12: =IF(APP="","未填写",AT16) -> 未填写 | CB12: =IFERROR(INT(APPA/5),0) -> 0 | CF12: =IF(EDU="","未填写",AT19) -> 未填写 | CH12: =IFERROR(INT(EDUA/5),0) -> 0 | CT12: =IF(STRA="未填写","",IF(STRA=0,"",IF(STRA<=15,"虚弱，孱弱",IF(STRA<=40,"力量弱小",IF(STRA<=60,"有正常人的力量",IF(STRA<=80,"超乎常人的力量",IF(STRA<100,"超乎超乎常人的力量","奥运举重冠军，人类极限！"))))))) | DB12: =IF(DEXA="未填写","",IF(DEXA=0,"",IF(DEXA<=20,"很不灵活",IF(DEXA<=40,"不是很灵活",IF(DEXA<=60,"普通人水平",IF(DEXA<=80,"是一位运动健将",IF(DEXA<100,"高速而灵活,可以达成超凡的技艺","超越人类极限的反应力！"))))))) | DJ12: =IF(POWA="未填写","",IF(POWA=0,"",IF(POWA<=20,"尔不过玩物",IF(POWA<=40,"痴愚盲目",IF(POWA<=60,"如常人一般会有一定自制力",IF(POWA<=80,"我心如铁，心坚石穿",IF(POWA<100,"泰山崩于面而色不变",IF(POWA<140,"钢铁之心，还能看见鬼","基本是异界生物"))))))))
C13: - | F13: - | I13: - | L13: - | O13: - | R13: - | U13: - | X13: - | AA13: - | AD13: - | AG13: - | AJ13: - | AM13: - | AP13: - | AR13: =SUM(AO13,AL13,AI13,AF13,AC13,Z13,W13,T13,Q13,N13,K13,H13,E13,B13)-SUM(AQ13,AN13,AK13,AH13,AE13,AB13,Y13,V13,S13,P13,M13,J13,G13,D13) -> 0 | AT13: =AR13+CON -> 0 | AV13: 体质 | AY13: =IF(AR13>0,"健体",IF(AR13<0,"衰弱","")) | BA13: 国籍 | BI13: 货币 | BL13: 美元 | BR13: 体型 SIZ | BV13: =IFERROR(INT(SIZA/2),0) -> 0 | BX13: 智力 灵感 | CB13: =IFERROR(INT(INTA/2),0) -> 0 | CD13: 幸运 Luck | CH13: =IFERROR(INT(LuckA/2),0) -> 0
C14: - | F14: - | I14: - | L14: - | O14: - | R14: - | U14: - | X14: - | AA14: - | AD14: - | AG14: - | AJ14: - | AM14: - | AP14: - | AR14: =SUM(AO14,AL14,AI14,AF14,AC14,Z14,W14,T14,Q14,N14,K14,H14,E14,B14)-SUM(AQ14,AN14,AK14,AH14,AE14,AB14,Y14,V14,S14,P14,M14,J14,G14,D14) -> 0 | AT14: =AR14+SIZ -> 0 | AV14: 体型 | AY14: =IF(AR14>0,"壮硕",IF(AR14<0,"苗条","")) | BA14: 住地 | BI14: 故乡 | BT14: =IF(SIZ="","未填写",AT14) -> 未填写 | BV14: =IFERROR(INT(SIZA/5),0) -> 0 | BZ14: =IF(INT="","未填写",AT17) -> 未填写 | CB14: =IFERROR(INT(INTA/5),0) -> 0 | CF14: =IF(Luck="","未改运",AT20) -> 未改运 | CH14: =IFERROR(INT(LuckA/5),0) -> 0 | CT14: =IF(CONA="未填写","",IF(CONA=0,"",IF(CONA<=20,"常年患病在身",IF(CONA<=40,"体弱多病",IF(CONA<=60,"不会生什么大毛病",IF(CONA<=80,"健硕，浑身湿透也不会感冒",IF(CONA<100,"身体素质极好，精神抖擞","钢铁之躯，人类极限！"))))))) | DB14: =IF(APPA="未填写","",IF(APPA=0,"",IF(APPA<=20,"用脸就能恐惧敌人。。或队友",IF(APPA<=40,"有些难看",IF(APPA<=60,"人群之中谁也不会看你一眼之后就忘不掉你容颜",IF(APPA<=80,"五官端正，仪表堂堂",IF(APPA<100,"沉鱼落雁，闭月羞花","古神之容貌"))))))) | DJ14: =IF(EDUA="未填写","",IF(EDUA=0,"",IF(EDUA<=20,"目不识丁",IF(EDUA<=40,"小学毕业",IF(EDUA<=50,"高中毕业",IF(EDUA<=60,"普通大学生",IF(EDUA<70,"重点大学的普通学生，或是普通大学的研究生",IF(EDUA<80,"重点大学的高材生",IF(EDUA<96,"经验丰富的研究生",IF(EDUA<100,"教授，博士","世界级权威!"))))))))))
C15: - | F15: - | I15: - | L15: - | O15: - | R15: - | U15: - | X15: - | AA15: - | AD15: - | AG15: - | AJ15: - | AM15: - | AP15: - | AR15: =SUM(AO15,AL15,AI15,AF15,AC15,Z15,W15,T15,Q15,N15,K15,H15,E15,B15)-SUM(AQ15,AN15,AK15,AH15,AE15,AB15,Y15,V15,S15,P15,M15,J15,G15,D15) -> 0 | AT15: =AR15+DEX -> 0 | AV15: 敏捷 | AY15: =IF(AR15>0,"加速",IF(AR15<0,"减速","")) | BR15: 上方填写属性的初始值，属性成长可前往左表 上方、左方皆有隐藏行列，可以展开查看下拉栏与成长表
C16: - | F16: - | I16: - | L16: - | O16: - | R16: - | U16: - | X16: - | AA16: - | AD16: - | AG16: - | AJ16: - | AM16: - | AP16: - | AR16: =SUM(AO16,AL16,AI16,AF16,AC16,Z16,W16,T16,Q16,N16,K16,H16,E16,B16)-SUM(AQ16,AN16,AK16,AH16,AE16,AB16,Y16,V16,S16,P16,M16,J16,G16,D16) -> 0 | AT16: =AR16+APP -> 0 | AV16: 外貌 | AY16: =IF(AR16>0,"进化",IF(AR16<0,"退化","")) | BA16: 组织 | BC16: =IF(BV157="","暂无组织",BV157) -> 暂无组织 | BI16: 任职 | BK16: =IF(BX159="","无职位",BX159) -> 无职位 | BM16: 经验 | BO16: =IF(BX160=0,"无",BX160) -> 无 | BP16: 年 | CT16: =IF(SIZA="未填写","",IF(SIZA=0,"",IF(SIZA<=20,"孩童，身短体瘦",IF(SIZA<=40,"乙女身材",IF(SIZA<=60,"普遍身高155-175",IF(SIZA<=80,"不是高就是胖",IF(SIZA<=100,"大号的人",IF(SIZA<150,"听说你正在申请身高世界记录？",IF(SIZA<180,"你可能是一头牛",IF(SIZA<200,"你已经是历史上最重的人类了","过分了喂！")))))))))) | DB16: =IF(INTA="未填写","",IF(INTA=0,"",IF(INTA<=20,"脑子是个好东西，可惜。。。",IF(INTA<=40,"理解知识要耗费比普通人更多的时间",IF(INTA<=60,"有着普通人的灵光一现",IF(INTA<=80,"可以自主进行发明创造",IF(INTA<90,"天才级水准",IF(INTA<99,"超凡之脑，能够理解多门语言与法则","超越人类之智，能够产生跨时代的想法！")))))))) | DJ16: =IF(LuckA="未改运","",IF(LuckA=0,"",IF(LuckA<=20,"克夫克妻",IF(LuckA<=40,"霉运连连",IF(LuckA<=60,"命格平庸",IF(LuckA<=80,"在马路边捡到100块",IF(LuckA<100,"被幸运女神所眷顾","凌驾于幸运女神之上")))))))
C17: - | F17: - | I17: - | L17: - | O17: - | R17: - | U17: - | X17: - | AA17: - | AD17: - | AG17: - | AJ17: - | AM17: - | AP17: - | AR17: =SUM(AO17,AL17,AI17,AF17,AC17,Z17,W17,T17,Q17,N17,K17,H17,E17,B17)-SUM(AQ17,AN17,AK17,AH17,AE17,AB17,Y17,V17,S17,P17,M17,J17,G17,D17) -> 0 | AT17: =AR17+INT -> 0 | AV17: 智力 | AY17: =IF(AR17>0,"汲取",IF(AR17<0,"散失","")) | BA17: 现时间 | BD17: 公元 | BJ17: 月 | BL17: 日 | BM17: 0
C18: - | F18: - | I18: - | L18: - | O18: - | R18: - | U18: - | X18: - | AA18: - | AD18: - | AG18: - | AJ18: - | AM18: - | AP18: - | AR18: =SUM(AO18,AL18,AI18,AF18,AC18,Z18,W18,T18,Q18,N18,K18,H18,E18,B18)-SUM(AQ18,AN18,AK18,AH18,AE18,AB18,Y18,V18,S18,P18,M18,J18,G18,D18) -> 0 | AT18: =AR18+POW -> 0 | AV18: 意志 | AY18: =IF(AR18>0,"强魂",IF(AR18<0,"衰志","")) | BA18: =IF(BE18=0,"","任意特长数：") | BE18: =INDEX(本职技能!$A$2:$IC$82,MATCH("任意特长",本职技能!$A$2:$A$87,0),MATCH($BL$11,本职技能!$A$1:$IC$1,0)) -> 0 | BJ18: =INDEX(本职技能!$A$2:$IC$82,MATCH("☆",本职技能!$A$2:$A$87,0),MATCH($BL$11,本职技能!$A$1:$IC$1,0)) -> 0 | BS18: =INDEX(本职技能!$A$2:$IC$82,MATCH("⊙",本职技能!$A$2:$A$87,0),MATCH($BL$11,本职技能!$A$1:$IC$1,0)) -> 0 | CB18: =INDEX(本职技能!$A$2:$IC$82,MATCH("☯",本职技能!$A$2:$A$87,0),MATCH($BL$11,本职技能!$A$1:$IC$1,0)) -> 0 | CK18: =INDEX(本职技能!$A$2:$IC$82,MATCH("※",本职技能!$A$2:$A$87,0),MATCH($BL$11,本职技能!$A$1:$IC$1,0)) -> 0 | CT18: 绝佳素质 | CU18: NO.1 | CW18: =_xlfn.XLOOKUP(DA18,$AT$12:$AT$22,$AV$12:$AV$22,,,1) -> 理智上限 | DA18: =LARGE($AT$12:$AU$22,1) -> 99 | DC18: 理智损 失倍率 | DF18: =IF(DH20="☑",0.5,1) -> 1
C19: - | F19: - | I19: - | L19: - | O19: - | R19: - | U19: - | X19: - | AA19: - | AD19: - | AG19: - | AJ19: - | AM19: - | AP19: - | AR19: =SUM(AO19,AL19,AI19,AF19,AC19,Z19,W19,T19,Q19,N19,K19,H19,E19,B19)-SUM(AQ19,AN19,AK19,AH19,AE19,AB19,Y19,V19,S19,P19,M19,J19,G19,D19) -> 0 | AT19: =AR19+EDU -> 0 | AV19: 教育 | AY19: =IF(AR19>0,"汲取",IF(AR19<0,"散失","")) | BA19: 生命值 HP | BD19: =IFERROR(BF19,"") -> 0 | BF19: =IFERROR(INT((CONA+SIZA)/10),0) -> 0 | BH19: 状态: | BJ19: 理智 Sanity | BM19: =IFERROR(AT21,"") -> 0 | BO19: =AT22 -> 99 | BQ19: 状态: | BS19: 魔法 MP | BV19: =IFERROR(BX19,"") -> 0 | BX19: =IFERROR(INT(POWA/5),0) -> 0 | BZ19: 每h恢复 | CB19: 移动力 MOV | CE19: =CH20+8 -> 8 | CH19: 调整值 | CJ19: 护甲 Armor | CM19: =IF($CM21=0,"0",VLOOKUP($CM21,'防具表 载具表'!B2:J82,2,FALSE)) -> 无 | CO19: 覆盖部位 | CU19: NO.2 | CW19: =_xlfn.XLOOKUP(DA19,$AT$12:$AT$22,$AV$12:$AV$22,,,-1) -> 理智 | DA19: =LARGE($AT$12:$AU$22,2) -> 0
C20: - | F20: - | I20: - | L20: - | O20: - | R20: - | U20: - | X20: - | AA20: - | AD20: - | AG20: - | AJ20: - | AM20: - | AP20: - | AR20: =SUM(AO20,AL20,AI20,AF20,AC20,Z20,W20,T20,Q20,N20,K20,H20,E20,B20)-SUM(AQ20,AN20,AK20,AH20,AE20,AB20,Y20,V20,S20,P20,M20,J20,G20,D20) -> 0 | AT20: =AR20+Luck -> 0 | AV20: 幸运 | AY20: =IF(AR20>0,"强运",IF(AR20<0,"弱运","")) | BH20: 健康 | BQ20: 清醒 | BZ20: =IFERROR(IF(POWA="","",INT(POWA/100+1)),"") | CH20: =附表!C9 -> 0 | CO20: =IF($CM21=0,"",VLOOKUP($CM21,'防具表 载具表'!B2:I101,4,FALSE)) -> —— | CU20: NO.3 | CW20: =VLOOKUP(DA20,$AT$12:$AX$22,3,FALSE) -> 力量 | DA20: =LARGE($AT$12:$AU$22,3) -> 0 | DC20: 精神固化 | DH20: ☐ | DJ20: 相信者 | DP20: ☐
C21: - | F21: - | I21: - | L21: - | O21: - | R21: - | U21: - | X21: - | AA21: - | AD21: - | AG21: - | AJ21: - | AM21: - | AP21: - | AR21: =SUM(AO21,AL21,AI21,AF21,AC21,Z21,W21,T21,Q21,N21,K21,H21,E21,B21)-SUM(AQ21,AN21,AK21,AH21,AE21,AB21,Y21,V21,S21,P21,M21,J21,G21,D21) -> 0 | AT21: =IFERROR(AR21+POWA,0) -> 0 | AV21: 理智 | AY21: =IF(AR21>0,"坚毅",IF(AR21<0,"衰退","")) | BA21: 重伤值: | BC21: =IFERROR(CEILING(BF19/2,1),"") -> 0 | BE21: 临时生命值： | BH21: 0 | BJ21: 今日损失 : | BM21: 0 | BO21: 剩余： | BQ21: =IFERROR(BM19-BM21,0) -> 0 | BS21: 用过的魔法： | CB21: 移动方式 | CD21: 步式 | CF21: 护甲减值 | CH21: 关 | CJ21: 护甲类型 : | CM21: 请看【防具表】 | CT21: 纯熟技艺 | CU21: NO.1 | CW21: =IFERROR(_xlfn.XLOOKUP(DA21,$AT$25:$AT$104,$AV$25:$AV$104,,,1),"") -> 急救 | DA21: =IFERROR(MAX(AT25:AU104),"") -> 30 | DC21: =IF(LEN(BV94)=0,"你的背景故事还没动笔哦","你共写了"&LEN(BV94)&"字的背景故事！") -> 你的背景故事还没动笔哦 | DT21: =成长经历!B115 -> 书籍是人类进步的阶梯，快去找本书看吧 | EF21: =成长经历!U115 -> 韦编三而绝，书读百遍，其义才能自现
AR22: =SUM(B22:AQ22) -> 0 | AT22: =99-BQ34+AR22 -> 99 | AV22: 理智上限 | AY22: =IF(AT22>99,"坚毅",IF(AT22<99,"衰退","")) | BA22: =IF(BL11=0," ","["&LOOKUP(BL11,职业列表!A2:A237,职业列表!B2:B237)&"]的本职技能："&LOOKUP(BL11,职业列表!A2:A237,职业列表!G2:G237)) | CU22: NO.2 | CW22: =IFERROR(_xlfn.XLOOKUP(DA22,$AT$25:$AT$104,$AV$25:$AV$104,,,-1),"") -> 侦查 | DA22: =IFERROR(LARGE($AT$25:$AU$104,2),"") -> 25 | DT22: =成长经历!K31 -> 你还未踏上旅途···
B23: 成长表 | BA23: 技能表 | CI23: =附表!M58 -> 母语未填写！ | CU23: NO.3 | CW23: =IFERROR(VLOOKUP(DA23,$AT$25:$AX$104,3,FALSE),"") -> 格斗:斗殴 | DA23: =IFERROR(LARGE($AT$25:$AU$104,3),"") -> 25 | DT23: =成长经历!B73 -> 你对世界的真相一无所知···
B24: 模组名 | E24: 模组名 | H24: 模组名 | K24: 模组名 | N24: 模组名 | Q24: 模组名 | T24: 模组名 | W24: 模组名 | Z24: 模组名 | AC24: 模组名 | AF24: 模组名 | AI24: 模组名 | AL24: 模组名 | AO24: 模组名 | AR24: 成长 | AT24: 总计 | AV24: 技能 | AY24: 本职 | BA24: 成功标 | BC24: 本职 | BE24: 技能名称 | BI24: 初始 | BK24: 成长 | BM24: 职业 | BO24: 兴趣 | BQ24: 成功率 普通/困难/极难 | BW24: 成功标 | BY24: 本职 | CA24: 技能名称 | CE24: 初始 | CG24: 成长 | CI24: 职业 | CK24: 兴趣 | CM24: 成功率 普通/困难/极难 | CT24: 你现在有这么多 | CZ24: 那么你分配到了哪里? | DT24: =成长经历!AI73 -> 你从未见过何为真正之绝望···
C25: - | F25: - | I25: - | L25: - | O25: - | R25: - | U25: - | X25: - | AA25: - | AD25: - | AG25: - | AJ25: - | AM25: - | AP25: - | AR25: =SUM(AO25,AL25,AI25,AF25,AC25,Z25,W25,T25,Q25,N25,K25,H25,E25,B25)-SUM(AQ25,AN25,AK25,AH25,AE25,AB25,Y25,V25,S25,P25,M25,J25,G25,D25) -> 0 | AT25: =AR25+BI25+BM26+BO25 -> 5 | AV25: =BE25 -> 会计 | AY25: =BC25 -> 0 | BA25: ☐ | BC25: =IF(ISTEXT(IFERROR(VLOOKUP(人物卡!BE25,人物卡!$DI$25:$DQ$29,1,FALSE),IFERROR(VLOOKUP(人物卡!BE25,人物卡!$CZ$25:$DB$29,1,FALSE),0))),"★",INDEX(本职技能!$A$2:$IC$87,MATCH(人物卡!BE25,本职技能!$A$2:$A$87,0),MATCH(人物卡!$BL$11,本职技能!$A$1:$IC$1,0))) -> 0 | BE25: 会计 | BI25: 5 | BK25: =AR25 -> 0 | BQ25: =SUM(BI25:BO25) -> 5 | BS25: =INT(BQ25/2) -> 2 | BU25: =INT(BQ25/5) -> 1 | BW25: ☐ | BY25: =IF(ISTEXT(IFERROR(VLOOKUP(人物卡!CA25,人物卡!$DI$25:$DQ$29,1,FALSE),IFERROR(VLOOKUP(人物卡!CA25,人物卡!$CZ$25:$DB$29,1,FALSE),0))),"★",INDEX(本职技能!$A$2:$IC$87,MATCH(人物卡!CA25,本职技能!$A$2:$A$87,0),MATCH(人物卡!$BL$11,本职技能!$A$1:$IC$1,0))) -> 0 | CA25: 锁匠 | CE25: 1 | CG25: =AR65 -> 0 | CM25: =SUM(CE25:CK25) -> 1 | CO25: =INT(CM25/2) -> 0 | CQ25: =INT(CM25/5) -> 0 | CT25: 任意特长 | DT25: =成长经历!R73 -> 你的理智防线还坚挺着···
C26: - | F26: - | I26: - | L26: - | O26: - | R26: - | U26: - | X26: - | AA26: - | AD26: - | AG26: - | AJ26: - | AM26: - | AP26: - | AR26: =SUM(AO26,AL26,AI26,AF26,AC26,Z26,W26,T26,Q26,N26,K26,H26,E26,B26)-SUM(AQ26,AN26,AK26,AH26,AE26,AB26,Y26,V26,S26,P26,M26,J26,G26,D26) -> 0 | AT26: =AR26+BI26+BM26+BO26 -> 5 | AV26: =BE26 -> 法律 | AY26: =BC26 -> 0 | BA26: ☐ | BC26: =IF(ISTEXT(IFERROR(VLOOKUP(人物卡!BE26,人物卡!$DI$25:$DQ$29,1,FALSE),IFERROR(VLOOKUP(人物卡!BE26,人物卡!$CZ$25:$DB$29,1,FALSE),0))),"★",INDEX(本职技能!$A$2:$IC$87,MATCH(人物卡!BE26,本职技能!$A$2:$A$87,0),MATCH(人物卡!$BL$11,本职技能!$A$1:$IC$1,0))) -> 0 | BE26: 法律 | BI26: 5 | BK26: =AR26 -> 0 | BQ26: =SUM(BI26:BO26) -> 5 | BS26: =INT(BQ26/2) -> 2 | BU26: =INT(BQ26/5) -> 1 | BW26: ☐ | BY26: =IF(ISTEXT(IFERROR(VLOOKUP(人物卡!CA26,人物卡!$DI$25:$DQ$29,1,FALSE),IFERROR(VLOOKUP(人物卡!CA26,人物卡!$CZ$25:$DB$29,1,FALSE),0))),"★",INDEX(本职技能!$A$2:$IC$87,MATCH(人物卡!CA26,本职技能!$A$2:$A$87,0),MATCH(人物卡!$BL$11,本职技能!$A$1:$IC$1,0))) -> 0 | CA26: 乔装 | CE26: 5 | CG26: =AR66 -> 0 | CM26: =SUM(CE26:CK26) -> 5 | CO26: =INT(CM26/2) -> 2 | CQ26: =INT(CM26/5) -> 1 | CT26: =附表!AD25 -> 无 | DT26: =成长经历!BA31 -> 超乎想象的能力，等待你窥探···
C27: - | F27: - | I27: - | L27: - | O27: - | R27: - | U27: - | X27: - | AA27: - | AD27: - | AG27: - | AJ27: - | AM27: - | AP27: - | AR27: =SUM(AO27,AL27,AI27,AF27,AC27,Z27,W27,T27,Q27,N27,K27,H27,E27,B27)-SUM(AQ27,AN27,AK27,AH27,AE27,AB27,Y27,V27,S27,P27,M27,J27,G27,D27) -> 0 | AT27: =AR27+BI27+BM27+BO27 -> 5 | AV27: =BE27 -> 历史 | AY27: =BC27 -> 0 | BA27: ☐ | BC27: =IF(ISTEXT(IFERROR(VLOOKUP(人物卡!BE27,人物卡!$DI$25:$DQ$29,1,FALSE),IFERROR(VLOOKUP(人物卡!BE27,人物卡!$CZ$25:$DB$29,1,FALSE),0))),"★",INDEX(本职技能!$A$2:$IC$87,MATCH(人物卡!BE27,本职技能!$A$2:$A$87,0),MATCH(人物卡!$BL$11,本职技能!$A$1:$IC$1,0))) -> 0 | BE27: 历史 | BI27: 5 | BK27: =AR27 -> 0 | BQ27: =SUM(BI27:BO27) -> 5 | BS27: =INT(BQ27/2) -> 2 | BU27: =INT(BQ27/5) -> 1 | BW27: ☐ | BY27: =IF(ISTEXT(IFERROR(VLOOKUP(人物卡!CA27,人物卡!$DI$25:$DQ$29,1,FALSE),IFERROR(VLOOKUP(人物卡!CA27,人物卡!$CZ$25:$DB$29,1,FALSE),0))),"★",INDEX(本职技能!$A$2:$IC$87,MATCH(人物卡!CA27,本职技能!$A$2:$A$87,0),MATCH(人物卡!$BL$11,本职技能!$A$1:$IC$1,0))) -> 0 | CA27: 妙手 | CE27: 10 | CG27: =AR67 -> 0 | CM27: =SUM(CE27:CK27) -> 10 | CO27: =INT(CM27/2) -> 5 | CQ27: =INT(CM27/5) -> 2 | DT27: =成长经历!BA73 -> 你接触到的还只是凡尘之物···
C28: - | F28: - | I28: - | L28: - | O28: - | R28: - | U28: - | X28: - | AA28: - | AD28: - | AG28: - | AJ28: - | AM28: - | AP28: - | AR28: =SUM(AO28,AL28,AI28,AF28,AC28,Z28,W28,T28,Q28,N28,K28,H28,E28,B28)-SUM(AQ28,AN28,AK28,AH28,AE28,AB28,Y28,V28,S28,P28,M28,J28,G28,D28) -> 0 | AT28: =AR28+BI28+BM28+BO28 -> 1 | AV28: =BE28 -> 人类学 | AY28: =BC28 -> 0 | BA28: ☐ | BC28: =IF(ISTEXT(IFERROR(VLOOKUP(人物卡!BE28,人物卡!$DI$25:$DQ$29,1,FALSE),IFERROR(VLOOKUP(人物卡!BE28,人物卡!$CZ$25:$DB$29,1,FALSE),0))),"★",INDEX(本职技能!$A$2:$IC$87,MATCH(人物卡!BE28,本职技能!$A$2:$A$87,0),MATCH(人物卡!$BL$11,本职技能!$A$1:$IC$1,0))) -> 0 | BE28: 人类学 | BI28: 1 | BK28: =AR28 -> 0 | BQ28: =SUM(BI28:BO28) -> 1 | BS28: =INT(BQ28/2) -> 0 | BU28: =INT(BQ28/5) -> 0 | BW28: ☐ | BY28: =IF(ISTEXT(IFERROR(VLOOKUP(人物卡!CA28,人物卡!$DI$25:$DQ$29,1,FALSE),IFERROR(VLOOKUP(人物卡!CA28,人物卡!$CZ$25:$DB$29,1,FALSE),0))),"★",INDEX(本职技能!$A$2:$IC$87,MATCH(人物卡!CA28,本职技能!$A$2:$A$87,0),MATCH(人物卡!$BL$11,本职技能!$A$1:$IC$1,0))) -> 0 | CA28: 潜行 | CE28: 20 | CG28: =AR68 -> 0 | CM28: =SUM(CE28:CK28) -> 20 | CO28: =INT(CM28/2) -> 10 | CQ28: =INT(CM28/5) -> 4 | DT28: =IF(COUNTA(BF69:BJ73)=0,"你目前手无寸铁","你共携带了"&COUNTA(BF69:BJ73)&"种武器！") -> 你目前手无寸铁 | EA28: =IF(COUNTA(BE99:BT113)=0,"你还没携带任何物品","你共携带了"&COUNTA(BE99:BJ107,BM99:BR107,BE85:BJ89,BM85:BR89)&"种物品！") -> 你还没携带任何物品
C29: - | F29: - | I29: - | L29: - | O29: - | R29: - | U29: - | X29: - | AA29: - | AD29: - | AG29: - | AJ29: - | AM29: - | AP29: - | AR29: =SUM(AO29,AL29,AI29,AF29,AC29,Z29,W29,T29,Q29,N29,K29,H29,E29,B29)-SUM(AQ29,AN29,AK29,AH29,AE29,AB29,Y29,V29,S29,P29,M29,J29,G29,D29) -> 0 | AT29: =AR29+BI29+BM29+BO29 -> 5 | AV29: =BE29 -> 估价 | AY29: =BC29 -> 0 | BA29: ☐ | BC29: =IF(ISTEXT(IFERROR(VLOOKUP(人物卡!BE29,人物卡!$DI$25:$DQ$29,1,FALSE),IFERROR(VLOOKUP(人物卡!BE29,人物卡!$CZ$25:$DB$29,1,FALSE),0))),"★",INDEX(本职技能!$A$2:$IC$87,MATCH(人物卡!BE29,本职技能!$A$2:$A$87,0),MATCH(人物卡!$BL$11,本职技能!$A$1:$IC$1,0))) -> 0 | BE29: 估价 | BI29: 5 | BK29: =AR29 -> 0 | BQ29: =SUM(BI29:BO29) -> 5 | BS29: =INT(BQ29/2) -> 2 | BU29: =INT(BQ29/5) -> 1 | BW29: ☐ | BY29: =IF(ISTEXT(IFERROR(VLOOKUP(人物卡!CA29,人物卡!$DI$25:$DQ$29,1,FALSE),IFERROR(VLOOKUP(人物卡!CA29,人物卡!$CZ$25:$DB$29,1,FALSE),0))),"★",INDEX(本职技能!$A$2:$IC$87,MATCH(人物卡!CA29,本职技能!$A$2:$A$87,0),MATCH(人物卡!$BL$11,本职技能!$A$1:$IC$1,0))) -> 0 | CA29: 图书馆使用 | CE29: 20 | CG29: =AR69 -> 0 | CM29: =SUM(CE29:CK29) -> 20 | CO29: =INT(CM29/2) -> 10 | CQ29: =INT(CM29/5) -> 4 | CT29: 提示当前职业 | DT29: ="你共点了"&COUNTA(BM26:BN33,BM35:BN64,CI25:CJ64)&"种职业技能！" -> 你共点了0种职业技能！ | EA29: ="你共点了"&COUNTA(CK25:CL64,BO35:BP64,BO25:BP33)&"种兴趣技能！" -> 你共点了0种兴趣技能！
C30: - | F30: - | I30: - | L30: - | O30: - | R30: - | U30: - | X30: - | AA30: - | AD30: - | AG30: - | AJ30: - | AM30: - | AP30: - | AR30: =SUM(AO30,AL30,AI30,AF30,AC30,Z30,W30,T30,Q30,N30,K30,H30,E30,B30)-SUM(AQ30,AN30,AK30,AH30,AE30,AB30,Y30,V30,S30,P30,M30,J30,G30,D30) -> 0 | AT30: =AR30+BI30+BM30+BO30 -> 1 | AV30: =BE30 -> 考古学 | AY30: =BC30 -> 0 | BA30: ☐ | BC30: =IF(ISTEXT(IFERROR(VLOOKUP(人物卡!BE30,人物卡!$DI$25:$DQ$29,1,FALSE),IFERROR(VLOOKUP(人物卡!BE30,人物卡!$CZ$25:$DB$29,1,FALSE),0))),"★",INDEX(本职技能!$A$2:$IC$87,MATCH(人物卡!BE30,本职技能!$A$2:$A$87,0),MATCH(人物卡!$BL$11,本职技能!$A$1:$IC$1,0))) -> 0 | BE30: 考古学 | BI30: 1 | BK30: =AR30 -> 0 | BQ30: =SUM(BI30:BO30) -> 1 | BS30: =INT(BQ30/2) -> 0 | BU30: =INT(BQ30/5) -> 0 | BW30: ☐ | BY30: =IF(ISTEXT(IFERROR(VLOOKUP(人物卡!CA30,人物卡!$DI$25:$DQ$29,1,FALSE),IFERROR(VLOOKUP(人物卡!CA30,人物卡!$CZ$25:$DB$29,1,FALSE),0))),"★",INDEX(本职技能!$A$2:$IC$87,MATCH(人物卡!CA30,本职技能!$A$2:$A$87,0),MATCH(人物卡!$BL$11,本职技能!$A$1:$IC$1,0))) -> 0 | CA30: 聆听 | CE30: 20 | CG30: =AR70 -> 0 | CM30: =SUM(CE30:CK30) -> 20 | CO30: =INT(CM30/2) -> 10 | CQ30: =INT(CM30/5) -> 4 | CT30: 请将你选择的任意特长写在上方栏内，这样既方便你写卡又方便KP审卡 | DT30: =附表!D75 -> 本次任务携带0.6美元
C31: - | F31: - | I31: - | L31: - | O31: - | R31: - | U31: - | X31: - | AA31: - | AD31: - | AG31: - | AJ31: - | AM31: - | AP31: - | AR31: =SUM(AO31,AL31,AI31,AF31,AC31,Z31,W31,T31,Q31,N31,K31,H31,E31,B31)-SUM(AQ31,AN31,AK31,AH31,AE31,AB31,Y31,V31,S31,P31,M31,J31,G31,D31) -> 0 | AT31: =AR31+BI31+BM31+BO31 -> 10 | AV31: =BE31 -> 博物学 | AY31: =BC31 -> 0 | BA31: ☐ | BC31: =IF(ISTEXT(IFERROR(VLOOKUP(人物卡!BE31,人物卡!$DI$25:$DQ$29,1,FALSE),IFERROR(VLOOKUP(人物卡!BE31,人物卡!$CZ$25:$DB$29,1,FALSE),0))),"★",INDEX(本职技能!$A$2:$IC$87,MATCH(人物卡!BE31,本职技能!$A$2:$A$87,0),MATCH(人物卡!$BL$11,本职技能!$A$1:$IC$1,0))) -> 0 | BE31: 博物学 | BI31: 10 | BK31: =AR31 -> 0 | BQ31: =SUM(BI31:BO31) -> 10 | BS31: =INT(BQ31/2) -> 5 | BU31: =INT(BQ31/5) -> 2 | BW31: ☐ | BY31: =IF(ISTEXT(IFERROR(VLOOKUP(人物卡!CA31,人物卡!$DI$25:$DQ$29,1,FALSE),IFERROR(VLOOKUP(人物卡!CA31,人物卡!$CZ$25:$DB$29,1,FALSE),0))),"★",INDEX(本职技能!$A$2:$IC$87,MATCH(人物卡!CA31,本职技能!$A$2:$A$87,0),MATCH(人物卡!$BL$11,本职技能!$A$1:$IC$1,0))) -> 0 | CA31: 侦查 | CE31: 25 | CG31: =AR71 -> 0 | CM31: =SUM(CE31:CK31) -> 25 | CO31: =INT(CM31/2) -> 12 | CQ31: =INT(CM31/5) -> 5 | CT31: 推 荐 关 系 人 | CU31: =IF(BL11=0," ",""&LOOKUP(BL11,职业列表!A2:A237,职业列表!K2:K237))
C32: - | F32: - | I32: - | L32: - | O32: - | R32: - | U32: - | X32: - | AA32: - | AD32: - | AG32: - | AJ32: - | AM32: - | AP32: - | AR32: =SUM(AO32,AL32,AI32,AF32,AC32,Z32,W32,T32,Q32,N32,K32,H32,E32,B32)-SUM(AQ32,AN32,AK32,AH32,AE32,AB32,Y32,V32,S32,P32,M32,J32,G32,D32) -> 0 | AT32: =AR32+BI32+BM32+BO32 -> 5 | AV32: =BE32 -> 神秘学 | AY32: =BC32 -> 0 | BA32: ☐ | BC32: =IF(ISTEXT(IFERROR(VLOOKUP(人物卡!BE32,人物卡!$DI$25:$DQ$29,1,FALSE),IFERROR(VLOOKUP(人物卡!BE32,人物卡!$CZ$25:$DB$29,1,FALSE),0))),"★",INDEX(本职技能!$A$2:$IC$87,MATCH(人物卡!BE32,本职技能!$A$2:$A$87,0),MATCH(人物卡!$BL$11,本职技能!$A$1:$IC$1,0))) -> 0 | BE32: 神秘学 | BI32: 5 | BK32: =AR32 -> 0 | BQ32: =SUM(BI32:BO32) -> 5 | BS32: =INT(BQ32/2) -> 2 | BU32: =INT(BQ32/5) -> 1 | BW32: ☐ | BY32: =IF(ISTEXT(IFERROR(VLOOKUP(人物卡!CA32,人物卡!$DI$25:$DQ$29,1,FALSE),IFERROR(VLOOKUP(人物卡!CA32,人物卡!$CZ$25:$DB$29,1,FALSE),0))),"★",INDEX(本职技能!$A$2:$IC$87,MATCH(人物卡!CA32,本职技能!$A$2:$A$87,0),MATCH(人物卡!$BL$11,本职技能!$A$1:$IC$1,0))) -> 0 | CA32: 追踪 | CE32: 10 | CG32: =AR72 -> 0 | CM32: =SUM(CE32:CK32) -> 10 | CO32: =INT(CM32/2) -> 5 | CQ32: =INT(CM32/5) -> 2
C33: - | F33: - | I33: - | L33: - | O33: - | R33: - | U33: - | X33: - | AA33: - | AD33: - | AG33: - | AJ33: - | AM33: - | AP33: - | AR33: =SUM(AO33,AL33,AI33,AF33,AC33,Z33,W33,T33,Q33,N33,K33,H33,E33,B33)-SUM(AQ33,AN33,AK33,AH33,AE33,AB33,Y33,V33,S33,P33,M33,J33,G33,D33) -> 0 | AT33: =AR33+BI33+BM33+BO33 -> 0 | AV33: =BE33 -> 信用评级 | AY33: =BC33 -> ★ | BA33: —— | BC33: ★ | BE33: 信用评级 | BI33: 0 | BK33: =AR33 -> 0 | BQ33: =SUM(BI33:BO33) -> 0 | BS33: =INT(BQ33/2) -> 0 | BU33: =INT(BQ33/5) -> 0 | BW33: ☐ | BY33: =IF(ISTEXT(IFERROR(VLOOKUP(人物卡!CA33,人物卡!$DI$25:$DQ$29,1,FALSE),IFERROR(VLOOKUP(人物卡!CA33,人物卡!$CZ$25:$DB$29,1,FALSE),0))),"★",INDEX(本职技能!$A$2:$IC$87,MATCH(人物卡!CA33,本职技能!$A$2:$A$87,0),MATCH(人物卡!$BL$11,本职技能!$A$1:$IC$1,0))) -> 0 | CA33: 导航 | CE33: 10 | CG33: =AR73 -> 0 | CM33: =SUM(CE33:CK33) -> 10 | CO33: =INT(CM33/2) -> 5 | CQ33: =INT(CM33/5) -> 2
C34: - | F34: - | I34: - | L34: - | O34: - | R34: - | U34: - | X34: - | AA34: - | AD34: - | AG34: - | AJ34: - | AM34: - | AP34: - | AR34: =SUM(AO34,AL34,AI34,AF34,AC34,Z34,W34,T34,Q34,N34,K34,H34,E34,B34)-SUM(AQ34,AN34,AK34,AH34,AE34,AB34,Y34,V34,S34,P34,M34,J34,G34,D34) -> 0 | AT34: =AR34+BI34 -> 0 | AV34: =BE34 -> 克苏鲁神话 | AY34: =BC34 -> 0 | BA34: —— | BC34: =IF(ISTEXT(IFERROR(VLOOKUP(人物卡!BE34,人物卡!$DI$25:$DQ$29,1,FALSE),IFERROR(VLOOKUP(人物卡!BE34,人物卡!$CZ$25:$DB$29,1,FALSE),0))),"★",INDEX(本职技能!$A$2:$IC$87,MATCH(人物卡!BE34,本职技能!$A$2:$A$87,0),MATCH(人物卡!$BL$11,本职技能!$A$1:$IC$1,0))) -> 0 | BE34: 克苏鲁神话 | BI34: 0 | BK34: =AR34 -> 0 | BM34: —— | BO34: —— | BQ34: =SUM(BI34:BO34) -> 0 | BS34: =INT(BQ34/2) -> 0 | BU34: =INT(BQ34/5) -> 0 | BW34: ☐ | BY34: =IF(ISTEXT(IFERROR(VLOOKUP(人物卡!CA34,人物卡!$DI$25:$DQ$29,1,FALSE),IFERROR(VLOOKUP(人物卡!CA34,人物卡!$CZ$25:$DB$29,1,FALSE),0))),"★",INDEX(本职技能!$A$2:$IC$87,MATCH(人物卡!CA34,本职技能!$A$2:$A$87,0),MATCH(人物卡!$BL$11,本职技能!$A$1:$IC$1,0))) -> 0 | CA34: 心理学 | CE34: 10 | CG34: =AR74 -> 0 | CM34: =SUM(CE34:CK34) -> 10 | CO34: =INT(CM34/2) -> 5 | CQ34: =INT(CM34/5) -> 2
C35: - | F35: - | I35: - | L35: - | O35: - | R35: - | U35: - | X35: - | AA35: - | AD35: - | AG35: - | AJ35: - | AM35: - | AP35: - | AR35: =SUM(AO35,AL35,AI35,AF35,AC35,Z35,W35,T35,Q35,N35,K35,H35,E35,B35)-SUM(AQ35,AN35,AK35,AH35,AE35,AB35,Y35,V35,S35,P35,M35,J35,G35,D35) -> 0 | AT35: =AR35+BI35+BM35+BO35 -> 10 | AV35: =BE35 -> 机械维修 | AY35: =BC35 -> 0 | BA35: ☐ | BC35: =IF(ISTEXT(IFERROR(VLOOKUP(人物卡!BE35,人物卡!$DI$25:$DQ$29,1,FALSE),IFERROR(VLOOKUP(人物卡!BE35,人物卡!$CZ$25:$DB$29,1,FALSE),0))),"★",INDEX(本职技能!$A$2:$IC$87,MATCH(人物卡!BE35,本职技能!$A$2:$A$87,0),MATCH(人物卡!$BL$11,本职技能!$A$1:$IC$1,0))) -> 0 | BE35: 机械维修 | BI35: 10 | BK35: =AR35 -> 0 | BQ35: =SUM(BI35:BO35) -> 10 | BS35: =INT(BQ35/2) -> 5 | BU35: =INT(BQ35/5) -> 2 | BW35: ☐ | BY35: =IF(ISTEXT(IFERROR(VLOOKUP(人物卡!CA35,人物卡!$DI$25:$DQ$29,1,FALSE),IFERROR(VLOOKUP(人物卡!CA35,人物卡!$CZ$25:$DB$29,1,FALSE),0))),"★",INDEX(本职技能!$A$2:$IC$87,MATCH(人物卡!CA35,本职技能!$A$2:$A$87,0),MATCH(人物卡!$BL$11,本职技能!$A$1:$IC$1,0))) -> 0 | CA35: 取悦 | CE35: 15 | CG35: =AR75 -> 0 | CM35: =SUM(CE35:CK35) -> 15 | CO35: =INT(CM35/2) -> 7 | CQ35: =INT(CM35/5) -> 3
C36: - | F36: - | I36: - | L36: - | O36: - | R36: - | U36: - | X36: - | AA36: - | AD36: - | AG36: - | AJ36: - | AM36: - | AP36: - | AR36: =SUM(AO36,AL36,AI36,AF36,AC36,Z36,W36,T36,Q36,N36,K36,H36,E36,B36)-SUM(AQ36,AN36,AK36,AH36,AE36,AB36,Y36,V36,S36,P36,M36,J36,G36,D36) -> 0 | AT36: =AR36+BI36+BM36+BO36 -> 10 | AV36: =BE36 -> 电气维修 | AY36: =BC36 -> 0 | BA36: ☐ | BC36: =IF(ISTEXT(IFERROR(VLOOKUP(人物卡!BE36,人物卡!$DI$25:$DQ$29,1,FALSE),IFERROR(VLOOKUP(人物卡!BE36,人物卡!$CZ$25:$DB$29,1,FALSE),0))),"★",INDEX(本职技能!$A$2:$IC$87,MATCH(人物卡!BE36,本职技能!$A$2:$A$87,0),MATCH(人物卡!$BL$11,本职技能!$A$1:$IC$1,0))) -> 0 | BE36: 电气维修 | BI36: 10 | BK36: =AR36 -> 0 | BQ36: =SUM(BI36:BO36) -> 10 | BS36: =INT(BQ36/2) -> 5 | BU36: =INT(BQ36/5) -> 2 | BW36: ☐ | BY36: =IF(ISTEXT(IFERROR(VLOOKUP(人物卡!CA36,人物卡!$DI$25:$DQ$29,1,FALSE),IFERROR(VLOOKUP(人物卡!CA36,人物卡!$CZ$25:$DB$29,1,FALSE),0))),"★",INDEX(本职技能!$A$2:$IC$87,MATCH(人物卡!CA36,本职技能!$A$2:$A$87,0),MATCH(人物卡!$BL$11,本职技能!$A$1:$IC$1,0))) -> 0 | CA36: 话术 | CE36: 5 | CG36: =AR76 -> 0 | CM36: =SUM(CE36:CK36) -> 5 | CO36: =INT(CM36/2) -> 2 | CQ36: =INT(CM36/5) -> 1 | CT36: 职业介绍
C37: - | F37: - | I37: - | L37: - | O37: - | R37: - | U37: - | X37: - | AA37: - | AD37: - | AG37: - | AJ37: - | AM37: - | AP37: - | AR37: =SUM(AO37,AL37,AI37,AF37,AC37,Z37,W37,T37,Q37,N37,K37,H37,E37,B37)-SUM(AQ37,AN37,AK37,AH37,AE37,AB37,Y37,V37,S37,P37,M37,J37,G37,D37) -> 0 | AT37: =AR37+BI37+BM37+BO37 -> 1 | AV37: =BE37 -> 电子学 Ω | AY37: =BC37 -> 0 | BA37: ☐ | BC37: =IF(ISTEXT(IFERROR(VLOOKUP(人物卡!BE37,人物卡!$DI$25:$DQ$29,1,FALSE),IFERROR(VLOOKUP(人物卡!BE37,人物卡!$CZ$25:$DB$29,1,FALSE),0))),"★",INDEX(本职技能!$A$2:$IC$87,MATCH(人物卡!BE37,本职技能!$A$2:$A$87,0),MATCH(人物卡!$BL$11,本职技能!$A$1:$IC$1,0))) -> 0 | BE37: 电子学 Ω | BI37: 1 | BK37: =AR37 -> 0 | BQ37: =SUM(BI37:BO37) -> 1 | BS37: =INT(BQ37/2) -> 0 | BU37: =INT(BQ37/5) -> 0 | BW37: ☐ | BY37: =IF(ISTEXT(IFERROR(VLOOKUP(人物卡!CA37,人物卡!$DI$25:$DQ$29,1,FALSE),IFERROR(VLOOKUP(人物卡!CA37,人物卡!$CZ$25:$DB$29,1,FALSE),0))),"★",INDEX(本职技能!$A$2:$IC$87,MATCH(人物卡!CA37,本职技能!$A$2:$A$87,0),MATCH(人物卡!$BL$11,本职技能!$A$1:$IC$1,0))) -> 0 | CA37: 恐吓 | CE37: 15 | CG37: =AR77 -> 0 | CM37: =SUM(CE37:CK37) -> 15 | CO37: =INT(CM37/2) -> 7 | CQ37: =INT(CM37/5) -> 3 | CT37: =IF(BL11=0," ",""&LOOKUP(BL11,职业列表!A2:A237,职业列表!M2:M237))
C38: - | F38: - | I38: - | L38: - | O38: - | R38: - | U38: - | X38: - | AA38: - | AD38: - | AG38: - | AJ38: - | AM38: - | AP38: - | AR38: =SUM(AO38,AL38,AI38,AF38,AC38,Z38,W38,T38,Q38,N38,K38,H38,E38,B38)-SUM(AQ38,AN38,AK38,AH38,AE38,AB38,Y38,V38,S38,P38,M38,J38,G38,D38) -> 0 | AT38: =AR38+BI38+BM38+BO38 -> 1 | AV38: =BE38 -> 操作重型机械 | AY38: =BC38 -> 0 | BA38: ☐ | BC38: =IF(ISTEXT(IFERROR(VLOOKUP(人物卡!BE38,人物卡!$DI$25:$DQ$29,1,FALSE),IFERROR(VLOOKUP(人物卡!BE38,人物卡!$CZ$25:$DB$29,1,FALSE),0))),"★",INDEX(本职技能!$A$2:$IC$87,MATCH(人物卡!BE38,本职技能!$A$2:$A$87,0),MATCH(人物卡!$BL$11,本职技能!$A$1:$IC$1,0))) -> 0 | BE38: 操作重型机械 | BI38: 1 | BK38: =AR38 -> 0 | BQ38: =SUM(BI38:BO38) -> 1 | BS38: =INT(BQ38/2) -> 0 | BU38: =INT(BQ38/5) -> 0 | BW38: ☐ | BY38: =IF(ISTEXT(IFERROR(VLOOKUP(人物卡!CA38,人物卡!$DI$25:$DQ$29,1,FALSE),IFERROR(VLOOKUP(人物卡!CA38,人物卡!$CZ$25:$DB$29,1,FALSE),0))),"★",INDEX(本职技能!$A$2:$IC$87,MATCH(人物卡!CA38,本职技能!$A$2:$A$87,0),MATCH(人物卡!$BL$11,本职技能!$A$1:$IC$1,0))) -> 0 | CA38: 说服 | CE38: 10 | CG38: =AR78 -> 0 | CM38: =SUM(CE38:CK38) -> 10 | CO38: =INT(CM38/2) -> 5 | CQ38: =INT(CM38/5) -> 2
C39: - | F39: - | I39: - | L39: - | O39: - | R39: - | U39: - | X39: - | AA39: - | AD39: - | AG39: - | AJ39: - | AM39: - | AP39: - | AR39: =SUM(AO39,AL39,AI39,AF39,AC39,Z39,W39,T39,Q39,N39,K39,H39,E39,B39)-SUM(AQ39,AN39,AK39,AH39,AE39,AB39,Y39,V39,S39,P39,M39,J39,G39,D39) -> 0 | AT39: =AR39+BI39+BM39+BO39 -> 1 | AV39: =BE39 -> 爆破 | AY39: =BC39 -> 0 | BA39: ☐ | BC39: =IF(ISTEXT(IFERROR(VLOOKUP(人物卡!BE39,人物卡!$DI$25:$DQ$29,1,FALSE),IFERROR(VLOOKUP(人物卡!BE39,人物卡!$CZ$25:$DB$29,1,FALSE),0))),"★",INDEX(本职技能!$A$2:$IC$87,MATCH(人物卡!BE39,本职技能!$A$2:$A$87,0),MATCH(人物卡!$BL$11,本职技能!$A$1:$IC$1,0))) -> 0 | BE39: 爆破 | BI39: 1 | BK39: =AR39 -> 0 | BQ39: =SUM(BI39:BO39) -> 1 | BS39: =INT(BQ39/2) -> 0 | BU39: =INT(BQ39/5) -> 0 | BW39: ☐ | BY39: =IF(ISTEXT(IFERROR(VLOOKUP(人物卡!CA39,人物卡!$DI$25:$DQ$29,1,FALSE),IFERROR(VLOOKUP(人物卡!CA39,人物卡!$CZ$25:$DB$29,1,FALSE),0))),"★",INDEX(本职技能!$A$2:$IC$87,MATCH(人物卡!CA39,本职技能!$A$2:$A$87,0),MATCH(人物卡!$BL$11,本职技能!$A$1:$IC$1,0))) -> 0 | CA39: 跳跃 | CE39: 20 | CG39: =AR79 -> 0 | CM39: =SUM(CE39:CK39) -> 20 | CO39: =INT(CM39/2) -> 10 | CQ39: =INT(CM39/5) -> 4
C40: - | F40: - | I40: - | L40: - | O40: - | R40: - | U40: - | X40: - | AA40: - | AD40: - | AG40: - | AJ40: - | AM40: - | AP40: - | AR40: =SUM(AO40,AL40,AI40,AF40,AC40,Z40,W40,T40,Q40,N40,K40,H40,E40,B40)-SUM(AQ40,AN40,AK40,AH40,AE40,AB40,Y40,V40,S40,P40,M40,J40,G40,D40) -> 0 | AT40: =IFERROR(AR40+BI40+BM40+BO40,"禁用") -> 禁用 | AV40: =BE40 -> 计算机使用 Ω | AY40: =BC40 -> 0 | BA40: ☐ | BC40: =IF(ISTEXT(IFERROR(VLOOKUP(人物卡!BE40,人物卡!$DI$25:$DQ$29,1,FALSE),IFERROR(VLOOKUP(人物卡!BE40,人物卡!$CZ$25:$DB$29,1,FALSE),0))),"★",INDEX(本职技能!$A$2:$IC$87,MATCH(人物卡!BE40,本职技能!$A$2:$A$87,0),MATCH(人物卡!$BL$11,本职技能!$A$1:$IC$1,0))) -> 0 | BE40: 计算机使用 Ω | BI40: =IF(BL10="1920s","禁用",5) -> 禁用 | BK40: =AR40 -> 0 | BQ40: =SUM(BI40:BO40) -> 0 | BS40: =INT(BQ40/2) -> 0 | BU40: =INT(BQ40/5) -> 0 | BW40: ☐ | BY40: =IF(ISTEXT(IFERROR(VLOOKUP(人物卡!CA40,人物卡!$DI$25:$DQ$29,1,FALSE),IFERROR(VLOOKUP(人物卡!CA40,人物卡!$CZ$25:$DB$29,1,FALSE),0))),"★",INDEX(本职技能!$A$2:$IC$87,MATCH(人物卡!CA40,本职技能!$A$2:$A$87,0),MATCH(人物卡!$BL$11,本职技能!$A$1:$IC$1,0))) -> 0 | CA40: 攀爬 | CE40: 20 | CG40: =AR80 -> 0 | CM40: =SUM(CE40:CK40) -> 20 | CO40: =INT(CM40/2) -> 10 | CQ40: =INT(CM40/5) -> 4
C41: - | F41: - | I41: - | L41: - | O41: - | R41: - | U41: - | X41: - | AA41: - | AD41: - | AG41: - | AJ41: - | AM41: - | AP41: - | AR41: =SUM(AO41,AL41,AI41,AF41,AC41,Z41,W41,T41,Q41,N41,K41,H41,E41,B41)-SUM(AQ41,AN41,AK41,AH41,AE41,AB41,Y41,V41,S41,P41,M41,J41,G41,D41) -> 0 | AT41: =AR41+BI41+BM41+BO41 -> 1 | AV41: =IF(BG41=0,"科学:",BG41) -> 科学: | AY41: =BC41 -> 0 | BA41: ☐ | BC41: =IF(ISTEXT(IFERROR(VLOOKUP(人物卡!BE41,人物卡!$DI$25:$DQ$29,1,FALSE),IFERROR(VLOOKUP(人物卡!BE41,人物卡!$CZ$25:$DB$29,1,FALSE),0))),"★",INDEX(本职技能!$A$2:$IC$87,MATCH(人物卡!BE41,本职技能!$A$2:$A$87,0),MATCH(人物卡!$BL$11,本职技能!$A$1:$IC$1,0))) -> 0 | BE41: 科学① | BI41: =IF(ISBLANK($AD$116),IF(BG41="数学",10,1),IF(BG41=$X$116,$AD$116,1)) -> 1 | BK41: =AR41 -> 0 | BQ41: =BI41+BK41+BO41+BM41 -> 1 | BS41: =INT(BQ41/2) -> 0 | BU41: =INT(BQ41/5) -> 0 | BW41: ☐ | BY41: =IF(ISTEXT(IFERROR(VLOOKUP(人物卡!CA41,人物卡!$DI$25:$DQ$29,1,FALSE),IFERROR(VLOOKUP(人物卡!CA41,人物卡!$CZ$25:$DB$29,1,FALSE),0))),"★",INDEX(本职技能!$A$2:$IC$87,MATCH(人物卡!CA41,本职技能!$A$2:$A$87,0),MATCH(人物卡!$BL$11,本职技能!$A$1:$IC$1,0))) -> 0 | CA41: 生存① | CE41: 10 | CG41: =AR81 -> 0 | CM41: =SUM(CE41:CK41) -> 10 | CO41: =INT(CM41/2) -> 5 | CQ41: =INT(CM41/5) -> 2
C42: - | F42: - | I42: - | L42: - | O42: - | R42: - | U42: - | X42: - | AA42: - | AD42: - | AG42: - | AJ42: - | AM42: - | AP42: - | AR42: =SUM(AO42,AL42,AI42,AF42,AC42,Z42,W42,T42,Q42,N42,K42,H42,E42,B42)-SUM(AQ42,AN42,AK42,AH42,AE42,AB42,Y42,V42,S42,P42,M42,J42,G42,D42) -> 0 | AT42: =AR42+BI42+BM42+BO42 -> 1 | AV42: =IF(BG42=0,"科学:",BG42) -> 科学: | AY42: =BC42 -> 0 | BA42: ☐ | BC42: =IF(ISTEXT(IFERROR(VLOOKUP(人物卡!BE42,人物卡!$DI$25:$DQ$29,1,FALSE),IFERROR(VLOOKUP(人物卡!BE42,人物卡!$CZ$25:$DB$29,1,FALSE),0))),"★",INDEX(本职技能!$A$2:$IC$87,MATCH(人物卡!BE42,本职技能!$A$2:$A$87,0),MATCH(人物卡!$BL$11,本职技能!$A$1:$IC$1,0))) -> 0 | BE42: 科学② | BI42: =IF(ISBLANK($AD$116),IF(BG42="数学",10,1),IF(BG42=$X$116,$AD$116,1)) -> 1 | BK42: =AR42 -> 0 | BQ42: =BO42+BM42+BI42+BK42 -> 1 | BS42: =INT(BQ42/2) -> 0 | BU42: =INT(BQ42/5) -> 0 | BW42: ☐ | BY42: =IF(ISTEXT(IFERROR(VLOOKUP(人物卡!CA42,人物卡!$DI$25:$DQ$29,1,FALSE),IFERROR(VLOOKUP(人物卡!CA42,人物卡!$CZ$25:$DB$29,1,FALSE),0))),"★",INDEX(本职技能!$A$2:$IC$87,MATCH(人物卡!CA42,本职技能!$A$2:$A$87,0),MATCH(人物卡!$BL$11,本职技能!$A$1:$IC$1,0))) -> 0 | CA42: 生存② | CE42: 10 | CG42: =AR82 -> 0 | CM42: =SUM(CE42:CK42) -> 10 | CO42: =INT(CM42/2) -> 5 | CQ42: =INT(CM42/5) -> 2
C43: - | F43: - | I43: - | L43: - | O43: - | R43: - | U43: - | X43: - | AA43: - | AD43: - | AG43: - | AJ43: - | AM43: - | AP43: - | AR43: =SUM(AO43,AL43,AI43,AF43,AC43,Z43,W43,T43,Q43,N43,K43,H43,E43,B43)-SUM(AQ43,AN43,AK43,AH43,AE43,AB43,Y43,V43,S43,P43,M43,J43,G43,D43) -> 0 | AT43: =AR43+BI43+BM43+BO43 -> 1 | AV43: =IF(BG43=0,"科学:",BG43) -> 科学: | AY43: =BC43 -> 0 | BA43: ☐ | BC43: =IF(ISTEXT(IFERROR(VLOOKUP(人物卡!BE43,人物卡!$DI$25:$DQ$29,1,FALSE),IFERROR(VLOOKUP(人物卡!BE43,人物卡!$CZ$25:$DB$29,1,FALSE),0))),"★",INDEX(本职技能!$A$2:$IC$87,MATCH(人物卡!BE43,本职技能!$A$2:$A$87,0),MATCH(人物卡!$BL$11,本职技能!$A$1:$IC$1,0))) -> 0 | BE43: 科学③ | BI43: =IF(ISBLANK($AD$116),IF(BG43="数学",10,1),IF(BG43=$X$116,$AD$116,1)) -> 1 | BK43: =AR43 -> 0 | BQ43: =BI43+BK43+BM43+BO43 -> 1 | BS43: =INT(BQ43/2) -> 0 | BU43: =INT(BQ43/5) -> 0 | BW43: ☐ | BY43: =IF(ISTEXT(IFERROR(VLOOKUP(人物卡!CA43,人物卡!$DI$25:$DQ$29,1,FALSE),IFERROR(VLOOKUP(人物卡!CA43,人物卡!$CZ$25:$DB$29,1,FALSE),0))),"★",INDEX(本职技能!$A$2:$IC$87,MATCH(人物卡!CA43,本职技能!$A$2:$A$87,0),MATCH(人物卡!$BL$11,本职技能!$A$1:$IC$1,0))) -> 0 | CA43: 游泳 | CE43: 20 | CG43: =AR83 -> 0 | CM43: =SUM(CE43:CK43) -> 20 | CO43: =INT(CM43/2) -> 10 | CQ43: =INT(CM43/5) -> 4
C44: - | F44: - | I44: - | L44: - | O44: - | R44: - | U44: - | X44: - | AA44: - | AD44: - | AG44: - | AJ44: - | AM44: - | AP44: - | AR44: =SUM(AO44,AL44,AI44,AF44,AC44,Z44,W44,T44,Q44,N44,K44,H44,E44,B44)-SUM(AQ44,AN44,AK44,AH44,AE44,AB44,Y44,V44,S44,P44,M44,J44,G44,D44) -> 0 | AT44: =AR44+BI44+BM44+BO44 -> 1 | AV44: =IF(BG44=0,"科学:",BG44) -> 科学: | AY44: =BC44 -> 0 | BA44: ☐ | BC44: =IF(ISTEXT(IFERROR(VLOOKUP(人物卡!BE44,人物卡!$DI$25:$DQ$29,1,FALSE),IFERROR(VLOOKUP(人物卡!BE44,人物卡!$CZ$25:$DB$29,1,FALSE),0))),"★",INDEX(本职技能!$A$2:$IC$87,MATCH(人物卡!BE44,本职技能!$A$2:$A$87,0),MATCH(人物卡!$BL$11,本职技能!$A$1:$IC$1,0))) -> 0 | BE44: 科学④ | BI44: =IF(ISBLANK($AD$116),IF(BG44="数学",10,1),IF(BG44=$X$116,$AD$116,1)) -> 1 | BK44: =AR44 -> 0 | BQ44: =BO44+BM44+BI44+BK44 -> 1 | BS44: =INT(BQ44/2) -> 0 | BU44: =INT(BQ44/5) -> 0 | BW44: ☐ | BY44: =IF(ISTEXT(IFERROR(VLOOKUP(人物卡!CA44,人物卡!$DI$25:$DQ$29,1,FALSE),IFERROR(VLOOKUP(人物卡!CA44,人物卡!$CZ$25:$DB$29,1,FALSE),0))),"★",INDEX(本职技能!$A$2:$IC$87,MATCH(人物卡!CA44,本职技能!$A$2:$A$87,0),MATCH(人物卡!$BL$11,本职技能!$A$1:$IC$1,0))) -> 0 | CA44: 精神分析 | CE44: 1 | CG44: =AR84 -> 0 | CM44: =SUM(CE44:CK44) -> 1 | CO44: =INT(CM44/2) -> 0 | CQ44: =INT(CM44/5) -> 0
C45: - | F45: - | I45: - | L45: - | O45: - | R45: - | U45: - | X45: - | AA45: - | AD45: - | AG45: - | AJ45: - | AM45: - | AP45: - | AR45: =SUM(AO45,AL45,AI45,AF45,AC45,Z45,W45,T45,Q45,N45,K45,H45,E45,B45)-SUM(AQ45,AN45,AK45,AH45,AE45,AB45,Y45,V45,S45,P45,M45,J45,G45,D45) -> 0 | AT45: =AR45+BI45+BM45+BO45 -> 1 | AV45: =IF(BG45=0,"科学:",BG45) -> 科学: | AY45: =BC45 -> 0 | BA45: ☐ | BC45: =IF(ISTEXT(IFERROR(VLOOKUP(人物卡!BE45,人物卡!$DI$25:$DQ$29,1,FALSE),IFERROR(VLOOKUP(人物卡!BE45,人物卡!$CZ$25:$DB$29,1,FALSE),0))),"★",INDEX(本职技能!$A$2:$IC$87,MATCH(人物卡!BE45,本职技能!$A$2:$A$87,0),MATCH(人物卡!$BL$11,本职技能!$A$1:$IC$1,0))) -> 0 | BE45: 科学⑤ | BI45: =IF(ISBLANK($AD$116),IF(BG45="数学",10,1),IF(BG45=$X$116,$AD$116,1)) -> 1 | BK45: =AR45 -> 0 | BQ45: =BI45+BK45+BM45+BO45 -> 1 | BS45: =INT(BQ45/2) -> 0 | BU45: =INT(BQ45/5) -> 0 | BW45: ☐ | BY45: =IF(ISTEXT(IFERROR(VLOOKUP(人物卡!CA45,人物卡!$DI$25:$DQ$29,1,FALSE),IFERROR(VLOOKUP(人物卡!CA45,人物卡!$CZ$25:$DB$29,1,FALSE),0))),"★",INDEX(本职技能!$A$2:$IC$87,MATCH(人物卡!CA45,本职技能!$A$2:$A$87,0),MATCH(人物卡!$BL$11,本职技能!$A$1:$IC$1,0))) -> 0 | CA45: 医学 | CE45: 1 | CG45: =AR85 -> 0 | CM45: =SUM(CE45:CK45) -> 1 | CO45: =INT(CM45/2) -> 0 | CQ45: =INT(CM45/5) -> 0
C46: - | F46: - | I46: - | L46: - | O46: - | R46: - | U46: - | X46: - | AA46: - | AD46: - | AG46: - | AJ46: - | AM46: - | AP46: - | AR46: =SUM(AO46,AL46,AI46,AF46,AC46,Z46,W46,T46,Q46,N46,K46,H46,E46,B46)-SUM(AQ46,AN46,AK46,AH46,AE46,AB46,Y46,V46,S46,P46,M46,J46,G46,D46) -> 0 | AT46: =AR46+BI46+BM46+BO46 -> 1 | AV46: =BE46 -> 学识： | AY46: =BC46 -> 0 | BA46: ☐ | BC46: =IF(ISTEXT(IFERROR(VLOOKUP(人物卡!BE46,人物卡!$DI$25:$DQ$29,1,FALSE),IFERROR(VLOOKUP(人物卡!BE46,人物卡!$CZ$25:$DB$29,1,FALSE),0))),"★",INDEX(本职技能!$A$2:$IC$87,MATCH(人物卡!BE46,本职技能!$A$2:$A$87,0),MATCH(人物卡!$BL$11,本职技能!$A$1:$IC$1,0))) -> 0 | BE46: 学识： | BI46: 1 | BK46: =AR46 -> 0 | BQ46: =SUM(BI46:BO46) -> 1 | BS46: =INT(BQ46/2) -> 0 | BU46: =INT(BQ46/5) -> 0 | BW46: ☐ | BY46: =IF(ISTEXT(IFERROR(VLOOKUP(人物卡!CA46,人物卡!$DI$25:$DQ$29,1,FALSE),IFERROR(VLOOKUP(人物卡!CA46,人物卡!$CZ$25:$DB$29,1,FALSE),0))),"★",INDEX(本职技能!$A$2:$IC$87,MATCH(人物卡!CA46,本职技能!$A$2:$A$87,0),MATCH(人物卡!$BL$11,本职技能!$A$1:$IC$1,0))) -> 0 | CA46: 急救 | CE46: 30 | CG46: =AR86 -> 0 | CM46: =SUM(CE46:CK46) -> 30 | CO46: =INT(CM46/2) -> 15 | CQ46: =INT(CM46/5) -> 6
C47: - | F47: - | I47: - | L47: - | O47: - | R47: - | U47: - | X47: - | AA47: - | AD47: - | AG47: - | AJ47: - | AM47: - | AP47: - | AR47: =SUM(AO47,AL47,AI47,AF47,AC47,Z47,W47,T47,Q47,N47,K47,H47,E47,B47)-SUM(AQ47,AN47,AK47,AH47,AE47,AB47,Y47,V47,S47,P47,M47,J47,G47,D47) -> 0 | AT47: =AR47+BI47+BM47+BO47 -> 5 | AV47: =IF(BG47=0,"技艺:",BG47) -> 技艺: | AY47: =BC47 -> 0 | BA47: ☐ | BC47: =IF(ISTEXT(IFERROR(VLOOKUP(人物卡!BE47,人物卡!$DI$25:$DQ$29,1,FALSE),IFERROR(VLOOKUP(人物卡!BE47,人物卡!$CZ$25:$DB$29,1,FALSE),0))),"★",INDEX(本职技能!$A$2:$IC$87,MATCH(人物卡!BE47,本职技能!$A$2:$A$87,0),MATCH(人物卡!$BL$11,本职技能!$A$1:$IC$1,0))) -> 0 | BE47: 技艺① | BI47: =IF(ISBLANK(BG47),5,IF(BG47=$X$108,$AD$108,5)) -> 5 | BK47: =AR47 -> 0 | BQ47: =BI47+BK47+BM47+BO47 -> 5 | BS47: =INT(BQ47/2) -> 2 | BU47: =INT(BQ47/5) -> 1 | BW47: ☐ | BY47: =IF(ISTEXT(IFERROR(VLOOKUP(人物卡!CA47,人物卡!$DI$25:$DQ$29,1,FALSE),IFERROR(VLOOKUP(人物卡!CA47,人物卡!$CZ$25:$DB$29,1,FALSE),0))),"★",INDEX(本职技能!$A$2:$IC$87,MATCH(人物卡!CA47,本职技能!$A$2:$A$87,0),MATCH(人物卡!$BL$11,本职技能!$A$1:$IC$1,0))) -> 0 | CA47: 驾驶① | CE47: =IF(ISBLANK(CT34),1,IF(CC47=CT34,#REF!,1)) -> 1 | CG47: =AR87 -> 0 | CM47: =SUM(CE47:CK47) -> 1 | CO47: =INT(CM47/2) -> 0 | CQ47: =INT(CM47/5) -> 0 | CT47: =IF(附表!AE22="仅显示1890_2012","时代介绍仅显示1890_2012这段时间","时代介绍") -> 时代介绍
C48: - | F48: - | I48: - | L48: - | O48: - | R48: - | U48: - | X48: - | AA48: - | AD48: - | AG48: - | AJ48: - | AM48: - | AP48: - | AR48: =SUM(AO48,AL48,AI48,AF48,AC48,Z48,W48,T48,Q48,N48,K48,H48,E48,B48)-SUM(AQ48,AN48,AK48,AH48,AE48,AB48,Y48,V48,S48,P48,M48,J48,G48,D48) -> 0 | AT48: =AR48+BI48+BM48+BO48 -> 5 | AV48: =IF(BG48=0,"技艺:",BG48) -> 技艺: | AY48: =BC48 -> 0 | BA48: ☐ | BC48: =IF(ISTEXT(IFERROR(VLOOKUP(人物卡!BE48,人物卡!$DI$25:$DQ$29,1,FALSE),IFERROR(VLOOKUP(人物卡!BE48,人物卡!$CZ$25:$DB$29,1,FALSE),0))),"★",INDEX(本职技能!$A$2:$IC$87,MATCH(人物卡!BE48,本职技能!$A$2:$A$87,0),MATCH(人物卡!$BL$11,本职技能!$A$1:$IC$1,0))) -> 0 | BE48: 技艺② | BI48: =IF(ISBLANK(BG48),5,IF(BG48=$X$108,$AD$108,5)) -> 5 | BK48: =AR48 -> 0 | BQ48: =BO48+BM48+BK48+BI48 -> 5 | BS48: =INT(BQ48/2) -> 2 | BU48: =INT(BQ48/5) -> 1 | BW48: ☐ | BY48: =IF(ISTEXT(IFERROR(VLOOKUP(人物卡!CA48,人物卡!$DI$25:$DQ$29,1,FALSE),IFERROR(VLOOKUP(人物卡!CA48,人物卡!$CZ$25:$DB$29,1,FALSE),0))),"★",INDEX(本职技能!$A$2:$IC$87,MATCH(人物卡!CA48,本职技能!$A$2:$A$87,0),MATCH(人物卡!$BL$11,本职技能!$A$1:$IC$1,0))) -> 0 | CA48: 驾驶② | CE48: =IF(ISBLANK(CT35),1,IF(CC48=CT35,#REF!,1)) -> 1 | CG48: =AR88 -> 0 | CM48: =SUM(CE48:CK48) -> 1 | CO48: =INT(CM48/2) -> 0 | CQ48: =INT(CM48/5) -> 0 | CT48: 年代 | CY48: 国际重大历史进程 | DE48: 中国重大历史进程 | DK48: 年代
C49: - | F49: - | I49: - | L49: - | O49: - | R49: - | U49: - | X49: - | AA49: - | AD49: - | AG49: - | AJ49: - | AM49: - | AP49: - | AR49: =SUM(AO49,AL49,AI49,AF49,AC49,Z49,W49,T49,Q49,N49,K49,H49,E49,B49)-SUM(AQ49,AN49,AK49,AH49,AE49,AB49,Y49,V49,S49,P49,M49,J49,G49,D49) -> 0 | AT49: =AR49+BI49+BM49+BO49 -> 5 | AV49: =IF(BG49=0,"技艺:",BG49) -> 技艺: | AY49: =BC49 -> 0 | BA49: ☐ | BC49: =IF(ISTEXT(IFERROR(VLOOKUP(人物卡!BE49,人物卡!$DI$25:$DQ$29,1,FALSE),IFERROR(VLOOKUP(人物卡!BE49,人物卡!$CZ$25:$DB$29,1,FALSE),0))),"★",INDEX(本职技能!$A$2:$IC$87,MATCH(人物卡!BE49,本职技能!$A$2:$A$87,0),MATCH(人物卡!$BL$11,本职技能!$A$1:$IC$1,0))) -> 0 | BE49: 技艺③ | BI49: =IF(ISBLANK(BG49),5,IF(BG49=$X$108,$AD$108,5)) -> 5 | BK49: =AR49 -> 0 | BQ49: =BO49+BM49+BK49+BI49 -> 5 | BS49: =INT(BQ49/2) -> 2 | BU49: =INT(BQ49/5) -> 1 | BW49: ☐ | BY49: =IF(ISTEXT(IFERROR(VLOOKUP(人物卡!CA49,人物卡!$DI$25:$DQ$29,1,FALSE),IFERROR(VLOOKUP(人物卡!CA49,人物卡!$CZ$25:$DB$29,1,FALSE),0))),"★",INDEX(本职技能!$A$2:$IC$87,MATCH(人物卡!CA49,本职技能!$A$2:$A$87,0),MATCH(人物卡!$BL$11,本职技能!$A$1:$IC$1,0))) -> 0 | CA49: 汽车驾驶 | CE49: 20 | CG49: =AR89 -> 0 | CM49: =SUM(CE49:CK49) -> 20 | CO49: =INT(CM49/2) -> 10 | CQ49: =INT(CM49/5) -> 4 | CT49: =IF(BD17="公元","A.C."&BF17,"B.C."&BF17) -> A.C. | CY49: =附表!AF22 | DE49: =附表!AI22 -> #N/A | DK49: =附表!AL22 -> #N/A
C50: - | F50: - | I50: - | L50: - | O50: - | R50: - | U50: - | X50: - | AA50: - | AD50: - | AG50: - | AJ50: - | AM50: - | AP50: - | AR50: =SUM(AO50,AL50,AI50,AF50,AC50,Z50,W50,T50,Q50,N50,K50,H50,E50,B50)-SUM(AQ50,AN50,AK50,AH50,AE50,AB50,Y50,V50,S50,P50,M50,J50,G50,D50) -> 0 | AT50: =AR50+BI50+BM50+BO50 -> 5 | AV50: =IF(BG50=0,"技艺:",BG50) -> 技艺: | AY50: =BC50 -> 0 | BA50: ☐ | BC50: =IF(ISTEXT(IFERROR(VLOOKUP(人物卡!BE50,人物卡!$DI$25:$DQ$29,1,FALSE),IFERROR(VLOOKUP(人物卡!BE50,人物卡!$CZ$25:$DB$29,1,FALSE),0))),"★",INDEX(本职技能!$A$2:$IC$87,MATCH(人物卡!BE50,本职技能!$A$2:$A$87,0),MATCH(人物卡!$BL$11,本职技能!$A$1:$IC$1,0))) -> 0 | BE50: 技艺④ | BI50: =IF(ISBLANK(BG50),5,IF(BG50=$X$108,$AD$108,5)) -> 5 | BK50: =AR50 -> 0 | BQ50: =BO50+BM50+BK50+BI50 -> 5 | BS50: =INT(BQ50/2) -> 2 | BU50: =INT(BQ50/5) -> 1 | BW50: ☐ | BY50: =IF(ISTEXT(IFERROR(VLOOKUP(人物卡!CA50,人物卡!$DI$25:$DQ$29,1,FALSE),IFERROR(VLOOKUP(人物卡!CA50,人物卡!$CZ$25:$DB$29,1,FALSE),0))),"★",INDEX(本职技能!$A$2:$IC$87,MATCH(人物卡!CA50,本职技能!$A$2:$A$87,0),MATCH(人物卡!$BL$11,本职技能!$A$1:$IC$1,0))) -> 0 | CA50: 骑术 | CE50: 5 | CG50: =AR90 -> 0 | CM50: =SUM(CE50:CK50) -> 5 | CO50: =INT(CM50/2) -> 2 | CQ50: =INT(CM50/5) -> 1 | CY50: =附表!AG22 -> #N/A | DE50: =附表!AJ22 -> #N/A | DK50: =附表!AM22 -> #N/A
C51: - | F51: - | I51: - | L51: - | O51: - | R51: - | U51: - | X51: - | AA51: - | AD51: - | AG51: - | AJ51: - | AM51: - | AP51: - | AR51: =SUM(AO51,AL51,AI51,AF51,AC51,Z51,W51,T51,Q51,N51,K51,H51,E51,B51)-SUM(AQ51,AN51,AK51,AH51,AE51,AB51,Y51,V51,S51,P51,M51,J51,G51,D51) -> 0 | AT51: =AR51+BI51+BM51+BO51 -> 5 | AV51: =IF(BG51=0,"技艺:",BG51) -> 技艺: | AY51: =BC51 -> 0 | BA51: ☐ | BC51: =IF(ISTEXT(IFERROR(VLOOKUP(人物卡!BE51,人物卡!$DI$25:$DQ$29,1,FALSE),IFERROR(VLOOKUP(人物卡!BE51,人物卡!$CZ$25:$DB$29,1,FALSE),0))),"★",INDEX(本职技能!$A$2:$IC$87,MATCH(人物卡!BE51,本职技能!$A$2:$A$87,0),MATCH(人物卡!$BL$11,本职技能!$A$1:$IC$1,0))) -> 0 | BE51: 技艺⑤ | BI51: =IF(ISBLANK(BG51),5,IF(BG51=$X$108,$AD$108,5)) -> 5 | BK51: =AR51 -> 0 | BQ51: =BO51+BM51+BK51+BI51 -> 5 | BS51: =INT(BQ51/2) -> 2 | BU51: =INT(BQ51/5) -> 1 | BW51: ☐ | BY51: =IF(ISTEXT(IFERROR(VLOOKUP(人物卡!CA51,人物卡!$DI$25:$DQ$29,1,FALSE),IFERROR(VLOOKUP(人物卡!CA51,人物卡!$CZ$25:$DB$29,1,FALSE),0))),"★",INDEX(本职技能!$A$2:$IC$87,MATCH(人物卡!CA51,本职技能!$A$2:$A$87,0),MATCH(人物卡!$BL$11,本职技能!$A$1:$IC$1,0))) -> 0 | CA51: 动物驯养 | CE51: 5 | CG51: =AR91 -> 0 | CM51: =SUM(CE51:CK51) -> 5 | CO51: =INT(CM51/2) -> 2 | CQ51: =INT(CM51/5) -> 1 | CY51: =附表!AH22 -> #N/A | DE51: =附表!AK22 -> #N/A | DK51: =附表!AN22 -> #N/A
C52: - | F52: - | I52: - | L52: - | O52: - | R52: - | U52: - | X52: - | AA52: - | AD52: - | AG52: - | AJ52: - | AM52: - | AP52: - | AR52: =SUM(AO52,AL52,AI52,AF52,AC52,Z52,W52,T52,Q52,N52,K52,H52,E52,B52)-SUM(AQ52,AN52,AK52,AH52,AE52,AB52,Y52,V52,S52,P52,M52,J52,G52,D52) -> 0 | AT52: =AR52+BI52+BM52+BO52 -> 0 | AV52: =BE52 -> 母语 | AY52: =BC52 -> 0 | BA52: ☐ | BC52: =IF(ISTEXT(IFERROR(VLOOKUP(人物卡!BE52,人物卡!$DI$25:$DQ$29,1,FALSE),IFERROR(VLOOKUP(人物卡!BE52,人物卡!$CZ$25:$DB$29,1,FALSE),0))),"★",INDEX(本职技能!$A$2:$IC$87,MATCH(人物卡!BE52,本职技能!$A$2:$A$87,0),MATCH(人物卡!$BL$11,本职技能!$A$1:$IC$1,0))) -> 0 | BE52: 母语 | BI52: =IF(EDUA="未填写",0,EDUA) -> 0 | BK52: =AR52 -> 0 | BQ52: =SUM(BI52:BO52) -> 0 | BS52: =INT(BQ52/2) -> 0 | BU52: =INT(BQ52/5) -> 0 | BW52: ☐ | BY52: =IF(ISTEXT(IFERROR(VLOOKUP(人物卡!CA52,人物卡!$DI$25:$DQ$29,1,FALSE),IFERROR(VLOOKUP(人物卡!CA52,人物卡!$CZ$25:$DB$29,1,FALSE),0))),"★",INDEX(本职技能!$A$2:$IC$87,MATCH(人物卡!CA52,本职技能!$A$2:$A$87,0),MATCH(人物卡!$BL$11,本职技能!$A$1:$IC$1,0))) -> 0 | CA52: 潜水 | CE52: 1 | CG52: =AR92 -> 0 | CM52: =SUM(CE52:CK52) -> 1 | CO52: =INT(CM52/2) -> 0 | CQ52: =INT(CM52/5) -> 0 | CT52: 新闻
C53: - | F53: - | I53: - | L53: - | O53: - | R53: - | U53: - | X53: - | AA53: - | AD53: - | AG53: - | AJ53: - | AM53: - | AP53: - | AR53: =SUM(AO53,AL53,AI53,AF53,AC53,Z53,W53,T53,Q53,N53,K53,H53,E53,B53)-SUM(AQ53,AN53,AK53,AH53,AE53,AB53,Y53,V53,S53,P53,M53,J53,G53,D53) -> 0 | AT53: =AR53+BI53+BM53+BO53 -> 1 | AV53: =IF(BG53=0,"外语:",BG53) -> 外语: | AY53: =BC53 -> 0 | BA53: ☐ | BC53: =IF(ISTEXT(IFERROR(VLOOKUP(人物卡!BE53,人物卡!$DI$25:$DQ$29,1,FALSE),IFERROR(VLOOKUP(人物卡!BE53,人物卡!$CZ$25:$DB$29,1,FALSE),0))),"★",INDEX(本职技能!$A$2:$IC$87,MATCH(人物卡!BE53,本职技能!$A$2:$A$87,0),MATCH(人物卡!$BL$11,本职技能!$A$1:$IC$1,0))) -> 0 | BE53: 外语① | BI53: 1 | BK53: =AR53 -> 0 | BQ53: =SUM(BI53:BO53) -> 1 | BS53: =INT(BQ53/2) -> 0 | BU53: =INT(BQ53/5) -> 0 | BW53: ☐ | BY53: =IF(ISTEXT(IFERROR(VLOOKUP(人物卡!CA53,人物卡!$DI$25:$DQ$29,1,FALSE),IFERROR(VLOOKUP(人物卡!CA53,人物卡!$CZ$25:$DB$29,1,FALSE),0))),"★",INDEX(本职技能!$A$2:$IC$87,MATCH(人物卡!CA53,本职技能!$A$2:$A$87,0),MATCH(人物卡!$BL$11,本职技能!$A$1:$IC$1,0))) -> 0 | CA53: 读唇 | CE53: 1 | CG53: =AR93 -> 0 | CM53: =SUM(CE53:CK53) -> 1 | CO53: =INT(CM53/2) -> 0 | CQ53: =INT(CM53/5) -> 0 | CT53: =附表!AO22 -> #N/A
C54: - | F54: - | I54: - | L54: - | O54: - | R54: - | U54: - | X54: - | AA54: - | AD54: - | AG54: - | AJ54: - | AM54: - | AP54: - | AR54: =SUM(AO54,AL54,AI54,AF54,AC54,Z54,W54,T54,Q54,N54,K54,H54,E54,B54)-SUM(AQ54,AN54,AK54,AH54,AE54,AB54,Y54,V54,S54,P54,M54,J54,G54,D54) -> 0 | AT54: =AR54+BI54+BM54+BO54 -> 1 | AV54: =IF(BG54=0,"外语:",BG54) -> 外语: | AY54: =BC54 -> 0 | BA54: ☐ | BC54: =IF(ISTEXT(IFERROR(VLOOKUP(人物卡!BE54,人物卡!$DI$25:$DQ$29,1,FALSE),IFERROR(VLOOKUP(人物卡!BE54,人物卡!$CZ$25:$DB$29,1,FALSE),0))),"★",INDEX(本职技能!$A$2:$IC$87,MATCH(人物卡!BE54,本职技能!$A$2:$A$87,0),MATCH(人物卡!$BL$11,本职技能!$A$1:$IC$1,0))) -> 0 | BE54: 外语② | BI54: 1 | BK54: =AR54 -> 0 | BQ54: =SUM(BI54:BO54) -> 1 | BS54: =INT(BQ54/2) -> 0 | BU54: =INT(BQ54/5) -> 0 | BW54: ☐ | BY54: =IF(ISTEXT(IFERROR(VLOOKUP(人物卡!CA54,人物卡!$DI$25:$DQ$29,1,FALSE),IFERROR(VLOOKUP(人物卡!CA54,人物卡!$CZ$25:$DB$29,1,FALSE),0))),"★",INDEX(本职技能!$A$2:$IC$87,MATCH(人物卡!CA54,本职技能!$A$2:$A$87,0),MATCH(人物卡!$BL$11,本职技能!$A$1:$IC$1,0))) -> 0 | CA54: 催眠 | CE54: 1 | CG54: =AR94 -> 0 | CM54: =SUM(CE54:CK54) -> 1 | CO54: =INT(CM54/2) -> 0 | CQ54: =INT(CM54/5) -> 0
C55: - | F55: - | I55: - | L55: - | O55: - | R55: - | U55: - | X55: - | AA55: - | AD55: - | AG55: - | AJ55: - | AM55: - | AP55: - | AR55: =SUM(AO55,AL55,AI55,AF55,AC55,Z55,W55,T55,Q55,N55,K55,H55,E55,B55)-SUM(AQ55,AN55,AK55,AH55,AE55,AB55,Y55,V55,S55,P55,M55,J55,G55,D55) -> 0 | AT55: =AR55+BI55+BM55+BO55 -> 1 | AV55: =IF(BG55=0,"外语:",BG55) -> 外语: | AY55: =BC55 -> 0 | BA55: ☐ | BC55: =IF(ISTEXT(IFERROR(VLOOKUP(人物卡!BE55,人物卡!$DI$25:$DQ$29,1,FALSE),IFERROR(VLOOKUP(人物卡!BE55,人物卡!$CZ$25:$DB$29,1,FALSE),0))),"★",INDEX(本职技能!$A$2:$IC$87,MATCH(人物卡!BE55,本职技能!$A$2:$A$87,0),MATCH(人物卡!$BL$11,本职技能!$A$1:$IC$1,0))) -> 0 | BE55: 外语③ | BI55: 1 | BK55: =AR55 -> 0 | BQ55: =SUM(BI55:BO55) -> 1 | BS55: =INT(BQ55/2) -> 0 | BU55: =INT(BQ55/5) -> 0 | BW55: ☐ | BY55: =IF(ISTEXT(IFERROR(VLOOKUP(人物卡!CA55,人物卡!$DI$25:$DQ$29,1,FALSE),IFERROR(VLOOKUP(人物卡!CA55,人物卡!$CZ$25:$DB$29,1,FALSE),0))),"★",INDEX(本职技能!$A$2:$IC$87,MATCH(人物卡!CA55,本职技能!$A$2:$A$87,0),MATCH(人物卡!$BL$11,本职技能!$A$1:$IC$1,0))) -> 0 | CA55: 自定义① | CE55: 1 | CG55: =AR95 -> 0 | CM55: =SUM(CE55:CK55) -> 1 | CO55: =INT(CM55/2) -> 0 | CQ55: =INT(CM55/5) -> 0
C56: - | F56: - | I56: - | L56: - | O56: - | R56: - | U56: - | X56: - | AA56: - | AD56: - | AG56: - | AJ56: - | AM56: - | AP56: - | AR56: =SUM(AO56,AL56,AI56,AF56,AC56,Z56,W56,T56,Q56,N56,K56,H56,E56,B56)-SUM(AQ56,AN56,AK56,AH56,AE56,AB56,Y56,V56,S56,P56,M56,J56,G56,D56) -> 0 | AT56: =AR56+BI56+BM56+BO56 -> 1 | AV56: =IF(BG56=0,"外语:",BG56) -> 外语: | AY56: =BC56 -> 0 | BA56: ☐ | BC56: =IF(ISTEXT(IFERROR(VLOOKUP(人物卡!BE56,人物卡!$DI$25:$DQ$29,1,FALSE),IFERROR(VLOOKUP(人物卡!BE56,人物卡!$CZ$25:$DB$29,1,FALSE),0))),"★",INDEX(本职技能!$A$2:$IC$87,MATCH(人物卡!BE56,本职技能!$A$2:$A$87,0),MATCH(人物卡!$BL$11,本职技能!$A$1:$IC$1,0))) -> 0 | BE56: 外语④ | BI56: 1 | BK56: =AR56 -> 0 | BQ56: =SUM(BI56:BO56) -> 1 | BS56: =INT(BQ56/2) -> 0 | BU56: =INT(BQ56/5) -> 0 | BW56: ☐ | BY56: =IF(ISTEXT(IFERROR(VLOOKUP(人物卡!CA56,人物卡!$DI$25:$DQ$29,1,FALSE),IFERROR(VLOOKUP(人物卡!CA56,人物卡!$CZ$25:$DB$29,1,FALSE),0))),"★",INDEX(本职技能!$A$2:$IC$87,MATCH(人物卡!CA56,本职技能!$A$2:$A$87,0),MATCH(人物卡!$BL$11,本职技能!$A$1:$IC$1,0))) -> 0 | CA56: 自定义② | CE56: 1 | CG56: =AR96 -> 0 | CM56: =SUM(CE56:CK56) -> 1 | CO56: =INT(CM56/2) -> 0 | CQ56: =INT(CM56/5) -> 0
C57: - | F57: - | I57: - | L57: - | O57: - | R57: - | U57: - | X57: - | AA57: - | AD57: - | AG57: - | AJ57: - | AM57: - | AP57: - | AR57: =SUM(AO57,AL57,AI57,AF57,AC57,Z57,W57,T57,Q57,N57,K57,H57,E57,B57)-SUM(AQ57,AN57,AK57,AH57,AE57,AB57,Y57,V57,S57,P57,M57,J57,G57,D57) -> 0 | AT57: =AR57+BI57+BM57+BO57 -> 1 | AV57: =IF(BG57=0,"外语:",BG57) -> 外语: | AY57: =BC57 -> 0 | BA57: ☐ | BC57: =IF(ISTEXT(IFERROR(VLOOKUP(人物卡!BE57,人物卡!$DI$25:$DQ$29,1,FALSE),IFERROR(VLOOKUP(人物卡!BE57,人物卡!$CZ$25:$DB$29,1,FALSE),0))),"★",INDEX(本职技能!$A$2:$IC$87,MATCH(人物卡!BE57,本职技能!$A$2:$A$87,0),MATCH(人物卡!$BL$11,本职技能!$A$1:$IC$1,0))) -> 0 | BE57: 外语⑤ | BI57: 1 | BK57: =AR57 -> 0 | BQ57: =SUM(BI57:BO57) -> 1 | BS57: =INT(BQ57/2) -> 0 | BU57: =INT(BQ57/5) -> 0 | BW57: ☐ | BY57: =IF(ISTEXT(IFERROR(VLOOKUP(人物卡!CA57,人物卡!$DI$25:$DQ$29,1,FALSE),IFERROR(VLOOKUP(人物卡!CA57,人物卡!$CZ$25:$DB$29,1,FALSE),0))),"★",INDEX(本职技能!$A$2:$IC$87,MATCH(人物卡!CA57,本职技能!$A$2:$A$87,0),MATCH(人物卡!$BL$11,本职技能!$A$1:$IC$1,0))) -> 0 | CA57: 炮术 | CE57: 1 | CG57: =AR97 -> 0 | CM57: =SUM(CE57:CK57) -> 1 | CO57: =INT(CM57/2) -> 0 | CQ57: =INT(CM57/5) -> 0
C58: - | F58: - | I58: - | L58: - | O58: - | R58: - | U58: - | X58: - | AA58: - | AD58: - | AG58: - | AJ58: - | AM58: - | AP58: - | AR58: =SUM(AO58,AL58,AI58,AF58,AC58,Z58,W58,T58,Q58,N58,K58,H58,E58,B58)-SUM(AQ58,AN58,AK58,AH58,AE58,AB58,Y58,V58,S58,P58,M58,J58,G58,D58) -> 0 | AT58: =AR58+BI58+BM58+BO58 -> 0 | AV58: =BE58 -> 闪避 | AY58: =BC58 -> 0 | BA58: ☐ | BC58: =IF(ISTEXT(IFERROR(VLOOKUP(人物卡!BE58,人物卡!$DI$25:$DQ$29,1,FALSE),IFERROR(VLOOKUP(人物卡!BE58,人物卡!$CZ$25:$DB$29,1,FALSE),0))),"★",INDEX(本职技能!$A$2:$IC$87,MATCH(人物卡!BE58,本职技能!$A$2:$A$87,0),MATCH(人物卡!$BL$11,本职技能!$A$1:$IC$1,0))) -> 0 | BE58: 闪避 | BI58: =IFERROR(INT(DEXA/2),0) -> 0 | BK58: =AR58 -> 0 | BQ58: =SUM(BI58:BO58) -> 0 | BS58: =INT(BQ58/2) -> 0 | BU58: =INT(BQ58/5) -> 0 | BW58: ☐ | BY58: =IF(ISTEXT(IFERROR(VLOOKUP(人物卡!CA58,人物卡!$DI$25:$DQ$29,1,FALSE),IFERROR(VLOOKUP(人物卡!CA58,人物卡!$CZ$25:$DB$29,1,FALSE),0))),"★",INDEX(本职技能!$A$2:$IC$87,MATCH(人物卡!CA58,本职技能!$A$2:$A$87,0),MATCH(人物卡!$BL$11,本职技能!$A$1:$IC$1,0))) -> 0 | CA58: 投掷 | CE58: 20 | CG58: =AR98 -> 0 | CM58: =SUM(CE58:CK58) -> 20 | CO58: =INT(CM58/2) -> 10 | CQ58: =INT(CM58/5) -> 4
C59: - | F59: - | I59: - | L59: - | O59: - | R59: - | U59: - | X59: - | AA59: - | AD59: - | AG59: - | AJ59: - | AM59: - | AP59: - | AR59: =SUM(AO59,AL59,AI59,AF59,AC59,Z59,W59,T59,Q59,N59,K59,H59,E59,B59)-SUM(AQ59,AN59,AK59,AH59,AE59,AB59,Y59,V59,S59,P59,M59,J59,G59,D59) -> 0 | AT59: =AR59+BI59+BM59+BO59 -> 25 | AV59: 格斗:斗殴 | AY59: =BC59 -> 0 | BA59: ☐ | BC59: =IF(ISTEXT(IFERROR(VLOOKUP(人物卡!BE59,人物卡!$DI$25:$DQ$29,1,FALSE),IFERROR(VLOOKUP(人物卡!BE59,人物卡!$CZ$25:$DB$29,1,FALSE),0))),"★",INDEX(本职技能!$A$2:$IC$87,MATCH(人物卡!BE59,本职技能!$A$2:$A$87,0),MATCH(人物卡!$BL$11,本职技能!$A$1:$IC$1,0))) -> 0 | BE59: 格斗： | BG59: 斗殴 | BI59: 25 | BK59: =AR59 -> 0 | BQ59: =SUM(BI59:BO59) -> 25 | BS59: =INT(BQ59/2) -> 12 | BU59: =INT(BQ59/5) -> 5 | BW59: ☐ | BY59: =IF(ISTEXT(IFERROR(VLOOKUP(人物卡!CA59,人物卡!$DI$25:$DQ$29,1,FALSE),IFERROR(VLOOKUP(人物卡!CA59,人物卡!$CZ$25:$DB$29,1,FALSE),0))),"★",INDEX(本职技能!$A$2:$IC$87,MATCH(人物卡!CA59,本职技能!$A$2:$A$87,0),MATCH(人物卡!$BL$11,本职技能!$A$1:$IC$1,0))) -> 0 | CA59: 射击： | CC59: 手枪 | CE59: 20 | CG59: =AR99 -> 0 | CM59: =SUM(CE59:CK59) -> 20 | CO59: =INT(CM59/2) -> 10 | CQ59: =INT(CM59/5) -> 4
C60: - | F60: - | I60: - | L60: - | O60: - | R60: - | U60: - | X60: - | AA60: - | AD60: - | AG60: - | AJ60: - | AM60: - | AP60: - | AR60: =SUM(AO60,AL60,AI60,AF60,AC60,Z60,W60,T60,Q60,N60,K60,H60,E60,B60)-SUM(AQ60,AN60,AK60,AH60,AE60,AB60,Y60,V60,S60,P60,M60,J60,G60,D60) -> 0 | AT60: =AR60+BI60+BM60+BO60 -> 0 | AV60: =IF(BG60=0,"格斗:","格斗:"&BG60) -> 格斗: | AY60: =BC60 -> 0 | BA60: ☐ | BC60: =IF(ISTEXT(IFERROR(VLOOKUP(人物卡!BE60,人物卡!$DI$25:$DQ$29,1,FALSE),IFERROR(VLOOKUP(人物卡!BE60,人物卡!$CZ$25:$DB$29,1,FALSE),0))),"★",INDEX(本职技能!$A$2:$IC$87,MATCH(人物卡!BE60,本职技能!$A$2:$A$87,0),MATCH(人物卡!$BL$11,本职技能!$A$1:$IC$1,0))) -> 0 | BE60: 格斗① | BI60: =附表!Z14 -> 0 | BK60: =AR60 -> 0 | BQ60: =BI60+BK60+BM60+BO60 -> 0 | BS60: =INT(BQ60/2) -> 0 | BU60: =INT(BQ60/5) -> 0 | BW60: ☐ | BY60: =IF(ISTEXT(IFERROR(VLOOKUP(人物卡!CA60,人物卡!$DI$25:$DQ$29,1,FALSE),IFERROR(VLOOKUP(人物卡!CA60,人物卡!$CZ$25:$DB$29,1,FALSE),0))),"★",INDEX(本职技能!$A$2:$IC$87,MATCH(人物卡!CA60,本职技能!$A$2:$A$87,0),MATCH(人物卡!$BL$11,本职技能!$A$1:$IC$1,0))) -> 0 | CA60: 射击① | CE60: =附表!AB14 -> 0 | CG60: =AR100 -> 0 | CM60: =CK60+CI60+CG60+CE60 -> 0 | CO60: =INT(CM60/2) -> 0 | CQ60: =INT(CM60/5) -> 0
C61: - | F61: - | I61: - | L61: - | O61: - | R61: - | U61: - | X61: - | AA61: - | AD61: - | AG61: - | AJ61: - | AM61: - | AP61: - | AR61: =SUM(AO61,AL61,AI61,AF61,AC61,Z61,W61,T61,Q61,N61,K61,H61,E61,B61)-SUM(AQ61,AN61,AK61,AH61,AE61,AB61,Y61,V61,S61,P61,M61,J61,G61,D61) -> 0 | AT61: =AR61+BI61+BM61+BO61 -> 0 | AV61: =IF(BG61=0,"格斗:","格斗:"&BG61) -> 格斗: | AY61: =BC61 -> 0 | BA61: ☐ | BC61: =IF(ISTEXT(IFERROR(VLOOKUP(人物卡!BE61,人物卡!$DI$25:$DQ$29,1,FALSE),IFERROR(VLOOKUP(人物卡!BE61,人物卡!$CZ$25:$DB$29,1,FALSE),0))),"★",INDEX(本职技能!$A$2:$IC$87,MATCH(人物卡!BE61,本职技能!$A$2:$A$87,0),MATCH(人物卡!$BL$11,本职技能!$A$1:$IC$1,0))) -> 0 | BE61: 格斗② | BI61: =附表!Z15 -> 0 | BK61: =AR61 -> 0 | BQ61: =BI61+BK61+BO61+BM61 -> 0 | BS61: =INT(BQ61/2) -> 0 | BU61: =INT(BQ61/5) -> 0 | BW61: ☐ | BY61: =IF(ISTEXT(IFERROR(VLOOKUP(人物卡!CA61,人物卡!$DI$25:$DQ$29,1,FALSE),IFERROR(VLOOKUP(人物卡!CA61,人物卡!$CZ$25:$DB$29,1,FALSE),0))),"★",INDEX(本职技能!$A$2:$IC$87,MATCH(人物卡!CA61,本职技能!$A$2:$A$87,0),MATCH(人物卡!$BL$11,本职技能!$A$1:$IC$1,0))) -> 0 | CA61: 射击② | CE61: =附表!AB15 -> 0 | CG61: =AR101 -> 0 | CM61: =CK61+CI61+CG61+CE61 -> 0 | CO61: =INT(CM61/2) -> 0 | CQ61: =INT(CM61/5) -> 0
C62: - | F62: - | I62: - | L62: - | O62: - | R62: - | U62: - | X62: - | AA62: - | AD62: - | AG62: - | AJ62: - | AM62: - | AP62: - | AR62: =SUM(AO62,AL62,AI62,AF62,AC62,Z62,W62,T62,Q62,N62,K62,H62,E62,B62)-SUM(AQ62,AN62,AK62,AH62,AE62,AB62,Y62,V62,S62,P62,M62,J62,G62,D62) -> 0 | AT62: =AR62+BI62+BM62+BO62 -> 0 | AV62: =IF(BG62=0,"格斗:","格斗:"&BG62) -> 格斗: | AY62: =BC62 -> 0 | BA62: ☐ | BC62: =IF(ISTEXT(IFERROR(VLOOKUP(人物卡!BE62,人物卡!$DI$25:$DQ$29,1,FALSE),IFERROR(VLOOKUP(人物卡!BE62,人物卡!$CZ$25:$DB$29,1,FALSE),0))),"★",INDEX(本职技能!$A$2:$IC$87,MATCH(人物卡!BE62,本职技能!$A$2:$A$87,0),MATCH(人物卡!$BL$11,本职技能!$A$1:$IC$1,0))) -> 0 | BE62: 格斗③ | BI62: =附表!Z16 -> 0 | BK62: =AR62 -> 0 | BQ62: =BO62+BM62+BK62+BI62 -> 0 | BS62: =INT(BQ62/2) -> 0 | BU62: =INT(BQ62/5) -> 0 | BW62: ☐ | BY62: =IF(ISTEXT(IFERROR(VLOOKUP(人物卡!CA62,人物卡!$DI$25:$DQ$29,1,FALSE),IFERROR(VLOOKUP(人物卡!CA62,人物卡!$CZ$25:$DB$29,1,FALSE),0))),"★",INDEX(本职技能!$A$2:$IC$87,MATCH(人物卡!CA62,本职技能!$A$2:$A$87,0),MATCH(人物卡!$BL$11,本职技能!$A$1:$IC$1,0))) -> 0 | CA62: 射击③ | CE62: =附表!AB16 -> 0 | CG62: =AR102 -> 0 | CM62: =CK62+CI62+CG62+CE62 -> 0 | CO62: =INT(CM62/2) -> 0 | CQ62: =INT(CM62/5) -> 0
C63: - | F63: - | I63: - | L63: - | O63: - | R63: - | U63: - | X63: - | AA63: - | AD63: - | AG63: - | AJ63: - | AM63: - | AP63: - | AR63: =SUM(AO63,AL63,AI63,AF63,AC63,Z63,W63,T63,Q63,N63,K63,H63,E63,B63)-SUM(AQ63,AN63,AK63,AH63,AE63,AB63,Y63,V63,S63,P63,M63,J63,G63,D63) -> 0 | AT63: =AR63+BI63+BM63+BO63 -> 0 | AV63: =IF(BG63=0,"格斗:","格斗:"&BG63) -> 格斗: | AY63: =BC63 -> 0 | BA63: ☐ | BC63: =IF(ISTEXT(IFERROR(VLOOKUP(人物卡!BE63,人物卡!$DI$25:$DQ$29,1,FALSE),IFERROR(VLOOKUP(人物卡!BE63,人物卡!$CZ$25:$DB$29,1,FALSE),0))),"★",INDEX(本职技能!$A$2:$IC$87,MATCH(人物卡!BE63,本职技能!$A$2:$A$87,0),MATCH(人物卡!$BL$11,本职技能!$A$1:$IC$1,0))) -> 0 | BE63: 格斗④ | BI63: =附表!Z17 -> 0 | BK63: =AR63 -> 0 | BQ63: =BI63+BK63+BO63+BM63 -> 0 | BS63: =INT(BQ63/2) -> 0 | BU63: =INT(BQ63/5) -> 0 | BW63: ☐ | BY63: =IF(ISTEXT(IFERROR(VLOOKUP(人物卡!CA63,人物卡!$DI$25:$DQ$29,1,FALSE),IFERROR(VLOOKUP(人物卡!CA63,人物卡!$CZ$25:$DB$29,1,FALSE),0))),"★",INDEX(本职技能!$A$2:$IC$87,MATCH(人物卡!CA63,本职技能!$A$2:$A$87,0),MATCH(人物卡!$BL$11,本职技能!$A$1:$IC$1,0))) -> 0 | CA63: 射击④ | CE63: =附表!AB17 -> 0 | CG63: =AR103 -> 0 | CM63: =CK63+CI63+CG63+CE63 -> 0 | CO63: =INT(CM63/2) -> 0 | CQ63: =INT(CM63/5) -> 0
C64: - | F64: - | I64: - | L64: - | O64: - | R64: - | U64: - | X64: - | AA64: - | AD64: - | AG64: - | AJ64: - | AM64: - | AP64: - | AR64: =SUM(AO64,AL64,AI64,AF64,AC64,Z64,W64,T64,Q64,N64,K64,H64,E64,B64)-SUM(AQ64,AN64,AK64,AH64,AE64,AB64,Y64,V64,S64,P64,M64,J64,G64,D64) -> 0 | AT64: =AR64+BI64+BM64+BO64 -> 0 | AV64: =IF(BG64=0,"格斗:","格斗:"&BG64) -> 格斗: | AY64: =BC64 -> 0 | BA64: ☐ | BC64: =IF(ISTEXT(IFERROR(VLOOKUP(人物卡!BE64,人物卡!$DI$25:$DQ$29,1,FALSE),IFERROR(VLOOKUP(人物卡!BE64,人物卡!$CZ$25:$DB$29,1,FALSE),0))),"★",INDEX(本职技能!$A$2:$IC$87,MATCH(人物卡!BE64,本职技能!$A$2:$A$87,0),MATCH(人物卡!$BL$11,本职技能!$A$1:$IC$1,0))) -> 0 | BE64: 格斗⑤ | BI64: =附表!Z18 -> 0 | BK64: =AR64 -> 0 | BQ64: =BO64+BM64+BK64+BI64 -> 0 | BS64: =INT(BQ64/2) -> 0 | BU64: =INT(BQ64/5) -> 0 | BW64: ☐ | BY64: =IF(ISTEXT(IFERROR(VLOOKUP(人物卡!CA64,人物卡!$DI$25:$DQ$29,1,FALSE),IFERROR(VLOOKUP(人物卡!CA64,人物卡!$CZ$25:$DB$29,1,FALSE),0))),"★",INDEX(本职技能!$A$2:$IC$87,MATCH(人物卡!CA64,本职技能!$A$2:$A$87,0),MATCH(人物卡!$BL$11,本职技能!$A$1:$IC$1,0))) -> 0 | CA64: 射击⑤ | CE64: =附表!AB18 -> 0 | CG64: =AR104 -> 0 | CM64: =CK64+CI64+CG64+CE64 -> 0 | CO64: =INT(CM64/2) -> 0 | CQ64: =INT(CM64/5) -> 0
C65: - | F65: - | I65: - | L65: - | O65: - | R65: - | U65: - | X65: - | AA65: - | AD65: - | AG65: - | AJ65: - | AM65: - | AP65: - | AR65: =SUM(AO65,AL65,AI65,AF65,AC65,Z65,W65,T65,Q65,N65,K65,H65,E65,B65)-SUM(AQ65,AN65,AK65,AH65,AE65,AB65,Y65,V65,S65,P65,M65,J65,G65,D65) -> 0 | AT65: =AR65+CE25+CI25+CK25 -> 1 | AV65: =CA25 -> 锁匠 | AY65: =BY25 -> 0 | BA65: =IF(BL11=0,"","职业信用范围："&LOOKUP(BL11,职业列表!A2:A237,职业列表!D2:D237)) | BI65: =IF(BL11=0,"","本职属性："&附表!J52&" ")&IF(BL11=0,"",IF(AND(附表!J53-SUM(BM26:BN64,CI25:CJ64)=0,INTA+INTA-SUM(BO25:BP64,CK25:CL64)=0),"",("剩余职业点="&附表!M52&" 剩余兴趣点="&附表!M54&IF(BE148=附表!B26,""," 剩余经历包点="&IF(ISNUMBER(附表!D34),附表!D34-SUM(BK25:BL64,CG25:CH64),附表!D34)))))
C66: - | F66: - | I66: - | L66: - | O66: - | R66: - | U66: - | X66: - | AA66: - | AD66: - | AG66: - | AJ66: - | AM66: - | AP66: - | AR66: =SUM(AO66,AL66,AI66,AF66,AC66,Z66,W66,T66,Q66,N66,K66,H66,E66,B66)-SUM(AQ66,AN66,AK66,AH66,AE66,AB66,Y66,V66,S66,P66,M66,J66,G66,D66) -> 0 | AT66: =AR66+CE26+CI26+CK26 -> 5 | AV66: =CA26 -> 乔装 | AY66: =BY26 -> 0 | BA66: 武器表 | CN66: 格斗
C67: - | F67: - | I67: - | L67: - | O67: - | R67: - | U67: - | X67: - | AA67: - | AD67: - | AG67: - | AJ67: - | AM67: - | AP67: - | AR67: =SUM(AO67,AL67,AI67,AF67,AC67,Z67,W67,T67,Q67,N67,K67,H67,E67,B67)-SUM(AQ67,AN67,AK67,AH67,AE67,AB67,Y67,V67,S67,P67,M67,J67,G67,D67) -> 0 | AT67: =AR67+CE27+CI27+CK27 -> 10 | AV67: =CA27 -> 妙手 | AY67: =BY27 -> 0 | BA67: 武器名称 | BF67: 类型 | BK67: 使用技能 | BO67: 成功率 | BU67: 伤害 | BY67: 基础射程 | CA67: 贯穿 | CC67: 次数 | CE67: 装弹量 | CH67: 故障值 | CJ67: 参考价值 | CN67: 加值 DB | CP67: =附表!P9 -> 0
C68: - | F68: - | I68: - | L68: - | O68: - | R68: - | U68: - | X68: - | AA68: - | AD68: - | AG68: - | AJ68: - | AM68: - | AP68: - | AR68: =SUM(AO68,AL68,AI68,AF68,AC68,Z68,W68,T68,Q68,N68,K68,H68,E68,B68)-SUM(AQ68,AN68,AK68,AH68,AE68,AB68,Y68,V68,S68,P68,M68,J68,G68,D68) -> 0 | AT68: =AR68+CE28+CI28+CK28 -> 20 | AV68: =CA28 -> 潜行 | AY68: =BY28 -> 0 | BA68: 无 | BF68: 肉搏 | BK68: 斗殴 | BO68: =BQ59 -> 25 | BQ68: =INT(BO68/2) -> 12 | BS68: =INT(BO68/5) -> 5 | BU68: 1D3+DB | BY68: —— | CA68: × | CC68: 1 | CE68: —— | CH68: —— | CJ68: —— | CT68: 杂项
C69: - | F69: - | I69: - | L69: - | O69: - | R69: - | U69: - | X69: - | AA69: - | AD69: - | AG69: - | AJ69: - | AM69: - | AP69: - | AR69: =SUM(AO69,AL69,AI69,AF69,AC69,Z69,W69,T69,Q69,N69,K69,H69,E69,B69)-SUM(AQ69,AN69,AK69,AH69,AE69,AB69,Y69,V69,S69,P69,M69,J69,G69,D69) -> 0 | AT69: =AR69+CE29+CI29+CK29 -> 20 | AV69: =CA29 -> 图书馆使用 | AY69: =BY29 -> 0 | BK69: =IF($BF69=0,"←请选择类型",VLOOKUP($BF69,'武器列表 战斗'!$B$2:$I$121,2,FALSE)) -> ←请选择类型 | BO69: =附表!BG5 | BQ69: =IF(BO69="","",INT(BO69/2)) | BS69: =IF(BO69="","",INT(BO69/5)) | BU69: =IF(BF69="武术",IF(BO69<21,"1D2+半DB",IF(BO69<41,"1D3+半DB",IF(BO69<61,"1D4+DB",IF(BO69<81,"1D4+1+DB",IF(BO69<91,"1D4+2+DB",IF(BO69<95,"1D4+3+DB","1D4+4+DB")))))),IF($BF69=0,"",VLOOKUP($BF69,'武器列表 战斗'!$B$2:$I$121,3,FALSE))) | BY69: =IF($BF69=0,"",VLOOKUP($BF69,'武器列表 战斗'!$B$2:$I$121,4,FALSE)) | CA69: =IF($BF69=0,"",VLOOKUP($BF69,'武器列表 战斗'!$B$2:$I$121,5,FALSE)) | CC69: =IF(BF69="武术",IF(BO69<91,1,2),IF($BF69=0,"",VLOOKUP($BF69,'武器列表 战斗'!$B$2:$I$121,6,FALSE))) | CE69: =IF($BF69=0,"",VLOOKUP($BF69,'武器列表 战斗'!$B$2:$I$121,7,FALSE)) | CH69: =IF($BF69=0,"",VLOOKUP($BF69,'武器列表 战斗'!$B$2:$I$121,8,FALSE)) | CJ69: =IF($BF69=0,"",VLOOKUP($BF69,'武器列表 战斗'!$B$2:$K$121,10,FALSE)) | CT69: =附表!AP22 -> #N/A
C70: - | F70: - | I70: - | L70: - | O70: - | R70: - | U70: - | X70: - | AA70: - | AD70: - | AG70: - | AJ70: - | AM70: - | AP70: - | AR70: =SUM(AO70,AL70,AI70,AF70,AC70,Z70,W70,T70,Q70,N70,K70,H70,E70,B70)-SUM(AQ70,AN70,AK70,AH70,AE70,AB70,Y70,V70,S70,P70,M70,J70,G70,D70) -> 0 | AT70: =AR70+CE30+CI30+CK30 -> 20 | AV70: =CA30 -> 聆听 | AY70: =BY30 -> 0 | BK70: =IF($BF70=0,IF(BK69="←请选择类型","","←请选择类型"),VLOOKUP($BF70,'武器列表 战斗'!$B$2:$I$121,2,FALSE)) | BO70: =附表!BG6 | BQ70: =IF(BO70="","",INT(BO70/2)) | BS70: =IF(BO70="","",INT(BO70/5)) | BU70: =IF(BF70="武术",IF(BO70<21,"1D2+半DB",IF(BO70<41,"1D3+半DB",IF(BO70<61,"1D4+DB",IF(BO70<81,"1D4+1+DB",IF(BO70<91,"1D4+2+DB",IF(BO70<95,"1D4+3+DB","1D4+4+DB")))))),IF($BF70=0,"",VLOOKUP($BF70,'武器列表 战斗'!$B$2:$I$121,3,FALSE))) | BY70: =IF($BF70=0,"",VLOOKUP($BF70,'武器列表 战斗'!$B$2:$I$121,4,FALSE)) | CA70: =IF($BF70=0,"",VLOOKUP($BF70,'武器列表 战斗'!$B$2:$I$121,5,FALSE)) | CC70: =IF(BF70="武术",IF(BO70<91,1,2),IF($BF70=0,"",VLOOKUP($BF70,'武器列表 战斗'!$B$2:$I$121,6,FALSE))) | CE70: =IF($BF70=0,"",VLOOKUP($BF70,'武器列表 战斗'!$B$2:$I$121,7,FALSE)) | CH70: =IF($BF70=0,"",VLOOKUP($BF70,'武器列表 战斗'!$B$2:$I$121,8,FALSE)) | CJ70: =IF($BF70=0,"",VLOOKUP($BF70,'武器列表 战斗'!$B$2:$K$121,10,FALSE)) | CN70: 体格 Build | CP70: =附表!P7 -> 0
C71: - | F71: - | I71: - | L71: - | O71: - | R71: - | U71: - | X71: - | AA71: - | AD71: - | AG71: - | AJ71: - | AM71: - | AP71: - | AR71: =SUM(AO71,AL71,AI71,AF71,AC71,Z71,W71,T71,Q71,N71,K71,H71,E71,B71)-SUM(AQ71,AN71,AK71,AH71,AE71,AB71,Y71,V71,S71,P71,M71,J71,G71,D71) -> 0 | AT71: =AR71+CE31+CI31+CK31 -> 25 | AV71: =CA31 -> 侦查 | AY71: =BY31 -> 0 | BK71: =IF($BF71=0,IF(OR(BK69="←请选择类型",BK70="←请选择类型"),"","←请选择类型"),VLOOKUP($BF71,'武器列表 战斗'!$B$2:$I$121,2,FALSE)) | BO71: =附表!BG7 | BQ71: =IF(BO71="","",INT(BO71/2)) | BS71: =IF(BO71="","",INT(BO71/5)) | BU71: =IF(BF71="武术",IF(BO71<21,"1D2+半DB",IF(BO71<41,"1D3+半DB",IF(BO71<61,"1D4+DB",IF(BO71<81,"1D4+1+DB",IF(BO71<91,"1D4+2+DB",IF(BO71<95,"1D4+3+DB","1D4+4+DB")))))),IF($BF71=0,"",VLOOKUP($BF71,'武器列表 战斗'!$B$2:$I$121,3,FALSE))) | BY71: =IF($BF71=0,"",VLOOKUP($BF71,'武器列表 战斗'!$B$2:$I$121,4,FALSE)) | CA71: =IF($BF71=0,"",VLOOKUP($BF71,'武器列表 战斗'!$B$2:$I$121,5,FALSE)) | CC71: =IF(BF71="武术",IF(BO71<91,1,2),IF($BF71=0,"",VLOOKUP($BF71,'武器列表 战斗'!$B$2:$I$121,6,FALSE))) | CE71: =IF($BF71=0,"",VLOOKUP($BF71,'武器列表 战斗'!$B$2:$I$121,7,FALSE)) | CH71: =IF($BF71=0,"",VLOOKUP($BF71,'武器列表 战斗'!$B$2:$I$121,8,FALSE)) | CJ71: =IF($BF71=0,"",VLOOKUP($BF71,'武器列表 战斗'!$B$2:$K$121,10,FALSE))
C72: - | F72: - | I72: - | L72: - | O72: - | R72: - | U72: - | X72: - | AA72: - | AD72: - | AG72: - | AJ72: - | AM72: - | AP72: - | AR72: =SUM(AO72,AL72,AI72,AF72,AC72,Z72,W72,T72,Q72,N72,K72,H72,E72,B72)-SUM(AQ72,AN72,AK72,AH72,AE72,AB72,Y72,V72,S72,P72,M72,J72,G72,D72) -> 0 | AT72: =AR72+CE32+CI32+CK32 -> 10 | AV72: =CA32 -> 追踪 | AY72: =BY32 -> 0 | BK72: =IF($BF72=0,"",VLOOKUP($BF72,'武器列表 战斗'!$B$2:$I$121,2,FALSE)) | BO72: =附表!BG8 | BQ72: =IF(BO72="","",INT(BO72/2)) | BS72: =IF(BO72="","",INT(BO72/5)) | BU72: =IF(BF72="武术",IF(BO72<21,"1D2+半DB",IF(BO72<41,"1D3+半DB",IF(BO72<61,"1D4+DB",IF(BO72<81,"1D4+1+DB",IF(BO72<91,"1D4+2+DB",IF(BO72<95,"1D4+3+DB","1D4+4+DB")))))),IF($BF72=0,"",VLOOKUP($BF72,'武器列表 战斗'!$B$2:$I$121,3,FALSE))) | BY72: =IF($BF72=0,"",VLOOKUP($BF72,'武器列表 战斗'!$B$2:$I$121,4,FALSE)) | CA72: =IF($BF72=0,"",VLOOKUP($BF72,'武器列表 战斗'!$B$2:$I$121,5,FALSE)) | CC72: =IF(BF72="武术",IF(BO72<91,1,2),IF($BF72=0,"",VLOOKUP($BF72,'武器列表 战斗'!$B$2:$I$121,6,FALSE))) | CE72: =IF($BF72=0,"",VLOOKUP($BF72,'武器列表 战斗'!$B$2:$I$121,7,FALSE)) | CH72: =IF($BF72=0,"",VLOOKUP($BF72,'武器列表 战斗'!$B$2:$I$121,8,FALSE)) | CJ72: =IF($BF72=0,"",VLOOKUP($BF72,'武器列表 战斗'!$B$2:$K$121,10,FALSE)) | CN72: 闪避 Dodge | CP72: =BQ58 -> 0 | CR72: =BS58 -> 0
C73: - | F73: - | I73: - | L73: - | O73: - | R73: - | U73: - | X73: - | AA73: - | AD73: - | AG73: - | AJ73: - | AM73: - | AP73: - | AR73: =SUM(AO73,AL73,AI73,AF73,AC73,Z73,W73,T73,Q73,N73,K73,H73,E73,B73)-SUM(AQ73,AN73,AK73,AH73,AE73,AB73,Y73,V73,S73,P73,M73,J73,G73,D73) -> 0 | AT73: =AR73+CE33+CI33+CK33 -> 10 | AV73: =CA33 -> 导航 | AY73: =BY33 -> 0 | BK73: =IF($BF73=0,"",VLOOKUP($BF73,'武器列表 战斗'!$B$2:$I$121,2,FALSE)) | BO73: =附表!BG9 | BQ73: =IF(BO73="","",INT(BO73/2)) | BS73: =IF(BO73="","",INT(BO73/5)) | BU73: =IF(BF73="武术",IF(BO73<21,"1D2+半DB",IF(BO73<41,"1D3+半DB",IF(BO73<61,"1D4+DB",IF(BO73<81,"1D4+1+DB",IF(BO73<91,"1D4+2+DB",IF(BO73<95,"1D4+3+DB","1D4+4+DB")))))),IF($BF73=0,"",VLOOKUP($BF73,'武器列表 战斗'!$B$2:$I$121,3,FALSE))) | BY73: =IF($BF73=0,"",VLOOKUP($BF73,'武器列表 战斗'!$B$2:$I$121,4,FALSE)) | CA73: =IF($BF73=0,"",VLOOKUP($BF73,'武器列表 战斗'!$B$2:$I$121,5,FALSE)) | CC73: =IF(BF73="武术",IF(BO73<91,1,2),IF($BF73=0,"",VLOOKUP($BF73,'武器列表 战斗'!$B$2:$I$121,6,FALSE))) | CE73: =IF($BF73=0,"",VLOOKUP($BF73,'武器列表 战斗'!$B$2:$I$121,7,FALSE)) | CH73: =IF($BF73=0,"",VLOOKUP($BF73,'武器列表 战斗'!$B$2:$I$121,8,FALSE)) | CJ73: =IF($BF73=0,"",VLOOKUP($BF73,'武器列表 战斗'!$B$2:$K$121,10,FALSE)) | CR73: =BU58 -> 0
C74: - | F74: - | I74: - | L74: - | O74: - | R74: - | U74: - | X74: - | AA74: - | AD74: - | AG74: - | AJ74: - | AM74: - | AP74: - | AR74: =SUM(AO74,AL74,AI74,AF74,AC74,Z74,W74,T74,Q74,N74,K74,H74,E74,B74)-SUM(AQ74,AN74,AK74,AH74,AE74,AB74,Y74,V74,S74,P74,M74,J74,G74,D74) -> 0 | AT74: =AR74+CE34+CI34+CK34 -> 10 | AV74: =CA34 -> 心理学 | AY74: =BY34 -> 0 | BA74: 注意：填写进表格内的物品才有可能使用于模组中，请仔细填写 | BV74: 请根据【属性简要】和【角色职业】填写【长相】和【穿着】
C75: - | F75: - | I75: - | L75: - | O75: - | R75: - | U75: - | X75: - | AA75: - | AD75: - | AG75: - | AJ75: - | AM75: - | AP75: - | AR75: =SUM(AO75,AL75,AI75,AF75,AC75,Z75,W75,T75,Q75,N75,K75,H75,E75,B75)-SUM(AQ75,AN75,AK75,AH75,AE75,AB75,Y75,V75,S75,P75,M75,J75,G75,D75) -> 0 | AT75: =AR75+CE35+CI35+CK35 -> 15 | AV75: =CA35 -> 取悦 | AY75: =BY35 -> 0 | BA75: 资产 | BV75: =附表!N106 -> 形象未填写！ | CC75: 背景故事 | CQ75: 关键
C76: - | F76: - | I76: - | L76: - | O76: - | R76: - | U76: - | X76: - | AA76: - | AD76: - | AG76: - | AJ76: - | AM76: - | AP76: - | AR76: =SUM(AO76,AL76,AI76,AF76,AC76,Z76,W76,T76,Q76,N76,K76,H76,E76,B76)-SUM(AQ76,AN76,AK76,AH76,AE76,AB76,Y76,V76,S76,P76,M76,J76,G76,D76) -> 0 | AT76: =AR76+CE36+CI36+CK36 -> 5 | AV76: =CA36 -> 话术 | AY76: =BY36 -> 0 | BA76: 信用评级 | BE76: 生活水平 | BH76: 消费水平 | BK76: 其他资产 | BN76: 当前现金($) | BR76: 单位 | BV76: 形象描述 | BY76: 腐化 | CA76: 外貌 | CQ76: ☐
C77: - | F77: - | I77: - | L77: - | O77: - | R77: - | U77: - | X77: - | AA77: - | AD77: - | AG77: - | AJ77: - | AM77: - | AP77: - | AR77: =SUM(AO77,AL77,AI77,AF77,AC77,Z77,W77,T77,Q77,N77,K77,H77,E77,B77)-SUM(AQ77,AN77,AK77,AH77,AE77,AB77,Y77,V77,S77,P77,M77,J77,G77,D77) -> 0 | AT77: =AR77+CE37+CI37+CK37 -> 15 | AV77: =CA37 -> 恐吓 | AY77: =BY37 -> 0 | BA77: =附表!Z223 -> 0%/0%/0% | BE77: =附表!Z225 -> 身无分文 | BH77: =附表!AE240 -> 0.5 | BK77: =附表!AG240 -> 没有 | BN77: =附表!AF240 -> 0.5 | BR77: =BL13 -> 美元 | BY77: ☐ | CA77: 穿着
C78: - | F78: - | I78: - | L78: - | O78: - | R78: - | U78: - | X78: - | AA78: - | AD78: - | AG78: - | AJ78: - | AM78: - | AP78: - | AR78: =SUM(AO78,AL78,AI78,AF78,AC78,Z78,W78,T78,Q78,N78,K78,H78,E78,B78)-SUM(AQ78,AN78,AK78,AH78,AE78,AB78,Y78,V78,S78,P78,M78,J78,G78,D78) -> 0 | AT78: =AR78+CE38+CI38+CK38 -> 10 | AV78: =CA38 -> 说服 | AY78: =BY38 -> 0 | BA78: =IF(BQ33<=0,"连贫穷都够不上的人才能够叫做身无分文。住所：大概只有睡大街。旅行：步行，扒车或逃票上火车轮船。",IF(BQ33<=9,"刚好买得起最廉价的屋顶，每天能够吃到一餐廉价食物。住所：最最最廉价的出租屋或睡袋旅馆。旅行：最便宜的公众运输方式。反正只要赶便宜就对了，与之相伴的是不可靠。",IF(BQ33<=49,"舒适的生活水平，一日三餐，偶尔下馆子。住所：普通的家或公寓，无论是租赁还是自购。外出住普通的旅馆。旅行：会使用普通的旅行方式，不会用最高级。在现代来看，大概会有一辆自己的小车。",IF(BQ33<=89,"小康级别已经可以享受奢侈品的舒适了。住所：真材实料的住地，也许会有一些仆人（管家，主妇，清洁工，园丁，等等）。乡下估计还有小别墅。会住昂贵的宾馆。旅行：头等舱。会买高档车或同等的交通工具。",IF(BQ33<=98,"富裕级别就是享受超级奢侈品的时候了。住所：豪华住所和有着大量仆人的庭院。乡下和别处有着别墅是定番。住总统套房。旅行：头等舱。现代社会估摸还会有很多豪车。",IF(BQ33=99,"与富裕差不多，但钱已经只是一个代号了。你将是世界上最富有的人。","请正确分配您的技能点！")))))) -> 连贫穷都够不上的人才能够叫做身无分文。住所：大概只有睡大街。旅行：步行，扒车或逃票上火车轮船。 | BV78: 思想与信念 | BY78: 腐化 | CA78: 信条 | CQ78: ☐
C79: - | F79: - | I79: - | L79: - | O79: - | R79: - | U79: - | X79: - | AA79: - | AD79: - | AG79: - | AJ79: - | AM79: - | AP79: - | AR79: =SUM(AO79,AL79,AI79,AF79,AC79,Z79,W79,T79,Q79,N79,K79,H79,E79,B79)-SUM(AQ79,AN79,AK79,AH79,AE79,AB79,Y79,V79,S79,P79,M79,J79,G79,D79) -> 0 | AT79: =AR79+CE39+CI39+CK39 -> 20 | AV79: =CA39 -> 跳跃 | AY79: =BY39 -> 0 | BY79: ☐ | CA79: 剖析
C80: - | F80: - | I80: - | L80: - | O80: - | R80: - | U80: - | X80: - | AA80: - | AD80: - | AG80: - | AJ80: - | AM80: - | AP80: - | AR80: =SUM(AO80,AL80,AI80,AF80,AC80,Z80,W80,T80,Q80,N80,K80,H80,E80,B80)-SUM(AQ80,AN80,AK80,AH80,AE80,AB80,Y80,V80,S80,P80,M80,J80,G80,D80) -> 0 | AT80: =AR80+CE40+CI40+CK40 -> 20 | AV80: =CA40 -> 攀爬 | AY80: =BY40 -> 0 | BV80: 重要之人 | BY80: 腐化 | CA80: 人名 | CQ80: ☐
C81: - | F81: - | I81: - | L81: - | O81: - | R81: - | U81: - | X81: - | AA81: - | AD81: - | AG81: - | AJ81: - | AM81: - | AP81: - | AR81: =SUM(AO81,AL81,AI81,AF81,AC81,Z81,W81,T81,Q81,N81,K81,H81,E81,B81)-SUM(AQ81,AN81,AK81,AH81,AE81,AB81,Y81,V81,S81,P81,M81,J81,G81,D81) -> 0 | AT81: =AR81+CE41+CI41+CK41 -> 10 | AV81: =IF(CC41=0,"生存:","生:"&CC41) -> 生存: | AY81: =BY41 -> 0 | BY81: ☐ | CA81: 缘由
C82: - | F82: - | I82: - | L82: - | O82: - | R82: - | U82: - | X82: - | AA82: - | AD82: - | AG82: - | AJ82: - | AM82: - | AP82: - | AR82: =SUM(AO82,AL82,AI82,AF82,AC82,Z82,W82,T82,Q82,N82,K82,H82,E82,B82)-SUM(AQ82,AN82,AK82,AH82,AE82,AB82,Y82,V82,S82,P82,M82,J82,G82,D82) -> 0 | AT82: =AR82+CE42+CI42+CK42 -> 10 | AV82: =IF(CC42=0,"生存:","生:"&CC42) -> 生存: | AY82: =BY42 -> 0 | BV82: 意义非凡之地 | BY82: 腐化 | CA82: 地区 | CQ82: ☐
C83: - | F83: - | I83: - | L83: - | O83: - | R83: - | U83: - | X83: - | AA83: - | AD83: - | AG83: - | AJ83: - | AM83: - | AP83: - | AR83: =SUM(AO83,AL83,AI83,AF83,AC83,Z83,W83,T83,Q83,N83,K83,H83,E83,B83)-SUM(AQ83,AN83,AK83,AH83,AE83,AB83,Y83,V83,S83,P83,M83,J83,G83,D83) -> 0 | AT83: =AR83+CE43+CI43+CK43 -> 20 | AV83: =CA43 -> 游泳 | AY83: =BY43 -> 0 | BA83: ="消费能力："&BN77&BR77 -> 消费能力：0.5美元 | BH83: =附表!D76 -> 已使用0美元 | BN83: =附表!D75 -> 本次任务携带0.6美元 | BY83: ☐ | CA83: 缘由
C84: - | F84: - | I84: - | L84: - | O84: - | R84: - | U84: - | X84: - | AA84: - | AD84: - | AG84: - | AJ84: - | AM84: - | AP84: - | AR84: =SUM(AO84,AL84,AI84,AF84,AC84,Z84,W84,T84,Q84,N84,K84,H84,E84,B84)-SUM(AQ84,AN84,AK84,AH84,AE84,AB84,Y84,V84,S84,P84,M84,J84,G84,D84) -> 0 | AT84: =AR84+CE44+CI44+CK44 -> 1 | AV84: =CA44 -> 精神分析 | AY84: =BY44 -> 0 | BA84: 武器装备（类型 | 名称 | 价值） | BP84: =附表!K78 -> 未携带武器！ | BV84: 宝贵之物 | BY84: 腐化 | CA84: 物品 | CQ84: ☐
C85: - | F85: - | I85: - | L85: - | O85: - | R85: - | U85: - | X85: - | AA85: - | AD85: - | AG85: - | AJ85: - | AM85: - | AP85: - | AR85: =SUM(AO85,AL85,AI85,AF85,AC85,Z85,W85,T85,Q85,N85,K85,H85,E85,B85)-SUM(AQ85,AN85,AK85,AH85,AE85,AB85,Y85,V85,S85,P85,M85,J85,G85,D85) -> 0 | AT85: =AR85+CE45+CI45+CK45 -> 1 | AV85: =CA45 -> 医学 | AY85: =BY45 -> 0 | BA85: =IF(BF69="","",BF69) | BK85: =IF(BA85="","",IF(BA69="","未取名！",BA69)) | BY85: ☐ | CA85: 缘由
C86: - | F86: - | I86: - | L86: - | O86: - | R86: - | U86: - | X86: - | AA86: - | AD86: - | AG86: - | AJ86: - | AM86: - | AP86: - | AR86: =SUM(AO86,AL86,AI86,AF86,AC86,Z86,W86,T86,Q86,N86,K86,H86,E86,B86)-SUM(AQ86,AN86,AK86,AH86,AE86,AB86,Y86,V86,S86,P86,M86,J86,G86,D86) -> 0 | AT86: =AR86+CE46+CI46+CK46 -> 30 | AV86: =CA46 -> 急救 | AY86: =BY46 -> 0 | BA86: =IF(BF70="","",BF70) | BK86: =IF(BA86="","",IF(BA70="","未取名！",BA70)) | BV86: 特质 | BY86: 腐化 | CA86: 概括 | CQ86: ☐
C87: - | F87: - | I87: - | L87: - | O87: - | R87: - | U87: - | X87: - | AA87: - | AD87: - | AG87: - | AJ87: - | AM87: - | AP87: - | AR87: =SUM(AO87,AL87,AI87,AF87,AC87,Z87,W87,T87,Q87,N87,K87,H87,E87,B87)-SUM(AQ87,AN87,AK87,AH87,AE87,AB87,Y87,V87,S87,P87,M87,J87,G87,D87) -> 0 | AT87: =AR87+CE47+CI47+CK47 -> 1 | AV87: =IF(CC47=0,"驾驶:","驾:"&CC47) -> 驾驶: | AY87: =BY47 -> 0 | BA87: =IF(BF71="","",BF71) | BK87: =IF(BA87="","",IF(BA71="","未取名！",BA71)) | BY87: ☐ | CA87: 剖析
C88: - | F88: - | I88: - | L88: - | O88: - | R88: - | U88: - | X88: - | AA88: - | AD88: - | AG88: - | AJ88: - | AM88: - | AP88: - | AR88: =SUM(AO88,AL88,AI88,AF88,AC88,Z88,W88,T88,Q88,N88,K88,H88,E88,B88)-SUM(AQ88,AN88,AK88,AH88,AE88,AB88,Y88,V88,S88,P88,M88,J88,G88,D88) -> 0 | AT88: =AR88+CE48+CI48+CK48 -> 1 | AV88: =IF(CC48=0,"驾驶:","驾:"&CC48) -> 驾驶: | AY88: =BY48 -> 0 | BA88: =IF(BF72="","",BF72) | BK88: =IF(BA88="","",IF(BA72="","未取名！",BA72)) | BV88: 伤口和疤痕 | CA88: 轻伤 | CQ88: ☐
C89: - | F89: - | I89: - | L89: - | O89: - | R89: - | U89: - | X89: - | AA89: - | AD89: - | AG89: - | AJ89: - | AM89: - | AP89: - | AR89: =SUM(AO89,AL89,AI89,AF89,AC89,Z89,W89,T89,Q89,N89,K89,H89,E89,B89)-SUM(AQ89,AN89,AK89,AH89,AE89,AB89,Y89,V89,S89,P89,M89,J89,G89,D89) -> 0 | AT89: =AR89+CE49+CI49+CK49 -> 20 | AV89: =CA49 -> 汽车驾驶 | AY89: =BY49 -> 0 | BA89: =IF(BF73="","",BF73) | BK89: =IF(BA89="","",IF(BA73="","未取名！",BA73)) | CA89: 重伤
C90: - | F90: - | I90: - | L90: - | O90: - | R90: - | U90: - | X90: - | AA90: - | AD90: - | AG90: - | AJ90: - | AM90: - | AP90: - | AR90: =SUM(AO90,AL90,AI90,AF90,AC90,Z90,W90,T90,Q90,N90,K90,H90,E90,B90)-SUM(AQ90,AN90,AK90,AH90,AE90,AB90,Y90,V90,S90,P90,M90,J90,G90,D90) -> 0 | AT90: =AR90+CE50+CI50+CK50 -> 5 | AV90: =CA50 -> 骑术 | AY90: =BY50 -> 0 | BA90: 弹药类型（选择/自填） | BK90: 弹药数量 | BP90: 储存方式 | BS90: 价值 | BV90: 恐惧症和躁狂症 | CA90: 恐惧 | CQ90: ☐
C91: - | F91: - | I91: - | L91: - | O91: - | R91: - | U91: - | X91: - | AA91: - | AD91: - | AG91: - | AJ91: - | AM91: - | AP91: - | AR91: =SUM(AO91,AL91,AI91,AF91,AC91,Z91,W91,T91,Q91,N91,K91,H91,E91,B91)-SUM(AQ91,AN91,AK91,AH91,AE91,AB91,Y91,V91,S91,P91,M91,J91,G91,D91) -> 0 | AT91: =AR91+CE51+CI51+CK51 -> 5 | AV91: =CA51 -> 动物驯养 | AY91: =BY51 -> 0 | CA91: 躁狂
C92: - | F92: - | I92: - | L92: - | O92: - | R92: - | U92: - | X92: - | AA92: - | AD92: - | AG92: - | AJ92: - | AM92: - | AP92: - | AR92: =SUM(AO92,AL92,AI92,AF92,AC92,Z92,W92,T92,Q92,N92,K92,H92,E92,B92)-SUM(AQ92,AN92,AK92,AH92,AE92,AB92,Y92,V92,S92,P92,M92,J92,G92,D92) -> 0 | AT92: =AR92+CE52+CI52+CK52 -> 1 | AV92: =CA52 -> 潜水 | AY92: =BY52 -> 0 | BV92: 诞辰 | CD92: 年 | CH92: 月 | CM92: 日 | CO92: 年龄 | CQ92: =IF(BF17="","时间未填",IF(CA92="","诞辰未填",BF17-CA92)) -> 时间未填 | CT92: 发明/发现/概念
C93: - | F93: - | I93: - | L93: - | O93: - | R93: - | U93: - | X93: - | AA93: - | AD93: - | AG93: - | AJ93: - | AM93: - | AP93: - | AR93: =SUM(AO93,AL93,AI93,AF93,AC93,Z93,W93,T93,Q93,N93,K93,H93,E93,B93)-SUM(AQ93,AN93,AK93,AH93,AE93,AB93,Y93,V93,S93,P93,M93,J93,G93,D93) -> 0 | AT93: =AR93+CE53+CI53+CK53 -> 1 | AV93: =CA53 -> 读唇 | AY93: =BY53 -> 0 | CT93: 显示类型： | CY93: 已出现的 | DF93: =IF(CY93=附表!AT29,"要搜索的年份：","当前年份"&BF17&"年") -> 当前年份年 | DK93: 1924
C94: - | F94: - | I94: - | L94: - | O94: - | R94: - | U94: - | X94: - | AA94: - | AD94: - | AG94: - | AJ94: - | AM94: - | AP94: - | AR94: =SUM(AO94,AL94,AI94,AF94,AC94,Z94,W94,T94,Q94,N94,K94,H94,E94,B94)-SUM(AQ94,AN94,AK94,AH94,AE94,AB94,Y94,V94,S94,P94,M94,J94,G94,D94) -> 0 | AT94: =AR94+CE54+CI54+CK54 -> 1 | AV94: =CA54 -> 催眠 | AY94: =BY54 -> 0 | CT94: =附表!BA14 -> #N/A
C95: - | F95: - | I95: - | L95: - | O95: - | R95: - | U95: - | X95: - | AA95: - | AD95: - | AG95: - | AJ95: - | AM95: - | AP95: - | AR95: =SUM(AO95,AL95,AI95,AF95,AC95,Z95,W95,T95,Q95,N95,K95,H95,E95,B95)-SUM(AQ95,AN95,AK95,AH95,AE95,AB95,Y95,V95,S95,P95,M95,J95,G95,D95) -> 0 | AT95: =AR95+CE55+CI55+CK55 -> 1 | AV95: =IF(CD55=0,"自定义:","自:"&CD55) -> 自定义: | AY95: =BY55 -> 0
C96: - | F96: - | I96: - | L96: - | O96: - | R96: - | U96: - | X96: - | AA96: - | AD96: - | AG96: - | AJ96: - | AM96: - | AP96: - | AR96: =SUM(AO96,AL96,AI96,AF96,AC96,Z96,W96,T96,Q96,N96,K96,H96,E96,B96)-SUM(AQ96,AN96,AK96,AH96,AE96,AB96,Y96,V96,S96,P96,M96,J96,G96,D96) -> 0 | AT96: =AR96+CE56+CI56+CK56 -> 1 | AV96: =IF(CD56=0,"自定义:","自:"&CD56) -> 自定义: | AY96: =BY56 -> 0 | BA96: =附表!O70 -> 手无寸铁！ | BK96: =附表!K89 -> 没携带弹药？或许是不需要
C97: - | F97: - | I97: - | L97: - | O97: - | R97: - | U97: - | X97: - | AA97: - | AD97: - | AG97: - | AJ97: - | AM97: - | AP97: - | AR97: =SUM(AO97,AL97,AI97,AF97,AC97,Z97,W97,T97,Q97,N97,K97,H97,E97,B97)-SUM(AQ97,AN97,AK97,AH97,AE97,AB97,Y97,V97,S97,P97,M97,J97,G97,D97) -> 0 | AT97: =AR97+CE57+CI57+CK57 -> 1 | AV97: =CA57 -> 炮术 | AY97: =BY57 -> 0 | BA97: 随身物品（使用右侧栏位需要背包）
C98: - | F98: - | I98: - | L98: - | O98: - | R98: - | U98: - | X98: - | AA98: - | AD98: - | AG98: - | AJ98: - | AM98: - | AP98: - | AR98: =SUM(AO98,AL98,AI98,AF98,AC98,Z98,W98,T98,Q98,N98,K98,H98,E98,B98)-SUM(AQ98,AN98,AK98,AH98,AE98,AB98,Y98,V98,S98,P98,M98,J98,G98,D98) -> 0 | AT98: =AR98+CE58+CI58+CK58 -> 20 | AV98: =CA58 -> 投掷 | AY98: =BY58 -> 0 | BA98: 状态 | BC98: 部位 | BE98: 物品名称 | BK98: 价值 | BM98: 背包格↓ | BS98: 价值
C99: - | F99: - | I99: - | L99: - | O99: - | R99: - | U99: - | X99: - | AA99: - | AD99: - | AG99: - | AJ99: - | AM99: - | AP99: - | AR99: =SUM(AO99,AL99,AI99,AF99,AC99,Z99,W99,T99,Q99,N99,K99,H99,E99,B99)-SUM(AQ99,AN99,AK99,AH99,AE99,AB99,Y99,V99,S99,P99,M99,J99,G99,D99) -> 0 | AT99: =AR99+CE59+CI59+CK59 -> 20 | AV99: =IF(CC59=0,"射击:","射击:"&CC59) -> 射击:手枪 | AY99: =BY59 -> 0 | BA99: 隐藏 | BC99: 腰
C100: - | F100: - | I100: - | L100: - | O100: - | R100: - | U100: - | X100: - | AA100: - | AD100: - | AG100: - | AJ100: - | AM100: - | AP100: - | AR100: =SUM(AO100,AL100,AI100,AF100,AC100,Z100,W100,T100,Q100,N100,K100,H100,E100,B100)-SUM(AQ100,AN100,AK100,AH100,AE100,AB100,Y100,V100,S100,P100,M100,J100,G100,D100) -> 0 | AT100: =AR100+CE60+CI60+CK60 -> 0 | AV100: =IF(CC60=0,"射击:","射击:"&CC60) -> 射击: | AY100: =BY60 -> 0 | BA100: 隐藏 | BC100: 腰
...

Sheet 附表
AJ1: 自定义职业属性
B2: 移动力计算 | S2: 自定义职业
A3: 护甲表减值 是否开启 | B3: 护甲表减值 | C3: 年龄减值 | D3: 力量-体型 | E3: =G14-I14 -> 0 | G3: 技能雷达表 | H3: 值 | I3: 总数 | J3: 百分比 | N3: 伤害加值与体格 | S3: 属性名称 | T3: shiyong | U3: 使用倍数 | V3: 计算
D4: 敏捷-体型 | E4: =J14-I14 -> 0 | G4: 调查 | H4: 交涉 | I4: 战斗 | J4: 特技 | K4: 支援 | L4: 学问 | N4: 力量+体型 | S4: ="力量×"&U4 -> 力量×0 | T4: =职业列表!I20 -> × | U4: =职业列表!J20 -> 0 | V4: =G14*U4 -> 0 | X4: =IF(U4>0,S4,"") | Y4: =IF(AND(U5>0,U4>0),"+","") | Z4: =IF(U5>0,S5,"") | AK4: 战斗 | AL4: ←请选择类型 | AM4: 爆破 | AN4: 电气维修 | AO4: 炮术 | AP4: 投掷 | AQ4: 格斗1 | AR4: 格斗2 | AS4: 格斗3 | AT4: 格斗4 | AU4: 格斗5 | AV4: 射击1 | AW4: 射击2 | AX4: 射击3 | AY4: 射击4 | AZ4: 射击5 | BC4: 斗殴 | BD4: 手枪 | BE4: 没有数值 | BF4: 最大值 | BG4: 最终出目
A5: =IF(人物卡!CH21="开",1,IF(人物卡!CH21="关",0)) -> 0 | B5: =IF(人物卡!CM21=0,"0",VLOOKUP(人物卡!CM21,'防具表 载具表'!B2:I101,3,FALSE)) -> 0 | C5: =IFERROR(0,IF(人物卡!BD12<40,0,INT((人物卡!BD12/10)-3))) -> 0 | D5: 力量大小 | E5: =IF(E3>0,"1",IF(E3=0,"0",IF(E3<0,"-1"))) -> 0 | G5: =AVERAGE(人物卡!BZ13+人物卡!BQ25+人物卡!BQ26+人物卡!BQ27+人物卡!BQ28+人物卡!BQ34+人物卡!BQ36+人物卡!BQ55+人物卡!BQ56+人物卡!BQ57+人物卡!CM26+人物卡!CM27+人物卡!CM31+人物卡!CM33+人物卡!CM37+人物卡!CM38+人物卡!CM44+人物卡!CM49+人物卡!CM53-122) -> 4 | H5: =AVERAGE(人物卡!BZ11+人物卡!BQ26+人物卡!BQ27+人物卡!BQ32+人物卡!BQ35+人物卡!BQ37+人物卡!BQ42+人物卡!BQ53+人物卡!BQ55+人物卡!BQ56+人物卡!BQ57+人物卡!BQ58+人物卡!CM25+人物卡!CM35+人物卡!CM37+人物卡!CM38+人物卡!CM44+人物卡!CM49+人物卡!CM53-111-人物卡!BI58) -> -17 | I5: =AVERAGE((人物卡!BT9+人物卡!BT13)/2+人物卡!BT11+人物卡!BZ9+人物卡!BQ38+人物卡!BQ43+人物卡!BQ44+人物卡!BQ45+人物卡!BQ47+人物卡!BQ48+人物卡!BQ49+人物卡!BQ53+人物卡!BQ54+人物卡!CM27+人物卡!CM34+人物卡!CM38+人物卡!CM39+人物卡!CM44+人物卡!CM45+人物卡!CM48+人物卡!CM50+人物卡!CM52+人物卡!CM54+人物卡!CM55-189-人物卡!BI38) -> -108 | J5: =AVERAGE(人物卡!BZ9+人物卡!BQ28+人物卡!BQ29+人物卡!BQ30+人物卡!BQ31+人物卡!BQ33+人物卡!BQ37+人物卡!BQ39+人物卡!BQ40+人物卡!BQ54+人物卡!CM28+人物卡!CM29+人物卡!CM30+人物卡!CM32+人物卡!CM34+人物卡!CM36+人物卡!CM39+人物卡!CM43+人物卡!CM45+人物卡!CM46+人物卡!CM47+人物卡!CM48+人物卡!CM49+人物卡!CM50+人物卡!CM51+人物卡!CM52+人物卡!CM54+人物卡!CM55-219) -> -8 | K5: =AVERAGE(人物卡!BQ51+人物卡!CM30+人物卡!CM37+人物卡!BQ39+人物卡!CM36+人物卡!CM39+人物卡!CM32+人物卡!BQ35+人物卡!BQ26+人物卡!CM50+人物卡!CM54+人物卡!CM55-76) -> 22 | L5: =AVERAGE(人物卡!CF11+人物卡!BZ13+人物卡!BQ25+人物卡!BQ26+人物卡!BQ34+人物卡!BQ36+人物卡!BQ41+人物卡!BQ52+人物卡!BQ55+人物卡!BQ56+人物卡!BQ57+人物卡!BQ58-人物卡!BI58+人物卡!CM25+人物卡!CM26+人物卡!CM30+人物卡!CM31+人物卡!CM33+人物卡!CM37+人物卡!CM38+人物卡!CM40+人物卡!CM41+人物卡!CM42+人物卡!CM53-76) -> 75 | N5: =IFERROR(G14+I14,0) -> 0 | S5: ="敏捷×"&U5 -> 敏捷×0 | T5: =职业列表!I21 -> × | U5: =职业列表!J21 -> 0 | V5: =J14*U5 -> 0 | X5: =IF(U5>0,S5,"") | Y5: =IF(AND(U6>0,U5>0),"+","") | AL5: =IF(人物卡!BK69=AL4,"") | AM5: =IF(人物卡!BK69=Blasting,blast) -> FALSE | AN5: =IF(人物卡!BK69=memaing,mema) -> FALSE | AO5: =IF(人物卡!BK69=arting,arti) -> FALSE | AP5: =IF(人物卡!BK69=throwing,throw) -> FALSE | AQ5: =IF(人物卡!BK69=dbog,dbo) -> FALSE | AR5: =IF(人物卡!BK69=dbtg,dbt) -> FALSE | AS5: =IF(人物卡!BK69=dbthg,dbth) -> FALSE | AT5: =IF(人物卡!BK69=dbfg,dbf) -> FALSE | AU5: =IF(人物卡!BK69=dbfig,dbfi) -> FALSE | AV5: =IF(人物卡!BK69=shog,sho) -> FALSE | AW5: =IF(人物卡!BK69=shtg,sht) -> FALSE | AX5: =IF(人物卡!BK69=shthg,shth) -> FALSE | AY5: =IF(人物卡!BK69=shfg,shf) -> FALSE | AZ5: =IF(人物卡!BK69=shfig,shfi) -> FALSE | BC5: =IF(人物卡!BK69=fighting,fight) -> FALSE | BD5: =IF(人物卡!BK69=pistoling,pistol) -> FALSE | BE5: =IF(BF5=0,IF(人物卡!BK69=附表!U227,附表!V227,IF(人物卡!BK69=附表!U220,附表!V220,IF(人物卡!BK69=附表!U221,附表!V221,IF(人物卡!BK69=附表!U219,附表!V219,IF(人物卡!BK69=附表!U224,附表!V224,IF(人物卡!BK69=附表!U225,附表!V225,IF(人物卡!BK69=附表!U223,附表!V223,IF(人物卡!BK69=附表!U222,附表!V222,IF(人物卡!BK69=附表!U226,技能注释!#REF!,IF(人物卡!BK69=附表!Q220,附表!R220,IF(人物卡!BK69=附表!Q221,附表!R221,IF(人物卡!BK69=附表!Q222,附表!R222,IF(人物卡!BK69=附表!Q223,附表!R223,IF(人物卡!BK69=附表!Q224,附表!R224,IF(人物卡!BK69=附表!Q219,附表!R219,IF(人物卡!BK69=附表!Q225,附表!R225,""))))))))))))))))) | BF5: =MAX(AL5:BD5) -> 0 | BG5: =IF(BF5=0,BE5,BF5)
B6: 检测是否为数字 | C6: 最终年龄减值 | D6: 敏捷大小 | E6: =IF(E4>0,"1",IF(E4=0,"0",IF(E4<0,"-1"))) -> 0 | J6: =G5+H5+I5+J5+K5+L5 -> -32 | N6: 非八十整数体格 | O6: 减485后八十的倍数 | P6: 最终体格出目 | S6: ="体质×"&U6 -> 体质×0 | T6: =职业列表!I22 -> × | U6: =职业列表!J22 -> 0 | V6: =H14*U6 -> 0 | X6: =IF(U6>0,S6,"") | Y6: =IF(AND(U7>0,U6>0),"+","") | AL6: =IF(人物卡!BK70=$AL$4,"") -> FALSE | AM6: =IF(人物卡!BK70=AM4,blast) -> FALSE | AN6: =IF(人物卡!BK70=AN4,mema) -> FALSE | AO6: =IF(人物卡!BK70=AO4,arti) -> FALSE | AP6: =IF(人物卡!BK70=AP4,throw) -> FALSE | AQ6: =IF(ISBLANK(dbog),FALSE,IF(人物卡!BK70=dbog,dbo)) -> FALSE | AR6: =IF(ISBLANK(dbt),FALSE,IF(人物卡!BK70=dbtg,dbt)) -> 0 | AS6: =IF(ISBLANK(dbth),FALSE,IF(人物卡!BK70=dbthg,dbth)) -> 0 | AT6: =IF(人物卡!BK70=dbfg,dbf) -> 0 | AU6: =IF(人物卡!BK70=dbfig,dbfi) -> 0 | AV6: =IF(ISBLANK(shog),FALSE,IF(人物卡!BK70=shog,sho)) -> FALSE | AW6: =IF(ISBLANK(shtg),FALSE,IF(人物卡!BK70=shtg,sht)) -> FALSE | AX6: =IF(ISBLANK(shthg),FALSE,IF(人物卡!BK70=shthg,shth)) -> FALSE | AY6: =IF(人物卡!BK70=shfg,shf) -> 0 | AZ6: =IF(人物卡!BK70=shfig,shfi) -> 0 | BC6: =IF(人物卡!BK70=BC4,fight) -> FALSE | BD6: =IF(人物卡!BK70=BD4,pistol) -> FALSE | BE6: =IF(BF6=0,IF(人物卡!BK70=附表!U227,附表!V227,IF(人物卡!BK70=附表!U220,附表!V220,IF(人物卡!BK70=附表!U221,附表!V221,IF(人物卡!BK70=附表!U219,附表!V219,IF(人物卡!BK70=附表!U224,附表!V224,IF(人物卡!BK70=附表!U225,附表!V225,IF(人物卡!BK70=附表!U223,附表!V223,IF(人物卡!BK70=附表!U222,附表!V222,IF(人物卡!BK70=附表!U226,技能注释!#REF!,IF(人物卡!BK70=附表!Q220,附表!R220,IF(人物卡!BK70=附表!Q221,附表!R221,IF(人物卡!BK70=附表!Q222,附表!R222,IF(人物卡!BK70=附表!Q223,附表!R223,IF(人物卡!BK70=附表!Q224,附表!R224,IF(人物卡!BK70=附表!Q219,附表!R219,IF(人物卡!BK70=附表!Q225,附表!R225,""))))))))))))))))) | BF6: =MAX(AL6:BD6) -> 0 | BG6: =IF(BF6=0,BE6,BF6)
B7: =ISNUMBER(B5) -> TRUE | C7: =IF(ISBLANK(人物卡!BD12),0,IF(人物卡!BD12>=0,C5,0)) -> 0 | D7: 总值 | E7: =E6+E5 -> 0 | G7: 调查 | H7: 交涉 | I7: 战斗 | J7: 特技 | K7: 支援 | L7: 学问 | N7: =IF(N5<=1,"0",IF(N5<=64,"-2",IF(N5<=84,"-1",IF(N5<=124,"0",IF(N5<=164,"1",IF(N5<=204,"2",IF(N5<=284,"3",IF(N5>284,"4","0")))))))) -> 0 | O7: =INT((N5-285)/80) -> -4 | P7: =IF(O7>=0,O7+N7,N7) -> 0 | S7: ="体型×"&U7 -> 体型×0 | T7: =职业列表!I23 -> × | U7: =职业列表!J23 -> 0 | V7: =I14*U7 -> 0 | X7: =IF(U7>0,S7,"") | Y7: =IF(AND(U8>0,U7>0),"+","") | AL7: =IF(人物卡!BK71=$AL$4,"") -> FALSE | AM7: =IF(人物卡!BK71=$AM$4,blast) -> FALSE | AN7: =IF(人物卡!BK71=$AN$4,mema) -> FALSE | AO7: =IF(人物卡!BK71=$AO$4,arti) -> FALSE | AP7: =IF(人物卡!BK71=$AP$4,throw) -> FALSE | AQ7: =IF(ISBLANK(dbog),FALSE,IF(人物卡!BK71=dbog,dbo)) -> FALSE | AR7: =IF(ISBLANK(dbt),FALSE,IF(人物卡!BK71=dbtg,dbt)) -> 0 | AS7: =IF(ISBLANK(dbth),FALSE,IF(人物卡!BK71=dbthg,dbth)) -> 0 | AT7: =IF(人物卡!BK71=dbfg,dbf) -> 0 | AU7: =IF(人物卡!BK71=dbfig,dbfi) -> 0 | AV7: =IF(ISBLANK(shog),FALSE,IF(人物卡!BK71=shog,sho)) -> FALSE | AW7: =IF(ISBLANK(shtg),FALSE,IF(人物卡!BK71=shtg,sht)) -> FALSE | AX7: =IF(ISBLANK(shthg),FALSE,IF(人物卡!BK71=shthg,shth)) -> FALSE | AY7: =IF(人物卡!BK71=shfg,shf) -> 0 | AZ7: =IF(人物卡!BK71=shfig,shfi) -> 0 | BC7: =IF(人物卡!BK71=$BC$4,fight) -> FALSE | BD7: =IF(人物卡!BK71=$BD$4,pistol) -> FALSE | BE7: =IF(BF7=0,IF(人物卡!BK71=附表!U227,附表!V227,IF(人物卡!BK71=附表!U220,附表!V220,IF(人物卡!BK71=附表!U221,附表!V221,IF(人物卡!BK71=附表!U219,附表!V219,IF(人物卡!BK71=附表!U224,附表!V224,IF(人物卡!BK71=附表!U225,附表!V225,IF(人物卡!BK71=附表!U223,附表!V223,IF(人物卡!BK71=附表!U222,附表!V222,IF(人物卡!BK71=附表!U226,技能注释!#REF!,IF(人物卡!BK71=附表!Q220,附表!R220,IF(人物卡!BK71=附表!Q221,附表!R221,IF(人物卡!BK71=附表!Q222,附表!R222,IF(人物卡!BK71=附表!Q223,附表!R223,IF(人物卡!BK71=附表!Q224,附表!R224,IF(人物卡!BK71=附表!Q219,附表!R219,IF(人物卡!BK71=附表!Q225,附表!R225,""))))))))))))))))) | BF7: =MAX(AL7:BD7) -> 0 | BG7: =IF(BF7=0,BE7,BF7)
B8: 护甲表最终减值 | C8: =IF(B7=FALSE,"0",IF(A5=1,B5,0)) -> 0 | D8: 属性最终值 | E8: =IF(E7=2,"1",IF(E7=-2,"-1",0)) -> 0 | G8: =G5/J6 -> -0.125 | H8: =H5/J6 -> 0.53125 | I8: =I5/J6 -> 3.375 | J8: =J5/J6 -> 0.25 | K8: =K5/J6 -> -0.6875 | L8: =L5/J6 -> -2.34375 | N8: 小于1D6的话 | O8: 超过1d6的话 | P8: 最终伤害加值出目 | S8: ="外貌×"&U8 -> 外貌×0 | T8: =职业列表!I24 -> × | U8: =职业列表!J24 -> 0 | V8: =K14*U8 -> 0 | X8: =IF(U8>0,S8,"") | Y8: =IF(AND(U9>0,U8>0),"+","") | AL8: =IF(人物卡!BK72=$AL$4,"") -> FALSE | AM8: =IF(人物卡!BK72=$AM$4,blast) -> FALSE | AN8: =IF(人物卡!BK72=$AN$4,mema) -> FALSE | AO8: =IF(人物卡!BK72=$AO$4,arti) -> FALSE | AP8: =IF(人物卡!BK72=$AP$4,throw) -> FALSE | AQ8: =IF(ISBLANK(dbog),FALSE,IF(人物卡!BK72=dbog,dbo)) -> FALSE | AR8: =IF(ISBLANK(dbt),FALSE,IF(人物卡!BK72=dbtg,dbt)) -> 0 | AS8: =IF(ISBLANK(dbth),FALSE,IF(人物卡!BK72=dbthg,dbth)) -> 0 | AT8: =IF(人物卡!BK72=dbfg,dbf) -> 0 | AU8: =IF(人物卡!BK72=dbfig,dbfi) -> 0 | AV8: =IF(ISBLANK(shog),FALSE,IF(人物卡!BK72=shog,sho)) -> FALSE | AW8: =IF(ISBLANK(shtg),FALSE,IF(人物卡!BK72=shtg,sht)) -> FALSE | AX8: =IF(ISBLANK(shthg),FALSE,IF(人物卡!BK72=shthg,shth)) -> FALSE | AY8: =IF(人物卡!BK72=shfg,shf) -> 0 | AZ8: =IF(人物卡!BK72=shfig,shfi) -> 0 | BC8: =IF(人物卡!BK72=$BC$4,fight) -> FALSE | BD8: =IF(人物卡!BK72=$BD$4,pistol) -> FALSE | BE8: =IF(BF8=0,IF(人物卡!BK72=附表!U227,附表!V227,IF(人物卡!BK72=附表!U220,附表!V220,IF(人物卡!BK72=附表!U221,附表!V221,IF(人物卡!BK72=附表!U219,附表!V219,IF(人物卡!BK72=附表!U224,附表!V224,IF(人物卡!BK72=附表!U225,附表!V225,IF(人物卡!BK72=附表!U223,附表!V223,IF(人物卡!BK72=附表!U222,附表!V222,IF(人物卡!BK72=附表!U226,技能注释!#REF!,IF(人物卡!BK72=附表!Q220,附表!R220,IF(人物卡!BK72=附表!Q221,附表!R221,IF(人物卡!BK72=附表!Q222,附表!R222,IF(人物卡!BK72=附表!Q223,附表!R223,IF(人物卡!BK72=附表!Q224,附表!R224,IF(人物卡!BK72=附表!Q219,附表!R219,IF(人物卡!BK72=附表!Q225,附表!R225,""))))))))))))))))) | BF8: =MAX(AL8:BD8) -> 0 | BG8: =IF(BF8=0,BE8,BF8)
B9: 最终补正值 | C9: =E8-C8-C7 -> 0 | N9: =IF(P7="-2","-2",IF(P7="-1","-1",IF(P7="0","0",IF(P7="1","+1D4",IF(P7=2,"+1D6",IF(P7>2,"D6",0)))))) -> 0 | O9: =IF(N9="D6",P7-1,"0") -> 0 | P9: =IF(N9="D6",O10,N9) -> 0 | S9: ="智力×"&U9 -> 智力×0 | T9: =职业列表!I25 -> × | U9: =职业列表!J25 -> 0 | V9: =L14*U9 -> 0 | X9: =IF(U9>0,S9,"") | Y9: =IF(AND(U10>0,U9>0),"+","") | AA9: =X4&Y4&X5&Y5&X6&Y6&X7&Y7&X8&Y8&X9&Y9&X10&Y10&X11&Y11&X12 | AF9: 最终值 | AL9: =IF(人物卡!BK73=$AL$4,"") -> FALSE | AM9: =IF(人物卡!BK73=$AM$4,blast) -> FALSE | AN9: =IF(人物卡!BK73=$AN$4,mema) -> FALSE | AO9: =IF(人物卡!BK73=$AO$4,arti) -> FALSE | AP9: =IF(人物卡!BK73=$AP$4,throw) -> FALSE | AQ9: =IF(ISBLANK(dbog),FALSE,IF(人物卡!BK73=dbog,dbo)) -> FALSE | AR9: =IF(ISBLANK(dbt),FALSE,IF(人物卡!BK73=dbtg,dbt)) -> 0 | AS9: =IF(ISBLANK(dbth),FALSE,IF(人物卡!BK73=dbthg,dbth)) -> 0 | AT9: =IF(人物卡!BK73=dbfg,dbf) -> 0 | AU9: =IF(人物卡!BK73=dbfig,dbfi) -> 0 | AV9: =IF(ISBLANK(shog),FALSE,IF(人物卡!BK73=shog,sho)) -> FALSE | AW9: =IF(ISBLANK(shtg),FALSE,IF(人物卡!BK73=shtg,sht)) -> FALSE | AX9: =IF(ISBLANK(shthg),FALSE,IF(人物卡!BK73=shthg,shth)) -> FALSE | AY9: =IF(人物卡!BK73=shfg,shf) -> 0 | AZ9: =IF(人物卡!BK73=shfig,shfi) -> 0 | BC9: =IF(人物卡!BK73=$BC$4,fight) -> FALSE | BD9: =IF(人物卡!BK73=$BD$4,pistol) -> FALSE | BE9: =IF(BF9=0,IF(人物卡!BK73=附表!U227,附表!V227,IF(人物卡!BK73=附表!U220,附表!V220,IF(人物卡!BK73=附表!U221,附表!V221,IF(人物卡!BK73=附表!U219,附表!V219,IF(人物卡!BK73=附表!U224,附表!V224,IF(人物卡!BK73=附表!U225,附表!V225,IF(人物卡!BK73=附表!U223,附表!V223,IF(人物卡!BK73=附表!U222,附表!V222,IF(人物卡!BK73=附表!U226,技能注释!#REF!,IF(人物卡!BK73=附表!Q220,附表!R220,IF(人物卡!BK73=附表!Q221,附表!R221,IF(人物卡!BK73=附表!Q222,附表!R222,IF(人物卡!BK73=附表!Q223,附表!R223,IF(人物卡!BK73=附表!Q224,附表!R224,IF(人物卡!BK73=附表!Q219,附表!R219,IF(人物卡!BK73=附表!Q225,附表!R225,""))))))))))))))))) | BF9: =MAX(AL9:BD9) -> 0 | BG9: =IF(BF9=0,BE9,BF9)
O10: ="+"&O9&"D6" -> +0D6 | S10: ="教育×"&U10 -> 教育×0 | T10: =职业列表!I26 -> × | U10: =职业列表!J26 -> 0 | V10: =N14*U10 -> 0 | X10: =IF(U10>0,S10,"") | Y10: =IF(AND(U11>0,U10>0),"+","") | AA10: =IF(AB10=职业列表!H30,1,0) -> 0 | AB10: 教育+其他属性点数中的最大值（官方） | AF10: =IF(AA10=1,MAX(V4:V9,V11:V12)+V10,0) -> 0
S11: ="意志×"&U11 -> 意志×0 | T11: =职业列表!I27 -> × | U11: =职业列表!J27 -> 0 | V11: =M14*U11 -> 0 | X11: =IF(U11>0,S11,"") | Y11: =IF(AND(U12>0,U11>0),"+","") | AA11: =IF(AB11=职业列表!H30,1,0) -> 0 | AB11: 教育+其他属性点数中的所有值 | AF11: =IF(AA11=1,V10+SUM(V4:V9,V11:V12),0) -> 0
G12: 属性雷达表 | H12: 基础属性 | I12: 出目 | S12: ="幸运×"&U12 -> 幸运×0 | T12: =职业列表!I28 -> × | U12: =职业列表!J28 -> 0 | V12: =O14*U12 -> 0 | X12: =IF(U12>0,S12,"") | AA12: =IF(AB12=职业列表!H30,1,0) -> 1 | AB12: 所有属性的点数相加 | AF12: =IF(AA12=1,SUM(V4:V12),0) -> 0
G13: 力量 STR | H13: 体质 CON | I13: 体型 SIZ | J13: 敏捷 DEX | K13: 外貌 APP | L13: 智力 灵感 | M13: 意志 POW | N13: 教育 EDU | O13: 幸运 Luck | Y13: 格斗射击基础成功率
B14: 熟练下拉 | G14: =IF(STRA="未填写",0,STRA) -> 0 | H14: =IF(CONA="未填写",0,CONA) -> 0 | I14: =IF(SIZA="未填写",0,SIZA) -> 0 | J14: =IF(DEXA="未填写",0,) -> 0 | K14: =IF(APPA="未填写",0,) -> 0 | L14: =IF(INTA="未填写",0,) -> 0 | M14: =IF(POWA="未填写",0,) -> 0 | N14: =IF(EDUA="未填写",0,) -> 0 | O14: =IF(LuckA="未填写",0,) -> 0 | U14: 自定义技能剩余计算 | Y14: 格斗1 | Z14: =IF(人物卡!BG60="武术",1,IF(人物卡!BG60="鞭子","5",IF(人物卡!BG60="电锯","10",IF(人物卡!BG60="斧","15",IF(人物卡!BG60="剑","20",IF(人物卡!BG60="绞具","15",IF(人物卡!BG60="链枷","10",IF(人物卡!BG60="矛","20",IF(人物卡!BG60=人物卡!$X$110,人物卡!$AD$110,0))))))))) -> 0 | AA14: 射击1 | AB14: =IF(人物卡!CC60="步枪/霰弹枪","25",IF(人物卡!CC60="冲锋枪","15",IF(人物卡!CC60="弓术","15",IF(人物卡!CC60="喷射器","10",IF(人物卡!CC60="机枪","10",IF(人物卡!CC60="重武器","10",IF(人物卡!CC60=人物卡!$X$112,人物卡!$AD$112,0))))))) -> 0 | AZ14: 出目 | BA14: =IF(AX27="仅显示1890_2023","",VLOOKUP(AX27,AZ25:BB29,3,FALSE)) -> #N/A | BF14: 国家数 | BG14: 第一行政区 | BH14: 国家
B15: ★ | O15: 随身物品下拉表 | U15: 1 | V15: =人物卡!BG48 -> 0 | W15: =IF(V15="步枪/霰弹枪",1,0) -> 0 | Y15: 格斗2 | Z15: =IF(人物卡!BG61="武术",1,IF(人物卡!BG61="鞭子","5",IF(人物卡!BG61="电锯","10",IF(人物卡!BG61="斧","15",IF(人物卡!BG61="剑","20",IF(人物卡!BG61="绞具","15",IF(人物卡!BG61="链枷","10",IF(人物卡!BG61="矛","20",IF(人物卡!BG61=人物卡!$X$110,人物卡!$AD$110,0))))))))) -> 0 | AA15: 射击2 | AB15: =IF(人物卡!CC61="步枪/霰弹枪","25",IF(人物卡!CC61="冲锋枪","15",IF(人物卡!CC61="弓术","15",IF(人物卡!CC61="喷射器","10",IF(人物卡!CC61="机枪","10",IF(人物卡!CC61="重武器","10",IF(人物卡!CC61=人物卡!$X$112,人物卡!$AD$112,0))))))) -> 0 | BF15: =COUNTA(BH17:BH21,BH24:BH34,BH37:BH43,BH46:BH64,BH67:BH71,BH75:BH80,BH83:BH89,BH92:BH99,BH102:BH117,BH120:BH127,BH131:BH137,BH140:BH149,BH152:BH167,BH170:BH177,BH180:BH192,BH195:BH207,BH210:BH224) -> 174 | BG15: =COUNTA(BI17:EO224) -> 2834 | BH15: ——亚洲——
L16: san值计算 | O16: 颅———— | U16: 2 | V16: =人物卡!BG49 -> 0 | W16: =IF(V16="步枪/霰弹枪",1,0) -> 0 | Y16: 格斗3 | Z16: =IF(人物卡!BG62="武术",1,IF(人物卡!BG62="鞭子","5",IF(人物卡!BG62="电锯","10",IF(人物卡!BG62="斧","15",IF(人物卡!BG62="剑","20",IF(人物卡!BG62="绞具","15",IF(人物卡!BG62="链枷","10",IF(人物卡!BG62="矛","20",IF(人物卡!BG62=人物卡!$X$110,人物卡!$AD$110,0))))))))) -> 0 | AA16: 射击3 | AB16: =IF(人物卡!CC62="步枪/霰弹枪","25",IF(人物卡!CC62="冲锋枪","15",IF(人物卡!CC62="弓术","15",IF(人物卡!CC62="喷射器","10",IF(人物卡!CC62="机枪","10",IF(人物卡!CC62="重武器","10",IF(人物卡!CC62=人物卡!$X$112,人物卡!$AD$112,0))))))) -> 0 | BH16: *东亚*
L17: 意志 | M17: 最大值 | O17: 头部 | R17: 健康 | S17: 清醒 | U17: 3 | V17: =人物卡!BG50 -> 0 | W17: =IF(V17="步枪/霰弹枪",1,0) -> 0 | Y17: 格斗4 | Z17: =IF(人物卡!BG63="武术",1,IF(人物卡!BG63="鞭子","5",IF(人物卡!BG63="电锯","10",IF(人物卡!BG63="斧","15",IF(人物卡!BG63="剑","20",IF(人物卡!BG63="绞具","15",IF(人物卡!BG63="链枷","10",IF(人物卡!BG63="矛","20",IF(人物卡!BG63=人物卡!$X$110,人物卡!$AD$110,0))))))))) -> 0 | AA17: 射击4 | AB17: =IF(人物卡!CC63="步枪/霰弹枪","25",IF(人物卡!CC63="冲锋枪","15",IF(人物卡!CC63="弓术","15",IF(人物卡!CC63="喷射器","10",IF(人物卡!CC63="机枪","10",IF(人物卡!CC63="重武器","10",IF(人物卡!CC63=人物卡!$X$112,人物卡!$AD$112,0))))))) -> 0 | BH17: 中国 | BI17: 北京市* | BJ17: 天津市 | BK17: 河北省 | BL17: 山西省 | BM17: 内蒙古自治区 | BN17: 辽宁省 | BO17: 吉林省 | BP17: 黑龙江省 | BQ17: 上海市 | BR17: 江苏省 | BS17: 浙江省 | BT17: 安徽省 | BU17: 福建省 | BV17: 江西省 | BW17: 山东省 | BX17: 河南省 | BY17: 湖北省 | BZ17: 湖南省 | CA17: 广东省 | CB17: 广西壮族自治区 | CC17: 海南省 | CD17: 重庆市 | CE17: 四川省 | CF17: 贵州省 | CG17: 云南省 | CH17: 西藏自治区 | CI17: 陕西省 | CJ17: 甘肃省 | CK17: 青海省 | CL17: 宁夏回族自治区 | CM17: 新疆维吾尔自治区 | CN17: 台湾省 | CO17: 香港特别行政区 | CP17: 澳门特别行政区
B18: 可选规则：有故事的调查员 | L18: =M14 -> 0 | M18: =人物卡!BO19 -> 99 | O18: 头发 | R18: 昏迷 | S18: 临时疯狂 | U18: 自定义 | V18: =人物卡!CA57 -> 炮术 | W18: =IF(V18="自定义技能",1,0) -> 0 | Y18: 格斗5 | Z18: =IF(人物卡!BG64="武术",1,IF(人物卡!BG64="鞭子","5",IF(人物卡!BG64="电锯","10",IF(人物卡!BG64="斧","15",IF(人物卡!BG64="剑","20",IF(人物卡!BG64="绞具","15",IF(人物卡!BG64="链枷","10",IF(人物卡!BG64="矛","20",IF(人物卡!BG64=人物卡!$X$110,人物卡!$AD$110,0))))))))) -> 0 | AA18: 射击5 | AB18: =IF(人物卡!CC64="步枪/霰弹枪","25",IF(人物卡!CC64="冲锋枪","15",IF(人物卡!CC64="弓术","15",IF(人物卡!CC64="喷射器","10",IF(人物卡!CC64="机枪","10",IF(人物卡!CC64="重武器","10",IF(人物卡!CC64=人物卡!$X$112,人物卡!$AD$112,0))))))) -> 0 | BH18: 日本 | BI18: 东京都 | BJ18: 北海道 | BK18: 大阪府 | BL18: 京都府* | BM18: 青森县 | BN18: 岩手县 | BO18: 宫城县 | BP18: 秋田县 | BQ18: 山形县 | BR18: 福岛县 | BS18: 茨城县 | BT18: 栃木县 | BU18: 群马县 | BV18: 埼玉县 | BW18: 千叶县 | BX18: 神奈川县 | BY18: 新潟县 | BZ18: 富山县 | CA18: 石川县 | CB18: 福井县 | CC18: 山梨县 | CD18: 长野县 | CE18: 岐阜县 | CF18: 静冈县 | CG18: 爱知县 | CH18: 三重县 | CI18: 滋贺县 | CJ18: 兵库县 | CK18: 奈良县 | CL18: 和歌山县 | CM18: 鸟取县 | CN18: 岛根县 | CO18: 冈山县 | CP18: 山口县 | CQ18: 徳岛县 | CR18: 香川县 | CS18: 爱媛县 | CT18: 高知县 | CU18: 福冈县 | CV18: 佐贺县 | CW18: 长崎县 | CX18: 熊本县 | CY18: 大分县 | CZ18: 宫崎县 | DA18: 鹿儿岛县 | DB18: 冲绳县 | DC18: 广岛县
B19: 名称 | C19: san | D19: 技能 | E19: 备注 | L19: 最终值 | O19: 耳朵 | R19: 重伤 | S19: 不定性疯狂 | BH19: 韩国 | BI19: 首尔* | BJ19: 釜山 | BK19: 大邱 | BL19: 仁川 | BM19: 光州 | BN19: 大田 | BO19: 蔚山 | BP19: 世宗 | BQ19: 京畿道 | BR19: 江原道 | BS19: 忠北 | BT19: 忠南 | BU19: 全北 | BV19: 全南 | BW19: 庆北 | BX19: 庆南
B20: 战场经历包 | C20: 1d10+5 | D20: 70 | E20: 对目击尸体和重伤员造成的理智损失免疫;根据战争的年份和模组发生时的年份调整年龄；背景增加一项：战争相关的伤疤 / 疤痕或恐惧症 / 躁狂症 | L20: =IF(L18>M18,M18,L18) -> 0 | O20: 面部 | R20: 死亡 | S20: 永久疯狂 | AA20: 任意 | AR20: 特定时间 | BH20: 朝鲜 | BI20: 平壤* | BJ20: 平安南道 | BK20: 平安北道 | BL20: 慈江道 | BM20: 两江道 | BN20: 咸镜南道 | BO20: 咸镜北道 | BP20: 黄海北道 | BQ20: 黄海南道 | BR20: 江原道
B21: 警务经历包 | C21: 1d10 | D21: 60 | E21: 对目击尸体造成的理智损失免疫;初始年龄不能低于 25 岁;背景增加一项：警察工作相关的伤疤 / 疤痕或恐惧症 / 躁狂症； | O21: 颈部 | R21: =IF(ISBLANK(人物卡!X122),"",人物卡!X122) | S21: =IF(ISBLANK(人物卡!AB122),"",人物卡!AB122) | AA21: =IF(ISBLANK(人物卡!CZ25),0,1) -> 0 | AB21: =IF(ISBLANK(人物卡!DI25),0,1) -> 0 | AC21: 已用总数 | AD21: 是否停用 | AE21: 最终值 | AR21: =人物卡!DK93 -> 1924 | AS21: =IF(AR21="仅显示1890_2023","",VLOOKUP(AR21,AE33:AS166,15,FALSE)) -> 纸制鸡蛋托 面巾纸 | BH21: 蒙古 | BI21: 乌兰巴托市* | BJ21: 后杭爱省 | BK21: 巴彦乌勒盖省 | BL21: 巴彦洪格尔省 | BM21: 布尔干省 | BN21: 戈壁阿尔泰省 | BO21: 东戈壁省 | BP21: 东方省 | BQ21: 中戈壁省 | BR21: 扎布汗省 | BS21: 前杭爱省 | BT21: 南戈壁省 | BU21: 苏赫巴托尔省 | BV21: 色楞格省 | BW21: 中央省 | BX21: 乌布苏省 | BY21: 科布多省 | BZ21: 库苏古尔省 | CA21: 肯特省 | CB21: 鄂尔浑省 | CC21: 达尔汗乌勒省 | CD21: 戈壁苏木贝尔省
B22: 罪犯经历包 | C22: 1d10 | D22: 60 | E22: 对目击尸体、目击或亲自谋杀、目击对人类的暴力残害造成的理智损失免疫;初始年龄不能低于 20 岁；背景增加一项：犯罪历史相关的伤疤 / 疤痕或恐惧症 / 躁狂症 | O22: 其他(头) | AA22: =IF(ISBLANK(人物卡!CZ26),0,1) -> 0 | AB22: =IF(ISBLANK(人物卡!DI26),0,1) -> 0 | AC22: =AA21+AA23+AA22+AA25+AA24+AB21+AB22+AB23+AB24+AB25 -> 0 | AD22: =IF(人物卡!CT29="提示当前职业",0,1) -> 0 | AE22: =IF(AD32=1,"仅显示1890_2023",AE28) -> 仅显示1890_2023 | AF22: =IF(AE22="仅显示1890_2023","",VLOOKUP(AE22,AE33:AS166,2,FALSE)) | AG22: =IF(AE22="仅显示1890～2023","",VLOOKUP(AE22,AE33:AS166,3,FALSE)) -> #N/A | AH22: =IF(AE22="仅显示1890～2023","",VLOOKUP(AE22,AE33:AS166,4,FALSE)) -> #N/A | AI22: =IF(AE22="仅显示1890～2023","",VLOOKUP(AE22,AE33:AS166,5,FALSE)) -> #N/A | AJ22: =IF(AE22="仅显示1890～2023","",VLOOKUP(AE22,AE33:AS166,6,FALSE)) -> #N/A | AK22: =IF(AE22="仅显示1890～2023","",VLOOKUP(AE22,AE33:AS166,7,FALSE)) -> #N/A | AL22: =IF(AE22="仅显示1890～2023","",VLOOKUP(AE22,AE33:AS166,8,FALSE)) -> #N/A | AM22: =IF(AE22="仅显示1890～2023","",VLOOKUP(AE22,AE33:AS166,9,FALSE)) -> #N/A | AN22: =IF(AE22="仅显示1890～2023","",VLOOKUP(AE22,AE33:AS166,10,FALSE)) -> #N/A | AO22: =IF(AE22="仅显示1890～2023","",VLOOKUP(AE22,AE33:AS166,11,FALSE)) -> #N/A | AP22: =IF(AE22="仅显示1890～2023","",VLOOKUP(AE22,AE33:AS166,12,FALSE)) -> #N/A | AQ22: =IF(AE22="仅显示1890～2023","",VLOOKUP(AE22,AE33:AS166,13,FALSE)) -> #N/A | AR22: =IF(AE22="仅显示1890～2023","",VLOOKUP(AE22,AE33:AS166,14,FALSE)) -> #N/A | AS22: =IF(AE22="仅显示1890～2023","",VLOOKUP(AE22,AE33:AS166,15,FALSE)) -> #N/A
B23: 医务经历包 | C23: 1d10 | D23: 60 | E23: 对目击尸体和重伤员造成的理智损失免疫;初始年龄不能低于 30 岁；背景增加一项：个人背景相关的伤疤 / 疤痕或恐惧症 / 躁狂症； | O23: 躯———— | Q23: 显露 | AA23: =IF(ISBLANK(人物卡!CZ27),0,1) -> 0 | AB23: =IF(ISBLANK(人物卡!DI27),0,1) -> 0 | AC23: 剩余 | AE23: 目前值 | BH23: *东南亚*
B24: 神话经历包 | C24: 如果是"相信者"，减少和克苏鲁神话相同的san值 | D24: 0 | E24: 按 KP 允许的数值增加「克苏鲁神话」技能;背景增加两项：与神话经历相关的伤疤 /疤痕、恐惧症 / 躁狂症、遭遇的怪异存在 | O24: 肩 | Q24: 隐藏 | S24: =".st "&"力量"&G14&"str"&G14&"敏捷"&J14&"dex"&J14&"意志"&M14&"pow"&M14&"体质"&H14&"con"&H14&"外貌"&K14&"app"&K14&"教育"&N14&"edu"&N14&"体型"&I14&"siz"&I14&"智力"&L14&"灵感"&L14&"int"&L14&"san"&人物卡!BM19&"san值"&人物卡!BM19&"理智"&人物卡!BM19&"理智值"&人物卡!BM19&"幸运"&O14&"运气"&O14&"mp"&人物卡!BV19&"魔法"&人物卡!BV19&"hp"&人物卡!BD19&"体力"&人物卡!BD19&人物卡!BE25&人物卡!BQ25&人物卡!BE26&人物卡!BQ26&人物卡!BE27&人物卡!BQ27&人物卡!BE28&人物卡!BQ28&IF(人物卡!BG29="","",人物卡!BG29&人物卡!BQ29)&IF(人物卡!BG30="","",人物卡!BG30&人物卡!BQ30)&IF(人物卡!BG31="","",人物卡!BG31&人物卡!BQ31)&人物卡!BE32&人物卡!BQ32&"魅惑"&人物卡!BQ32&人物卡!BE33&人物卡!BQ33&"计算机"&人物卡!BQ34&"计算机使用"&人物卡!BQ34&"电脑"&人物卡!BQ34&"信用"&人物卡!BQ35&"信誉"&人物卡!BQ35&"信用评级"&人物卡!BQ35&"克苏鲁"&人物卡!BQ36&"克苏鲁神话"&人物卡!BQ36&"cm"&人物卡!BQ36&人物卡!BE37&人物卡!BQ37&人物卡!BE38&人物卡!BQ38&"汽车"&人物卡!BQ39&"驾驶"&人物卡!BQ39&"汽车驾驶"&人物卡!BQ39&人物卡!BE40&人物卡!BQ40&"电子学"&人物卡!BQ41&人物卡!BE42&人物卡!BQ42&人物卡!BG43&人物卡!BQ43&IF(人物卡!BG44="","",人物卡!BG44&人物卡!BQ44)&IF(人物卡!BG45="","",人物卡!BG45&人物卡!BQ45)&IF(人物卡!BG46="","",人物卡!BG46&人物卡!BQ46)&人物卡!BG47&人物卡!BQ47&IF(W15=1,人物卡!CA48&人物卡!BQ48&"步枪"&人物卡!BQ48&"霰弹枪"&人物卡!BQ48&"步霰"&人物卡!BQ48,IF(人物卡!BG48="","",人物卡!BG48&人物卡!BQ48))&IF(W16=1,人物卡!CA49&人物卡!BQ49&"步枪"&人物卡!BQ49&"霰弹枪"&人物卡!BQ49&"步霰"&人物卡!BQ49,IF(人物卡!BG49="","",人物卡!BG49&人物卡!BQ49))&IF(W17=1,人物卡!CA50&人物卡!BQ50&"步枪"&人物卡!BQ50&"霰弹枪"&人物卡!BQ50&"步霰"&人物卡!BQ50,IF(人物卡!BG50="","",人物卡!BG50&人物卡!BQ50))&人物卡!BE51&人物卡!BQ51&人物卡!BE52&人物卡!BQ52&人物卡!BE53&人物卡!BQ53&人物卡!BE54&人物卡!BQ54&IF(人物卡!BG55="","",人物卡!BG55&人物卡!BQ55)&IF(人物卡!BG56="","",人物卡!BG56&人物卡!BQ56)&IF(人物卡!BG57="","",人物卡!BG57&人物卡!BQ57)&人物卡!BE58&人物卡!BQ58&人物卡!CA25&人物卡!CM25&"图书馆"&人物卡!CM26&"图书馆使用"&人物卡!CM26&人物卡!CA27&人物卡!CM27&"开锁"&人物卡!CM28&"撬锁"&人物卡!CM28&"锁匠"&人物卡!CM28&人物卡!CA29&人物卡!CM29&人物卡!CA30&人物卡!CM30&"博物学"&人物卡!CM31&"自然学"&人物卡!CM31&"领航"&人物卡!CM32&"导航"&人物卡!CM32&人物卡!CA33&人物卡!CM33&"重型操作"&人物卡!CM34&"重型机械"&人物卡!CM34&"操作重型机械"&人物卡!CM34&"重型"&人物卡!CM34&人物卡!CA35&人物卡!CM35&IF(人物卡!CC36="","",人物卡!CC36&人物卡!CM36)&人物卡!CA37&人物卡!CM37&人物卡!CA38&人物卡!CM38&人物卡!CA39&人物卡!CM39&IF(人物卡!CC40="","",人物卡!CC40&人物卡!CM40)&IF(人物卡!CC41="","",人物卡!CC41&人物卡!CM41)&IF(人物卡!CC42="","",人物卡!CC42&人物卡!CM42)&人物卡!CA43&人物卡!CM43&人物卡!CA44&人物卡!CM44&人物卡!CA45&人物卡!CM45&"生存"&人物卡!CM46&人物卡!CA47&人物卡!CM47&人物卡!CA48&人物卡!CM48&人物卡!CA49&人物卡!CM49&人物卡!CA50&人物卡!CM50&人物卡!CA51&人物卡!CM51&人物卡!CA52&人物卡!CM52&人物卡!CA53&人物卡!CM53&人物卡!CA54&人物卡!CM54&人物卡!CA55&人物卡!CM55&IF(人物卡!CC56="","",人物卡!CC56&人物卡!CM56)&IF(W18=1,"",人物卡!CA57&人物卡!CM57)&IF(人物卡!CA58="","",人物卡!CA58&人物卡!CM58) -> .st 力量0str0敏捷0dex0意志0pow0体质0con0外貌0app0教育0edu0体型0siz0智力0灵感0int0san0san值0理智0理智值0幸运0运气0mp0魔法0hp0体力0会计5法律5历史5人类学1神秘学5魅惑5信用评级0计算机0计算机使用0电脑0信用10信誉10信用评级10克苏鲁10克苏鲁神话10cm10电子学 Ω1操作重型机械1汽车1驾驶1汽车驾驶1计算机使用 Ω0电子学1科学②115技艺⑤5母语0外语①1外语②1闪避0锁匠1图书馆5图书馆使用5妙手10开锁20撬锁20锁匠20图书馆使用20聆听20博物学25自然学25领航10导航10导航10重型操作10重型机械10操作重型机械10重型10取悦15恐吓15说服10跳跃20游泳20精神分析1医学1生存30驾驶①1驾驶②1汽车驾驶20骑术5动物驯养5潜水1读唇1催眠1自定义①1炮术1投掷20 | AA24: =IF(ISBLANK(人物卡!CZ28),0,1) -> 0 | AB24: =IF(ISBLANK(人物卡!DI28),0,1) -> 0 | AC24: =人物卡!BE18-AC22 -> 0 | AE24: =人物卡!BF17 -> 0 | AX24: 总值 | AZ24: 分类 | BH24: 越南 | BI24: 河内市* | BJ24: 胡志明市 | BK24: 岘港市 | BL24: 海防市 | BM24: 芹苴市 | BN24: 安江省 | BO24: 北江省 | BP24: 北件省 | BQ24: 北宁省 | BR24: 薄辽省 | BS24: 北𣴓省 | BT24: 巴地-头顿省 | BU24: 槟椥省 | BV24: 平定省 | BW24: 平阳省 | BX24: 平福省 | BY24: 平顺省 | BZ24: 富安省 | CA24: 富寿省 | CB24: 高平省 | CC24: 广安省 | CD24: 广宁省 | CE24: 广平省 | CF24: 广南省 | CG24: 广义省 | CH24: 广治省 | CI24: 河南省 | CJ24: 和平省 | CK24: 后江省 | CL24: 海阳省 | CM24: 海防市 | CN24: 河江省 | CO24: 河静省 | CP24: 河北省 | CQ24: 河东省 | CR24: 河西省 | CS24: 兴安省 | CT24: 坚江省 | CU24: 嘉莱省 | CV24: 昆嵩省 | CW24: 莱州省 | CX24: 林同省 | CY24: 谅山省 | CZ24: 隆安省 | DA24: 南定省 | DB24: 宁平省 | DC24: 宁顺省 | DD24: 义安省 | DE24: 前江省 | DF24: 芹苴市 | DG24: 清化省 | DH24: 庆和省 | DI24: 山罗省 | DJ24: 山西省 | DK24: 西宁省 | DL24: 太平省 | DM24: 太原省 | DN24: 同奈省 | DO24: 同塔省 | DP24: 宣光省 | DQ24: 永福省 | DR24: 永隆省 | DS24: 安沛省
B25: =IF(ISBLANK(人物卡!AF108),"自定义经历包",人物卡!AF108) -> 自定义经历包 | C25: ='简化卡 骰娘导入'!E96 | D25: ='简化卡 骰娘导入'!H96 | E25: ='简化卡 骰娘导入'!J96 | O25: 胸前 | X25: 会计 | AB25: =IF(ISBLANK(人物卡!DI29),0,1) -> 0 | AC25: 最终显示 | AD25: =IF(AD22=1," ",IF(AC24=0,"无",IF(AC24<0,"过多！",AC24))) -> 无 | AE25: 公元调整 | AT25: 未出现的 | AV25: =IF(AT25=人物卡!CY93,1,0) -> 0 | AZ25: 1 | BA25: 未出现的发明 | BB25: =AQ22 -> #N/A | BH25: 老挝 | BI25: 万象市* | BJ25: 波里坎赛省 | BK25: 博胶省 | BL25: 川圹省 | BM25: 甘蒙省 | BN25: 华潘省 | BO25: 琅勃拉邦省 | BP25: 琅南塔省 | BQ25: 丰沙里省 | BR25: 乌多姆赛省 | BS25: 沙耶武里省 | BT25: 沙湾拿吉省 | BU25: 色贡省 | BV25: 沙拉湾省 | BW25: 赛宋本行政特区 | BX25: 万象省 | BY25: 占巴塞省
B26: 无 | O26: 背后 | X26: 法律 | AE26: =IF(人物卡!BD17="公元前",人物卡!BF17*2,0) -> 0 | AT26: 已出现的 | AV26: =IF(AT26=人物卡!CY93,2,0) -> 2 | AZ26: 2 | BA26: 已出现的发明 | BB26: =AR22 -> #N/A | BH26: 柬埔寨 | BI26: 金边直辖市* | BJ26: 马德望省 | BK26: 磅湛省 | BL26: 磅清扬省 | BM26: 磅士卑省 | BN26: 磅同省 | BO26: 贡布省 | BP26: 干丹省 | BQ26: 茶胶省 | BR26: 柴桢省 | BS26: 波萝勉省 | BT26: 菩萨省 | BU26: 西哈努克省 | BV26: 柏威夏省 | BW26: 上丁省 | BX26: 桔井省 | BY26: 腊塔纳基里省 | BZ26: 蒙多基里省
C27: =IF(人物卡!BE148=B20,C20,0) -> 0 | D27: =IF(人物卡!BE148=B20,D20,0) -> 0 | E27: =IF(人物卡!BE148=B20,E20,0) -> 0 | O27: 肋 | X27: 历史 | AB27: 经历包剩余点 | AC27: =D34-SUM(人物卡!BK25:BK58,人物卡!CG25:CG58) -> #VALUE! | AD27: 最终值 | AE27: 调整出目 | AX27: =AV25+AV26+AV28+AV29+AV30 -> 2 | AZ27: 3 | BA27: 本年的发明 | BB27: =AS22 -> #N/A | BH27: 泰国 | BI27: 曼谷直辖市* | BJ27: 清迈府 | BK27: 清莱府 | BL27: 甘烹碧府 | BM27: 南邦府 | BN27: 南奔府 | BO27: 夜丰颂府 | BP27: 北榄坡府 | BQ27: 楠府 | BR27: 帕尧府 | BS27: 碧差汶府 | BT27: 披集府 | BU27: 彭世洛府 | BV27: 帕府 | BW27: 素可泰府 | BX27: 达府 | BY27: 乌泰他尼府 | BZ27: 程逸府 | CA27: 安纳乍能府 | CB27: 武里南府 | CC27: 猜也奔府 | CD27: 加拉信府 | CE27: 孔敬府 | CF27: 黎府 | CG27: 玛哈沙拉堪府 | CH27: 莫拉限府 | CI27: 那空帕侬府 | CJ27: 呵叻府 | CK27: 廊磨喃蒲府 | CL27: 廊开府 | CM27: 横逸府 | CN27: 色军府 | CO27: 四色菊府 | CP27: 素辇府 | CQ27: 乌汶府 | CR27: 乌隆他尼府 | CS27: 益梭通府 | CT27: 汶干府 | CU27: 北柳府 | CV27: 尖竹汶府 | CW27: 春武里府 | CX27: 巴真府 | CY27: 罗勇府 | CZ27: 沙缴府 | DA27: 达叻府 | DB27: 红统府 | DC27: 大城府 | DD27: 猜纳府 | DE27: 北碧府 | DF27: 华富里府 | DG27: 那空那育府 | DH27: 佛统府 | DI27: 暖武里府 | DJ27: 巴吞他尼府 | DK27: 佛丕府 | DL27: 班武里府 | DM27: 叻丕府 | DN27: 北榄府 | DO27: 龙仔厝府 | DP27: 夜功府 | DQ27: 北标府 | DR27: 信武里府 | DS27: 素攀府 | DT27: 洛坤府 | DU27: 甲米府 | DV27: 攀牙府 | DW27: 普吉府 | DX27: 素叻他尼府 | DY27: 拉侬府 | DZ27: 春蓬府 | EA27: 宋卡府 | EB27: 沙敦府 | EC27: 董里府 | ED27: 博达伦府 | EE27: 北大年府 | EF27: 也拉府 | EG27: 陶公府
C28: =IF(人物卡!BE148=B21,C21,0) -> 0 | D28: =IF(人物卡!BE148=B21,D21,0) -> 0 | E28: =IF(人物卡!BE148=B21,E21,0) -> 0 | O28: 裆 | X28: 人类学 | AB28: 检测是否为数字 | AC28: =ISNUMBER(AC27) -> FALSE | AD28: =IF(AC28=FALSE,"0",AC27) -> 0 | AE28: =AE24-AE26 -> 0 | AT28: 本年的发明 | AV28: =IF(AT28=人物卡!CY93,3,0) -> 0 | AZ28: 4 | BA28: 查找年份发明 | BB28: =AS21 -> 纸制鸡蛋托 面巾纸 | BH28: 缅甸 | BI28: 内比都联邦区* | BJ28: 仰光省 | BK28: 曼德勒省 | BL28: 马圭省 | BM28: 实皆省 | BN28: 伊洛瓦底省 | BO28: 德林达依省 | BP28: 勃固省 | BQ28: 若开邦 | BR28: 钦邦 | BS28: 掸邦 | BT28: 克耶邦 | BU28: 克伦邦 | BV28: 孟邦 | BW28: 克钦邦
C29: =IF(人物卡!BE148=B22,C22,0) -> 0 | D29: =IF(人物卡!BE148=B22,D22,0) -> 0 | E29: =IF(人物卡!BE148=B22,E22,0) -> 0 | O29: 腰 | X29: 估价 | AB29: 职业点数 | AC29: =IF(人物卡!BL11=0," ",LOOKUP(人物卡!BL11,职业列表!A2:C237,职业列表!F2:F237)) | AD29: 检测大小 | AT29: 查找年份发明 | AV29: =IF(AT29=人物卡!CY93,4,0) -> 0 | AZ29: 5 | BA29: 查找发明的时间 | BB29: ? | BH29: 马来西亚 | BI29: 吉隆坡联邦直辖区* | BJ29: 玻璃市州 | BK29: 吉打州 | BL29: 吉兰丹州 | BM29: 槟城州 | BN29: 霹雳州 | BO29: 雪兰莪州 | BP29: 森美兰州 | BQ29: 马六甲州 | BR29: 柔佛州 | BS29: 彭亨州 | BT29: 登嘉楼州 | BU29: 沙巴州 | BV29: 砂拉越州 | BW29: 布城联邦直辖区 | BX29: 纳闽联邦直辖区
C30: =IF(人物卡!BE148=B23,C23,0) -> 0 | D30: =IF(人物卡!BE148=B23,D23,0) -> 0 | E30: =IF(人物卡!BE148=B23,E23,0) -> 0 | O30: 胯 | X30: 考古学 | AD30: =IF(AE30="大",1,0) -> 0 | AE30: =IF(AE28>2023,"大") -> FALSE | AT30: 研发中... | AU30: 查找发明的时间 | AV30: =IF(AU30=人物卡!CY93,5,0) -> 0 | BH30: 新加坡 | BI30: 新加坡市
C31: =IF(人物卡!BE148=B24,C24,0) -> 0 | D31: =IF(人物卡!BE148=B24,D24,0) -> 0 | E31: =IF(人物卡!BE148=B24,E24,0) -> 0 | O31: 其他(躯) | X31: 博物学 | AD31: =IF(AE31="小",1,0) -> 1 | AE31: =IF(AE28<1890,"小") -> 小 | BH31: 印度尼西亚 | BI31: 雅加达首都特区* | BJ31: 日惹特区 | BK31: 泗水（苏腊巴亚）市 | BL31: 棉兰市 | BM31: 登巴萨市 | BN31: 万隆市 | BO31: 巴厘省 | BP31: 西爪哇省 | BQ31: 中爪哇省 | BR31: 东爪哇省 | BS31: 北苏门答腊省 | BT31: 南苏门答腊省 | BU31: 楠榜省 | BV31: 邦加-勿里洞省 | BW31: 明古鲁省 | BX31: 廖内省 | BY31: 廖内群岛省 | BZ31: 占碑省 | CA31: 朋古鲁省 | CB31: 南榜省 | CC31: 巨港（巴邻旁）市 | CD31: 西苏门答腊省 | CE31: 西加里曼丹省 | CF31: 中加里曼丹省 | CG31: 南加里曼丹省 | CH31: 东加里曼丹省 | CI31: 北加里曼丹省 | CJ31: 马鲁古省 | CK31: 北马鲁古省 | CL31: 中马鲁古省 | CM31: 哈马黑拉省 | CN31: 东南苏拉威西省 | CO31: 南苏拉威西省 | CP31: 中苏拉威西省 | CQ31: 西苏拉威西省 | CR31: 哥伦打洛省 | CS31: 戈龙塔洛省 | CT31: 北苏拉威西省 | CU31: 巴厘岛省 | CV31: 努沙登加拉西省（西努沙登加拉省） | CW31: 努沙登加拉东省（东努沙登加拉省）
C32: =IF(人物卡!BE148=B25,C25,0) | D32: =IF(人物卡!BE148=B25,D25,0) | E32: =IF(人物卡!BE148=B25,E25,0) | O32: 服———— | X32: 神秘学 | AD32: =AD30+AD31 -> 1 | AE32: 年份 | AF32: 国际重大时代标志 | AG32: 2 | AH32: 3 | AI32: 中国重大时代标志 | AL32: 年代 | AO32: 重大事件 | AP32: 名人 | AQ32: 未出现的发明 | AR32: 已出现的发明 | AS32: 本年发明 | BH32: 菲律宾 | BI32: 马尼拉市* | BJ32: 甲米地省 | BK32: 巴丹省 | BL32: 布拉干省 | BM32: 黎刹省 | BN32: 邦板牙省 | BO32: 布拉卡省 | BP32: 打拉省 | BQ32: 北伊罗戈省 | BR32: 南伊罗戈省 | BS32: 拉翁省 | BT32: 卡加延省 | BU32: 伊莎贝拉省 | BV32: 新比斯开省 | BW32: 季里诺省 | BX32: 巴塔安省 | BY32: 巴拉望省 | BZ32: 本格特省 | CA32: 布尔迪奥斯省 | CB32: 卡林阿省 | CC32: 卡坦端内斯省 | CD32: 奎松省 | CE32: 马林杜克省 | CF32: 马京达瑙省 | CG32: 北三宝颜省 | CH32: 南三宝颜省 | CI32: 西民都洛省 | CJ32: 东民都洛省 | CK32: 棉兰老岛穆斯林自治区 | CL32: 米沙鄢群岛 | CM32: 棉兰老岛 | CN32: 宿务省 | CO32: 达沃省 | CP32: 东达沃省 | CQ32: 北苏里高省 | CR32: 南苏里高省 | CS32: 塔威塔威省
O33: 衣兜 | X33: 信用评级 | AE33: 1890 | AF33: 梵高饮弹自尽 | AG33: 发现火星“人工运河” | AI33: —— | AL33: 十九世纪 九十年代 | AM33: 庚寅虎年 | AN33: 清光绪16年 | AO33: 芝加哥建设世界首座全钢结构建筑 伦敦首条电气地铁 英国鱼雷巡洋舰蛇号在西班牙海岸失事，死亡 167 人 坐牛在印第安人起义中被杀 首个圣代冰淇淋 美国总人口达到 629 万 | AP33: 总统： 本杰明·哈里森（共和党） | AQ33: 实用水电站 手电 电影摄影机 收音机 霍乱疫苗 啤酒瓶盖 柴油发动机 双向电报 实用的胶卷 块麦片 电报 可口可乐 X射线 卷烟机发明 电影放映机 排球 印名片机福特车 潜望镜 油印蜡纸发明 阴极射线管 商品阿司匹林 凯洛格牌玉米片 手电筒 钋 镭 摇控器 α粒子 β粒子 打字机 柯达布朗尼相机 齐柏林飞艇 人类血型 跨大西洋电报 汽轮机游船 现代柏油路 铝罐奶粉 爆米花 泰迪熊 卡鲁索电唱机 便宜的肥皂和烹饪用油 飞机 荧光灯 邮戳机 摩托车发动机 热水瓶 农业轨道机械 木棉安全带 电动汽车喇叭 化学泡沫灭火器 狭义相对论 自动点唱机 量产舰艇舷外发动机 动画 电动洗衣机 家用洗洁精 立式吸尘器 饮用纸杯 双层公交车 无线电测向仪 电煎锅 质子和电子 玻璃纸 战壕风衣 汽车自动起动器 麦片 氯气毒气 防毒面具 拉链 机械雨刮器 广义相对论 芥子气 量产拖拉机 电子钟 黄油枪 降落伞 广播电台播音 茶包 罗夏墨迹测验 机器人 胰岛素 实用邮戳机 滑水 百日咳疫苗 纸制鸡蛋托 面巾纸 商用飞机农药喷撒 液体燃料火箭 劳力士防水表 遥控电唱机 面包机 防水玻璃纸 电传打字机 盖革计数器 纯维生素C 彩色电影胶片 透明胶带 音乐汽车喇叭 闪光灯 速冻食品 球形潜水舱 回旋加速器 折叠式雨伞 电动剃须刀 车载收音机 玛氏巧克力棒 变焦镜头 大富翁桌游 商业洗衣店 畅销平装书 里氏震级 磁带录音机 大众汽车 超市推车 带温控器的电熨斗 速溶咖啡 尼龙 圆珠笔 黄热病疫苗 雷达 汽车自动变速箱 充气救生衣 人工授精 青霉素 军用吉普车 原子裂变 火箭筒 凝固汽油弹 水肺 麦角酸二乙酰胺 神经毒气 原子弹 特百惠 计算机 静电复印法 比基尼泳衣 浓缩咖啡机 宝丽来相机 拼字盘 实心电吉他 尼龙扣 晶体管 黑胶唱片 有线电视 电视显像管 汽车自动点火装置 信用卡 复印机 宽荧幕电影 动力转向器 三色停车灯 人行红绿灯 晶体管助听器 氢弹 录像带 DNA双螺旋结构 麻疹疫苗 按动圆珠笔 硅晶体管 核导弹 空对空导弹 迪士尼乐园 特氟龙 卡丁车 地对空核导弹 沙宾疫苗 通讯卫星 呼啦圈 安全带 人工肾脏 避孕药 气象卫星 便携晶体管收音机 安定 砷化镓半导体激光器 三维全息技术 合成器 香烟健康警示 凯夫拉纤维 子午胎 IBM文字处理机 杜比A型降噪器 滑雪板 喇叭裤 绕月载人火箭 人工心脏移植 波音747喷气式客机 互联网 条形码 软盘 帆板 热裤 液晶显示 便携电子计算器 电视游戏 DNA重组技术 电子游戏机 超级计算机 光纤 试管婴儿 魔方 索尼Walkman 杜比C型降噪器 艾滋病毒 强效可卡因 温室效应 CD 暗物质 暗能量 太阳能飞行器 甲型H1N1 流感 希格斯玻色子 引力波 | AR33: 电气地铁 圣代冰淇淋 | AS33: 电气地铁 圣代冰淇淋 | AT33: 1890 | BH33: 文莱 | BI33: 斯里巴加湾市*
C34: =IF(C27=0,IF(C28=0,IF(C29=0,IF(C30=0,IF(C31=0,IF(C32=0,"",C32),C31),C30),C29),C28),C27) | D34: =IF(D27=0,IF(D28=0,IF(D29=0,IF(D30=0,IF(D31=0,IF(D32=0,0,D32),D31),D30),D29),D28),D27) | E34: =IF(E27=0,IF(E28=0,IF(E29=0,IF(E30=0,IF(E31=0,IF(E32=0,"",E32),E31),E30),E29),E28),E27) | O34: 内衬 | X34: 克苏鲁神话 | AA34: =AA50&AA62 -> .st力量未填写str未填写敏捷未填写dex未填写意志未填写pow未填写体质未填写con未填写外貌未填写app未填写教育未填写edu未填写体型未填写siz未填写智力未填写int未填写灵感未填写san0san值0理智0理智值0幸运0运气0mp0魔法0hp0体力0会计5法律5历史5人类学1估价5考古学1博物学10神秘学5信用评级0克苏鲁神话0机械维修10电气维修10电子学1操作重型机械1爆破1计算机使用0母语0闪避0斗殴25锁匠1乔装5妙手10潜行20图书馆使用20聆听20侦查25追踪10导航10心理学10取悦15话术5恐吓15说服10跳跃20攀爬20游泳20精神分析1医学1急救30汽车驾驶20骑术5动物驯养5潜水1读唇1催眠1炮术1投掷20手枪20 | AC34: =_xlfn.CONCAT(AA56,AA67) -> .st力量str敏捷dex意志pow体质con外貌app教育edu体型siz智力int灵感san0san值0理智0理智值0幸运0运气0mp0魔法0hp0体力0会计5法律5历史5人类学1估价5考古学1博物学10神秘学5信用评级0克苏鲁神话0机械维修10电气维修10电子学1操作重型机械1爆破1计算机使用0母语0闪避0斗殴25锁匠1乔装5妙手10潜行20图书馆使用20聆听20侦查25追踪10导航10心理学10取悦15话术5恐吓15说服10跳跃20攀爬20游泳20精神分析1医学1急救30汽车驾驶20骑术5动物驯养5潜水1读唇1催眠1炮术1投掷20手枪20 | AD34: =IF(人物卡!CM69="","",".st&"&人物卡!CM69&"="&人物卡!BU69) | AE34: 1891 | AF34: 马德里协定 | AI34: —— | AL34: 十九世纪 九十年代 | AM34: 辛卯兔年 | AN34: 清光绪17年 | AO34: 日本浓尾大地震，毁坏 2 万房屋，死亡 2.5万人 首个实用水电站 英国普及手电 爱迪生申请到电影摄影机的专利权 爱迪生拿到收音机的专利 | AP34: 总统： 本杰明·哈里森（共和党） | AQ34: 霍乱疫苗 啤酒瓶盖 柴油发动机 双向电报 实用的胶卷 块麦片 电报 可口可乐 X射线 卷烟机发明 电影放映机 排球 印名片机福特车 潜望镜 油印蜡纸发明 阴极射线管 商品阿司匹林 凯洛格牌玉米片 手电筒 钋 镭 摇控器 α粒子 β粒子 打字机 柯达布朗尼相机 齐柏林飞艇 人类血型 跨大西洋电报 汽轮机游船 现代柏油路 铝罐奶粉 爆米花 泰迪熊 卡鲁索电唱机 便宜的肥皂和烹饪用油 飞机 荧光灯 邮戳机 摩托车发动机 热水瓶 农业轨道机械 木棉安全带 电动汽车喇叭 化学泡沫灭火器 狭义相对论 自动点唱机 量产舰艇舷外发动机 动画 电动洗衣机 家用洗洁精 立式吸尘器 饮用纸杯 双层公交车 无线电测向仪 电煎锅 质子和电子 玻璃纸 战壕风衣 汽车自动起动器 麦片 氯气毒气 防毒面具 拉链 机械雨刮器 广义相对论 芥子气 量产拖拉机 电子钟 黄油枪 降落伞 广播电台播音 茶包 罗夏墨迹测验 机器人 胰岛素 实用邮戳机 滑水 百日咳疫苗 纸制鸡蛋托 面巾纸 商用飞机农药喷撒 液体燃料火箭 劳力士防水表 遥控电唱机 面包机 防水玻璃纸 电传打字机 盖革计数器 纯维生素C 彩色电影胶片 透明胶带 音乐汽车喇叭 闪光灯 速冻食品 球形潜水舱 回旋加速器 折叠式雨伞 电动剃须刀 车载收音机 玛氏巧克力棒 变焦镜头 大富翁桌游 商业洗衣店 畅销平装书 里氏震级 磁带录音机 大众汽车 超市推车 带温控器的电熨斗 速溶咖啡 尼龙 圆珠笔 黄热病疫苗 雷达 汽车自动变速箱 充气救生衣 人工授精 青霉素 军用吉普车 原子裂变 火箭筒 凝固汽油弹 水肺 麦角酸二乙酰胺 神经毒气 原子弹 特百惠 计算机 静电复印法 比基尼泳衣 浓缩咖啡机 宝丽来相机 拼字盘 实心电吉他 尼龙扣 晶体管 黑胶唱片 有线电视 电视显像管 汽车自动点火装置 信用卡 复印机 宽荧幕电影 动力转向器 三色停车灯 人行红绿灯 晶体管助听器 氢弹 录像带 DNA双螺旋结构 麻疹疫苗 按动圆珠笔 硅晶体管 核导弹 空对空导弹 迪士尼乐园 特氟龙 卡丁车 地对空核导弹 沙宾疫苗 通讯卫星 呼啦圈 安全带 人工肾脏 避孕药 气象卫星 便携晶体管收音机 安定 砷化镓半导体激光器 三维全息技术 合成器 香烟健康警示 凯夫拉纤维 子午胎 IBM文字处理机 杜比A型降噪器 滑雪板 喇叭裤 绕月载人火箭 人工心脏移植 波音747喷气式客机 互联网 条形码 软盘 帆板 热裤 液晶显示 便携电子计算器 电视游戏 DNA重组技术 电子游戏机 超级计算机 光纤 试管婴儿 魔方 索尼Walkman 杜比C型降噪器 艾滋病毒 强效可卡因 温室效应 CD 暗物质 暗能量 太阳能飞行器 甲型H1N1 流感 希格斯玻色子 引力波 | AR34: 电气地铁 圣代冰淇淋 实用水电站 手电 电影摄影机 收音机 | AS34: 实用水电站 手电 电影摄影机 收音机 | AT34: 1891 | BH34: 东帝汶 | BI34: 帝力市*
O35: 衣服内 | X35: 机械维修 | AD35: =IF(人物卡!CM70="","",".st&"&人物卡!CM70&"="&人物卡!BU70) | AE35: 1892 | AF35: —— | AI35: —— | AL35: 十九世纪 九十年代 | AM35: 壬辰龙年 | AN35: 清光绪18年 | AO35: 宾夕法尼亚州石油城暴发洪水，死亡130 人 霍乱疫苗 开普敦 - 约翰内斯堡铁路竣工 啤酒瓶盖发明 柴油发动机取得专利 爱迪生获得双向电报的专利权 | AP35: 书籍： 阿瑟·柯南·道尔出版《福尔摩斯办案记》（The Adventures of Sherlock Holmes） 总统： 本杰明·哈里森（共和党） | AQ35: 实用的胶卷 块麦片 电报 可口可乐 X射线 卷烟机发明 电影放映机 排球 印名片机福特车 潜望镜 油印蜡纸发明 阴极射线管 商品阿司匹林 凯洛格牌玉米片 手电筒 钋 镭 摇控器 α粒子 β粒子 打字机 柯达布朗尼相机 齐柏林飞艇 人类血型 跨大西洋电报 汽轮机游船 现代柏油路 铝罐奶粉 爆米花 泰迪熊 卡鲁索电唱机 便宜的肥皂和烹饪用油 飞机 荧光灯 邮戳机 摩托车发动机 热水瓶 农业轨道机械 木棉安全带 电动汽车喇叭 化学泡沫灭火器 狭义相对论 自动点唱机 量产舰艇舷外发动机 动画 电动洗衣机 家用洗洁精 立式吸尘器 饮用纸杯 双层公交车 无线电测向仪 电煎锅 质子和电子 玻璃纸 战壕风衣 汽车自动起动器 麦片 氯气毒气 防毒面具 拉链 机械雨刮器 广义相对论 芥子气 量产拖拉机 电子钟 黄油枪 降落伞 广播电台播音 茶包 罗夏墨迹测验 机器人 胰岛素 实用邮戳机 滑水 百日咳疫苗 纸制鸡蛋托 面巾纸 商用飞机农药喷撒 液体燃料火箭 劳力士防水表 遥控电唱机 面包机 防水玻璃纸 电传打字机 盖革计数器 纯维生素C 彩色电影胶片 透明胶带 音乐汽车喇叭 闪光灯 速冻食品 球形潜水舱 回旋加速器 折叠式雨伞 电动剃须刀 车载收音机 玛氏巧克力棒 变焦镜头 大富翁桌游 商业洗衣店 畅销平装书 里氏震级 磁带录音机 大众汽车 超市推车 带温控器的电熨斗 速溶咖啡 尼龙 圆珠笔 黄热病疫苗 雷达 汽车自动变速箱 充气救生衣 人工授精 青霉素 军用吉普车 原子裂变 火箭筒 凝固汽油弹 水肺 麦角酸二乙酰胺 神经毒气 原子弹 特百惠 计算机 静电复印法 比基尼泳衣 浓缩咖啡机 宝丽来相机 拼字盘 实心电吉他 尼龙扣 晶体管 黑胶唱片 有线电视 电视显像管 汽车自动点火装置 信用卡 复印机 宽荧幕电影 动力转向器 三色停车灯 人行红绿灯 晶体管助听器 氢弹 录像带 DNA双螺旋结构 麻疹疫苗 按动圆珠笔 硅晶体管 核导弹 空对空导弹 迪士尼乐园 特氟龙 卡丁车 地对空核导弹 沙宾疫苗 通讯卫星 呼啦圈 安全带 人工肾脏 避孕药 气象卫星 便携晶体管收音机 安定 砷化镓半导体激光器 三维全息技术 合成器 香烟健康警示 凯夫拉纤维 子午胎 IBM文字处理机 杜比A型降噪器 滑雪板 喇叭裤 绕月载人火箭 人工心脏移植 波音747喷气式客机 互联网 条形码 软盘 帆板 热裤 液晶显示 便携电子计算器 电视游戏 DNA重组技术 电子游戏机 超级计算机 光纤 试管婴儿 魔方 索尼Walkman 杜比C型降噪器 艾滋病毒 强效可卡因 温室效应 CD 暗物质 暗能量 太阳能飞行器 甲型H1N1 流感 希格斯玻色子 引力波 | AR35: 电气地铁 圣代冰淇淋 实用水电站 手电 电影摄影机 收音机 霍乱疫苗 啤酒瓶盖 柴油发动机 双向电报 | AS35: 霍乱疫苗 啤酒瓶盖 柴油发动机 双向电报 | AT35: 1892
C36: 年龄 | D36: 最终值 | I36: 毒剂示例 | O36: 裤兜 | X36: 电气维修 | AD36: =IF(人物卡!CM71="","",".st&"&人物卡!CM71&"="&人物卡!BU71) | AE36: 1893 | AF36: 新西兰给予女性投票权 | AG36: 第一次里夫战争 | AI36: —— | AL36: 十九世纪 九十年代 | AM36: 癸巳蛇年 | AN36: 清光绪19年 | AO36: 飓风造成的洪水袭击美国南部西海岸 ,死亡 2000 人 首个实用的胶卷 块麦片 芝加哥万国博览会 | AP36: 总统： 本杰明·哈里森（共和党） 格罗佛·克利夫兰（民主党） | AQ36: 电报 可口可乐 X射线 卷烟机发明 电影放映机 排球 印名片机福特车 潜望镜 油印蜡纸发明 阴极射线管 商品阿司匹林 凯洛格牌玉米片 手电筒 钋 镭 摇控器 α粒子 β粒子 打字机 柯达布朗尼相机 齐柏林飞艇 人类血型 跨大西洋电报 汽轮机游船 现代柏油路 铝罐奶粉 爆米花 泰迪熊 卡鲁索电唱机 便宜的肥皂和烹饪用油 飞机 荧光灯 邮戳机 摩托车发动机 热水瓶 农业轨道机械 木棉安全带 电动汽车喇叭 化学泡沫灭火器 狭义相对论 自动点唱机 量产舰艇舷外发动机 动画 电动洗衣机 家用洗洁精 立式吸尘器 饮用纸杯 双层公交车 无线电测向仪 电煎锅 质子和电子 玻璃纸 战壕风衣 汽车自动起动器 麦片 氯气毒气 防毒面具 拉链 机械雨刮器 广义相对论 芥子气 量产拖拉机 电子钟 黄油枪 降落伞 广播电台播音 茶包 罗夏墨迹测验 机器人 胰岛素 实用邮戳机 滑水 百日咳疫苗 纸制鸡蛋托 面巾纸 商用飞机农药喷撒 液体燃料火箭 劳力士防水表 遥控电唱机 面包机 防水玻璃纸 电传打字机 盖革计数器 纯维生素C 彩色电影胶片 透明胶带 音乐汽车喇叭 闪光灯 速冻食品 球形潜水舱 回旋加速器 折叠式雨伞 电动剃须刀 车载收音机 玛氏巧克力棒 变焦镜头 大富翁桌游 商业洗衣店 畅销平装书 里氏震级 磁带录音机 大众汽车 超市推车 带温控器的电熨斗 速溶咖啡 尼龙 圆珠笔 黄热病疫苗 雷达 汽车自动变速箱 充气救生衣 人工授精 青霉素 军用吉普车 原子裂变 火箭筒 凝固汽油弹 水肺 麦角酸二乙酰胺 神经毒气 原子弹 特百惠 计算机 静电复印法 比基尼泳衣 浓缩咖啡机 宝丽来相机 拼字盘 实心电吉他 尼龙扣 晶体管 黑胶唱片 有线电视 电视显像管 汽车自动点火装置 信用卡 复印机 宽荧幕电影 动力转向器 三色停车灯 人行红绿灯 晶体管助听器 氢弹 录像带 DNA双螺旋结构 麻疹疫苗 按动圆珠笔 硅晶体管 核导弹 空对空导弹 迪士尼乐园 特氟龙 卡丁车 地对空核导弹 沙宾疫苗 通讯卫星 呼啦圈 安全带 人工肾脏 避孕药 气象卫星 便携晶体管收音机 安定 砷化镓半导体激光器 三维全息技术 合成器 香烟健康警示 凯夫拉纤维 子午胎 IBM文字处理机 杜比A型降噪器 滑雪板 喇叭裤 绕月载人火箭 人工心脏移植 波音747喷气式客机 互联网 条形码 软盘 帆板 热裤 液晶显示 便携电子计算器 电视游戏 DNA重组技术 电子游戏机 超级计算机 光纤 试管婴儿 魔方 索尼Walkman 杜比C型降噪器 艾滋病毒 强效可卡因 温室效应 CD 暗物质 暗能量 太阳能飞行器 甲型H1N1 流感 希格斯玻色子 引力波 | AR36: 电气地铁 圣代冰淇淋 实用水电站 手电 电影摄影机 收音机 霍乱疫苗 啤酒瓶盖 柴油发动机 双向电报 实用的胶卷 块麦片 | AS36: 实用的胶卷 块麦片 | AT36: 1893 | AV36: 电报 可口可乐 | BB36: 名片 | BH36: *南亚*
C37: {=IFERROR(0,fABS(人物卡!BD12))} -> 0 | D37: =IF(ISBLANK(人物卡!X119),IF(AND(C37>=15,C37<=19),D39,IF(AND(C37>=20,C37<=39),D40,IF(AND(C37>=40,C37<=49),D41,IF(AND(C37>=50,C37<=59),D42,IF(AND(C37>=60,C37<=69),D43,IF(AND(C37>=70,C37<=79),D44,IF(AND(C37>=80,C37<=89),D45,IF(ABS(C37)>=90,D48,"请和kp商议")))))))),人物卡!X119) -> 请和kp商议 | I37: 毒剂名称 | J37: 生效时间 | K37: 症状 | L37: 伤害 | M37: 备注 | O37: 其他(服) | S37: =IF(人物卡!BL10="","","时代:"&人物卡!BL10&CHAR(9))&IF(人物卡!BD11="","","职业:"&人物卡!BD11&CHAR(9))&IF(人物卡!BD12="","","年龄"&人物卡!BD12&" ")&IF(人物卡!BL12="","","性别:"&人物卡!BL12&CHAR(9))&IF(人物卡!BD14="","","住地:"&人物卡!BD14&CHAR(9))&IF(人物卡!BL14="","","出身:"&人物卡!BL14&CHAR(9)) -> 时代:1920s 年龄时间未填 | X37: 电子学 Ω | AD37: =IF(人物卡!CM72="","",".st&"&人物卡!CM72&"="&人物卡!BU72) | AE37: 1894 | AF37: 朝鲜东学党起义 | AG37: 奥林匹克委员会成立 | AI37: 中日甲午战争 | AJ37: 孙中山建立兴中会 | AL37: 十九世纪 九十年代 | AM37: 甲午马年 | AN37: 清光绪20年 | AO37: 明尼苏达森林大火，死亡 480 人 德雷福斯事件，其被流放魔鬼岛 首份电报 瓶装可口可乐 | AP37: 总统： 格罗佛·克利夫兰（民主党） | AQ37: X射线 卷烟机发明 电影放映机 排球 印名片机福特车 潜望镜 油印蜡纸发明 阴极射线管 商品阿司匹林 凯洛格牌玉米片 手电筒 钋 镭 摇控器 α粒子 β粒子 打字机 柯达布朗尼相机 齐柏林飞艇 人类血型 跨大西洋电报 汽轮机游船 现代柏油路 铝罐奶粉 爆米花 泰迪熊 卡鲁索电唱机 便宜的肥皂和烹饪用油 飞机 荧光灯 邮戳机 摩托车发动机 热水瓶 农业轨道机械 木棉安全带 电动汽车喇叭 化学泡沫灭火器 狭义相对论 自动点唱机 量产舰艇舷外发动机 动画 电动洗衣机 家用洗洁精 立式吸尘器 饮用纸杯 双层公交车 无线电测向仪 电煎锅 质子和电子 玻璃纸 战壕风衣 汽车自动起动器 麦片 氯气毒气 防毒面具 拉链 机械雨刮器 广义相对论 芥子气 量产拖拉机 电子钟 黄油枪 降落伞 广播电台播音 茶包 罗夏墨迹测验 机器人 胰岛素 实用邮戳机 滑水 百日咳疫苗 纸制鸡蛋托 面巾纸 商用飞机农药喷撒 液体燃料火箭 劳力士防水表 遥控电唱机 面包机 防水玻璃纸 电传打字机 盖革计数器 纯维生素C 彩色电影胶片 透明胶带 音乐汽车喇叭 闪光灯 速冻食品 球形潜水舱 回旋加速器 折叠式雨伞 电动剃须刀 车载收音机 玛氏巧克力棒 变焦镜头 大富翁桌游 商业洗衣店 畅销平装书 里氏震级 磁带录音机 大众汽车 超市推车 带温控器的电熨斗 速溶咖啡 尼龙 圆珠笔 黄热病疫苗 雷达 汽车自动变速箱 充气救生衣 人工授精 青霉素 军用吉普车 原子裂变 火箭筒 凝固汽油弹 水肺 麦角酸二乙酰胺 神经毒气 原子弹 特百惠 计算机 静电复印法 比基尼泳衣 浓缩咖啡机 宝丽来相机 拼字盘 实心电吉他 尼龙扣 晶体管 黑胶唱片 有线电视 电视显像管 汽车自动点火装置 信用卡 复印机 宽荧幕电影 动力转向器 三色停车灯 人行红绿灯 晶体管助听器 氢弹 录像带 DNA双螺旋结构 麻疹疫苗 按动圆珠笔 硅晶体管 核导弹 空对空导弹 迪士尼乐园 特氟龙 卡丁车 地对空核导弹 沙宾疫苗 通讯卫星 呼啦圈 安全带 人工肾脏 避孕药 气象卫星 便携晶体管收音机 安定 砷化镓半导体激光器 三维全息技术 合成器 香烟健康警示 凯夫拉纤维 子午胎 IBM文字处理机 杜比A型降噪器 滑雪板 喇叭裤 绕月载人火箭 人工心脏移植 波音747喷气式客机 互联网 条形码 软盘 帆板 热裤 液晶显示 便携电子计算器 电视游戏 DNA重组技术 电子游戏机 超级计算机 光纤 试管婴儿 魔方 索尼Walkman 杜比C型降噪器 艾滋病毒 强效可卡因 温室效应 CD 暗物质 暗能量 太阳能飞行器 甲型H1N1 流感 希格斯玻色子 引力波 | AR37: 电气地铁 圣代冰淇淋 实用水电站 手电 电影摄影机 收音机 霍乱疫苗 啤酒瓶盖 柴油发动机 双向电报 实用的胶卷 块麦片 电报 可口可乐 | AS37: 电报 可口可乐 | AT37: 1894 | BB37: 名 | BC37: =IF(人物卡!BD9="",1,0) -> 1 | BH37: 印度 | BI37: 德里（Delhi） | BJ37: 安得拉邦（Andhra Pradesh） | BK37: 阿萨姆邦（Assam） | BL37: 比哈尔邦（Bihar） | BM37: 恰蒂斯加尔邦（Chhattisgarh） | BN37: 果阿邦（Goa） | BO37: 古吉拉特邦（Gujarat） | BP37: 哈里亚纳邦（Haryana） | BQ37: 喜马偕尔邦（Himachal Pradesh） | BR37: 查谟-克什米尔邦（Jammu and Kashmir，注意：该邦存在争议） | BS37: 贾坎德邦（Jharkhand） | BT37: 卡纳塔克邦（Karnataka） | BU37: 喀拉拉邦（Kerala） | BV37: 中央邦（Madhya Pradesh） | BW37: 马哈拉施特拉邦（Maharashtra） | BX37: 曼尼普尔邦（Manipur） | BY37: 梅加拉亚邦（Meghalaya） | BZ37: 米佐拉姆邦（Mizoram） | CA37: 那加兰邦（Nagaland） | CB37: 奥里萨邦（Odisha） | CC37: 旁遮普邦（Punjab） | CD37: 拉贾斯坦邦（Rajasthan） | CE37: 锡金邦（Sikkim） | CF37: 泰米尔纳德邦（Tamil Nadu） | CG37: 特里普拉邦（Tripura） | CH37: 北方邦（Uttar Pradesh） | CI37: 北阿坎德邦（Uttarakhand） | CJ37: 西孟加拉邦（West Bengal） | CK37: 特伦甘纳邦（Telangana） | CL37: 安达曼-尼科巴群岛（Andaman and Nicobar Islands） | CM37: 昌迪加尔（Chandigarh） | CN37: 达德拉-纳加尔哈维利（Dadra and Nagar Haveli） | CO37: 达曼-第乌（Daman and Diu） | CP37: 拉克沙群岛（Lakshadweep） | CQ37: 本地治里（Puducherry）
C38: 年龄年龄补正 | I38: 鹅膏菌（毒蘑菇） | J38: 6～24小时 | K38: 剧烈腹痛、呕吐、黄疸 | L38: 1D10 | M38: 造成了95%的毒蘑菇致死事件，鬼笔鹅膏是最常见的一种蘑菇毒素。 | O38: 上肢———— | X38: 操作重型机械 | AD38: =IF(人物卡!CM73="","",".st&"&人物卡!CM73&"="&人物卡!BU73) | AE38: 1895 | AF38: 台湾民主国成立 | AG38: 台湾民主国被日军占领 | AI38: 《马关条约》 | AJ38: 公车上书 | AL38: 十九世纪 九十年代 | AM38: 乙未羊年 | AN38: 清光绪21年 | AO38: 伦琴发现 X 射线 卷烟机发明 卢米埃兄弟制成电影放映机并在巴黎首次放映电影 卡尔斯滕·埃格贝尔格·博克格尔文克成为第一名在南极洲大陆登陆的人 韦廉姆·G·摩根在美国发明排球 | AP38: 总统： 格罗佛·克利夫兰（民主党） | AQ38: 印名片机 福特车 潜望镜 油印蜡纸发明 阴极射线管 商品阿司匹林 凯洛格牌玉米片 手电筒 钋 镭 摇控器 α粒子 β粒子 打字机 柯达布朗尼相机 齐柏林飞艇 人类血型 跨大西洋电报 汽轮机游船 现代柏油路 铝罐奶粉 爆米花 泰迪熊 卡鲁索电唱机 便宜的肥皂和烹饪用油 飞机 荧光灯 邮戳机 摩托车发动机 热水瓶 农业轨道机械 木棉安全带 电动汽车喇叭 化学泡沫灭火器 狭义相对论 自动点唱机 量产舰艇舷外发动机 动画 电动洗衣机 家用洗洁精 立式吸尘器 饮用纸杯 双层公交车 无线电测向仪 电煎锅 质子和电子 玻璃纸 战壕风衣 汽车自动起动器 麦片 氯气毒气 防毒面具 拉链 机械雨刮器 广义相对论 芥子气 量产拖拉机 电子钟 黄油枪 降落伞 广播电台播音 茶包 罗夏墨迹测验 机器人 胰岛素 实用邮戳机 滑水 百日咳疫苗 纸制鸡蛋托 面巾纸 商用飞机农药喷撒 液体燃料火箭 劳力士防水表 遥控电唱机 面包机 防水玻璃纸 电传打字机 盖革计数器 纯维生素C 彩色电影胶片 透明胶带 音乐汽车喇叭 闪光灯 速冻食品 球形潜水舱 回旋加速器 折叠式雨伞 电动剃须刀 车载收音机 玛氏巧克力棒 变焦镜头 大富翁桌游 商业洗衣店 畅销平装书 里氏震级 磁带录音机 大众汽车 超市推车 带温控器的电熨斗 速溶咖啡 尼龙 圆珠笔 黄热病疫苗 雷达 汽车自动变速箱 充气救生衣 人工授精 青霉素 军用吉普车 原子裂变 火箭筒 凝固汽油弹 水肺 麦角酸二乙酰胺 神经毒气 原子弹 特百惠 计算机 静电复印法 比基尼泳衣 浓缩咖啡机 宝丽来相机 拼字盘 实心电吉他 尼龙扣 晶体管 黑胶唱片 有线电视 电视显像管 汽车自动点火装置 信用卡 复印机 宽荧幕电影 动力转向器 三色停车灯 人行红绿灯 晶体管助听器 氢弹 录像带 DNA双螺旋结构 麻疹疫苗 按动圆珠笔 硅晶体管 核导弹 空对空导弹 迪士尼乐园 特氟龙 卡丁车 地对空核导弹 沙宾疫苗 通讯卫星 呼啦圈 安全带 人工肾脏 避孕药 气象卫星 便携晶体管收音机 安定 砷化镓半导体激光器 三维全息技术 合成器 香烟健康警示 凯夫拉纤维 子午胎 IBM文字处理机 杜比A型降噪器 滑雪板 喇叭裤 绕月载人火箭 人工心脏移植 波音747喷气式客机 互联网 条形码 软盘 帆板 热裤 液晶显示 便携电子计算器 电视游戏 DNA重组技术 电子游戏机 超级计算机 光纤 试管婴儿 魔方 索尼Walkman 杜比C型降噪器 艾滋病毒 强效可卡因 温室效应 CD 暗物质 暗能量 太阳能飞行器 甲型H1N1 流感 希格斯玻色子 引力波 | AR38: 电气地铁 圣代冰淇淋 实用水电站 手电 电影摄影机 收音机 霍乱疫苗 啤酒瓶盖 柴油发动机 双向电报 实用的胶卷 块麦片 电报 可口可乐 X射线 卷烟机 电影放映机 排球 | AS38: X 射线 卷烟机 电影放映机 排球 | AT38: 1895 | AV38: =IF(AV36="仅显示1890_2012","",VLOOKUP(AV36,AS33:AT155,2,FALSE)) -> 1894 | BB38: 玩 | BC38: =IF(人物卡!BD10="",1,0) -> 1 | BD38: 时 | BE38: =IF(人物卡!BL10="",1,0) -> 0 | BH38: 巴基斯坦 | BI38: 伊斯兰堡* | BJ38: 俾路支省 | BK38: 信德省 | BL38: 旁遮普省 | BM38: 吉尔吉特-巴尔蒂斯坦地区 | BN38: 巴基斯坦管辖克什米尔 | BO38: 巴拉蒂斯坦 | BP38: 开伯尔-普赫图赫瓦省
B39: 15 | C39: 19 | D39: 力量体型共-5 E-5 L*2 | I39: 砷化物 | J39: 30分钟～24小时 | K39: 灼痛、呕吐、剧烈腹泻 | L39: 4D10 | M39: 砷中毒难以确认（这使得它作为毒杀工具大受欢迎），直到1836年马氏试砷法发明为止。 | O39: 左手 | S39: =IF(人物卡!BH20="",""," 身体状态:"&人物卡!BH20&CHAR(9))&IF(人物卡!BQ20="",""," 精神状态:"&人物卡!BQ20&CHAR(9)) -> 身体状态:健康 精神状态:清醒 | X39: 爆破 | AE39: 1896 | AF39: 雅典奥运会 | AI39: 《中俄密约》 | AL39: 十九世纪 九十年代 | AM39: 丙申猴年 | AN39: 清光绪22年 | AO39: 克朗代克淘金热 印名片机取得专利 首辆福特车 潜望镜 雅典举办首届奥运会 | AP39: 总统： 格罗佛·克利夫兰（民主党） | AQ39: 油印蜡纸发明 阴极射线管 商品阿司匹林 凯洛格牌玉米片 手电筒 钋 镭 摇控器 α粒子 β粒子 打字机 柯达布朗尼相机 齐柏林飞艇 人类血型 跨大西洋电报 汽轮机游船 现代柏油路 铝罐奶粉 爆米花 泰迪熊 卡鲁索电唱机 便宜的肥皂和烹饪用油 飞机 荧光灯 邮戳机 摩托车发动机 热水瓶 农业轨道机械 木棉安全带 电动汽车喇叭 化学泡沫灭火器 狭义相对论 自动点唱机 量产舰艇舷外发动机 动画 电动洗衣机 家用洗洁精 立式吸尘器 饮用纸杯 双层公交车 无线电测向仪 电煎锅 质子和电子 玻璃纸 战壕风衣 汽车自动起动器 麦片 氯气毒气 防毒面具 拉链 机械雨刮器 广义相对论 芥子气 量产拖拉机 电子钟 黄油枪 降落伞 广播电台播音 茶包 罗夏墨迹测验 机器人 胰岛素 实用邮戳机 滑水 百日咳疫苗 纸制鸡蛋托 面巾纸 商用飞机农药喷撒 液体燃料火箭 劳力士防水表 遥控电唱机 面包机 防水玻璃纸 电传打字机 盖革计数器 纯维生素C 彩色电影胶片 透明胶带 音乐汽车喇叭 闪光灯 速冻食品 球形潜水舱 回旋加速器 折叠式雨伞 电动剃须刀 车载收音机 玛氏巧克力棒 变焦镜头 大富翁桌游 商业洗衣店 畅销平装书 里氏震级 磁带录音机 大众汽车 超市推车 带温控器的电熨斗 速溶咖啡 尼龙 圆珠笔 黄热病疫苗 雷达 汽车自动变速箱 充气救生衣 人工授精 青霉素 军用吉普车 原子裂变 火箭筒 凝固汽油弹 水肺 麦角酸二乙酰胺 神经毒气 原子弹 特百惠 计算机 静电复印法 比基尼泳衣 浓缩咖啡机 宝丽来相机 拼字盘 实心电吉他 尼龙扣 晶体管 黑胶唱片 有线电视 电视显像管 汽车自动点火装置 信用卡 复印机 宽荧幕电影 动力转向器 三色停车灯 人行红绿灯 晶体管助听器 氢弹 录像带 DNA双螺旋结构 麻疹疫苗 按动圆珠笔 硅晶体管 核导弹 空对空导弹 迪士尼乐园 特氟龙 卡丁车 地对空核导弹 沙宾疫苗 通讯卫星 呼啦圈 安全带 人工肾脏 避孕药 气象卫星 便携晶体管收音机 安定 砷化镓半导体激光器 三维全息技术 合成器 香烟健康警示 凯夫拉纤维 子午胎 IBM文字处理机 杜比A型降噪器 滑雪板 喇叭裤 绕月载人火箭 人工心脏移植 波音747喷气式客机 互联网 条形码 软盘 帆板 热裤 液晶显示 便携电子计算器 电视游戏 DNA重组技术 电子游戏机 超级计算机 光纤 试管婴儿 魔方 索尼Walkman 杜比C型降噪器 艾滋病毒 强效可卡因 温室效应 CD 暗物质 暗能量 太阳能飞行器 甲型H1N1 流感 希格斯玻色子 引力波 | AR39: 电气地铁 圣代冰淇淋 实用水电站 手电 电影摄影机 收音机 霍乱疫苗 啤酒瓶盖 柴油发动机 双向电报 实用的胶卷 块麦片 电报 可口可乐 X射线 卷烟机发明 电影放映机 排球 印名片机 福特车 潜望镜 | AS39: 印名片机 福特车 潜望镜 | AT39: 1896 | BB39: 职 | BC39: =IF(人物卡!BD11="",1,0) -> 1 | BD39: 序 | BE39: =IF(人物卡!BL11="",1,0) -> 1 | BH39: 孟加拉国 | BI39: 达卡* | BJ39: 巴里萨尔大区 | BK39: 吉大港区 | BL39: 库尔纳大区 | BM39: 拉杰沙希大区 | BN39: 朗布尔大区 | BO39: 锡尔赫特大区 | BP39: 锡尔盖特大区 | BQ39: 迈门辛大区 | BR39: 孟加拉邦
B40: 20 | C40: 39 | D40: 教育进步*1 | I40: 颠茄 | J40: 2小时～2天 | K40: 心率加快、视力受损、惊厥 | L40: 4D10 | M40: 世界上毒性最大的植物之一，成人食用10～20颗就可能死亡。 | O40: 右手 | S40: =IF(人物卡!CP67="","","&DB="&人物卡!CP67&" 体格:"&人物卡!CP70)&IF(OR(人物卡!CP72="",,人物卡!BQ38<>人物卡!BI38),""," 闪避:"&人物卡!CP72)&IF(人物卡!CM19="",""," 护甲:"&人物卡!CM19) -> &DB=0 体格:0 闪避:0 护甲:无 | X40: 计算机使用 Ω | AD40: =AD34&AD35&AD36&AD37&AD38 | AE40: 1897 | AF40: —— | AI40: —— | AL40: 十九世纪 九十年代 | AM40: 丁酉鸡年 | AN40: 清光绪23年 | AO40: 油印蜡纸发明 首个阴极射线管 | AP40: 总统： 格罗佛·克利夫兰（民主党） 威廉·麦金利（共和党） | AQ40: 商品阿司匹林 凯洛格牌玉米片 手电筒 钋 镭 摇控器 α粒子 β粒子 打字机 柯达布朗尼相机 齐柏林飞艇 人类血型 跨大西洋电报 汽轮机游船 现代柏油路 铝罐奶粉 爆米花 泰迪熊 卡鲁索电唱机 便宜的肥皂和烹饪用油 飞机 荧光灯 邮戳机 摩托车发动机 热水瓶 农业轨道机械 木棉安全带 电动汽车喇叭 化学泡沫灭火器 狭义相对论 自动点唱机 量产舰艇舷外发动机 动画 电动洗衣机 家用洗洁精 立式吸尘器 饮用纸杯 双层公交车 无线电测向仪 电煎锅 质子和电子 玻璃纸 战壕风衣 汽车自动起动器 麦片 氯气毒气 防毒面具 拉链 机械雨刮器 广义相对论 芥子气 量产拖拉机 电子钟 黄油枪 降落伞 广播电台播音 茶包 罗夏墨迹测验 机器人 胰岛素 实用邮戳机 滑水 百日咳疫苗 纸制鸡蛋托 面巾纸 商用飞机农药喷撒 液体燃料火箭 劳力士防水表 遥控电唱机 面包机 防水玻璃纸 电传打字机 盖革计数器 纯维生素C 彩色电影胶片 透明胶带 音乐汽车喇叭 闪光灯 速冻食品 球形潜水舱 回旋加速器 折叠式雨伞 电动剃须刀 车载收音机 玛氏巧克力棒 变焦镜头 大富翁桌游 商业洗衣店 畅销平装书 里氏震级 磁带录音机 大众汽车 超市推车 带温控器的电熨斗 速溶咖啡 尼龙 圆珠笔 黄热病疫苗 雷达 汽车自动变速箱 充气救生衣 人工授精 青霉素 军用吉普车 原子裂变 火箭筒 凝固汽油弹 水肺 麦角酸二乙酰胺 神经毒气 原子弹 特百惠 计算机 静电复印法 比基尼泳衣 浓缩咖啡机 宝丽来相机 拼字盘 实心电吉他 尼龙扣 晶体管 黑胶唱片 有线电视 电视显像管 汽车自动点火装置 信用卡 复印机 宽荧幕电影 动力转向器 三色停车灯 人行红绿灯 晶体管助听器 氢弹 录像带 DNA双螺旋结构 麻疹疫苗 按动圆珠笔 硅晶体管 核导弹 空对空导弹 迪士尼乐园 特氟龙 卡丁车 地对空核导弹 沙宾疫苗 通讯卫星 呼啦圈 安全带 人工肾脏 避孕药 气象卫星 便携晶体管收音机 安定 砷化镓半导体激光器 三维全息技术 合成器 香烟健康警示 凯夫拉纤维 子午胎 IBM文字处理机 杜比A型降噪器 滑雪板 喇叭裤 绕月载人火箭 人工心脏移植 波音747喷气式客机 互联网 条形码 软盘 帆板 热裤 液晶显示 便携电子计算器 电视游戏 DNA重组技术 电子游戏机 超级计算机 光纤 试管婴儿 魔方 索尼Walkman 杜比C型降噪器 艾滋病毒 强效可卡因 温室效应 CD 暗物质 暗能量 太阳能飞行器 甲型H1N1 流感 希格斯玻色子 引力波 | AR40: 电气地铁 圣代冰淇淋 实用水电站 手电 电影摄影机 收音机 霍乱疫苗 啤酒瓶盖 柴油发动机 双向电报 实用的胶卷 块麦片 电报 可口可乐 X射线 卷烟机发明 电影放映机 排球 印名片机 福特车 潜望镜 油印蜡纸发明 阴极射线管 | AS40: 油印蜡纸发明 阴极射线管 | AT40: 1897 | BB40: 年 | BC40: =IF(人物卡!BD12="",1,0) -> 0 | BD40: 性 | BE40: =IF(人物卡!BL12="",1,0) -> 1 | BH40: 尼泊尔 | BI40: 加德满都市* | BJ40: 巴格马蒂专区 | BK40: 甘达基专区 | BL40: 贾纳克普尔专区
B41: 40 | C41: 49 | D41: 进步*2,SCD共-5 A-5 | I41: 黑寡妇蜘蛛毒 | J41: 2～8小时 | K41: 寒战、出汗、恶心 | L41: 1D10 | M41: 如果及时进行医治，基本不会死亡。 | O41: 双手 | S41: =IF(人物卡!BF69="",IF(人物卡!BA69="",""," &"&人物卡!BA69&"="&人物卡!BU69)," &"&人物卡!BA69&"="&VLOOKUP(人物卡!BF69,'武器列表 战斗'!B2:T121,19,FALSE)) | X41: 科学① | AE41: 1898 | AF41: 美西战争 | AG41: 美国兼并夏威夷共和国 | AI41: 戊戌变法/百日维新 | AL41: 十九世纪 九十年代 | AM41: 戊戌狗年 | AN41: 清光绪24年 | AO41: 飓风袭击美国南部数百人死亡 美西战争，死亡 2446 美军 唱片普及 商品阿司匹林出现 凯洛格牌玉米片 手电筒 居里夫妇宣布发现新的放射性元素钋 居里夫妇发现了化学元素镭 尼古拉·特斯拉开发第一个摇控器 | AP41: 总统： 威廉·麦金利（共和党） | AQ41: α粒子 β粒子 打字机 柯达布朗尼相机 齐柏林飞艇 人类血型 跨大西洋电报 汽轮机游船 现代柏油路 铝罐奶粉 爆米花 泰迪熊 卡鲁索电唱机 便宜的肥皂和烹饪用油 飞机 荧光灯 邮戳机 摩托车发动机 热水瓶 农业轨道机械 木棉安全带 电动汽车喇叭 化学泡沫灭火器 狭义相对论 自动点唱机 量产舰艇舷外发动机 动画 电动洗衣机 家用洗洁精 立式吸尘器 饮用纸杯 双层公交车 无线电测向仪 电煎锅 质子和电子 玻璃纸 战壕风衣 汽车自动起动器 麦片 氯气毒气 防毒面具 拉链 机械雨刮器 广义相对论 芥子气 量产拖拉机 电子钟 黄油枪 降落伞 广播电台播音 茶包 罗夏墨迹测验 机器人 胰岛素 实用邮戳机 滑水 百日咳疫苗 纸制鸡蛋托 面巾纸 商用飞机农药喷撒 液体燃料火箭 劳力士防水表 遥控电唱机 面包机 防水玻璃纸 电传打字机 盖革计数器 纯维生素C 彩色电影胶片 透明胶带 音乐汽车喇叭 闪光灯 速冻食品 球形潜水舱 回旋加速器 折叠式雨伞 电动剃须刀 车载收音机 玛氏巧克力棒 变焦镜头 大富翁桌游 商业洗衣店 畅销平装书 里氏震级 磁带录音机 大众汽车 超市推车 带温控器的电熨斗 速溶咖啡 尼龙 圆珠笔 黄热病疫苗 雷达 汽车自动变速箱 充气救生衣 人工授精 青霉素 军用吉普车 原子裂变 火箭筒 凝固汽油弹 水肺 麦角酸二乙酰胺 神经毒气 原子弹 特百惠 计算机 静电复印法 比基尼泳衣 浓缩咖啡机 宝丽来相机 拼字盘 实心电吉他 尼龙扣 晶体管 黑胶唱片 有线电视 电视显像管 汽车自动点火装置 信用卡 复印机 宽荧幕电影 动力转向器 三色停车灯 人行红绿灯 晶体管助听器 氢弹 录像带 DNA双螺旋结构 麻疹疫苗 按动圆珠笔 硅晶体管 核导弹 空对空导弹 迪士尼乐园 特氟龙 卡丁车 地对空核导弹 沙宾疫苗 通讯卫星 呼啦圈 安全带 人工肾脏 避孕药 气象卫星 便携晶体管收音机 安定 砷化镓半导体激光器 三维全息技术 合成器 香烟健康警示 凯夫拉纤维 子午胎 IBM文字处理机 杜比A型降噪器 滑雪板 喇叭裤 绕月载人火箭 人工心脏移植 波音747喷气式客机 互联网 条形码 软盘 帆板 热裤 液晶显示 便携电子计算器 电视游戏 DNA重组技术 电子游戏机 超级计算机 光纤 试管婴儿 魔方 索尼Walkman 杜比C型降噪器 艾滋病毒 强效可卡因 温室效应 CD 暗物质 暗能量 太阳能飞行器 甲型H1N1 流感 希格斯玻色子 引力波 | AR41: 电气地铁 圣代冰淇淋 实用水电站 手电 电影摄影机 收音机 霍乱疫苗 啤酒瓶盖 柴油发动机 双向电报 实用的胶卷 块麦片 电报 可口可乐 X射线 卷烟机发明 电影放映机 排球 印名片机 福特车 潜望镜 油印蜡纸发明 阴极射线管 商品阿司匹林 凯洛格牌玉米片 手电筒 钋 镭 摇控器 | AS41: 商品阿司匹林 凯洛格牌玉米片 手电筒 钋 镭 摇控器 | AT41: 1898 | BB41: 国 | BC41: =IF(人物卡!BD13="",1,0) -> 1 | BD41: 货 | BE41: =IF(人物卡!BL13="",1,0) -> 0 | BF41: =SUM(BC37:BC41,BE38:BE41) -> 6 | BH41: 不丹 | BI41: 廷布* | BJ41: 帕罗宗 | BK41: 楚卡宗 | BL41: 达吉宗 | BM41: 萨姆卓宗 | BN41: 扎西冈宗 | BO41: 哈宗 | BP41: 旺杜波德朗宗 | BQ41: 普那卡宗 | BR41: 蓬格宗 | BS41: 加萨宗 | BT41: 达旺宗 | BU41: 萨姆德鲁琼卡尔宗
B42: 50 | C42: 59 | D42: 进步*3,SCD共-10 A-10 | I42: 三氯甲烷（氯仿） | J42: 1轮 | K42: 昏迷1小时 | L42: 无伤害 | M42: 在1800~1900s是常见的麻醉剂，不过高的摄入量也会致死。 | O42: 左臂 | S42: =IF(人物卡!BF70="",IF(人物卡!BA70="",""," &"&人物卡!BA70&"="&人物卡!BU70)," &"&人物卡!BA70&"="&VLOOKUP(人物卡!BF70,'武器列表 战斗'!B2:T121,19,FALSE)) | X42: 科学② | AE42: 1899 | AF42: 第二次布尔战争 | AI42: —— | AL42: 十九世纪 九十年代 | AM42: 己亥猪年 | AN42: 清光绪25年 | AO42: 纽约温莎酒店大火，数百万人受灾，死亡 14 人 卢瑟福发现 α 粒子和 β 粒子 打字机开始普及 | AP42: 总统： 威廉·麦金利（共和党） | AQ42: 柯达布朗尼相机 齐柏林飞艇 人类血型 跨大西洋电报 汽轮机游船 现代柏油路 铝罐奶粉 爆米花 泰迪熊 卡鲁索电唱机 便宜的肥皂和烹饪用油 飞机 荧光灯 邮戳机 摩托车发动机 热水瓶 农业轨道机械 木棉安全带 电动汽车喇叭 化学泡沫灭火器 狭义相对论 自动点唱机 量产舰艇舷外发动机 动画 电动洗衣机 家用洗洁精 立式吸尘器 饮用纸杯 双层公交车 无线电测向仪 电煎锅 质子和电子 玻璃纸 战壕风衣 汽车自动起动器 麦片 氯气毒气 防毒面具 拉链 机械雨刮器 广义相对论 芥子气 量产拖拉机 电子钟 黄油枪 降落伞 广播电台播音 茶包 罗夏墨迹测验 机器人 胰岛素 实用邮戳机 滑水 百日咳疫苗 纸制鸡蛋托 面巾纸 商用飞机农药喷撒 液体燃料火箭 劳力士防水表 遥控电唱机 面包机 防水玻璃纸 电传打字机 盖革计数器 纯维生素C 彩色电影胶片 透明胶带 音乐汽车喇叭 闪光灯 速冻食品 球形潜水舱 回旋加速器 折叠式雨伞 电动剃须刀 车载收音机 玛氏巧克力棒 变焦镜头 大富翁桌游 商业洗衣店 畅销平装书 里氏震级 磁带录音机 大众汽车 超市推车 带温控器的电熨斗 速溶咖啡 尼龙 圆珠笔 黄热病疫苗 雷达 汽车自动变速箱 充气救生衣 人工授精 青霉素 军用吉普车 原子裂变 火箭筒 凝固汽油弹 水肺 麦角酸二乙酰胺 神经毒气 原子弹 特百惠 计算机 静电复印法 比基尼泳衣 浓缩咖啡机 宝丽来相机 拼字盘 实心电吉他 尼龙扣 晶体管 黑胶唱片 有线电视 电视显像管 汽车自动点火装置 信用卡 复印机 宽荧幕电影 动力转向器 三色停车灯 人行红绿灯 晶体管助听器 氢弹 录像带 DNA双螺旋结构 麻疹疫苗 按动圆珠笔 硅晶体管 核导弹 空对空导弹 迪士尼乐园 特氟龙 卡丁车 地对空核导弹 沙宾疫苗 通讯卫星 呼啦圈 安全带 人工肾脏 避孕药 气象卫星 便携晶体管收音机 安定 砷化镓半导体激光器 三维全息技术 合成器 香烟健康警示 凯夫拉纤维 子午胎 IBM文字处理机 杜比A型降噪器 滑雪板 喇叭裤 绕月载人火箭 人工心脏移植 波音747喷气式客机 互联网 条形码 软盘 帆板 热裤 液晶显示 便携电子计算器 电视游戏 DNA重组技术 电子游戏机 超级计算机 光纤 试管婴儿 魔方 索尼Walkman 杜比C型降噪器 艾滋病毒 强效可卡因 温室效应 CD 暗物质 暗能量 太阳能飞行器 甲型H1N1 流感 希格斯玻色子 引力波 | AR42: 电气地铁 圣代冰淇淋 实用水电站 手电 电影摄影机 收音机 霍乱疫苗 啤酒瓶盖 柴油发动机 双向电报 实用的胶卷 块麦片 电报 可口可乐 X射线 卷烟机发明 电影放映机 排球 印名片机 福特车 潜望镜 油印蜡纸发明 阴极射线管 商品阿司匹林 凯洛格牌玉米片 手电筒 钋 镭 摇控器 α粒子 β粒子 打字机 | AS42: α 粒子和 β 粒子 打字机 | AT42: 1899 | BH42: 斯里兰卡 | BI42: 科伦坡* | BJ42: 中央省 | BK42: 西部省 | BL42: 南部省 | BM42: 萨巴拉加穆瓦省 | BN42: 北中央省 | BO42: 北方省 | BP42: 东方省 | BQ42: 乌瓦省
B43: 60 | C43: 69 | D43: 进步*4,SCD共-20 A-15 | I43: 眼镜蛇毒 | J43: 15～60分钟 | K43: 惊厥、呼吸衰竭 | L43: 4D10 | M43: 接触眼睛会产生直接的刺激，未经处理会失明。如果有血清，可以避免受重伤和死亡。 | O43: 右臂 | S43: =IF(人物卡!BF71="",IF(人物卡!BA71="",""," &"&人物卡!BA71&"="&人物卡!BU71)," &"&人物卡!BA71&"="&VLOOKUP(人物卡!BF71,'武器列表 战斗'!B2:T121,19,FALSE)) | X43: 科学③ | AE43: 1900 | AF43: 巴黎奥运会 | AG43: 诺贝尔奖基金会 | AI43: 八国联军侵华战争 | AJ43: 庚子国变 | AL43: 二十世纪初 | AM43: 庚子鼠年 | AN43: 清光绪26年 | AO43: 码头失火，蒸汽艇里约热内卢号在旧金山港沉没，死亡 128 人 大飓风加尔维斯顿，死亡 6000 人 庚子国变 柯达布朗尼相机 齐柏林伯爵起飞 420 英尺飞艇 美国公债12.63 亿美元 美国人口 760 万。 | AP43: 总统： 威廉·麦金利（共和党） | AQ43: 人类血型 跨大西洋电报 汽轮机游船 现代柏油路 铝罐奶粉 爆米花 泰迪熊 卡鲁索电唱机 便宜的肥皂和烹饪用油 飞机 荧光灯 邮戳机 摩托车发动机 热水瓶 农业轨道机械 木棉安全带 电动汽车喇叭 化学泡沫灭火器 狭义相对论 自动点唱机 量产舰艇舷外发动机 动画 电动洗衣机 家用洗洁精 立式吸尘器 饮用纸杯 双层公交车 无线电测向仪 电煎锅 质子和电子 玻璃纸 战壕风衣 汽车自动起动器 麦片 氯气毒气 防毒面具 拉链 机械雨刮器 广义相对论 芥子气 量产拖拉机 电子钟 黄油枪 降落伞 广播电台播音 茶包 罗夏墨迹测验 机器人 胰岛素 实用邮戳机 滑水 百日咳疫苗 纸制鸡蛋托 面巾纸 商用飞机农药喷撒 液体燃料火箭 劳力士防水表 遥控电唱机 面包机 防水玻璃纸 电传打字机 盖革计数器 纯维生素C 彩色电影胶片 透明胶带 音乐汽车喇叭 闪光灯 速冻食品 球形潜水舱 回旋加速器 折叠式雨伞 电动剃须刀 车载收音机 玛氏巧克力棒 变焦镜头 大富翁桌游 商业洗衣店 畅销平装书 里氏震级 磁带录音机 大众汽车 超市推车 带温控器的电熨斗 速溶咖啡 尼龙 圆珠笔 黄热病疫苗 雷达 汽车自动变速箱 充气救生衣 人工授精 青霉素 军用吉普车 原子裂变 火箭筒 凝固汽油弹 水肺 麦角酸二乙酰胺 神经毒气 原子弹 特百惠 计算机 静电复印法 比基尼泳衣 浓缩咖啡机 宝丽来相机 拼字盘 实心电吉他 尼龙扣 晶体管 黑胶唱片 有线电视 电视显像管 汽车自动点火装置 信用卡 复印机 宽荧幕电影 动力转向器 三色停车灯 人行红绿灯 晶体管助听器 氢弹 录像带 DNA双螺旋结构 麻疹疫苗 按动圆珠笔 硅晶体管 核导弹 空对空导弹 迪士尼乐园 特氟龙 卡丁车 地对空核导弹 沙宾疫苗 通讯卫星 呼啦圈 安全带 人工肾脏 避孕药 气象卫星 便携晶体管收音机 安定 砷化镓半导体激光器 三维全息技术 合成器 香烟健康警示 凯夫拉纤维 子午胎 IBM文字处理机 杜比A型降噪器 滑雪板 喇叭裤 绕月载人火箭 人工心脏移植 波音747喷气式客机 互联网 条形码 软盘 帆板 热裤 液晶显示 便携电子计算器 电视游戏 DNA重组技术 电子游戏机 超级计算机 光纤 试管婴儿 魔方 索尼Walkman 杜比C型降噪器 艾滋病毒 强效可卡因 温室效应 CD 暗物质 暗能量 太阳能飞行器 甲型H1N1 流感 希格斯玻色子 引力波 | AR43: 电气地铁 圣代冰淇淋 实用水电站 手电 电影摄影机 收音机 霍乱疫苗 啤酒瓶盖 柴油发动机 双向电报 实用的胶卷 块麦片 电报 可口可乐 X射线 卷烟机发明 电影放映机 排球 印名片机 福特车 潜望镜 油印蜡纸发明 阴极射线管 商品阿司匹林 凯洛格牌玉米片 手电筒 钋 镭 摇控器 α粒子 β粒子 打字机 柯达布朗尼相机 齐柏林飞艇 | AS43: 柯达布朗尼相机 齐柏林飞艇 | AT43: 1900 | BA43: 住 | BB43: 国 | BC43: =IF(人物卡!BC14="",1,0) -> 1 | BD43: 省 | BE43: =IF(人物卡!BF14="",1,0) -> 1 | BH43: 马尔代夫 | BI43: 马累*
B44: 70 | C44: 79 | D44: 进步*4,SCD共-40 A-20 | I44: 箭毒碱 | J44: 1轮 | K44: 肌肉麻痹、呼吸衰竭。 | L44: 4D10 | M44: 南美洲人涂在箭上毒剂的通称。口服无害，只有通过皮肤伤口直接侵入才会导致瘫痪。 | O44: 双臂 | S44: =S41&S42&S43 | X44: 科学④ | AE44: 1901 | AF44: 维多利亚时代结束（英国） | AI44: 《辛丑条约》 | AL44: 二十世纪初 | AM44: 辛丑牛年 | AN44: 清光绪27年 | AO44: 麦金莱总统遇刺 美国两次爆发伤寒 维多利亚女王逝世 人类血型发现 首份跨越大西洋电报 | AP44: 总统： 威廉·麦金利（共和党） 西奥多·罗斯福（共和党） | AQ44: 汽轮机游船 现代柏油路 铝罐奶粉 爆米花 泰迪熊 卡鲁索电唱机 便宜的肥皂和烹饪用油 飞机 荧光灯 邮戳机 摩托车发动机 热水瓶 农业轨道机械 木棉安全带 电动汽车喇叭 化学泡沫灭火器 狭义相对论 自动点唱机 量产舰艇舷外发动机 动画 电动洗衣机 家用洗洁精 立式吸尘器 饮用纸杯 双层公交车 无线电测向仪 电煎锅 质子和电子 玻璃纸 战壕风衣 汽车自动起动器 麦片 氯气毒气 防毒面具 拉链 机械雨刮器 广义相对论 芥子气 量产拖拉机 电子钟 黄油枪 降落伞 广播电台播音 茶包 罗夏墨迹测验 机器人 胰岛素 实用邮戳机 滑水 百日咳疫苗 纸制鸡蛋托 面巾纸 商用飞机农药喷撒 液体燃料火箭 劳力士防水表 遥控电唱机 面包机 防水玻璃纸 电传打字机 盖革计数器 纯维生素C 彩色电影胶片 透明胶带 音乐汽车喇叭 闪光灯 速冻食品 球形潜水舱 回旋加速器 折叠式雨伞 电动剃须刀 车载收音机 玛氏巧克力棒 变焦镜头 大富翁桌游 商业洗衣店 畅销平装书 里氏震级 磁带录音机 大众汽车 超市推车 带温控器的电熨斗 速溶咖啡 尼龙 圆珠笔 黄热病疫苗 雷达 汽车自动变速箱 充气救生衣 人工授精 青霉素 军用吉普车 原子裂变 火箭筒 凝固汽油弹 水肺 麦角酸二乙酰胺 神经毒气 原子弹 特百惠 计算机 静电复印法 比基尼泳衣 浓缩咖啡机 宝丽来相机 拼字盘 实心电吉他 尼龙扣 晶体管 黑胶唱片 有线电视 电视显像管 汽车自动点火装置 信用卡 复印机 宽荧幕电影 动力转向器 三色停车灯 人行红绿灯 晶体管助听器 氢弹 录像带 DNA双螺旋结构 麻疹疫苗 按动圆珠笔 硅晶体管 核导弹 空对空导弹 迪士尼乐园 特氟龙 卡丁车 地对空核导弹 沙宾疫苗 通讯卫星 呼啦圈 安全带 人工肾脏 避孕药 气象卫星 便携晶体管收音机 安定 砷化镓半导体激光器 三维全息技术 合成器 香烟健康警示 凯夫拉纤维 子午胎 IBM文字处理机 杜比A型降噪器 滑雪板 喇叭裤 绕月载人火箭 人工心脏移植 波音747喷气式客机 互联网 条形码 软盘 帆板 热裤 液晶显示 便携电子计算器 电视游戏 DNA重组技术 电子游戏机 超级计算机 光纤 试管婴儿 魔方 索尼Walkman 杜比C型降噪器 艾滋病毒 强效可卡因 温室效应 CD 暗物质 暗能量 太阳能飞行器 甲型H1N1 流感 希格斯玻色子 引力波 | AR44: 电气地铁 圣代冰淇淋 实用水电站 手电 电影摄影机 收音机 霍乱疫苗 啤酒瓶盖 柴油发动机 双向电报 实用的胶卷 块麦片 电报 可口可乐 X射线 卷烟机发明 电影放映机 排球 印名片机 福特车 潜望镜 油印蜡纸发明 阴极射线管 商品阿司匹林 凯洛格牌玉米片 手电筒 钋 镭 摇控器 α粒子 β粒子 打字机 柯达布朗尼相机 齐柏林飞艇 人类血型 跨大西洋电报 | AS44: 人类血型 跨大西洋电报 | AT44: 1901 | BB44: 市 | BC44: =IF(人物卡!BC15="",1,0) -> 1 | BD44: 号 | BE44: =IF(人物卡!BF15="",1,0) -> 1 | BF44: =SUM(BC43,BE43,BC44,BE44) -> 4
B45: 80 | C45: 89 | D45: 进步*4,SCD共-80 A-25 | I45: 氰化物 | J45: 1～15分钟 | K45: 眩晕、惊厥、晕厥、死亡。 | L45: 4D10 | M45: 剧毒——摄入了氰化物盐或者通过气体吸入都会致死。 | O45: 肘部 | X45: 科学⑤ | AE45: 1902 | AF45: 第二次布尔战争结束 | AI45: —— | AL45: 二十世纪初 | AM45: 壬寅虎年 | AN45: 清光绪28年 | AO45: 布尔战争 马提尼克（中美洲岛屿 ) 培雷火山爆发，死亡 4 万人 首个汽轮机游船 现代柏油路产生 首个铝罐奶粉 爆米花 首个泰迪熊 首个卡鲁索电唱机 商用氢化油脂使得制皂和烹饪用油来源增加 | AP45: 总统： 西奥多·罗斯福（共和党） | AQ45: 飞机 荧光灯 邮戳机 摩托车发动机 热水瓶 农业轨道机械 木棉安全带 电动汽车喇叭 化学泡沫灭火器 狭义相对论 自动点唱机 量产舰艇舷外发动机 动画 电动洗衣机 家用洗洁精 立式吸尘器 饮用纸杯 双层公交车 无线电测向仪 电煎锅 质子和电子 玻璃纸 战壕风衣 汽车自动起动器 麦片 氯气毒气 防毒面具 拉链 机械雨刮器 广义相对论 芥子气 量产拖拉机 电子钟 黄油枪 降落伞 广播电台播音 茶包 罗夏墨迹测验 机器人 胰岛素 实用邮戳机 滑水 百日咳疫苗 纸制鸡蛋托 面巾纸 商用飞机农药喷撒 液体燃料火箭 劳力士防水表 遥控电唱机 面包机 防水玻璃纸 电传打字机 盖革计数器 纯维生素C 彩色电影胶片 透明胶带 音乐汽车喇叭 闪光灯 速冻食品 球形潜水舱 回旋加速器 折叠式雨伞 电动剃须刀 车载收音机 玛氏巧克力棒 变焦镜头 大富翁桌游 商业洗衣店 畅销平装书 里氏震级 磁带录音机 大众汽车 超市推车 带温控器的电熨斗 速溶咖啡 尼龙 圆珠笔 黄热病疫苗 雷达 汽车自动变速箱 充气救生衣 人工授精 青霉素 军用吉普车 原子裂变 火箭筒 凝固汽油弹 水肺 麦角酸二乙酰胺 神经毒气 原子弹 特百惠 计算机 静电复印法 比基尼泳衣 浓缩咖啡机 宝丽来相机 拼字盘 实心电吉他 尼龙扣 晶体管 黑胶唱片 有线电视 电视显像管 汽车自动点火装置 信用卡 复印机 宽荧幕电影 动力转向器 三色停车灯 人行红绿灯 晶体管助听器 氢弹 录像带 DNA双螺旋结构 麻疹疫苗 按动圆珠笔 硅晶体管 核导弹 空对空导弹 迪士尼乐园 特氟龙 卡丁车 地对空核导弹 沙宾疫苗 通讯卫星 呼啦圈 安全带 人工肾脏 避孕药 气象卫星 便携晶体管收音机 安定 砷化镓半导体激光器 三维全息技术 合成器 香烟健康警示 凯夫拉纤维 子午胎 IBM文字处理机 杜比A型降噪器 滑雪板 喇叭裤 绕月载人火箭 人工心脏移植 波音747喷气式客机 互联网 条形码 软盘 帆板 热裤 液晶显示 便携电子计算器 电视游戏 DNA重组技术 电子游戏机 超级计算机 光纤 试管婴儿 魔方 索尼Walkman 杜比C型降噪器 艾滋病毒 强效可卡因 温室效应 CD 暗物质 暗能量 太阳能飞行器 甲型H1N1 流感 希格斯玻色子 引力波 | AR45: 电气地铁 圣代冰淇淋 实用水电站 手电 电影摄影机 收音机 霍乱疫苗 啤酒瓶盖 柴油发动机 双向电报 实用的胶卷 块麦片 电报 可口可乐 X射线 卷烟机发明 电影放映机 排球 印名片机 福特车 潜望镜 油印蜡纸发明 阴极射线管 商品阿司匹林 凯洛格牌玉米片 手电筒 钋 镭 摇控器 α粒子 β粒子 打字机 柯达布朗尼相机 齐柏林飞艇 人类血型 跨大西洋电报 汽轮机游船 现代柏油路 铝罐奶粉 爆米花 泰迪熊 卡鲁索电唱机 便宜的肥皂和烹饪用油 | AS45: 汽轮机游船 现代柏油路 铝罐奶粉 爆米花 泰迪熊 卡鲁索电唱机 便宜的肥皂和烹饪用油 | AT45: 1902 | BA45: 故 | BB45: 国 | BC45: =IF(人物卡!BK14="",1,0) -> 1 | BD45: 省 | BE45: =IF(人物卡!BN14="",1,0) -> 1 | BH45: *西亚*
C46: 年龄倍数 | D46: scd | E46: a | I46: 响尾蛇毒 | J46: 15～60分钟 | K46: 呕吐、剧烈抽搐、黄视。 | L46: 2D10 | M46: 毒液会破坏组织、引发坏死，不过很少致命（特别是一两个小时内就获得解药的话）。 | O46: 其他(上肢) | S46: =S24&S37&S39&S40&S44 -> .st 力量0str0敏捷0dex0意志0pow0体质0con0外貌0app0教育0edu0体型0siz0智力0灵感0int0san0san值0理智0理智值0幸运0运气0mp0魔法0hp0体力0会计5法律5历史5人类学1神秘学5魅惑5信用评级0计算机0计算机使用0电脑0信用10信誉10信用评级10克苏鲁10克苏鲁神话10cm10电子学 Ω1操作重型机械1汽车1驾驶1汽车驾驶1计算机使用 Ω0电子学1科学②115技艺⑤5母语0外语①1外语②1闪避0锁匠1图书馆5图书馆使用5妙手10开锁20撬锁20锁匠20图书馆使用20聆听20博物学25自然学25领航10导航10导航10重型操作10重型机械10操作重型机械10重型10取悦15恐吓15说服10跳跃20游泳20精神分析1医学1生存30驾驶①1驾驶②1汽车驾驶20骑术5动物驯养5潜水1读唇1催眠1自定义①1炮术1投掷20时代:1920s 年龄时间未填 身体状态:健康 精神状态:清醒 &DB=0 体格:0 闪避:0 护甲:无 | X46: 学识： | AE46: 1903 | AF46: —— | AI46: —— | AL46: 二十世纪初 | AM46: 癸卯兔年 | AN46: 清光绪29年 | AO46: 芝加哥易洛魁剧院大火，死亡 602 人，是美国历史上最严重的火灾 莱特兄弟试飞飞机 首个荧光灯 邮戳机产生 车架中心摩托车发动机 | AP46: 总统： 西奥多·罗斯福（共和党） | AQ46: 热水瓶 农业轨道机械 木棉安全带 电动汽车喇叭 化学泡沫灭火器 狭义相对论 自动点唱机 量产舰艇舷外发动机 动画 电动洗衣机 家用洗洁精 立式吸尘器 饮用纸杯 双层公交车 无线电测向仪 电煎锅 质子和电子 玻璃纸 战壕风衣 汽车自动起动器 麦片 氯气毒气 防毒面具 拉链 机械雨刮器 广义相对论 芥子气 量产拖拉机 电子钟 黄油枪 降落伞 广播电台播音 茶包 罗夏墨迹测验 机器人 胰岛素 实用邮戳机 滑水 百日咳疫苗 纸制鸡蛋托 面巾纸 商用飞机农药喷撒 液体燃料火箭 劳力士防水表 遥控电唱机 面包机 防水玻璃纸 电传打字机 盖革计数器 纯维生素C 彩色电影胶片 透明胶带 音乐汽车喇叭 闪光灯 速冻食品 球形潜水舱 回旋加速器 折叠式雨伞 电动剃须刀 车载收音机 玛氏巧克力棒 变焦镜头 大富翁桌游 商业洗衣店 畅销平装书 里氏震级 磁带录音机 大众汽车 超市推车 带温控器的电熨斗 速溶咖啡 尼龙 圆珠笔 黄热病疫苗 雷达 汽车自动变速箱 充气救生衣 人工授精 青霉素 军用吉普车 原子裂变 火箭筒 凝固汽油弹 水肺 麦角酸二乙酰胺 神经毒气 原子弹 特百惠 计算机 静电复印法 比基尼泳衣 浓缩咖啡机 宝丽来相机 拼字盘 实心电吉他 尼龙扣 晶体管 黑胶唱片 有线电视 电视显像管 汽车自动点火装置 信用卡 复印机 宽荧幕电影 动力转向器 三色停车灯 人行红绿灯 晶体管助听器 氢弹 录像带 DNA双螺旋结构 麻疹疫苗 按动圆珠笔 硅晶体管 核导弹 空对空导弹 迪士尼乐园 特氟龙 卡丁车 地对空核导弹 沙宾疫苗 通讯卫星 呼啦圈 安全带 人工肾脏 避孕药 气象卫星 便携晶体管收音机 安定 砷化镓半导体激光器 三维全息技术 合成器 香烟健康警示 凯夫拉纤维 子午胎 IBM文字处理机 杜比A型降噪器 滑雪板 喇叭裤 绕月载人火箭 人工心脏移植 波音747喷气式客机 互联网 条形码 软盘 帆板 热裤 液晶显示 便携电子计算器 电视游戏 DNA重组技术 电子游戏机 超级计算机 光纤 试管婴儿 魔方 索尼Walkman 杜比C型降噪器 艾滋病毒 强效可卡因 温室效应 CD 暗物质 暗能量 太阳能飞行器 甲型H1N1 流感 希格斯玻色子 引力波 | AR46: 电气地铁 圣代冰淇淋 实用水电站 手电 电影摄影机 收音机 霍乱疫苗 啤酒瓶盖 柴油发动机 双向电报 实用的胶卷 块麦片 电报 可口可乐 X射线 卷烟机发明 电影放映机 排球 印名片机 福特车 潜望镜 油印蜡纸发明 阴极射线管 商品阿司匹林 凯洛格牌玉米片 手电筒 钋 镭 摇控器 α粒子 β粒子 打字机 柯达布朗尼相机 齐柏林飞艇 人类血型 跨大西洋电报 汽轮机游船 现代柏油路 铝罐奶粉 爆米花 泰迪熊 卡鲁索电唱机 便宜的肥皂和烹饪用油 飞机 荧光灯 邮戳机 摩托车发动机 | AS46: 飞机 荧光灯 邮戳机 摩托车发动机 | AT46: 1903 | BB46: 市 | BC46: =IF(人物卡!BK15="",1,0) -> 1 | BD46: 号 | BE46: =IF(人物卡!BN15="",1,0) -> 1 | BF46: =SUM(BC45,BE45,BC46,BE46) -> 4 | BH46: 伊朗 | BI46: 德黑兰* | BJ46: 阿塞拜疆省 | BK46: 库尔德斯坦省 | BL46: 胡齐斯坦省 | BM46: 法尔斯省 | BN46: 克尔曼省 | BO46: 霍尔木兹甘省 | BP46: 伊斯法罕省 | BQ46: 克尔曼沙汗省 | BR46: 哈马丹省 | BS46: 恰哈马哈勒巴赫蒂亚里省 | BT46: 洛雷斯坦省 | BU46: 西阿塞拜疆省 | BV46: 吉兰省 | BW46: 马赞德兰省 | BX46: 戈尔甘省 | BY46: 北霍拉桑省 | BZ46: 南霍拉桑省 | CA46: 塞姆南省 | CB46: 锡斯坦和俾路支斯坦省 | CC46: 亚兹德省 | CD46: 赞詹省 | CE46: 马库兰省 | CF46: 中央省 | CG46: 科吉卢耶-博韦艾哈迈德省 | CH46: 布什尔省 | CI46: 扎黑丹省 | CJ46: 阿尔达比勒省 | CK46: 伊拉姆省 | CL46: 恰帕哈卢省 | CM46: 库姆省 | CN46: 拉扎维呼罗珊省 | CO46: 塞姆南省 | CP46: 阿尔伯兹省
C47: =INT((C37-B45)/10) -> -8 | D47: =80+80*C47 -> -560 | E47: 25 | I47: 氟硝西泮 | J47: 15～30分钟 | K47: 昏迷4～8小时，可能会失忆。 | L47: 无伤害 | M47: 无色无味，只在现代背景中出现。 | O47: 下肢———— | X47: 技艺① | AE47: 1904 | AF47: 日俄战争 | AG47: 圣路易斯奥运会 | AI47: —— | AL47: 二十世纪初 | AM47: 甲辰龙年 | AN47: 清光绪30年 | AO47: 伊甸火车在洪水中出轨，死亡 96 人 百老汇地铁在纽约城开通 热水瓶获得专利 轨道机械（相对于轮式 ) 出现在农业机械当中 木棉安全带 日俄战争 | AP47: 总统： 西奥多·罗斯福（共和党） | AQ47: 电动汽车喇叭 化学泡沫灭火器 狭义相对论 自动点唱机 量产舰艇舷外发动机 动画 电动洗衣机 家用洗洁精 立式吸尘器 饮用纸杯 双层公交车 无线电测向仪 电煎锅 质子和电子 玻璃纸 战壕风衣 汽车自动起动器 麦片 氯气毒气 防毒面具 拉链 机械雨刮器 广义相对论 芥子气 量产拖拉机 电子钟 黄油枪 降落伞 广播电台播音 茶包 罗夏墨迹测验 机器人 胰岛素 实用邮戳机 滑水 百日咳疫苗 纸制鸡蛋托 面巾纸 商用飞机农药喷撒 液体燃料火箭 劳力士防水表 遥控电唱机 面包机 防水玻璃纸 电传打字机 盖革计数器 纯维生素C 彩色电影胶片 透明胶带 音乐汽车喇叭 闪光灯 速冻食品 球形潜水舱 回旋加速器 折叠式雨伞 电动剃须刀 车载收音机 玛氏巧克力棒 变焦镜头 大富翁桌游 商业洗衣店 畅销平装书 里氏震级 磁带录音机 大众汽车 超市推车 带温控器的电熨斗 速溶咖啡 尼龙 圆珠笔 黄热病疫苗 雷达 汽车自动变速箱 充气救生衣 人工授精 青霉素 军用吉普车 原子裂变 火箭筒 凝固汽油弹 水肺 麦角酸二乙酰胺 神经毒气 原子弹 特百惠 计算机 静电复印法 比基尼泳衣 浓缩咖啡机 宝丽来相机 拼字盘 实心电吉他 尼龙扣 晶体管 黑胶唱片 有线电视 电视显像管 汽车自动点火装置 信用卡 复印机 宽荧幕电影 动力转向器 三色停车灯 人行红绿灯 晶体管助听器 氢弹 录像带 DNA双螺旋结构 麻疹疫苗 按动圆珠笔 硅晶体管 核导弹 空对空导弹 迪士尼乐园 特氟龙 卡丁车 地对空核导弹 沙宾疫苗 通讯卫星 呼啦圈 安全带 人工肾脏 避孕药 气象卫星 便携晶体管收音机 安定 砷化镓半导体激光器 三维全息技术 合成器 香烟健康警示 凯夫拉纤维 子午胎 IBM文字处理机 杜比A型降噪器 滑雪板 喇叭裤 绕月载人火箭 人工心脏移植 波音747喷气式客机 互联网 条形码 软盘 帆板 热裤 液晶显示 便携电子计算器 电视游戏 DNA重组技术 电子游戏机 超级计算机 光纤 试管婴儿 魔方 索尼Walkman 杜比C型降噪器 艾滋病毒 强效可卡因 温室效应 CD 暗物质 暗能量 太阳能飞行器 甲型H1N1 流感 希格斯玻色子 引力波 | AR47: 电气地铁 圣代冰淇淋 实用水电站 手电 电影摄影机 收音机 霍乱疫苗 啤酒瓶盖 柴油发动机 双向电报 实用的胶卷 块麦片 电报 可口可乐 X射线 卷烟机发明 电影放映机 排球 印名片机 福特车 潜望镜 油印蜡纸发明 阴极射线管 商品阿司匹林 凯洛格牌玉米片 手电筒 钋 镭 摇控器 α粒子 β粒子 打字机 柯达布朗尼相机 齐柏林飞艇 人类血型 跨大西洋电报 汽轮机游船 现代柏油路 铝罐奶粉 爆米花 泰迪熊 卡鲁索电唱机 便宜的肥皂和烹饪用油 飞机 荧光灯 邮戳机 摩托车发动机 热水瓶 农业轨道机械 木棉安全带 | AS47: 热水瓶 农业轨道机械 木棉安全带 | AT47: 1904 | BH47: 伊拉克 | BI47: 巴格达* | BJ47: 巴士拉省 | BK47: 埃尔比勒省 | BL47: 巴比伦省 | BM47: 穆萨纳省 | BN47: 杜胡克省 | BO47: 迪亚拉省 | BP47: 济加尔省 | BQ47: 卡尔巴拉省 | BR47: 卡迪西亚省 | BS47: 米桑省 | BT47: 纳杰夫省 | BU47: 尼尼微省 | BV47: 瓦西特省 | BW47: 萨拉赫丁省 | BX47: 安巴尔省 | BY47: 塔米姆省 | BZ47: 穆哈夫扎卡区
C48: =C37 -> 0 | D48: ="进步*4,SCD共-"&D47&" A-"&E47 -> 进步*4,SCD共--560 A-25 | I48: 番木鳖碱（马钱子碱、士的宁） | J48: 10～20分钟 | K48: 剧烈的肌肉痉挛、窒息、死亡。 | L48: 4D10 | M48: 如果不及时医治，几小时内就会死亡。 | O48: 左脚 | X48: 技艺② | AE48: 1905 | AF48: 俄国革命 | AI48: —— | AL48: 二十世纪初 | AM48: 乙巳蛇年 | AN48: 清光绪31年 | AO48: 库利南钻石（3000 克拉 )，当时世界最大的钻石 英国海军标准配备蒸汽轮机 1905 年俄国革命 电动汽车喇叭 化学泡沫灭火器 狭义相对论 | AP48: 总统： 西奥多·罗斯福（共和党） | AQ48: 自动点唱机 量产舰艇舷外发动机 动画 电动洗衣机 家用洗洁精 立式吸尘器 饮用纸杯 双层公交车 无线电测向仪 电煎锅 质子和电子 玻璃纸 战壕风衣 汽车自动起动器 麦片 氯气毒气 防毒面具 拉链 机械雨刮器 广义相对论 芥子气 量产拖拉机 电子钟 黄油枪 降落伞 广播电台播音 茶包 罗夏墨迹测验 机器人 胰岛素 实用邮戳机 滑水 百日咳疫苗 纸制鸡蛋托 面巾纸 商用飞机农药喷撒 液体燃料火箭 劳力士防水表 遥控电唱机 面包机 防水玻璃纸 电传打字机 盖革计数器 纯维生素C 彩色电影胶片 透明胶带 音乐汽车喇叭 闪光灯 速冻食品 球形潜水舱 回旋加速器 折叠式雨伞 电动剃须刀 车载收音机 玛氏巧克力棒 变焦镜头 大富翁桌游 商业洗衣店 畅销平装书 里氏震级 磁带录音机 大众汽车 超市推车 带温控器的电熨斗 速溶咖啡 尼龙 圆珠笔 黄热病疫苗 雷达 汽车自动变速箱 充气救生衣 人工授精 青霉素 军用吉普车 原子裂变 火箭筒 凝固汽油弹 水肺 麦角酸二乙酰胺 神经毒气 原子弹 特百惠 计算机 静电复印法 比基尼泳衣 浓缩咖啡机 宝丽来相机 拼字盘 实心电吉他 尼龙扣 晶体管 黑胶唱片 有线电视 电视显像管 汽车自动点火装置 信用卡 复印机 宽荧幕电影 动力转向器 三色停车灯 人行红绿灯 晶体管助听器 氢弹 录像带 DNA双螺旋结构 麻疹疫苗 按动圆珠笔 硅晶体管 核导弹 空对空导弹 迪士尼乐园 特氟龙 卡丁车 地对空核导弹 沙宾疫苗 通讯卫星 呼啦圈 安全带 人工肾脏 避孕药 气象卫星 便携晶体管收音机 安定 砷化镓半导体激光器 三维全息技术 合成器 香烟健康警示 凯夫拉纤维 子午胎 IBM文字处理机 杜比A型降噪器 滑雪板 喇叭裤 绕月载人火箭 人工心脏移植 波音747喷气式客机 互联网 条形码 软盘 帆板 热裤 液晶显示 便携电子计算器 电视游戏 DNA重组技术 电子游戏机 超级计算机 光纤 试管婴儿 魔方 索尼Walkman 杜比C型降噪器 艾滋病毒 强效可卡因 温室效应 CD 暗物质 暗能量 太阳能飞行器 甲型H1N1 流感 希格斯玻色子 引力波 | AR48: 电气地铁 圣代冰淇淋 实用水电站 手电 电影摄影机 收音机 霍乱疫苗 啤酒瓶盖 柴油发动机 双向电报 实用的胶卷 块麦片 电报 可口可乐 X射线 卷烟机发明 电影放映机 排球 印名片机 福特车 潜望镜 油印蜡纸发明 阴极射线管 商品阿司匹林 凯洛格牌玉米片 手电筒 钋 镭 摇控器 α粒子 β粒子 打字机 柯达布朗尼相机 齐柏林飞艇 人类血型 跨大西洋电报 汽轮机游船 现代柏油路 铝罐奶粉 爆米花 泰迪熊 卡鲁索电唱机 便宜的肥皂和烹饪用油 飞机 荧光灯 邮戳机 摩托车发动机 热水瓶 农业轨道机械 木棉安全带 电动汽车喇叭 化学泡沫灭火器 狭义相对论 | AS48: 电动汽车喇叭 化学泡沫灭火器 狭义相对论 | AT48: 1905 | BA48: 年 | BB48: =IF(人物卡!BF17="",1,0) -> 1 | BH48: 阿富汗 | BI48: 喀布尔* | BJ48: 巴德吉斯省 | BK48: 巴达赫尚省 | BL48: 巴格兰省 | BM48: 巴尔赫省 | BN48: 巴米扬省 | BO48: 戴孔迪省 | BP48: 法拉省 | BQ48: 赫尔曼德省 | BR48: 赫拉特省 | BS48: 朱兹詹省 | BT48: 坎大哈省 | BU48: 喀布尔省 | BV48: 库纳尔省 | BW48: 拉格曼省 | BX48: 洛加尔省 | BY48: 楠格哈尔省 | BZ48: 尼姆鲁兹省 | CA48: 努尔斯坦省 | CB48: 帕克蒂亚省 | CC48: 帕克蒂卡省 | CD48: 潘杰希尔省 | CE48: 帕尔万省 | CF48: 萨曼甘省 | CG48: 萨尔普勒省 | CH48: 塔哈尔省 | CI48: 瓦尔达克省 | CJ48: 扎布尔省 | CK48: 昆都士省
I49: 请打开下拉栏选择 | O49: 右脚 | X49: 技艺③ | AE49: 1906 | AF49: 美军占领古巴 | AG49: 印度民族解放运动 | AI49: —— | AL49: 二十世纪初 | AM49: 丙午马年 | AN49: 清光绪32年 | AO49: 1906 年旧金山大地震引发大火，死亡700 人，28818 间房屋损毁 美军占领古巴到 1909年 卢西塔尼亚和毛里塔尼亚号下水 自动点唱机 舰艇舷外发动机量产 | AP49: 总统： 西奥多·罗斯福（共和党） | AQ49: 动画 电动洗衣机 家用洗洁精 立式吸尘器 饮用纸杯 双层公交车 无线电测向仪 电煎锅 质子和电子 玻璃纸 战壕风衣 汽车自动起动器 麦片 氯气毒气 防毒面具 拉链 机械雨刮器 广义相对论 芥子气 量产拖拉机 电子钟 黄油枪 降落伞 广播电台播音 茶包 罗夏墨迹测验 机器人 胰岛素 实用邮戳机 滑水 百日咳疫苗 纸制鸡蛋托 面巾纸 商用飞机农药喷撒 液体燃料火箭 劳力士防水表 遥控电唱机 面包机 防水玻璃纸 电传打字机 盖革计数器 纯维生素C 彩色电影胶片 透明胶带 音乐汽车喇叭 闪光灯 速冻食品 球形潜水舱 回旋加速器 折叠式雨伞 电动剃须刀 车载收音机 玛氏巧克力棒 变焦镜头 大富翁桌游 商业洗衣店 畅销平装书 里氏震级 磁带录音机 大众汽车 超市推车 带温控器的电熨斗 速溶咖啡 尼龙 圆珠笔 黄热病疫苗 雷达 汽车自动变速箱 充气救生衣 人工授精 青霉素 军用吉普车 原子裂变 火箭筒 凝固汽油弹 水肺 麦角酸二乙酰胺 神经毒气 原子弹 特百惠 计算机 静电复印法 比基尼泳衣 浓缩咖啡机 宝丽来相机 拼字盘 实心电吉他 尼龙扣 晶体管 黑胶唱片 有线电视 电视显像管 汽车自动点火装置 信用卡 复印机 宽荧幕电影 动力转向器 三色停车灯 人行红绿灯 晶体管助听器 氢弹 录像带 DNA双螺旋结构 麻疹疫苗 按动圆珠笔 硅晶体管 核导弹 空对空导弹 迪士尼乐园 特氟龙 卡丁车 地对空核导弹 沙宾疫苗 通讯卫星 呼啦圈 安全带 人工肾脏 避孕药 气象卫星 便携晶体管收音机 安定 砷化镓半导体激光器 三维全息技术 合成器 香烟健康警示 凯夫拉纤维 子午胎 IBM文字处理机 杜比A型降噪器 滑雪板 喇叭裤 绕月载人火箭 人工心脏移植 波音747喷气式客机 互联网 条形码 软盘 帆板 热裤 液晶显示 便携电子计算器 电视游戏 DNA重组技术 电子游戏机 超级计算机 光纤 试管婴儿 魔方 索尼Walkman 杜比C型降噪器 艾滋病毒 强效可卡因 温室效应 CD 暗物质 暗能量 太阳能飞行器 甲型H1N1 流感 希格斯玻色子 引力波 | AR49: 电气地铁 圣代冰淇淋 实用水电站 手电 电影摄影机 收音机 霍乱疫苗 啤酒瓶盖 柴油发动机 双向电报 实用的胶卷 块麦片 电报 可口可乐 X射线 卷烟机发明 电影放映机 排球 印名片机 福特车 潜望镜 油印蜡纸发明 阴极射线管 商品阿司匹林 凯洛格牌玉米片 手电筒 钋 镭 摇控器 α粒子 β粒子 打字机 柯达布朗尼相机 齐柏林飞艇 人类血型 跨大西洋电报 汽轮机游船 现代柏油路 铝罐奶粉 爆米花 泰迪熊 卡鲁索电唱机 便宜的肥皂和烹饪用油 飞机 荧光灯 邮戳机 摩托车发动机 热水瓶 农业轨道机械 木棉安全带 电动汽车喇叭 化学泡沫灭火器 狭义相对论 自动点唱机 量产舰艇舷外发动机 | AS49: 自动点唱机 量产舰艇舷外发动机 | AT49: 1906 | BA49: 月 | BB49: =IF(人物卡!BI17="",1,0) -> 1 | BH49: 沙特阿拉伯 | BI49: 利雅得* | BJ49: 东部省 | BK49: 麦加省 | BL49: 麦地那省 | BM49: 北部边疆省 | BN49: 吉赞省 | BO49: 卡西姆省 | BP49: 纳季兰省 | BQ49: 焦夫省 | BR49: 哈伊勒省 | BS49: 阿西尔省 | BT49: 巴哈省 | BU49: 塔布克省 | BV49: 延布省
O50: 双脚 | X50: 技艺② | AA50: =".st"&"力量"&STRA&"str"&STRA&"敏捷"&DEXA&"dex"&DEXA&"意志"&POWA&"pow"&POWA&"体质"&CONA&"con"&CONA&"外貌"&APPA&"app"&APPA&"教育"&EDUA&"edu"&EDUA&"体型"&SIZA&"siz"&SIZA&"智力"&INTA&"int"&INTA&"灵感"&INTA&"san"&SAN&"san值"&SAN&"理智"&SAN&"理智值"&SAN&"幸运"&IF(LuckA="未改运",0,LuckA)&"运气"&IF(LuckA="未改运",0,LuckA)&"mp"&MP&"魔法"&MP&"hp"&hp&"体力"&hp -> .st力量未填写str未填写敏捷未填写dex未填写意志未填写pow未填写体质未填写con未填写外貌未填写app未填写教育未填写edu未填写体型未填写siz未填写智力未填写int未填写灵感未填写san0san值0理智0理智值0幸运0运气0mp0魔法0hp0体力0 | AE50: 1907 | AF50: —— | AI50: —— | AL50: 二十世纪初 | AM50: 丁未羊年 | AN50: 清光绪33年 | AO50: 西弗吉尼亚州煤矿矿难死亡361 人 拉斯普京在沙俄飞扬跋扈 动画 电动洗衣机 家用洗洁精 立式吸尘器 | AP50: 总统： 西奥多·罗斯福（共和党） | AQ50: 饮用纸杯 双层公交车 无线电测向仪 电煎锅 质子和电子 玻璃纸 战壕风衣 汽车自动起动器 麦片 氯气毒气 防毒面具 拉链 机械雨刮器 广义相对论 芥子气 量产拖拉机 电子钟 黄油枪 降落伞 广播电台播音 茶包 罗夏墨迹测验 机器人 胰岛素 实用邮戳机 滑水 百日咳疫苗 纸制鸡蛋托 面巾纸 商用飞机农药喷撒 液体燃料火箭 劳力士防水表 遥控电唱机 面包机 防水玻璃纸 电传打字机 盖革计数器 纯维生素C 彩色电影胶片 透明胶带 音乐汽车喇叭 闪光灯 速冻食品 球形潜水舱 回旋加速器 折叠式雨伞 电动剃须刀 车载收音机 玛氏巧克力棒 变焦镜头 大富翁桌游 商业洗衣店 畅销平装书 里氏震级 磁带录音机 大众汽车 超市推车 带温控器的电熨斗 速溶咖啡 尼龙 圆珠笔 黄热病疫苗 雷达 汽车自动变速箱 充气救生衣 人工授精 青霉素 军用吉普车 原子裂变 火箭筒 凝固汽油弹 水肺 麦角酸二乙酰胺 神经毒气 原子弹 特百惠 计算机 静电复印法 比基尼泳衣 浓缩咖啡机 宝丽来相机 拼字盘 实心电吉他 尼龙扣 晶体管 黑胶唱片 有线电视 电视显像管 汽车自动点火装置 信用卡 复印机 宽荧幕电影 动力转向器 三色停车灯 人行红绿灯 晶体管助听器 氢弹 录像带 DNA双螺旋结构 麻疹疫苗 按动圆珠笔 硅晶体管 核导弹 空对空导弹 迪士尼乐园 特氟龙 卡丁车 地对空核导弹 沙宾疫苗 通讯卫星 呼啦圈 安全带 人工肾脏 避孕药 气象卫星 便携晶体管收音机 安定 砷化镓半导体激光器 三维全息技术 合成器 香烟健康警示 凯夫拉纤维 子午胎 IBM文字处理机 杜比A型降噪器 滑雪板 喇叭裤 绕月载人火箭 人工心脏移植 波音747喷气式客机 互联网 条形码 软盘 帆板 热裤 液晶显示 便携电子计算器 电视游戏 DNA重组技术 电子游戏机 超级计算机 光纤 试管婴儿 魔方 索尼Walkman 杜比C型降噪器 艾滋病毒 强效可卡因 温室效应 CD 暗物质 暗能量 太阳能飞行器 甲型H1N1 流感 希格斯玻色子 引力波 | AR50: 电气地铁 圣代冰淇淋 实用水电站 手电 电影摄影机 收音机 霍乱疫苗 啤酒瓶盖 柴油发动机 双向电报 实用的胶卷 块麦片 电报 可口可乐 X射线 卷烟机发明 电影放映机 排球 印名片机 福特车 潜望镜 油印蜡纸发明 阴极射线管 商品阿司匹林 凯洛格牌玉米片 手电筒 钋 镭 摇控器 α粒子 β粒子 打字机 柯达布朗尼相机 齐柏林飞艇 人类血型 跨大西洋电报 汽轮机游船 现代柏油路 铝罐奶粉 爆米花 泰迪熊 卡鲁索电唱机 便宜的肥皂和烹饪用油 飞机 荧光灯 邮戳机 摩托车发动机 热水瓶 农业轨道机械 木棉安全带 电动汽车喇叭 化学泡沫灭火器 狭义相对论 自动点唱机 量产舰艇舷外发动机 动画 电动洗衣机 家用洗洁精 立式吸尘器 | AS50: 动画 电动洗衣机 家用洗洁精 立式吸尘器 | AT50: 1907 | BA50: 日 | BB50: =IF(人物卡!BK17="",1,0) -> 1 | BH50: 阿拉伯联合酋长国 | BI50: 阿布扎比* | BJ50: 迪拜 | BK50: 沙迦 | BL50: 阿治曼 | BM50: 乌姆盖万 | BN50: 拉斯海马 | BO50: 富查伊拉
O51: 左腿 | X51: 技艺③ | AE51: 1908 | AF51: 伦敦奥运会 | AI51: —— | AL51: 二十世纪初 | AM51: 戊申猴年 | AN51: 清光绪34年 | AO51: 敏可夫斯基阐述他的四维几何 饮用纸杯 | AP51: 总统： 西奥多·罗斯福（共和党） | AQ51: 双层公交车 无线电测向仪 电煎锅 质子和电子 玻璃纸 战壕风衣 汽车自动起动器 麦片 氯气毒气 防毒面具 拉链 机械雨刮器 广义相对论 芥子气 量产拖拉机 电子钟 黄油枪 降落伞 广播电台播音 茶包 罗夏墨迹测验 机器人 胰岛素 实用邮戳机 滑水 百日咳疫苗 纸制鸡蛋托 面巾纸 商用飞机农药喷撒 液体燃料火箭 劳力士防水表 遥控电唱机 面包机 防水玻璃纸 电传打字机 盖革计数器 纯维生素C 彩色电影胶片 透明胶带 音乐汽车喇叭 闪光灯 速冻食品 球形潜水舱 回旋加速器 折叠式雨伞 电动剃须刀 车载收音机 玛氏巧克力棒 变焦镜头 大富翁桌游 商业洗衣店 畅销平装书 里氏震级 磁带录音机 大众汽车 超市推车 带温控器的电熨斗 速溶咖啡 尼龙 圆珠笔 黄热病疫苗 雷达 汽车自动变速箱 充气救生衣 人工授精 青霉素 军用吉普车 原子裂变 火箭筒 凝固汽油弹 水肺 麦角酸二乙酰胺 神经毒气 原子弹 特百惠 计算机 静电复印法 比基尼泳衣 浓缩咖啡机 宝丽来相机 拼字盘 实心电吉他 尼龙扣 晶体管 黑胶唱片 有线电视 电视显像管 汽车自动点火装置 信用卡 复印机 宽荧幕电影 动力转向器 三色停车灯 人行红绿灯 晶体管助听器 氢弹 录像带 DNA双螺旋结构 麻疹疫苗 按动圆珠笔 硅晶体管 核导弹 空对空导弹 迪士尼乐园 特氟龙 卡丁车 地对空核导弹 沙宾疫苗 通讯卫星 呼啦圈 安全带 人工肾脏 避孕药 气象卫星 便携晶体管收音机 安定 砷化镓半导体激光器 三维全息技术 合成器 香烟健康警示 凯夫拉纤维 子午胎 IBM文字处理机 杜比A型降噪器 滑雪板 喇叭裤 绕月载人火箭 人工心脏移植 波音747喷气式客机 互联网 条形码 软盘 帆板 热裤 液晶显示 便携电子计算器 电视游戏 DNA重组技术 电子游戏机 超级计算机 光纤 试管婴儿 魔方 索尼Walkman 杜比C型降噪器 艾滋病毒 强效可卡因 温室效应 CD 暗物质 暗能量 太阳能飞行器 甲型H1N1 流感 希格斯玻色子 引力波 | AR51: 电气地铁 圣代冰淇淋 实用水电站 手电 电影摄影机 收音机 霍乱疫苗 啤酒瓶盖 柴油发动机 双向电报 实用的胶卷 块麦片 电报 可口可乐 X射线 卷烟机发明 电影放映机 排球 印名片机 福特车 潜望镜 油印蜡纸发明 阴极射线管 商品阿司匹林 凯洛格牌玉米片 手电筒 钋 镭 摇控器 α粒子 β粒子 打字机 柯达布朗尼相机 齐柏林飞艇 人类血型 跨大西洋电报 汽轮机游船 现代柏油路 铝罐奶粉 爆米花 泰迪熊 卡鲁索电唱机 便宜的肥皂和烹饪用油 飞机 荧光灯 邮戳机 摩托车发动机 热水瓶 农业轨道机械 木棉安全带 电动汽车喇叭 化学泡沫灭火器 狭义相对论 自动点唱机 量产舰艇舷外发动机 动画 电动洗衣机 家用洗洁精 立式吸尘器 饮用纸杯 | AS51: 饮用纸杯 | AT51: 1908 | BA51: 时 | BB51: =IF(人物卡!BM17="",1,0) -> 0 | BC51: =SUM(BB48:BB51) -> 3 | BH51: 科威特 | BI51: 科威特城* | BJ51: 艾哈迈迪省 | BK51: 法哈迪尔省 | BL51: 哈瓦利省 | BM51: 杰赫拉省 | BN51: 穆巴拉克·卡巴尔省 | BO51: 大穆巴拉克省
E52: =IF(人物卡!BL11=0," ","["&LOOKUP(人物卡!BL11,职业列表!A2:A237,职业列表!B2:B237)&"]") | H52: ←这个职业 要这样获得技能点→ | J52: =IF(人物卡!BL11=0," ","["&LOOKUP(人物卡!BL11,职业列表!A2:C237,职业列表!E2:E237)&"]") | L52: 剩职 | M52: =IFERROR(J53-SUM(人物卡!BM25:BN33,人物卡!BM35:BN64,人物卡!CI25:CJ64),0) -> 0 | O52: 右腿 | X52: 母语 | AE52: 1909 | AF52: —— | AI52: —— | AL52: 二十世纪初 清·宣统元年 | AM52: 己酉鸡年 | AN52: 清宣统元年 | AO52: 罗伯特·E·皮尔里抵达北极点 路易斯安那和密西西比州飓风，死亡350 人 首次穿越英吉利海峡的飞行 英国双层公交车 | AP52: 总统： 西奥多·罗斯福（共和党） 威廉·霍华德·塔夫脱（共和党） | AQ52: 无线电测向仪 电煎锅 质子和电子 玻璃纸 战壕风衣 汽车自动起动器 麦片 氯气毒气 防毒面具 拉链 机械雨刮器 广义相对论 芥子气 量产拖拉机 电子钟 黄油枪 降落伞 广播电台播音 茶包 罗夏墨迹测验 机器人 胰岛素 实用邮戳机 滑水 百日咳疫苗 纸制鸡蛋托 面巾纸 商用飞机农药喷撒 液体燃料火箭 劳力士防水表 遥控电唱机 面包机 防水玻璃纸 电传打字机 盖革计数器 纯维生素C 彩色电影胶片 透明胶带 音乐汽车喇叭 闪光灯 速冻食品 球形潜水舱 回旋加速器 折叠式雨伞 电动剃须刀 车载收音机 玛氏巧克力棒 变焦镜头 大富翁桌游 商业洗衣店 畅销平装书 里氏震级 磁带录音机 大众汽车 超市推车 带温控器的电熨斗 速溶咖啡 尼龙 圆珠笔 黄热病疫苗 雷达 汽车自动变速箱 充气救生衣 人工授精 青霉素 军用吉普车 原子裂变 火箭筒 凝固汽油弹 水肺 麦角酸二乙酰胺 神经毒气 原子弹 特百惠 计算机 静电复印法 比基尼泳衣 浓缩咖啡机 宝丽来相机 拼字盘 实心电吉他 尼龙扣 晶体管 黑胶唱片 有线电视 电视显像管 汽车自动点火装置 信用卡 复印机 宽荧幕电影 动力转向器 三色停车灯 人行红绿灯 晶体管助听器 氢弹 录像带 DNA双螺旋结构 麻疹疫苗 按动圆珠笔 硅晶体管 核导弹 空对空导弹 迪士尼乐园 特氟龙 卡丁车 地对空核导弹 沙宾疫苗 通讯卫星 呼啦圈 安全带 人工肾脏 避孕药 气象卫星 便携晶体管收音机 安定 砷化镓半导体激光器 三维全息技术 合成器 香烟健康警示 凯夫拉纤维 子午胎 IBM文字处理机 杜比A型降噪器 滑雪板 喇叭裤 绕月载人火箭 人工心脏移植 波音747喷气式客机 互联网 条形码 软盘 帆板 热裤 液晶显示 便携电子计算器 电视游戏 DNA重组技术 电子游戏机 超级计算机 光纤 试管婴儿 魔方 索尼Walkman 杜比C型降噪器 艾滋病毒 强效可卡因 温室效应 CD 暗物质 暗能量 太阳能飞行器 甲型H1N1 流感 希格斯玻色子 引力波 | AR52: 电气地铁 圣代冰淇淋 实用水电站 手电 电影摄影机 收音机 霍乱疫苗 啤酒瓶盖 柴油发动机 双向电报 实用的胶卷 块麦片 电报 可口可乐 X射线 卷烟机发明 电影放映机 排球 印名片机 福特车 潜望镜 油印蜡纸发明 阴极射线管 商品阿司匹林 凯洛格牌玉米片 手电筒 钋 镭 摇控器 α粒子 β粒子 打字机 柯达布朗尼相机 齐柏林飞艇 人类血型 跨大西洋电报 汽轮机游船 现代柏油路 铝罐奶粉 爆米花 泰迪熊 卡鲁索电唱机 便宜的肥皂和烹饪用油 飞机 荧光灯 邮戳机 摩托车发动机 热水瓶 农业轨道机械 木棉安全带 电动汽车喇叭 化学泡沫灭火器 狭义相对论 自动点唱机 量产舰艇舷外发动机 动画 电动洗衣机 家用洗洁精 立式吸尘器 饮用纸杯 双层公交车 | AS52: 双层公交车 | AT52: 1909 | BH52: 卡塔尔 | BI52: 多哈* | BJ52: 乌姆锡拉勒 | BK52: 拉斯拉凡 | BL52: 豪尔 | BM52: 沃克拉 | BN52: 北部市 | BO52: 杰里扬拜特奈 | BP52: 艾尔瓦克拉
E53: =IF(人物卡!BL11=0," ","["&LOOKUP(人物卡!BL11,职业列表!A2:A237,职业列表!B2:B237)&"]的本职技能："&LOOKUP(人物卡!BL11,职业列表!A2:A237,职业列表!G2:G237)) | J53: =IF(人物卡!BL11=0," ",LOOKUP(人物卡!BL11,职业列表!A2:C237,职业列表!F2:F237)) | O53: 双腿 | X53: 外语① | AE53: 1910 | AF53: —— | AI53: —— | AL53: 二十世纪 十年代 清·宣统二年 | AM53: 庚戌狗年 | AN53: 清宣统2年 | AO53: 明尼苏达州弗吉尼亚，滑坡掩埋诺曼露天煤矿工人 华盛顿州惠灵顿火车被雪崩掩埋，死亡96 人 约翰·默里和约翰·休特进行首次深海探险 无线电测向仪 美国童子军成立 美国人口920 万人 | AP53: 总统： 威廉·霍华德·塔夫脱（共和党） | AQ53: 电煎锅 质子和电子 玻璃纸 战壕风衣 汽车自动起动器 麦片 氯气毒气 防毒面具 拉链 机械雨刮器 广义相对论 芥子气 量产拖拉机 电子钟 黄油枪 降落伞 广播电台播音 茶包 罗夏墨迹测验 机器人 胰岛素 实用邮戳机 滑水 百日咳疫苗 纸制鸡蛋托 面巾纸 商用飞机农药喷撒 液体燃料火箭 劳力士防水表 遥控电唱机 面包机 防水玻璃纸 电传打字机 盖革计数器 纯维生素C 彩色电影胶片 透明胶带 音乐汽车喇叭 闪光灯 速冻食品 球形潜水舱 回旋加速器 折叠式雨伞 电动剃须刀 车载收音机 玛氏巧克力棒 变焦镜头 大富翁桌游 商业洗衣店 畅销平装书 里氏震级 磁带录音机 大众汽车 超市推车 带温控器的电熨斗 速溶咖啡 尼龙 圆珠笔 黄热病疫苗 雷达 汽车自动变速箱 充气救生衣 人工授精 青霉素 军用吉普车 原子裂变 火箭筒 凝固汽油弹 水肺 麦角酸二乙酰胺 神经毒气 原子弹 特百惠 计算机 静电复印法 比基尼泳衣 浓缩咖啡机 宝丽来相机 拼字盘 实心电吉他 尼龙扣 晶体管 黑胶唱片 有线电视 电视显像管 汽车自动点火装置 信用卡 复印机 宽荧幕电影 动力转向器 三色停车灯 人行红绿灯 晶体管助听器 氢弹 录像带 DNA双螺旋结构 麻疹疫苗 按动圆珠笔 硅晶体管 核导弹 空对空导弹 迪士尼乐园 特氟龙 卡丁车 地对空核导弹 沙宾疫苗 通讯卫星 呼啦圈 安全带 人工肾脏 避孕药 气象卫星 便携晶体管收音机 安定 砷化镓半导体激光器 三维全息技术 合成器 香烟健康警示 凯夫拉纤维 子午胎 IBM文字处理机 杜比A型降噪器 滑雪板 喇叭裤 绕月载人火箭 人工心脏移植 波音747喷气式客机 互联网 条形码 软盘 帆板 热裤 液晶显示 便携电子计算器 电视游戏 DNA重组技术 电子游戏机 超级计算机 光纤 试管婴儿 魔方 索尼Walkman 杜比C型降噪器 艾滋病毒 强效可卡因 温室效应 CD 暗物质 暗能量 太阳能飞行器 甲型H1N1 流感 希格斯玻色子 引力波 | AR53: 电气地铁 圣代冰淇淋 实用水电站 手电 电影摄影机 收音机 霍乱疫苗 啤酒瓶盖 柴油发动机 双向电报 实用的胶卷 块麦片 电报 可口可乐 X射线 卷烟机发明 电影放映机 排球 印名片机 福特车 潜望镜 油印蜡纸发明 阴极射线管 商品阿司匹林 凯洛格牌玉米片 手电筒 钋 镭 摇控器 α粒子 β粒子 打字机 柯达布朗尼相机 齐柏林飞艇 人类血型 跨大西洋电报 汽轮机游船 现代柏油路 铝罐奶粉 爆米花 泰迪熊 卡鲁索电唱机 便宜的肥皂和烹饪用油 飞机 荧光灯 邮戳机 摩托车发动机 热水瓶 农业轨道机械 木棉安全带 电动汽车喇叭 化学泡沫灭火器 狭义相对论 自动点唱机 量产舰艇舷外发动机 动画 电动洗衣机 家用洗洁精 立式吸尘器 饮用纸杯 双层公交车 无线电测向仪 | AS53: 无线电测向仪 | AT53: 1910 | BA53: 总 | BB53: =IF(BF41>0,"基本信息未填写！",IF(BF44>0,"住地未填写！",IF(BF46>0,"故乡未填写！",IF(BC510>0,"时间未填写！","名片准备完成")))) -> 基本信息未填写！ | BH53: 巴林 | BI53: 麦纳麦* | BJ53: 穆哈拉格 | BK53: 北方省 | BL53: 首都省 | BM53: 南部省 | BN53: 西部省
L54: 剩兴 | M54: =MAX(STRA,DEXA,POWA,CONA,APPA,EDUA,SIZA,INTA)*2-SUM(人物卡!BO25:BP33,人物卡!BO35:BP64,人物卡!CK25:CL64) -> 0 | O54: 膝部 | X54: 外语② | AE54: 1911 | AF54: —— | AI54: 辛亥革命 | AL54: 二十世纪 十年代 清·宣统三年 | AM54: 辛亥猪年 | AN54: 清宣统3年 | AO54: 泽西市火车站40 吨炸药爆炸，死亡30 人 纽约三角女衬衫厂火灾，死亡145 人 埃米利亚诺·萨帕塔兵临墨西哥城 辛亥革命 电煎锅 挪威探险家罗阿尔德·阿蒙森抵达南极 | AP54: 歌剧： 巴托克·贝拉《蓝胡子公爵的城堡》 总统： 威廉·霍华德·塔夫脱（共和党） | AQ54: 质子和电子 玻璃纸 战壕风衣 汽车自动起动器 麦片 氯气毒气 防毒面具 拉链 机械雨刮器 广义相对论 芥子气 量产拖拉机 电子钟 黄油枪 降落伞 广播电台播音 茶包 罗夏墨迹测验 机器人 胰岛素 实用邮戳机 滑水 百日咳疫苗 纸制鸡蛋托 面巾纸 商用飞机农药喷撒 液体燃料火箭 劳力士防水表 遥控电唱机 面包机 防水玻璃纸 电传打字机 盖革计数器 纯维生素C 彩色电影胶片 透明胶带 音乐汽车喇叭 闪光灯 速冻食品 球形潜水舱 回旋加速器 折叠式雨伞 电动剃须刀 车载收音机 玛氏巧克力棒 变焦镜头 大富翁桌游 商业洗衣店 畅销平装书 里氏震级 磁带录音机 大众汽车 超市推车 带温控器的电熨斗 速溶咖啡 尼龙 圆珠笔 黄热病疫苗 雷达 汽车自动变速箱 充气救生衣 人工授精 青霉素 军用吉普车 原子裂变 火箭筒 凝固汽油弹 水肺 麦角酸二乙酰胺 神经毒气 原子弹 特百惠 计算机 静电复印法 比基尼泳衣 浓缩咖啡机 宝丽来相机 拼字盘 实心电吉他 尼龙扣 晶体管 黑胶唱片 有线电视 电视显像管 汽车自动点火装置 信用卡 复印机 宽荧幕电影 动力转向器 三色停车灯 人行红绿灯 晶体管助听器 氢弹 录像带 DNA双螺旋结构 麻疹疫苗 按动圆珠笔 硅晶体管 核导弹 空对空导弹 迪士尼乐园 特氟龙 卡丁车 地对空核导弹 沙宾疫苗 通讯卫星 呼啦圈 安全带 人工肾脏 避孕药 气象卫星 便携晶体管收音机 安定 砷化镓半导体激光器 三维全息技术 合成器 香烟健康警示 凯夫拉纤维 子午胎 IBM文字处理机 杜比A型降噪器 滑雪板 喇叭裤 绕月载人火箭 人工心脏移植 波音747喷气式客机 互联网 条形码 软盘 帆板 热裤 液晶显示 便携电子计算器 电视游戏 DNA重组技术 电子游戏机 超级计算机 光纤 试管婴儿 魔方 索尼Walkman 杜比C型降噪器 艾滋病毒 强效可卡因 温室效应 CD 暗物质 暗能量 太阳能飞行器 甲型H1N1 流感 希格斯玻色子 引力波 | AR54: 电气地铁 圣代冰淇淋 实用水电站 手电 电影摄影机 收音机 霍乱疫苗 啤酒瓶盖 柴油发动机 双向电报 实用的胶卷 块麦片 电报 可口可乐 X射线 卷烟机发明 电影放映机 排球 印名片机 福特车 潜望镜 油印蜡纸发明 阴极射线管 商品阿司匹林 凯洛格牌玉米片 手电筒 钋 镭 摇控器 α粒子 β粒子 打字机 柯达布朗尼相机 齐柏林飞艇 人类血型 跨大西洋电报 汽轮机游船 现代柏油路 铝罐奶粉 爆米花 泰迪熊 卡鲁索电唱机 便宜的肥皂和烹饪用油 飞机 荧光灯 邮戳机 摩托车发动机 热水瓶 农业轨道机械 木棉安全带 电动汽车喇叭 化学泡沫灭火器 狭义相对论 自动点唱机 量产舰艇舷外发动机 动画 电动洗衣机 家用洗洁精 立式吸尘器 饮用纸杯 双层公交车 无线电测向仪 电煎锅 | AS54: 电煎锅 | AT54: 1911 | BH54: 阿曼 | BI54: 马斯喀特* | BJ54: 穆桑达姆省 | BK54: 佐法尔省 | BL54: 马赫拉省 | BM54: 达赫拉省 | BN54: 北巴提奈省 | BO54: 南巴提奈省 | BP54: 阿德拉省 | BQ54: 瓦哈巴省 | BR54: 穆桑达姆半岛
O55: 其他(下肢) | X55: 外语③ | AE55: 1912 | AF55: 日本改元大正 | AG55: 斯德哥尔摩奥运会 | AI55: 中华民国成立 | AJ55: 清帝退位 | AL55: 二十世纪 十年代 民国元年 | AM55: 壬子鼠年 | AN55: 民国元年 | AO55: 泰坦尼克号撞上冰山，1517 名船员和乘客死亡 由威尔逊云室发现质子和电子 赛璐玢（玻璃纸) 获得专利 伦敦裁缝街发明战壕风衣 凯迪拉克展示首个汽车自动起动器 加利福尼亚州两个自助杂货店开业 | AP55: 总统： 威廉·霍华德·塔夫脱（共和党） | AQ55: 麦片 氯气毒气 防毒面具 拉链 机械雨刮器 广义相对论 芥子气 量产拖拉机 电子钟 黄油枪 降落伞 广播电台播音 茶包 罗夏墨迹测验 机器人 胰岛素 实用邮戳机 滑水 百日咳疫苗 纸制鸡蛋托 面巾纸 商用飞机农药喷撒 液体燃料火箭 劳力士防水表 遥控电唱机 面包机 防水玻璃纸 电传打字机 盖革计数器 纯维生素C 彩色电影胶片 透明胶带 音乐汽车喇叭 闪光灯 速冻食品 球形潜水舱 回旋加速器 折叠式雨伞 电动剃须刀 车载收音机 玛氏巧克力棒 变焦镜头 大富翁桌游 商业洗衣店 畅销平装书 里氏震级 磁带录音机 大众汽车 超市推车 带温控器的电熨斗 速溶咖啡 尼龙 圆珠笔 黄热病疫苗 雷达 汽车自动变速箱 充气救生衣 人工授精 青霉素 军用吉普车 原子裂变 火箭筒 凝固汽油弹 水肺 麦角酸二乙酰胺 神经毒气 原子弹 特百惠 计算机 静电复印法 比基尼泳衣 浓缩咖啡机 宝丽来相机 拼字盘 实心电吉他 尼龙扣 晶体管 黑胶唱片 有线电视 电视显像管 汽车自动点火装置 信用卡 复印机 宽荧幕电影 动力转向器 三色停车灯 人行红绿灯 晶体管助听器 氢弹 录像带 DNA双螺旋结构 麻疹疫苗 按动圆珠笔 硅晶体管 核导弹 空对空导弹 迪士尼乐园 特氟龙 卡丁车 地对空核导弹 沙宾疫苗 通讯卫星 呼啦圈 安全带 人工肾脏 避孕药 气象卫星 便携晶体管收音机 安定 砷化镓半导体激光器 三维全息技术 合成器 香烟健康警示 凯夫拉纤维 子午胎 IBM文字处理机 杜比A型降噪器 滑雪板 喇叭裤 绕月载人火箭 人工心脏移植 波音747喷气式客机 互联网 条形码 软盘 帆板 热裤 液晶显示 便携电子计算器 电视游戏 DNA重组技术 电子游戏机 超级计算机 光纤 试管婴儿 魔方 索尼Walkman 杜比C型降噪器 艾滋病毒 强效可卡因 温室效应 CD 暗物质 暗能量 太阳能飞行器 甲型H1N1 流感 希格斯玻色子 引力波 | AR55: 电气地铁 圣代冰淇淋 实用水电站 手电 电影摄影机 收音机 霍乱疫苗 啤酒瓶盖 柴油发动机 双向电报 实用的胶卷 块麦片 电报 可口可乐 X射线 卷烟机发明 电影放映机 排球 印名片机 福特车 潜望镜 油印蜡纸发明 阴极射线管 商品阿司匹林 凯洛格牌玉米片 手电筒 钋 镭 摇控器 α粒子 β粒子 打字机 柯达布朗尼相机 齐柏林飞艇 人类血型 跨大西洋电报 汽轮机游船 现代柏油路 铝罐奶粉 爆米花 泰迪熊 卡鲁索电唱机 便宜的肥皂和烹饪用油 飞机 荧光灯 邮戳机 摩托车发动机 热水瓶 农业轨道机械 木棉安全带 电动汽车喇叭 化学泡沫灭火器 狭义相对论 自动点唱机 量产舰艇舷外发动机 动画 电动洗衣机 家用洗洁精 立式吸尘器 饮用纸杯 双层公交车 无线电测向仪 电煎锅 质子和电子 玻璃纸 战壕风衣 汽车自动起动器 | AS55: 质子和电子 玻璃纸 战壕风衣 汽车自动起动器 | AT55: 1912 | BH55: 也门 | BI55: 萨那* | BJ55: 阿比扬省 | BK55: 阿姆兰省 | BL55: 贝达省 | BM55: 达利耶省 | BN55: 荷台达省 | BO55: 伊卜省 | BP55: 贾夫省 | BQ55: 拉赫季省 | BR55: 马哈拉省 | BS55: 迈赫威特省 | BT55: 萨达省 | BU55: 萨那省 | BV55: 舍卜瓦省 | BW55: 塔伊兹省 | BX55: 哈德拉毛省 | BY55: 马里卜省
L56: 母 | M56: =IF(人物卡!BG52="",1,0) -> 1 | O56: 其他———— | X56: 外语④ | AA56: =".st"&"力量"&STR&"str"&STR&"敏捷"&DEX&"dex"&DEX&"意志"&POW&"pow"&POW&"体质"&CON&"con"&CON&"外貌"&APP&"app"&APP&"教育"&EDU&"edu"&EDU&"体型"&SIZ&"siz"&SIZ&"智力"&INT&"int"&INT&"灵感"&INT&"san"&SAN&"san值"&SAN&"理智"&SAN&"理智值"&SAN&"幸运"&IF(LuckA="未改运",0,LuckA)&"运气"&IF(LuckA="未改运",0,LuckA)&"mp"&MP&"魔法"&MP&"hp"&hp&"体力"&hp -> .st力量str敏捷dex意志pow体质con外貌app教育edu体型siz智力int灵感san0san值0理智0理智值0幸运0运气0mp0魔法0hp0体力0 | AE56: 1913 | AF56: 巴尔干战争 | AI56: —— | AL56: 二十世纪 十年代 | AM56: 癸丑牛年 | AN56: 民国2年 | AO56: 两次巴尔干战争 英国轮船卡尔瓦达斯号在马尔马拉海的暴风雨中失踪，200 人失踪 伍德罗·威尔逊就任美国总统 汽车自动起动器应用 美国宪法第十六号（所得税)、第十七号修正案（参议员直选) | AP56: 总统： 威廉·霍华德·塔夫脱（共和党） 伍德罗·威尔逊（民主党） | AQ56: 麦片 氯气毒气 防毒面具 拉链 机械雨刮器 广义相对论 芥子气 量产拖拉机 电子钟 黄油枪 降落伞 广播电台播音 茶包 罗夏墨迹测验 机器人 胰岛素 实用邮戳机 滑水 百日咳疫苗 纸制鸡蛋托 面巾纸 商用飞机农药喷撒 液体燃料火箭 劳力士防水表 遥控电唱机 面包机 防水玻璃纸 电传打字机 盖革计数器 纯维生素C 彩色电影胶片 透明胶带 音乐汽车喇叭 闪光灯 速冻食品 球形潜水舱 回旋加速器 折叠式雨伞 电动剃须刀 车载收音机 玛氏巧克力棒 变焦镜头 大富翁桌游 商业洗衣店 畅销平装书 里氏震级 磁带录音机 大众汽车 超市推车 带温控器的电熨斗 速溶咖啡 尼龙 圆珠笔 黄热病疫苗 雷达 汽车自动变速箱 充气救生衣 人工授精 青霉素 军用吉普车 原子裂变 火箭筒 凝固汽油弹 水肺 麦角酸二乙酰胺 神经毒气 原子弹 特百惠 计算机 静电复印法 比基尼泳衣 浓缩咖啡机 宝丽来相机 拼字盘 实心电吉他 尼龙扣 晶体管 黑胶唱片 有线电视 电视显像管 汽车自动点火装置 信用卡 复印机 宽荧幕电影 动力转向器 三色停车灯 人行红绿灯 晶体管助听器 氢弹 录像带 DNA双螺旋结构 麻疹疫苗 按动圆珠笔 硅晶体管 核导弹 空对空导弹 迪士尼乐园 特氟龙 卡丁车 地对空核导弹 沙宾疫苗 通讯卫星 呼啦圈 安全带 人工肾脏 避孕药 气象卫星 便携晶体管收音机 安定 砷化镓半导体激光器 三维全息技术 合成器 香烟健康警示 凯夫拉纤维 子午胎 IBM文字处理机 杜比A型降噪器 滑雪板 喇叭裤 绕月载人火箭 人工心脏移植 波音747喷气式客机 互联网 条形码 软盘 帆板 热裤 液晶显示 便携电子计算器 电视游戏 DNA重组技术 电子游戏机 超级计算机 光纤 试管婴儿 魔方 索尼Walkman 杜比C型降噪器 艾滋病毒 强效可卡因 温室效应 CD 暗物质 暗能量 太阳能飞行器 甲型H1N1 流感 希格斯玻色子 引力波 | AR56: 电气地铁 圣代冰淇淋 实用水电站 手电 电影摄影机 收音机 霍乱疫苗 啤酒瓶盖 柴油发动机 双向电报 实用的胶卷 块麦片 电报 可口可乐 X射线 卷烟机发明 电影放映机 排球 印名片机 福特车 潜望镜 油印蜡纸发明 阴极射线管 商品阿司匹林 凯洛格牌玉米片 手电筒 钋 镭 摇控器 α粒子 β粒子 打字机 柯达布朗尼相机 齐柏林飞艇 人类血型 跨大西洋电报 汽轮机游船 现代柏油路 铝罐奶粉 爆米花 泰迪熊 卡鲁索电唱机 便宜的肥皂和烹饪用油 飞机 荧光灯 邮戳机 摩托车发动机 热水瓶 农业轨道机械 木棉安全带 电动汽车喇叭 化学泡沫灭火器 狭义相对论 自动点唱机 量产舰艇舷外发动机 动画 电动洗衣机 家用洗洁精 立式吸尘器 饮用纸杯 双层公交车 无线电测向仪 电煎锅 质子和电子 玻璃纸 战壕风衣 汽车自动起动器 麦片 氯气毒气 防毒面具 拉链 | AT56: 1913 | BH56: 土耳其 | BI56: 安卡拉* | BJ56: 阿德里亚波利省 | BK56: 阿尔达汉省 | BL56: 阿尔特温省 | BM56: 比特利斯省 | BN56: 宾格尔省 | BO56: 布尔杜尔省 | BP56: 昌加尔省 | BQ56: 代尼兹利省 | BR56: 迪亚巴克尔省 | BS56: 埃尔津詹省 | BT56: 埃尔祖鲁姆省 | BU56: 埃斯基谢希尔省 | BV56: 加济安泰普省 | BW56: 吉雷松省 | BX56: 居米什哈内省 | BY56: 哈塔伊省 | BZ56: 伊斯帕尔塔省 | CA56: 伊切尔省 | CB56: 卡尔斯省 | CC56: 卡斯塔莫努省 | CD56: 开塞利省 | CE56: 科贾埃利省 | CF56: 克尔克拉雷利省 | CG56: 基利斯省 | CH56: 卡拉曼马拉什省 | CI56: 卡拉比克省 | CJ56: 卡尚省 | CK56: 马尔丁省 | CL56: 穆拉省 | CM56: 穆什省 | CN56: 内夫谢希尔省 | CO56: 尼代省 | CP56: 奥鲁姆省 | CQ56: 奥尔杜省 | CR56: 奥斯曼尼耶省 | CS56: 里泽省 | CT56: 萨卡里亚省 | CU56: 萨姆松省 | CV56: 尚勒乌尔法省 | CW56: 锡尔特省 | CX56: 特拉布宗省 | CY56: 图申省 | CZ56: 约兹加特省 | DA56: 宗古尔达克省 | DB56: 阿克萨赖省 | DC56: 巴特曼省 | DD56: 巴伊布尔特省 | DE56: 巴勒克埃西尔省 | DF56: 巴特省 | DG56: 比林奇省 | DH56: 布尔萨省 | DI56: 杜兹切省 | DJ56: 哈卡里省 | DK56: 伊吉尔省 | DL56: 梅尔辛省
O57: 其他 | X57: 外语⑤ | AE57: 1914 | AF57: 第一次世界大战 | AI57: —— | AL57: 二十世纪 十年代 | AM57: 甲寅虎年 | AN57: 民国3年 | AO57: 第一次世界大战爆发 首次空袭 巴拿马运河运行 加利福尼亚州太平洋轮船印度女皇号在圣劳伦斯河上与斯托斯塔德号[6]相撞，死亡1024 人 圣诞停火 | AP57: 总统： 伍德罗·威尔逊（民主党） | AQ57: 麦片 氯气毒气 防毒面具 拉链 机械雨刮器 广义相对论 芥子气 量产拖拉机 电子钟 黄油枪 降落伞 广播电台播音 茶包 罗夏墨迹测验 机器人 胰岛素 实用邮戳机 滑水 百日咳疫苗 纸制鸡蛋托 面巾纸 商用飞机农药喷撒 液体燃料火箭 劳力士防水表 遥控电唱机 面包机 防水玻璃纸 电传打字机 盖革计数器 纯维生素C 彩色电影胶片 透明胶带 音乐汽车喇叭 闪光灯 速冻食品 球形潜水舱 回旋加速器 折叠式雨伞 电动剃须刀 车载收音机 玛氏巧克力棒 变焦镜头 大富翁桌游 商业洗衣店 畅销平装书 里氏震级 磁带录音机 大众汽车 超市推车 带温控器的电熨斗 速溶咖啡 尼龙 圆珠笔 黄热病疫苗 雷达 汽车自动变速箱 充气救生衣 人工授精 青霉素 军用吉普车 原子裂变 火箭筒 凝固汽油弹 水肺 麦角酸二乙酰胺 神经毒气 原子弹 特百惠 计算机 静电复印法 比基尼泳衣 浓缩咖啡机 宝丽来相机 拼字盘 实心电吉他 尼龙扣 晶体管 黑胶唱片 有线电视 电视显像管 汽车自动点火装置 信用卡 复印机 宽荧幕电影 动力转向器 三色停车灯 人行红绿灯 晶体管助听器 氢弹 录像带 DNA双螺旋结构 麻疹疫苗 按动圆珠笔 硅晶体管 核导弹 空对空导弹 迪士尼乐园 特氟龙 卡丁车 地对空核导弹 沙宾疫苗 通讯卫星 呼啦圈 安全带 人工肾脏 避孕药 气象卫星 便携晶体管收音机 安定 砷化镓半导体激光器 三维全息技术 合成器 香烟健康警示 凯夫拉纤维 子午胎 IBM文字处理机 杜比A型降噪器 滑雪板 喇叭裤 绕月载人火箭 人工心脏移植 波音747喷气式客机 互联网 条形码 软盘 帆板 热裤 液晶显示 便携电子计算器 电视游戏 DNA重组技术 电子游戏机 超级计算机 光纤 试管婴儿 魔方 索尼Walkman 杜比C型降噪器 艾滋病毒 强效可卡因 温室效应 CD 暗物质 暗能量 太阳能飞行器 甲型H1N1 流感 希格斯玻色子 引力波 | AR57: 电气地铁 圣代冰淇淋 实用水电站 手电 电影摄影机 收音机 霍乱疫苗 啤酒瓶盖 柴油发动机 双向电报 实用的胶卷 块麦片 电报 可口可乐 X射线 卷烟机发明 电影放映机 排球 印名片机 福特车 潜望镜 油印蜡纸发明 阴极射线管 商品阿司匹林 凯洛格牌玉米片 手电筒 钋 镭 摇控器 α粒子 β粒子 打字机 柯达布朗尼相机 齐柏林飞艇 人类血型 跨大西洋电报 汽轮机游船 现代柏油路 铝罐奶粉 爆米花 泰迪熊 卡鲁索电唱机 便宜的肥皂和烹饪用油 飞机 荧光灯 邮戳机 摩托车发动机 热水瓶 农业轨道机械 木棉安全带 电动汽车喇叭 化学泡沫灭火器 狭义相对论 自动点唱机 量产舰艇舷外发动机 动画 电动洗衣机 家用洗洁精 立式吸尘器 饮用纸杯 双层公交车 无线电测向仪 电煎锅 质子和电子 玻璃纸 战壕风衣 汽车自动起动器 麦片 氯气毒气 防毒面具 拉链 | AT57: 1914 | BH57: 格鲁吉亚 | BI57: 第比利斯* | BJ57: 阿布哈兹 | BK57: 阿贾拉 | BL57: 萨姆茨赫-扎瓦赫季 | BM57: 古利亚 | BN57: 伊梅列季 | BO57: 卡赫季 | BP57: 克维莫-卡特利 | BQ57: 拉恰-列奇呼米和下斯瓦涅季 | BR57: 姆茨赫塔-姆季阿尼 | BS57: 什达-卡特利 | BT57: 茨欣瓦利
L58: 判 | M58: =IF(M56>0,"母语未填写！",IF(M52>0,"职业点未分配！",IF(M54>0,"兴趣点未分配！","技能表填写完毕"))) -> 母语未填写！ | X58: 闪避 | AE58: 1915 | AF58: 第一次世界大战 | AI58: 新文化运动 | AL58: 二十世纪 十年代 | AM58: 乙卯兔年 | AN58: 民国4年 | AO58: 卢西塔尼亚号被德国潜艇轰沉，死亡1199 人，美国表示惊愕与愤怒 第一次世界大战造成史无前例的重大伤亡 麦片上市 氯气用作毒气 防毒面具 拉链获得专利 | AP58: 总统： 伍德罗·威尔逊（民主党） | AQ58: 机械雨刮器 广义相对论 芥子气 量产拖拉机 电子钟 黄油枪 降落伞 广播电台播音 茶包 罗夏墨迹测验 机器人 胰岛素 实用邮戳机 滑水 百日咳疫苗 纸制鸡蛋托 面巾纸 商用飞机农药喷撒 液体燃料火箭 劳力士防水表 遥控电唱机 面包机 防水玻璃纸 电传打字机 盖革计数器 纯维生素C 彩色电影胶片 透明胶带 音乐汽车喇叭 闪光灯 速冻食品 球形潜水舱 回旋加速器 折叠式雨伞 电动剃须刀 车载收音机 玛氏巧克力棒 变焦镜头 大富翁桌游 商业洗衣店 畅销平装书 里氏震级 磁带录音机 大众汽车 超市推车 带温控器的电熨斗 速溶咖啡 尼龙 圆珠笔 黄热病疫苗 雷达 汽车自动变速箱 充气救生衣 人工授精 青霉素 军用吉普车 原子裂变 火箭筒 凝固汽油弹 水肺 麦角酸二乙酰胺 神经毒气 原子弹 特百惠 计算机 静电复印法 比基尼泳衣 浓缩咖啡机 宝丽来相机 拼字盘 实心电吉他 尼龙扣 晶体管 黑胶唱片 有线电视 电视显像管 汽车自动点火装置 信用卡 复印机 宽荧幕电影 动力转向器 三色停车灯 人行红绿灯 晶体管助听器 氢弹 录像带 DNA双螺旋结构 麻疹疫苗 按动圆珠笔 硅晶体管 核导弹 空对空导弹 迪士尼乐园 特氟龙 卡丁车 地对空核导弹 沙宾疫苗 通讯卫星 呼啦圈 安全带 人工肾脏 避孕药 气象卫星 便携晶体管收音机 安定 砷化镓半导体激光器 三维全息技术 合成器 香烟健康警示 凯夫拉纤维 子午胎 IBM文字处理机 杜比A型降噪器 滑雪板 喇叭裤 绕月载人火箭 人工心脏移植 波音747喷气式客机 互联网 条形码 软盘 帆板 热裤 液晶显示 便携电子计算器 电视游戏 DNA重组技术 电子游戏机 超级计算机 光纤 试管婴儿 魔方 索尼Walkman 杜比C型降噪器 艾滋病毒 强效可卡因 温室效应 CD 暗物质 暗能量 太阳能飞行器 甲型H1N1 流感 希格斯玻色子 引力波 | AR58: 电气地铁 圣代冰淇淋 实用水电站 手电 电影摄影机 收音机 霍乱疫苗 啤酒瓶盖 柴油发动机 双向电报 实用的胶卷 块麦片 电报 可口可乐 X射线 卷烟机发明 电影放映机 排球 印名片机 福特车 潜望镜 油印蜡纸发明 阴极射线管 商品阿司匹林 凯洛格牌玉米片 手电筒 钋 镭 摇控器 α粒子 β粒子 打字机 柯达布朗尼相机 齐柏林飞艇 人类血型 跨大西洋电报 汽轮机游船 现代柏油路 铝罐奶粉 爆米花 泰迪熊 卡鲁索电唱机 便宜的肥皂和烹饪用油 飞机 荧光灯 邮戳机 摩托车发动机 热水瓶 农业轨道机械 木棉安全带 电动汽车喇叭 化学泡沫灭火器 狭义相对论 自动点唱机 量产舰艇舷外发动机 动画 电动洗衣机 家用洗洁精 立式吸尘器 饮用纸杯 双层公交车 无线电测向仪 电煎锅 质子和电子 玻璃纸 战壕风衣 汽车自动起动器 麦片 氯气毒气 防毒面具 拉链 | AS58: 麦片 氯气毒气 防毒面具 拉链 | AT58: 1915 | BH58: 亚美尼亚 | BI58: 埃里温* | BJ58: 阿拉加茨省 | BK58: 阿尔马维尔省 | BL58: 阿拉拉特省 | BM58: 格加尔库尼克省 | BN58: 科泰克省 | BO58: 洛里省 | BP58: 什拉基省 | BQ58: 苏姆加伊特省 | BR58: 塔武什省 | BS58: 瓦约茨佐尔省 | BT58: 耶列万省
E59: =IF(人物卡!BL11=0," ",LOOKUP(人物卡!BL11,职业列表!A2:C237,职业列表!E2:E237)) | X59: 格斗： | AE59: 1916 | AF59: 第一次世界大战 | AG59: 奥运停办 | AI59: 袁世凯恢复帝制失败 | AL59: 二十世纪 十年代 | AM59: 丙辰龙年 | AN59: 民国5年 | AO59: 凡尔登战役，死亡70 万人 索姆河战役，死亡100 万人 美国脊髓灰质炎流行，死亡7000 人并致2.7 万青少年残疾 加利波利战役 爱尔兰复活节起义 日德兰海战 机械雨刮器 广义相对论 潘兴入侵墨西哥镇压起义军 | AP59: 总统： 伍德罗·威尔逊（民主党） | AQ59: 芥子气 量产拖拉机 电子钟 黄油枪 降落伞 广播电台播音 茶包 罗夏墨迹测验 机器人 胰岛素 实用邮戳机 滑水 百日咳疫苗 纸制鸡蛋托 面巾纸 商用飞机农药喷撒 液体燃料火箭 劳力士防水表 遥控电唱机 面包机 防水玻璃纸 电传打字机 盖革计数器 纯维生素C 彩色电影胶片 透明胶带 音乐汽车喇叭 闪光灯 速冻食品 球形潜水舱 回旋加速器 折叠式雨伞 电动剃须刀 车载收音机 玛氏巧克力棒 变焦镜头 大富翁桌游 商业洗衣店 畅销平装书 里氏震级 磁带录音机 大众汽车 超市推车 带温控器的电熨斗 速溶咖啡 尼龙 圆珠笔 黄热病疫苗 雷达 汽车自动变速箱 充气救生衣 人工授精 青霉素 军用吉普车 原子裂变 火箭筒 凝固汽油弹 水肺 麦角酸二乙酰胺 神经毒气 原子弹 特百惠 计算机 静电复印法 比基尼泳衣 浓缩咖啡机 宝丽来相机 拼字盘 实心电吉他 尼龙扣 晶体管 黑胶唱片 有线电视 电视显像管 汽车自动点火装置 信用卡 复印机 宽荧幕电影 动力转向器 三色停车灯 人行红绿灯 晶体管助听器 氢弹 录像带 DNA双螺旋结构 麻疹疫苗 按动圆珠笔 硅晶体管 核导弹 空对空导弹 迪士尼乐园 特氟龙 卡丁车 地对空核导弹 沙宾疫苗 通讯卫星 呼啦圈 安全带 人工肾脏 避孕药 气象卫星 便携晶体管收音机 安定 砷化镓半导体激光器 三维全息技术 合成器 香烟健康警示 凯夫拉纤维 子午胎 IBM文字处理机 杜比A型降噪器 滑雪板 喇叭裤 绕月载人火箭 人工心脏移植 波音747喷气式客机 互联网 条形码 软盘 帆板 热裤 液晶显示 便携电子计算器 电视游戏 DNA重组技术 电子游戏机 超级计算机 光纤 试管婴儿 魔方 索尼Walkman 杜比C型降噪器 艾滋病毒 强效可卡因 温室效应 CD 暗物质 暗能量 太阳能飞行器 甲型H1N1 流感 希格斯玻色子 引力波 | AR59: 电气地铁 圣代冰淇淋 实用水电站 手电 电影摄影机 收音机 霍乱疫苗 啤酒瓶盖 柴油发动机 双向电报 实用的胶卷 块麦片 电报 可口可乐 X射线 卷烟机发明 电影放映机 排球 印名片机 福特车 潜望镜 油印蜡纸发明 阴极射线管 商品阿司匹林 凯洛格牌玉米片 手电筒 钋 镭 摇控器 α粒子 β粒子 打字机 柯达布朗尼相机 齐柏林飞艇 人类血型 跨大西洋电报 汽轮机游船 现代柏油路 铝罐奶粉 爆米花 泰迪熊 卡鲁索电唱机 便宜的肥皂和烹饪用油 飞机 荧光灯 邮戳机 摩托车发动机 热水瓶 农业轨道机械 木棉安全带 电动汽车喇叭 化学泡沫灭火器 狭义相对论 自动点唱机 量产舰艇舷外发动机 动画 电动洗衣机 家用洗洁精 立式吸尘器 饮用纸杯 双层公交车 无线电测向仪 电煎锅 质子和电子 玻璃纸 战壕风衣 汽车自动起动器 麦片 氯气毒气 防毒面具 拉链 机械雨刮器 广义相对论 | AS59: 机械雨刮器 广义相对论 | AT59: 1916 | BH59: 阿塞拜疆 | BI59: 巴库* | BJ59: 阿巴斯特尔拉省 | BK59: 阿格达姆区 | BL59: 阿格达什区 | BM59: 阿格苏区 | BN59: 阿格达姆雷区 | BO59: 阿塞拜疆纳希切万自治共和国 | BP59: 巴库市 | BQ59: 巴尔达区 | BR59: 别尔德区 | BS59: 比尔苏区 | BT59: 达什凯桑区 | BU59: 菲祖利区 | BV59: 加布拉区 | BW59: 戈兰博伊区 | BX59: 戈兰博伊市 | BY59: 戈拉德日区 | BZ59: 哈奇马斯区 | CA59: 伊米什利区 | CB59: 伊斯梅尔雷区 | CC59: 贾利拉巴德区 | CD59: 卡巴拉区 | CE59: 卡尔巴卡尔区 | CF59: 库巴区 | CG59: 库达雷克区 | CH59: 拉钦区 | CI59: 兰卡拉区 | CJ59: 列扎克区 | CK59: 马西利区 | CL59: 纳夫塔兰区 | CM59: 纳希切万区 | CN59: 涅夫特卡拉区 | CO59: 奥古兹区 | CP59: 萨阿特利区 | CQ59: 萨比拉巴德区 | CR59: 萨利扬区 | CS59: 萨马希区 | CT59: 舍基区 | CU59: 舍马哈区 | CV59: 西阿扎尔区 | CW59: 苏姆盖特市 | CX59: 塔特区 | CY59: 托武兹区 | CZ59: 乌贾尔区 | DA59: 扎卡塔雷区 | DB59: 扎尔达布区 | DC59: 赞格兰区
J60: IF(14<SIZA<36,1,IF(35<SIZA<66,1.15,IF(65<SIZA≤86,1.375,IF(85<SIZA<100,1.5,0)))) | X60: 格斗① | AE60: 1917 | AF60: 第一次世界大战 | AG60: 十月革命 | AI60: 张勋复辟失败 | AJ60: 护法运动 | AL60: 二十世纪 十年代 | AM60: 丁巳蛇年 | AN60: 民国6年 | AO60: 美国参加协约国 二月革命和十月革命 芥子气 福特量产拖拉机 轮船卡斯塔利亚号在苏必利尔湖沉没，死亡22 人 宾夕法尼亚州军火库爆炸，死亡133 人 新斯科舍省哈利法克斯船舶爆炸沉没，1600 人死亡 | AP60: 总统： 伍德罗·威尔逊（民主党） | AQ60: 电子钟 黄油枪 降落伞 广播电台播音 茶包 罗夏墨迹测验 机器人 胰岛素 实用邮戳机 滑水 百日咳疫苗 纸制鸡蛋托 面巾纸 商用飞机农药喷撒 液体燃料火箭 劳力士防水表 遥控电唱机 面包机 防水玻璃纸 电传打字机 盖革计数器 纯维生素C 彩色电影胶片 透明胶带 音乐汽车喇叭 闪光灯 速冻食品 球形潜水舱 回旋加速器 折叠式雨伞 电动剃须刀 车载收音机 玛氏巧克力棒 变焦镜头 大富翁桌游 商业洗衣店 畅销平装书 里氏震级 磁带录音机 大众汽车 超市推车 带温控器的电熨斗 速溶咖啡 尼龙 圆珠笔 黄热病疫苗 雷达 汽车自动变速箱 充气救生衣 人工授精 青霉素 军用吉普车 原子裂变 火箭筒 凝固汽油弹 水肺 麦角酸二乙酰胺 神经毒气 原子弹 特百惠 计算机 静电复印法 比基尼泳衣 浓缩咖啡机 宝丽来相机 拼字盘 实心电吉他 尼龙扣 晶体管 黑胶唱片 有线电视 电视显像管 汽车自动点火装置 信用卡 复印机 宽荧幕电影 动力转向器 三色停车灯 人行红绿灯 晶体管助听器 氢弹 录像带 DNA双螺旋结构 麻疹疫苗 按动圆珠笔 硅晶体管 核导弹 空对空导弹 迪士尼乐园 特氟龙 卡丁车 地对空核导弹 沙宾疫苗 通讯卫星 呼啦圈 安全带 人工肾脏 避孕药 气象卫星 便携晶体管收音机 安定 砷化镓半导体激光器 三维全息技术 合成器 香烟健康警示 凯夫拉纤维 子午胎 IBM文字处理机 杜比A型降噪器 滑雪板 喇叭裤 绕月载人火箭 人工心脏移植 波音747喷气式客机 互联网 条形码 软盘 帆板 热裤 液晶显示 便携电子计算器 电视游戏 DNA重组技术 电子游戏机 超级计算机 光纤 试管婴儿 魔方 索尼Walkman 杜比C型降噪器 艾滋病毒 强效可卡因 温室效应 CD 暗物质 暗能量 太阳能飞行器 甲型H1N1 流感 希格斯玻色子 引力波 | AR60: 电气地铁 圣代冰淇淋 实用水电站 手电 电影摄影机 收音机 霍乱疫苗 啤酒瓶盖 柴油发动机 双向电报 实用的胶卷 块麦片 电报 可口可乐 X射线 卷烟机发明 电影放映机 排球 印名片机 福特车 潜望镜 油印蜡纸发明 阴极射线管 商品阿司匹林 凯洛格牌玉米片 手电筒 钋 镭 摇控器 α粒子 β粒子 打字机 柯达布朗尼相机 齐柏林飞艇 人类血型 跨大西洋电报 汽轮机游船 现代柏油路 铝罐奶粉 爆米花 泰迪熊 卡鲁索电唱机 便宜的肥皂和烹饪用油 飞机 荧光灯 邮戳机 摩托车发动机 热水瓶 农业轨道机械 木棉安全带 电动汽车喇叭 化学泡沫灭火器 狭义相对论 自动点唱机 量产舰艇舷外发动机 动画 电动洗衣机 家用洗洁精 立式吸尘器 饮用纸杯 双层公交车 无线电测向仪 电煎锅 质子和电子 玻璃纸 战壕风衣 汽车自动起动器 麦片 氯气毒气 防毒面具 拉链 机械雨刮器 广义相对论 芥子气 量产拖拉机 | AS60: 芥子气 量产拖拉机 | AT60: 1917 | BH60: 以色列 | BI60: 耶路撒冷* | BJ60: 特拉维夫-雅法 | BK60: 海法 | BL60: 阿卡 | BM60: 贝尔谢巴 | BN60: 阿什杜德 | BO60: 阿什凯隆 | BP60: 贝特谢安 | BQ60: 贝特谢梅什 | BR60: 贝尔谢巴区 | BS60: 贝特霍尔 | BT60: 埃拉特 | BU60: 耶胡达 | BV60: 霍隆 | BW60: 霍代什 | BX60: 卡梅尔 | BY60: 卡塔蒙 | BZ60: 卡法萨巴 | CA60: 内坦亚 | CB60: 内坦亚区 | CC60: 拿撒勒 | CD60: 拉姆拉 | CE60: 拉马特甘 | CF60: 拉安纳 | CG60: 雷霍沃特 | CH60: 里雄莱锡安 | CI60: 萨法德 | CJ60: 太巴列 | CK60: 蒂拉特卡尔梅尔 | CL60: 约旦河谷和耶路撒冷地区 | CM60: 中央区
E61: 13-15.75 | X61: 格斗② | AE61: 1918 | AF61: 第一次世界大战 | AI61: —— | AL61: 二十世纪 十年代 | AM61: 戊午马年 | AN61: 民国7年 | AO61: 第一次世界大战结束 苏俄内战 固定美国航空邮件服务 西班牙大流感，死亡2160 万人 美国独眼巨人号离开巴巴多斯后失踪 飞机时速达到150 迈，飞行高度达3万英尺 电子钟 | AP61: 总统： 伍德罗·威尔逊（民主党） | AQ61: 黄油枪 降落伞 广播电台播音 茶包 罗夏墨迹测验 机器人 胰岛素 实用邮戳机 滑水 百日咳疫苗 纸制鸡蛋托 面巾纸 商用飞机农药喷撒 液体燃料火箭 劳力士防水表 遥控电唱机 面包机 防水玻璃纸 电传打字机 盖革计数器 纯维生素C 彩色电影胶片 透明胶带 音乐汽车喇叭 闪光灯 速冻食品 球形潜水舱 回旋加速器 折叠式雨伞 电动剃须刀 车载收音机 玛氏巧克力棒 变焦镜头 大富翁桌游 商业洗衣店 畅销平装书 里氏震级 磁带录音机 大众汽车 超市推车 带温控器的电熨斗 速溶咖啡 尼龙 圆珠笔 黄热病疫苗 雷达 汽车自动变速箱 充气救生衣 人工授精 青霉素 军用吉普车 原子裂变 火箭筒 凝固汽油弹 水肺 麦角酸二乙酰胺 神经毒气 原子弹 特百惠 计算机 静电复印法 比基尼泳衣 浓缩咖啡机 宝丽来相机 拼字盘 实心电吉他 尼龙扣 晶体管 黑胶唱片 有线电视 电视显像管 汽车自动点火装置 信用卡 复印机 宽荧幕电影 动力转向器 三色停车灯 人行红绿灯 晶体管助听器 氢弹 录像带 DNA双螺旋结构 麻疹疫苗 按动圆珠笔 硅晶体管 核导弹 空对空导弹 迪士尼乐园 特氟龙 卡丁车 地对空核导弹 沙宾疫苗 通讯卫星 呼啦圈 安全带 人工肾脏 避孕药 气象卫星 便携晶体管收音机 安定 砷化镓半导体激光器 三维全息技术 合成器 香烟健康警示 凯夫拉纤维 子午胎 IBM文字处理机 杜比A型降噪器 滑雪板 喇叭裤 绕月载人火箭 人工心脏移植 波音747喷气式客机 互联网 条形码 软盘 帆板 热裤 液晶显示 便携电子计算器 电视游戏 DNA重组技术 电子游戏机 超级计算机 光纤 试管婴儿 魔方 索尼Walkman 杜比C型降噪器 艾滋病毒 强效可卡因 温室效应 CD 暗物质 暗能量 太阳能飞行器 甲型H1N1 流感 希格斯玻色子 引力波 | AR61: 电气地铁 圣代冰淇淋 实用水电站 手电 电影摄影机 收音机 霍乱疫苗 啤酒瓶盖 柴油发动机 双向电报 实用的胶卷 块麦片 电报 可口可乐 X射线 卷烟机发明 电影放映机 排球 印名片机 福特车 潜望镜 油印蜡纸发明 阴极射线管 商品阿司匹林 凯洛格牌玉米片 手电筒 钋 镭 摇控器 α粒子 β粒子 打字机 柯达布朗尼相机 齐柏林飞艇 人类血型 跨大西洋电报 汽轮机游船 现代柏油路 铝罐奶粉 爆米花 泰迪熊 卡鲁索电唱机 便宜的肥皂和烹饪用油 飞机 荧光灯 邮戳机 摩托车发动机 热水瓶 农业轨道机械 木棉安全带 电动汽车喇叭 化学泡沫灭火器 狭义相对论 自动点唱机 量产舰艇舷外发动机 动画 电动洗衣机 家用洗洁精 立式吸尘器 饮用纸杯 双层公交车 无线电测向仪 电煎锅 质子和电子 玻璃纸 战壕风衣 汽车自动起动器 麦片 氯气毒气 防毒面具 拉链 机械雨刮器 广义相对论 芥子气 量产拖拉机 电子钟 | AS61: 电子钟 | AT61: 1918 | BH61: 巴勒斯坦 | BI61: 拉姆安拉* | BJ61: 加沙地带 | BK61: 耶路撒冷 | BL61: 北部区 | BM61: 杰宁区 | BN61: 图勒凯尔姆区 | BO61: 纳布卢斯区 | BP61: 杰里科区 | BQ61: 伯利恒区 | BR61: 希伯伦区 | BS61: 南部区 | BT61: 拉法赫区 | BU61: 汗尤尼斯区 | BV61: 加沙区 | BW61: 代尔巴拉赫区 | BX61: 汉尤尼斯
D62: BMI | E62: 15.75-18.5 | F62: 瘦 | G62: ±2.75 | I62: BMI | J62: 力量修正 | K62: 体重 | L62: 身高 | M62: SIZA | X62: 格斗③ | AA62: =AA72&AA73&AA74&AA75&AA76&AA77&AA78&AA79&AA80&AA81&AA82&AA83&AA84&AA85&AA86&AA87&AA88&AA89&AA90&AA91&AA92&AA93&AA94&AA95&AA96&AA97&AA98&AA99&AA100&AA101&AA102&AA103&AA104&AA105&AA106&AA107&AA108&AA109&AA110&AA111&AC72&AC73&AC74&AC75&AC76&AC77&AC78&AC79&AC80&AC81&AC82&AC83&AC84&AC85&AC86&AC87&AC88&AC89&AC90&AC91&AC92&AC93&AC94&AC95&AC96&AC97&AC98&AC99&AC100&AC101&AC102&AC103&AC104&AC105&AC106&AC107&AC108&AC109&AC110&AC111 -> 会计5法律5历史5人类学1估价5考古学1博物学10神秘学5信用评级0克苏鲁神话0机械维修10电气维修10电子学1操作重型机械1爆破1计算机使用0母语0闪避0斗殴25锁匠1乔装5妙手10潜行20图书馆使用20聆听20侦查25追踪10导航10心理学10取悦15话术5恐吓15说服10跳跃20攀爬20游泳20精神分析1医学1急救30汽车驾驶20骑术5动物驯养5潜水1读唇1催眠1炮术1投掷20手枪20 | AE62: 1919 | AF62: 巴黎和会 | AI62: 五四爱国运动 | AL62: 二十世纪 十年代 | AM62: 己未羊年 | AN62: 民国8年 | AO62: 美国宪法第十八号修正案（禁酒令) 首次跨大西洋飞行（1880 英里，16 小时12 分钟) 黄油枪 降落伞 | AP62: 书籍： 威尔 · 罗杰斯《禁酒时代的牛仔哲学家》 影视： “妖妇”蒂达·巴拉主演《莎乐美》 D·W·格里菲斯导演《残花泪》 朗 · 钱尼《奇人》 总统： 伍德罗·威尔逊（民主党） | AQ62: 广播电台播音 茶包 罗夏墨迹测验 机器人 胰岛素 实用邮戳机 滑水 百日咳疫苗 纸制鸡蛋托 面巾纸 商用飞机农药喷撒 液体燃料火箭 劳力士防水表 遥控电唱机 面包机 防水玻璃纸 电传打字机 盖革计数器 纯维生素C 彩色电影胶片 透明胶带 音乐汽车喇叭 闪光灯 速冻食品 球形潜水舱 回旋加速器 折叠式雨伞 电动剃须刀 车载收音机 玛氏巧克力棒 变焦镜头 大富翁桌游 商业洗衣店 畅销平装书 里氏震级 磁带录音机 大众汽车 超市推车 带温控器的电熨斗 速溶咖啡 尼龙 圆珠笔 黄热病疫苗 雷达 汽车自动变速箱 充气救生衣 人工授精 青霉素 军用吉普车 原子裂变 火箭筒 凝固汽油弹 水肺 麦角酸二乙酰胺 神经毒气 原子弹 特百惠 计算机 静电复印法 比基尼泳衣 浓缩咖啡机 宝丽来相机 拼字盘 实心电吉他 尼龙扣 晶体管 黑胶唱片 有线电视 电视显像管 汽车自动点火装置 信用卡 复印机 宽荧幕电影 动力转向器 三色停车灯 人行红绿灯 晶体管助听器 氢弹 录像带 DNA双螺旋结构 麻疹疫苗 按动圆珠笔 硅晶体管 核导弹 空对空导弹 迪士尼乐园 特氟龙 卡丁车 地对空核导弹 沙宾疫苗 通讯卫星 呼啦圈 安全带 人工肾脏 避孕药 气象卫星 便携晶体管收音机 安定 砷化镓半导体激光器 三维全息技术 合成器 香烟健康警示 凯夫拉纤维 子午胎 IBM文字处理机 杜比A型降噪器 滑雪板 喇叭裤 绕月载人火箭 人工心脏移植 波音747喷气式客机 互联网 条形码 软盘 帆板 热裤 液晶显示 便携电子计算器 电视游戏 DNA重组技术 电子游戏机 超级计算机 光纤 试管婴儿 魔方 索尼Walkman 杜比C型降噪器 艾滋病毒 强效可卡因 温室效应 CD 暗物质 暗能量 太阳能飞行器 甲型H1N1 流感 希格斯玻色子 引力波 | AR62: 电气地铁 圣代冰淇淋 实用水电站 手电 电影摄影机 收音机 霍乱疫苗 啤酒瓶盖 柴油发动机 双向电报 实用的胶卷 块麦片 电报 可口可乐 X射线 卷烟机发明 电影放映机 排球 印名片机 福特车 潜望镜 油印蜡纸发明 阴极射线管 商品阿司匹林 凯洛格牌玉米片 手电筒 钋 镭 摇控器 α粒子 β粒子 打字机 柯达布朗尼相机 齐柏林飞艇 人类血型 跨大西洋电报 汽轮机游船 现代柏油路 铝罐奶粉 爆米花 泰迪熊 卡鲁索电唱机 便宜的肥皂和烹饪用油 飞机 荧光灯 邮戳机 摩托车发动机 热水瓶 农业轨道机械 木棉安全带 电动汽车喇叭 化学泡沫灭火器 狭义相对论 自动点唱机 量产舰艇舷外发动机 动画 电动洗衣机 家用洗洁精 立式吸尘器 饮用纸杯 双层公交车 无线电测向仪 电煎锅 质子和电子 玻璃纸 战壕风衣 汽车自动起动器 麦片 氯气毒气 防毒面具 拉链 机械雨刮器 广义相对论 芥子气 量产拖拉机 电子钟 黄油枪 降落伞 | AS62: 黄油枪 降落伞 | AT62: 1919 | BH62: 叙利亚 | BI62: 大马士革* | BJ62: 阿勒颇省 | BK62: 阿拉腊省 | BL62: 代尔祖尔省 | BM62: 德拉省 | BN62: 哈马省 | BO62: 哈塞克省 | BP62: 霍姆斯省 | BQ62: 伊德利卜省 | BR62: 拉塔基亚省 | BS62: 库奈特拉省 | BT62: 拉卡省 | BU62: 大马士革农村省 | BV62: 塔尔图斯省 | BW62: 苏韦达省
D63: 体重/身高² | E63: 18.5-24 | F63: 正常 | G63: 21.25 | I63: =FIXED(K63/(POWER(L63,2)),2)-4.79 -> #VALUE! | J63: =ABS(STRA/2-25) -> #VALUE! | K63: =MAX(K64:K66)+J63 -> #VALUE! | L63: =IF(人物卡!BL10="现代",FIXED(L64/100,2)+0.05,FIXED(L64/100,2)) -> 1.90 | S63: =".st "&人物卡!BD9&"-"&"力量"&G14&"str"&G14&"敏捷"&J14&"dex"&J14&"意志"&M14&"pow"&M14&"体质"&H14&"con"&H14&"外貌"&K14&"app"&K14&"教育"&N14&"edu"&N14&"体型"&I14&"siz"&I14&"智力"&L14&"灵感"&L14&"int"&L14&"san"&人物卡!BM19&"san值"&人物卡!BM19&"理智"&人物卡!BM19&"理智值"&人物卡!BM19&"幸运"&O14&"运气"&O14&"mp"&人物卡!BV19&"魔法"&人物卡!BV19&"hp"&人物卡!BD19&"体力"&人物卡!BD19&人物卡!BE25&人物卡!BQ25&人物卡!BE26&人物卡!BQ26&人物卡!BE27&人物卡!BQ27&人物卡!BE28&人物卡!BQ28&IF(人物卡!BG29="","",人物卡!BG29&人物卡!BQ29)&IF(人物卡!BG30="","",人物卡!BG30&人物卡!BQ30)&IF(人物卡!BG31="","",人物卡!BG31&人物卡!BQ31)&人物卡!BE32&人物卡!BQ32&"魅惑"&人物卡!BQ32&人物卡!BE33&人物卡!BQ33&"计算机"&人物卡!BQ34&"计算机使用"&人物卡!BQ34&"电脑"&人物卡!BQ34&"信用"&人物卡!BQ35&"信誉"&人物卡!BQ35&"信用评级"&人物卡!BQ35&"克苏鲁"&人物卡!BQ36&"克苏鲁神话"&人物卡!BQ36&"cm"&人物卡!BQ36&人物卡!BE37&人物卡!BQ37&人物卡!BE38&人物卡!BQ38&"汽车"&人物卡!BQ39&"驾驶"&人物卡!BQ39&"汽车驾驶"&人物卡!BQ39&人物卡!BE40&人物卡!BQ40&"电子学"&人物卡!BQ41&人物卡!BE42&人物卡!BQ42&人物卡!BG43&人物卡!BQ43&IF(人物卡!BG44="","",人物卡!BG44&人物卡!BQ44)&IF(人物卡!BG45="","",人物卡!BG45&人物卡!BQ45)&IF(人物卡!BG46="","",人物卡!BG46&人物卡!BQ46)&人物卡!BG47&人物卡!BQ47&IF(W15=1,人物卡!CA48&人物卡!BQ48&"步枪"&人物卡!BQ48&"霰弹枪"&人物卡!BQ48&"步霰"&人物卡!BQ48,IF(人物卡!BG48="","",人物卡!BG48&人物卡!BQ48))&IF(W16=1,人物卡!CA49&人物卡!BQ49&"步枪"&人物卡!BQ49&"霰弹枪"&人物卡!BQ49&"步霰"&人物卡!BQ49,IF(人物卡!BG49="","",人物卡!BG49&人物卡!BQ49))&IF(W17=1,人物卡!CA50&人物卡!BQ50&"步枪"&人物卡!BQ50&"霰弹枪"&人物卡!BQ50&"步霰"&人物卡!BQ50,IF(人物卡!BG50="","",人物卡!BG50&人物卡!BQ50))&人物卡!BE51&人物卡!BQ51&人物卡!BE52&人物卡!BQ52&人物卡!BE53&人物卡!BQ53&人物卡!BE54&人物卡!BQ54&IF(人物卡!BG55="","",人物卡!BG55&人物卡!BQ55)&IF(人物卡!BG56="","",人物卡!BG56&人物卡!BQ56)&IF(人物卡!BG57="","",人物卡!BG57&人物卡!BQ57)&人物卡!BE58&人物卡!BQ58&人物卡!CA25&人物卡!CM25&"图书馆"&人物卡!CM26&"图书馆使用"&人物卡!CM26&人物卡!CA27&人物卡!CM27&"开锁"&人物卡!CM28&"撬锁"&人物卡!CM28&"锁匠"&人物卡!CM28&人物卡!CA29&人物卡!CM29&人物卡!CA30&人物卡!CM30&"博物学"&人物卡!CM31&"自然学"&人物卡!CM31&"领航"&人物卡!CM32&"导航"&人物卡!CM32&人物卡!CA33&人物卡!CM33&"重型操作"&人物卡!CM34&"重型机械"&人物卡!CM34&"操作重型机械"&人物卡!CM34&"重型"&人物卡!CM34&人物卡!CA35&人物卡!CM35&IF(人物卡!CC36="","",人物卡!CC36&人物卡!CM36)&人物卡!CA37&人物卡!CM37&人物卡!CA38&人物卡!CM38&人物卡!CA39&人物卡!CM39&IF(人物卡!CC40="","",人物卡!CC40&人物卡!CM40)&IF(人物卡!CC41="","",人物卡!CC41&人物卡!CM41)&IF(人物卡!CC42="","",人物卡!CC42&人物卡!CM42)&人物卡!CA43&人物卡!CM43&人物卡!CA44&人物卡!CM44&人物卡!CA45&人物卡!CM45&"生存"&人物卡!CM46&人物卡!CA47&人物卡!CM47&人物卡!CA48&人物卡!CM48&人物卡!CA49&人物卡!CM49&人物卡!CA50&人物卡!CM50&人物卡!CA51&人物卡!CM51&人物卡!CA52&人物卡!CM52&人物卡!CA53&人物卡!CM53&人物卡!CA54&人物卡!CM54&人物卡!CA55&人物卡!CM55&IF(人物卡!CC56="","",人物卡!CC56&人物卡!CM56)&IF(W18=1,"",人物卡!CA57&人物卡!CM57)&IF(人物卡!CA58="","",人物卡!CA58&人物卡!CM58) -> .st -力量0str0敏捷0dex0意志0pow0体质0con0外貌0app0教育0edu0体型0siz0智力0灵感0int0san0san值0理智0理智值0幸运0运气0mp0魔法0hp0体力0会计5法律5历史5人类学1神秘学5魅惑5信用评级0计算机0计算机使用0电脑0信用10信誉10信用评级10克苏鲁10克苏鲁神话10cm10电子学 Ω1操作重型机械1汽车1驾驶1汽车驾驶1计算机使用 Ω0电子学1科学②115技艺⑤5母语0外语①1外语②1闪避0锁匠1图书馆5图书馆使用5妙手10开锁20撬锁20锁匠20图书馆使用20聆听20博物学25自然学25领航10导航10导航10重型操作10重型机械10操作重型机械10重型10取悦15恐吓15说服10跳跃20游泳20精神分析1医学1生存30驾驶①1驾驶②1汽车驾驶20骑术5动物驯养5潜水1读唇1催眠1自定义①1炮术1投掷20 | X63: 格斗② | AE63: 1920 | AF63: 咆哮的二十年代（美国） | AG63: 安特卫普奥运会 | AI63: 海原大地震 | AL63: 二十世纪 二十年代 | AM63: 庚申猴年 | AN63: 民国9年 | AO63: 禁酒令生效 布尔什维克赢得苏俄内战 中国海原大地震，死亡 20 万人 首次广播电台播音 茶包 美国公债 243 亿美元 美国人口 1.057 亿 | AP63: 书籍： 赞恩·格雷：《林中人》 弗·斯科特·菲茨杰拉德：《人间天堂》 影视： 朗·钱尼：主演《惩罚》 丽莲·吉许：主演《暴风雨中的孤儿》 约翰·巴里摩尔：出演《化身博士》 玛丽·毕克馥：出演《波丽安娜》 老道格拉斯·范朋克：出演《佐罗的面具》 查理·卓别林、玛丽·毕克馥、道格拉斯·范朋克和传奇制片人兼导演 D·W·格里菲斯成立联美电影公司。 流行歌曲： 《I'll be With You at Apple Blossom Time》 杰 洛 姆· 科 恩《Look for the Silver Lining》 《When My Baby Smiles at Me》 百老汇舞台： 齐格菲尔德歌舞团女星范妮·布莱斯出演《华盛顿广场的玫瑰》 总统： 威廉·塔夫脱（共和党） | AQ63: 罗夏墨迹测验 机器人 胰岛素 实用邮戳机 滑水 百日咳疫苗 纸制鸡蛋托 面巾纸 商用飞机农药喷撒 液体燃料火箭 劳力士防水表 遥控电唱机 面包机 防水玻璃纸 电传打字机 盖革计数器 纯维生素C 彩色电影胶片 透明胶带 音乐汽车喇叭 闪光灯 速冻食品 球形潜水舱 回旋加速器 折叠式雨伞 电动剃须刀 车载收音机 玛氏巧克力棒 变焦镜头 大富翁桌游 商业洗衣店 畅销平装书 里氏震级 磁带录音机 大众汽车 超市推车 带温控器的电熨斗 速溶咖啡 尼龙 圆珠笔 黄热病疫苗 雷达 汽车自动变速箱 充气救生衣 人工授精 青霉素 军用吉普车 原子裂变 火箭筒 凝固汽油弹 水肺 麦角酸二乙酰胺 神经毒气 原子弹 特百惠 计算机 静电复印法 比基尼泳衣 浓缩咖啡机 宝丽来相机 拼字盘 实心电吉他 尼龙扣 晶体管 黑胶唱片 有线电视 电视显像管 汽车自动点火装置 信用卡 复印机 宽荧幕电影 动力转向器 三色停车灯 人行红绿灯 晶体管助听器 氢弹 录像带 DNA双螺旋结构 麻疹疫苗 按动圆珠笔 硅晶体管 核导弹 空对空导弹 迪士尼乐园 特氟龙 卡丁车 地对空核导弹 沙宾疫苗 通讯卫星 呼啦圈 安全带 人工肾脏 避孕药 气象卫星 便携晶体管收音机 安定 砷化镓半导体激光器 三维全息技术 合成器 香烟健康警示 凯夫拉纤维 子午胎 IBM文字处理机 杜比A型降噪器 滑雪板 喇叭裤 绕月载人火箭 人工心脏移植 波音747喷气式客机 互联网 条形码 软盘 帆板 热裤 液晶显示 便携电子计算器 电视游戏 DNA重组技术 电子游戏机 超级计算机 光纤 试管婴儿 魔方 索尼Walkman 杜比C型降噪器 艾滋病毒 强效可卡因 温室效应 CD 暗物质 暗能量 太阳能飞行器 甲型H1N1 流感 希格斯玻色子 引力波 | AR63: 电气地铁 圣代冰淇淋 实用水电站 手电 电影摄影机 收音机 霍乱疫苗 啤酒瓶盖 柴油发动机 双向电报 实用的胶卷 块麦片 电报 可口可乐 X射线 卷烟机发明 电影放映机 排球 印名片机 福特车 潜望镜 油印蜡纸发明 阴极射线管 商品阿司匹林 凯洛格牌玉米片 手电筒 钋 镭 摇控器 α粒子 β粒子 打字机 柯达布朗尼相机 齐柏林飞艇 人类血型 跨大西洋电报 汽轮机游船 现代柏油路 铝罐奶粉 爆米花 泰迪熊 卡鲁索电唱机 便宜的肥皂和烹饪用油 飞机 荧光灯 邮戳机 摩托车发动机 热水瓶 农业轨道机械 木棉安全带 电动汽车喇叭 化学泡沫灭火器 狭义相对论 自动点唱机 量产舰艇舷外发动机 动画 电动洗衣机 家用洗洁精 立式吸尘器 饮用纸杯 双层公交车 无线电测向仪 电煎锅 质子和电子 玻璃纸 战壕风衣 汽车自动起动器 麦片 氯气毒气 防毒面具 拉链 机械雨刮器 广义相对论 芥子气 量产拖拉机 电子钟 黄油枪 降落伞 广播电台播音 茶包 | AS63: 广播电台 茶包 | AT63: 1920 | BH63: 黎巴嫩 | BI63: 贝鲁特* | BJ63: 阿卡省 | BK63: 巴勒贝克-赫尔梅尔省 | BL63: 贝卡省 | BM63: 的黎波里省 | BN63: 蒙费拉省 | BO63: 纳巴蒂耶省 | BP63: 北省 | BQ63: 南山省
E64: 24-26.75 | F64: 胖 | I64: =IF(BMI<13,"极其消瘦",IF(BMI<15.75,"过于消瘦",IF(BMI<18.5,"略微消瘦",IF(BMI<24,"正常",IF(BMI<26.75,"略壮/胖",IF(BMI<29.5,"过壮/胖","极壮/胖")))))) -> #VALUE! | K64: =IF(SIZA<41,SIZA+10,40) -> 40 | L64: =IF(SIZA<41,110+SIZA,L65) -> 190 | M64: 30-40 | X64: 格斗③ | AE64: 1921 | AF64: 咆哮的二十年代（美国） | AI64: 中国共产党成立 | AL64: 二十世纪 二十年代 | AM64: 辛酉鸡年 | AN64: 民国10年 | AO64: 罗夏墨迹测验获得专利 德国恶性通胀开始 KDKA 电台转播体育赛事 恰佩克提出“机器人”一词 | AP64: 书籍： 赫伯特·乔治·威尔斯《世界史纲》 赞恩·格雷《神秘骑手》 伊迪斯·华顿《纯真年代》 伊迪斯·霍尔《酋长》 影视： 鲁道夫·瓦伦蒂诺凭借《启示录四骑士》和《沙漠情酋》一夜成名 马克·森内特制作《小城偶像》 卓别林主演《寻子遇仙记》 道格拉斯·范朋克出演《三个火枪手》 流行歌曲： 《Sheik of Araby》 《I'm Just Wild About Harry》 《Ain't We Got Fun》 百老汇舞台： 萨蒂斯餐厅在曼哈顿剧院区开张 范妮·布莱斯出演《二手玫瑰》保持去年的热度 总统： 伍德罗·威尔逊（民主党） 沃伦·甘梅利尔·哈定（共和党） | AQ64: 胰岛素 实用邮戳机 滑水 百日咳疫苗 纸制鸡蛋托 面巾纸 商用飞机农药喷撒 液体燃料火箭 劳力士防水表 遥控电唱机 面包机 防水玻璃纸 电传打字机 盖革计数器 纯维生素C 彩色电影胶片 透明胶带 音乐汽车喇叭 闪光灯 速冻食品 球形潜水舱 回旋加速器 折叠式雨伞 电动剃须刀 车载收音机 玛氏巧克力棒 变焦镜头 大富翁桌游 商业洗衣店 畅销平装书 里氏震级 磁带录音机 大众汽车 超市推车 带温控器的电熨斗 速溶咖啡 尼龙 圆珠笔 黄热病疫苗 雷达 汽车自动变速箱 充气救生衣 人工授精 青霉素 军用吉普车 原子裂变 火箭筒 凝固汽油弹 水肺 麦角酸二乙酰胺 神经毒气 原子弹 特百惠 计算机 静电复印法 比基尼泳衣 浓缩咖啡机 宝丽来相机 拼字盘 实心电吉他 尼龙扣 晶体管 黑胶唱片 有线电视 电视显像管 汽车自动点火装置 信用卡 复印机 宽荧幕电影 动力转向器 三色停车灯 人行红绿灯 晶体管助听器 氢弹 录像带 DNA双螺旋结构 麻疹疫苗 按动圆珠笔 硅晶体管 核导弹 空对空导弹 迪士尼乐园 特氟龙 卡丁车 地对空核导弹 沙宾疫苗 通讯卫星 呼啦圈 安全带 人工肾脏 避孕药 气象卫星 便携晶体管收音机 安定 砷化镓半导体激光器 三维全息技术 合成器 香烟健康警示 凯夫拉纤维 子午胎 IBM文字处理机 杜比A型降噪器 滑雪板 喇叭裤 绕月载人火箭 人工心脏移植 波音747喷气式客机 互联网 条形码 软盘 帆板 热裤 液晶显示 便携电子计算器 电视游戏 DNA重组技术 电子游戏机 超级计算机 光纤 试管婴儿 魔方 索尼Walkman 杜比C型降噪器 艾滋病毒 强效可卡因 温室效应 CD 暗物质 暗能量 太阳能飞行器 甲型H1N1 流感 希格斯玻色子 引力波 | AR64: 电气地铁 圣代冰淇淋 实用水电站 手电 电影摄影机 收音机 霍乱疫苗 啤酒瓶盖 柴油发动机 双向电报 实用的胶卷 块麦片 电报 可口可乐 X射线 卷烟机发明 电影放映机 排球 印名片机 福特车 潜望镜 油印蜡纸发明 阴极射线管 商品阿司匹林 凯洛格牌玉米片 手电筒 钋 镭 摇控器 α粒子 β粒子 打字机 柯达布朗尼相机 齐柏林飞艇 人类血型 跨大西洋电报 汽轮机游船 现代柏油路 铝罐奶粉 爆米花 泰迪熊 卡鲁索电唱机 便宜的肥皂和烹饪用油 飞机 荧光灯 邮戳机 摩托车发动机 热水瓶 农业轨道机械 木棉安全带 电动汽车喇叭 化学泡沫灭火器 狭义相对论 自动点唱机 量产舰艇舷外发动机 动画 电动洗衣机 家用洗洁精 立式吸尘器 饮用纸杯 双层公交车 无线电测向仪 电煎锅 质子和电子 玻璃纸 战壕风衣 汽车自动起动器 麦片 氯气毒气 防毒面具 拉链 机械雨刮器 广义相对论 芥子气 量产拖拉机 电子钟 黄油枪 降落伞 广播电台播音 茶包 罗夏墨迹测验 机器人 | AS64: 罗夏墨迹测验 “机器人” | AT64: 1921 | BH64: 约旦 | BI64: 安曼* | BJ64: 阿贾隆省 | BK64: 伊尔比德省 | BL64: 马安省 | BM64: 马德巴省 | BN64: 扎尔卡省 | BO64: 卡拉克省 | BP64: 塔菲拉省 | BQ64: 亚喀巴省 | BR64: 巴尔卡省 | BS64: 杰拉什省 | BT64: 马弗拉克省
E65: 26.75-29.5 | K65: =IF(SIZA<81,SIZA*1.5-10,50) -> 50 | L65: =IF(SIZA<81,120+SIZA/4*3,L66) -> 190 | M65: 40-80 | X65: 锁匠 | AE65: 1922 | AF65: 咆哮的二十年代（美国） | AI65: —— | AL65: 二十世纪 二十年代 | AM65: 壬戌狗年 | AN65: 民国11年 | AO65: 三K 党死灰复燃 英国飞艇AR-2 断成两段，死亡62 人 分离胰岛素 首个实用邮戳机 苏联五一口号去掉“世界革命” 滑水 墨索里尼入主罗马 | AP65: 书籍： 辛克莱·刘易斯《巴比特》 《饮食与健康》首次介绍了卡路里计算方法，连续五年成为畅销书 房龙《人类的故事》 埃德娜·费伯《演艺船》 J·A·汤姆孙《科学大纲》 詹姆斯·乔伊斯《尤利西斯》 影视： 亨利·赫尔和卡洛儿·代姆斯特合作主演《恐怖之夜》 道格拉斯·范朋克出演《罗宾汉》 F·W·茂瑙在德导演《诺斯费拉图》 罗伯特·弗拉哈迪《北方的纳努克》开创了文献纪录片 约翰·巴里摩尔出演《哈姆雷特》成为当时评价最高的莎士比亚剧演员 流行歌曲： 《Chicago (That Toddlin' Town)》 《Toot, Toot, Tootsie Goodbye》 《Way Down Yonder in New Orleans》 《I Wish I Could Shimmy Like My Sister Kate》 《Carolina in the Morning》 百老汇舞台： 萨姆·哈里斯创作《雨》 总统： 沃伦·甘梅利尔·哈定（共和党） | AQ65: 百日咳疫苗 纸制鸡蛋托 面巾纸 商用飞机农药喷撒 液体燃料火箭 劳力士防水表 遥控电唱机 面包机 防水玻璃纸 电传打字机 盖革计数器 纯维生素C 彩色电影胶片 透明胶带 音乐汽车喇叭 闪光灯 速冻食品 球形潜水舱 回旋加速器 折叠式雨伞 电动剃须刀 车载收音机 玛氏巧克力棒 变焦镜头 大富翁桌游 商业洗衣店 畅销平装书 里氏震级 磁带录音机 大众汽车 超市推车 带温控器的电熨斗 速溶咖啡 尼龙 圆珠笔 黄热病疫苗 雷达 汽车自动变速箱 充气救生衣 人工授精 青霉素 军用吉普车 原子裂变 火箭筒 凝固汽油弹 水肺 麦角酸二乙酰胺 神经毒气 原子弹 特百惠 计算机 静电复印法 比基尼泳衣 浓缩咖啡机 宝丽来相机 拼字盘 实心电吉他 尼龙扣 晶体管 黑胶唱片 有线电视 电视显像管 汽车自动点火装置 信用卡 复印机 宽荧幕电影 动力转向器 三色停车灯 人行红绿灯 晶体管助听器 氢弹 录像带 DNA双螺旋结构 麻疹疫苗 按动圆珠笔 硅晶体管 核导弹 空对空导弹 迪士尼乐园 特氟龙 卡丁车 地对空核导弹 沙宾疫苗 通讯卫星 呼啦圈 安全带 人工肾脏 避孕药 气象卫星 便携晶体管收音机 安定 砷化镓半导体激光器 三维全息技术 合成器 香烟健康警示 凯夫拉纤维 子午胎 IBM文字处理机 杜比A型降噪器 滑雪板 喇叭裤 绕月载人火箭 人工心脏移植 波音747喷气式客机 互联网 条形码 软盘 帆板 热裤 液晶显示 便携电子计算器 电视游戏 DNA重组技术 电子游戏机 超级计算机 光纤 试管婴儿 魔方 索尼Walkman 杜比C型降噪器 艾滋病毒 强效可卡因 温室效应 CD 暗物质 暗能量 太阳能飞行器 甲型H1N1 流感 希格斯玻色子 引力波 | AR65: 电气地铁 圣代冰淇淋 实用水电站 手电 电影摄影机 收音机 霍乱疫苗 啤酒瓶盖 柴油发动机 双向电报 实用的胶卷 块麦片 电报 可口可乐 X射线 卷烟机发明 电影放映机 排球 印名片机 福特车 潜望镜 油印蜡纸发明 阴极射线管 商品阿司匹林 凯洛格牌玉米片 手电筒 钋 镭 摇控器 α粒子 β粒子 打字机 柯达布朗尼相机 齐柏林飞艇 人类血型 跨大西洋电报 汽轮机游船 现代柏油路 铝罐奶粉 爆米花 泰迪熊 卡鲁索电唱机 便宜的肥皂和烹饪用油 飞机 荧光灯 邮戳机 摩托车发动机 热水瓶 农业轨道机械 木棉安全带 电动汽车喇叭 化学泡沫灭火器 狭义相对论 自动点唱机 量产舰艇舷外发动机 动画 电动洗衣机 家用洗洁精 立式吸尘器 饮用纸杯 双层公交车 无线电测向仪 电煎锅 质子和电子 玻璃纸 战壕风衣 汽车自动起动器 麦片 氯气毒气 防毒面具 拉链 机械雨刮器 广义相对论 芥子气 量产拖拉机 电子钟 黄油枪 降落伞 广播电台播音 茶包 罗夏墨迹测验 机器人 胰岛素 实用邮戳机 滑水 | AS65: 胰岛素 实用邮戳机 滑水 | AT65: 1922
K66: =IF(SIZA<100,SIZA*2-50,110) -> 110 | L66: =IF(SIZA<100,140+SIZA/2,190) -> 190 | M66: 80-100 | X66: 乔装 | AE66: 1923 | AF66: 咆哮的二十年代（美国） | AI66: —— | AL66: 二十世纪 二十年代 | AM66: 癸亥猪年 | AN66: 民国12年 | AO66: 茶壶山丑闻动摇哈定总统 加利福尼亚州伯克利大火，毁坏600 栋房屋，造成损失1000 万美元，死亡60 人 德国恶性通胀结束 佐治亚州持续三K 党恐怖活动 德国啤酒馆暴动 图坦卡蒙陵墓发掘 百日咳疫苗 | AP66: 书籍： 爱弥儿·柯尔《通过有意识地自我暗示掌握自我》，激发了心理健康和自我完善的风潮 艾米莉·波斯特《礼仪：社交规范蓝皮书》 影视： 朗·钱尼主演《钟楼怪人》 赛西尔·德米尔制作《十诫》 威廉·S·哈特主演《狂野比尔》 喜剧演员哈罗德·劳埃德主演《安全至下》 喜剧导演麦克·塞纳特《尖叫》 流行歌曲： 《 是 的！ 我 们 没 有 香 蕉》 《Who's Sorry Now?》 《That Old Gang of Mine》 贝西·史密斯录制《Downhearted Blues》 百老汇舞台： 约瑟芬·贝克主演的《拖着脚步走》从哈林区一路公演到百老汇 大卫·贝拉斯科创作《笑，小丑，笑》 总统： 沃伦·甘梅利尔·哈定（共和党） 卡尔文·柯立芝（共和党） | AQ66: 纸制鸡蛋托 面巾纸 商用飞机农药喷撒 液体燃料火箭 劳力士防水表 遥控电唱机 面包机 防水玻璃纸 电传打字机 盖革计数器 纯维生素C 彩色电影胶片 透明胶带 音乐汽车喇叭 闪光灯 速冻食品 球形潜水舱 回旋加速器 折叠式雨伞 电动剃须刀 车载收音机 玛氏巧克力棒 变焦镜头 大富翁桌游 商业洗衣店 畅销平装书 里氏震级 磁带录音机 大众汽车 超市推车 带温控器的电熨斗 速溶咖啡 尼龙 圆珠笔 黄热病疫苗 雷达 汽车自动变速箱 充气救生衣 人工授精 青霉素 军用吉普车 原子裂变 火箭筒 凝固汽油弹 水肺 麦角酸二乙酰胺 神经毒气 原子弹 特百惠 计算机 静电复印法 比基尼泳衣 浓缩咖啡机 宝丽来相机 拼字盘 实心电吉他 尼龙扣 晶体管 黑胶唱片 有线电视 电视显像管 汽车自动点火装置 信用卡 复印机 宽荧幕电影 动力转向器 三色停车灯 人行红绿灯 晶体管助听器 氢弹 录像带 DNA双螺旋结构 麻疹疫苗 按动圆珠笔 硅晶体管 核导弹 空对空导弹 迪士尼乐园 特氟龙 卡丁车 地对空核导弹 沙宾疫苗 通讯卫星 呼啦圈 安全带 人工肾脏 避孕药 气象卫星 便携晶体管收音机 安定 砷化镓半导体激光器 三维全息技术 合成器 香烟健康警示 凯夫拉纤维 子午胎 IBM文字处理机 杜比A型降噪器 滑雪板 喇叭裤 绕月载人火箭 人工心脏移植 波音747喷气式客机 互联网 条形码 软盘 帆板 热裤 液晶显示 便携电子计算器 电视游戏 DNA重组技术 电子游戏机 超级计算机 光纤 试管婴儿 魔方 索尼Walkman 杜比C型降噪器 艾滋病毒 强效可卡因 温室效应 CD 暗物质 暗能量 太阳能飞行器 甲型H1N1 流感 希格斯玻色子 引力波 | AR66: 电气地铁 圣代冰淇淋 实用水电站 手电 电影摄影机 收音机 霍乱疫苗 啤酒瓶盖 柴油发动机 双向电报 实用的胶卷 块麦片 电报 可口可乐 X射线 卷烟机发明 电影放映机 排球 印名片机 福特车 潜望镜 油印蜡纸发明 阴极射线管 商品阿司匹林 凯洛格牌玉米片 手电筒 钋 镭 摇控器 α粒子 β粒子 打字机 柯达布朗尼相机 齐柏林飞艇 人类血型 跨大西洋电报 汽轮机游船 现代柏油路 铝罐奶粉 爆米花 泰迪熊 卡鲁索电唱机 便宜的肥皂和烹饪用油 飞机 荧光灯 邮戳机 摩托车发动机 热水瓶 农业轨道机械 木棉安全带 电动汽车喇叭 化学泡沫灭火器 狭义相对论 自动点唱机 量产舰艇舷外发动机 动画 电动洗衣机 家用洗洁精 立式吸尘器 饮用纸杯 双层公交车 无线电测向仪 电煎锅 质子和电子 玻璃纸 战壕风衣 汽车自动起动器 麦片 氯气毒气 防毒面具 拉链 机械雨刮器 广义相对论 芥子气 量产拖拉机 电子钟 黄油枪 降落伞 广播电台播音 茶包 罗夏墨迹测验 机器人 胰岛素 实用邮戳机 滑水 百日咳疫苗 | AS66: 百日咳疫苗 | AT66: 1923 | BH66: *中亚*
D67: 零钱值 | E67: =人物卡!BN77*1.2 -> 0.6 | F67: 携带现金 | G67: =E67-E73 -> 0.6 | I67: 货币 | J67: =人物卡!BL13 -> 美元 | X67: 妙手 | AA67: =_xlfn.CONCAT(AA72:AA111,AC72:AC111) -> 会计5法律5历史5人类学1估价5考古学1博物学10神秘学5信用评级0克苏鲁神话0机械维修10电气维修10电子学1操作重型机械1爆破1计算机使用0母语0闪避0斗殴25锁匠1乔装5妙手10潜行20图书馆使用20聆听20侦查25追踪10导航10心理学10取悦15话术5恐吓15说服10跳跃20攀爬20游泳20精神分析1医学1急救30汽车驾驶20骑术5动物驯养5潜水1读唇1催眠1炮术1投掷20手枪20 | AE67: 1924 | AF67: 咆哮的二十年代（美国） | AG67: 巴黎奥运会 | AI67: 国共两党第一次合作 | AL67: 二十世纪 二十年代 | AM67: 甲子鼠年 | AN67: 民国13年 | AO67: 李奥波德与勒伯案 纸制鸡蛋托应用 面巾纸 | AP67: 书籍： 赞恩·格雷《大峡谷的呼唤》 影视： 哈罗德·劳埃德出演《真情难诉》 巴斯特·基顿出演《航海家》 道格拉斯·范朋克出演《巴格达大盗》 约翰·福特导演《铁骑》 流行歌曲： 《Indian Love Call》 格什温《Fascinating Rhythm》 《It Had to Be You》 《鸳鸯茶》(Tea for Two) 《California Here I Come》 百老汇舞台： 诺埃尔·科沃德《漩涡》 马克斯兄弟登场《I'll Say She Is》 保罗·罗伯逊主演尤金·奥尼尔的《琼斯皇帝》 约瑟芬·贝克在《巧克力浪子》中登场，随后离开美国前往巴黎 总统： 卡尔文·柯立芝（共和党） | AQ67: 商用飞机农药喷撒 液体燃料火箭 劳力士防水表 遥控电唱机 面包机 防水玻璃纸 电传打字机 盖革计数器 纯维生素C 彩色电影胶片 透明胶带 音乐汽车喇叭 闪光灯 速冻食品 球形潜水舱 回旋加速器 折叠式雨伞 电动剃须刀 车载收音机 玛氏巧克力棒 变焦镜头 大富翁桌游 商业洗衣店 畅销平装书 里氏震级 磁带录音机 大众汽车 超市推车 带温控器的电熨斗 速溶咖啡 尼龙 圆珠笔 黄热病疫苗 雷达 汽车自动变速箱 充气救生衣 人工授精 青霉素 军用吉普车 原子裂变 火箭筒 凝固汽油弹 水肺 麦角酸二乙酰胺 神经毒气 原子弹 特百惠 计算机 静电复印法 比基尼泳衣 浓缩咖啡机 宝丽来相机 拼字盘 实心电吉他 尼龙扣 晶体管 黑胶唱片 有线电视 电视显像管 汽车自动点火装置 信用卡 复印机 宽荧幕电影 动力转向器 三色停车灯 人行红绿灯 晶体管助听器 氢弹 录像带 DNA双螺旋结构 麻疹疫苗 按动圆珠笔 硅晶体管 核导弹 空对空导弹 迪士尼乐园 特氟龙 卡丁车 地对空核导弹 沙宾疫苗 通讯卫星 呼啦圈 安全带 人工肾脏 避孕药 气象卫星 便携晶体管收音机 安定 砷化镓半导体激光器 三维全息技术 合成器 香烟健康警示 凯夫拉纤维 子午胎 IBM文字处理机 杜比A型降噪器 滑雪板 喇叭裤 绕月载人火箭 人工心脏移植 波音747喷气式客机 互联网 条形码 软盘 帆板 热裤 液晶显示 便携电子计算器 电视游戏 DNA重组技术 电子游戏机 超级计算机 光纤 试管婴儿 魔方 索尼Walkman 杜比C型降噪器 艾滋病毒 强效可卡因 温室效应 CD 暗物质 暗能量 太阳能飞行器 甲型H1N1 流感 希格斯玻色子 引力波 | AR67: 电气地铁 圣代冰淇淋 实用水电站 手电 电影摄影机 收音机 霍乱疫苗 啤酒瓶盖 柴油发动机 双向电报 实用的胶卷 块麦片 电报 可口可乐 X射线 卷烟机发明 电影放映机 排球 印名片机 福特车 潜望镜 油印蜡纸发明 阴极射线管 商品阿司匹林 凯洛格牌玉米片 手电筒 钋 镭 摇控器 α粒子 β粒子 打字机 柯达布朗尼相机 齐柏林飞艇 人类血型 跨大西洋电报 汽轮机游船 现代柏油路 铝罐奶粉 爆米花 泰迪熊 卡鲁索电唱机 便宜的肥皂和烹饪用油 飞机 荧光灯 邮戳机 摩托车发动机 热水瓶 农业轨道机械 木棉安全带 电动汽车喇叭 化学泡沫灭火器 狭义相对论 自动点唱机 量产舰艇舷外发动机 动画 电动洗衣机 家用洗洁精 立式吸尘器 饮用纸杯 双层公交车 无线电测向仪 电煎锅 质子和电子 玻璃纸 战壕风衣 汽车自动起动器 麦片 氯气毒气 防毒面具 拉链 机械雨刮器 广义相对论 芥子气 量产拖拉机 电子钟 黄油枪 降落伞 广播电台播音 茶包 罗夏墨迹测验 机器人 胰岛素 实用邮戳机 滑水 百日咳疫苗 纸制鸡蛋托 面巾纸 | AS67: 纸制鸡蛋托 面巾纸 | AT67: 1924 | BH67: 哈萨克斯坦 | BI67: 阿斯塔纳/努尔苏丹* | BJ67: 阿拉木图市 | BK67: 阿克纠宾斯克州 | BL67: 阿克莫拉州 | BM67: 阿特劳州 | BN67: 巴甫洛达尔州 | BO67: 北哈萨克斯坦州 | BP67: 东哈萨克斯坦州 | BQ67: 卡拉干达州 | BR67: 克孜勒奥尔达州 | BS67: 科斯塔奈州 | BT67: 库斯塔奈州 | BU67: 曼格斯套州 | BV67: 南哈萨克斯坦州 | BW67: 西哈萨克斯坦州 | BX67: 江布尔州 | BY67: 杰兹卡兹甘市 | BZ67: 彼得罗巴甫洛夫斯克市 | CA67: 乌拉尔斯克市 | CB67: 巴甫洛达尔市 | CC67: 塞梅伊市 | CD67: 塔拉兹市 | CE67: 乌斯季卡缅诺戈尔斯克市 | CF67: 希姆肯特市 | CG67: 科克舍套市
K68: 武器价值 | O68: 武器数量 | X68: 潜行 | AE68: 1925 | AF68: 咆哮的二十年代（美国） | AI68: 孙中山逝世 | AL68: 二十世纪 二十年代 | AM68: 乙丑牛年 | AN68: 民国14年 | AO68: W·泡利阐述不相容原理 I·G·法本化工成立 孙中山逝世 中西部地区龙卷风，一天死亡792 人 美国飞艇谢南多厄号解体，死亡14 人 纳粹党卫军成立 斯科普斯猿猴诉讼案 商用飞机农药喷撒 | AP68: 书籍： 辛克莱·刘易斯《阿罗史密斯》 弗·斯科特·菲茨杰拉德《了不起的盖茨比》 弗吉尼亚·伍尔芙《达洛维夫人》 西奥多·德雷塞《美国的悲剧》 厄尔·德尔·比格斯《没有钥匙的住宅》 影视： 朗·钱尼主演《歌剧魅影》 威廉·S· 哈特出演《风滚草》 哈罗德·劳埃德出演《新生》 阿道夫·门吉欧出演《撒旦的悲伤》 巴斯特·基顿出演《七次机会》 查理·卓别林出演《淘金记》 威利斯·奥布莱恩制作了《失落的世界》，将史前生物带入人们视野 流行歌曲： 《I'm Sittin' On Top of the World》; 《Alabamy Bound》 《If You Knew Susie Like I Know Susie》 《Sweet Georgia Brown》 《Yes Sir, That's My Baby》 胖子沃勒《Squeeze Me》 百老汇舞台： 诺埃尔·科沃德《枯草热》 萨姆·哈里斯创作《爵士歌王》，乔治·杰塞尔主演 马克斯兄弟主演《可可豆》 总统： 卡尔文·柯立芝（共和党） | AQ68: 液体燃料火箭 劳力士防水表 遥控电唱机 面包机 防水玻璃纸 电传打字机 盖革计数器 纯维生素C 彩色电影胶片 透明胶带 音乐汽车喇叭 闪光灯 速冻食品 球形潜水舱 回旋加速器 折叠式雨伞 电动剃须刀 车载收音机 玛氏巧克力棒 变焦镜头 大富翁桌游 商业洗衣店 畅销平装书 里氏震级 磁带录音机 大众汽车 超市推车 带温控器的电熨斗 速溶咖啡 尼龙 圆珠笔 黄热病疫苗 雷达 汽车自动变速箱 充气救生衣 人工授精 青霉素 军用吉普车 原子裂变 火箭筒 凝固汽油弹 水肺 麦角酸二乙酰胺 神经毒气 原子弹 特百惠 计算机 静电复印法 比基尼泳衣 浓缩咖啡机 宝丽来相机 拼字盘 实心电吉他 尼龙扣 晶体管 黑胶唱片 有线电视 电视显像管 汽车自动点火装置 信用卡 复印机 宽荧幕电影 动力转向器 三色停车灯 人行红绿灯 晶体管助听器 氢弹 录像带 DNA双螺旋结构 麻疹疫苗 按动圆珠笔 硅晶体管 核导弹 空对空导弹 迪士尼乐园 特氟龙 卡丁车 地对空核导弹 沙宾疫苗 通讯卫星 呼啦圈 安全带 人工肾脏 避孕药 气象卫星 便携晶体管收音机 安定 砷化镓半导体激光器 三维全息技术 合成器 香烟健康警示 凯夫拉纤维 子午胎 IBM文字处理机 杜比A型降噪器 滑雪板 喇叭裤 绕月载人火箭 人工心脏移植 波音747喷气式客机 互联网 条形码 软盘 帆板 热裤 液晶显示 便携电子计算器 电视游戏 DNA重组技术 电子游戏机 超级计算机 光纤 试管婴儿 魔方 索尼Walkman 杜比C型降噪器 艾滋病毒 强效可卡因 温室效应 CD 暗物质 暗能量 太阳能飞行器 甲型H1N1 流感 希格斯玻色子 引力波 | AR68: 电气地铁 圣代冰淇淋 实用水电站 手电 电影摄影机 收音机 霍乱疫苗 啤酒瓶盖 柴油发动机 双向电报 实用的胶卷 块麦片 电报 可口可乐 X射线 卷烟机发明 电影放映机 排球 印名片机 福特车 潜望镜 油印蜡纸发明 阴极射线管 商品阿司匹林 凯洛格牌玉米片 手电筒 钋 镭 摇控器 α粒子 β粒子 打字机 柯达布朗尼相机 齐柏林飞艇 人类血型 跨大西洋电报 汽轮机游船 现代柏油路 铝罐奶粉 爆米花 泰迪熊 卡鲁索电唱机 便宜的肥皂和烹饪用油 飞机 荧光灯 邮戳机 摩托车发动机 热水瓶 农业轨道机械 木棉安全带 电动汽车喇叭 化学泡沫灭火器 狭义相对论 自动点唱机 量产舰艇舷外发动机 动画 电动洗衣机 家用洗洁精 立式吸尘器 饮用纸杯 双层公交车 无线电测向仪 电煎锅 质子和电子 玻璃纸 战壕风衣 汽车自动起动器 麦片 氯气毒气 防毒面具 拉链 机械雨刮器 广义相对论 芥子气 量产拖拉机 电子钟 黄油枪 降落伞 广播电台播音 茶包 罗夏墨迹测验 机器人 胰岛素 实用邮戳机 滑水 百日咳疫苗 纸制鸡蛋托 面巾纸 商用飞机农药喷撒 | AS68: 商用飞机农药喷撒 | AT68: 1925 | BH68: 吉尔吉斯斯坦 | BI68: 比什凯克* | BJ68: 奥什州 | BK68: 巴特肯州 | BL68: 贾拉拉巴德州 | BM68: 纳伦州 | BN68: 塔拉斯州 | BO68: 伊塞克湖州 | BP68: 楚河州 | BQ68: 奥什市
D69: 物品值 | E69: =SUM(人物卡!BK99:BL113,人物卡!BS99:BT113) -> 0 | G69: 物品数 | H69: =COUNTA(人物卡!BE99:BJ113,人物卡!BM99:BR113) -> 0 | K69: 编号 | L69: 存在 | M69: 名 | N69: 价值填写 | O69: =COUNTA(人物卡!BF69:BJ73) -> 0 | X69: 图书馆使用 | AE69: 1926 | AF69: 咆哮的二十年代（美国） | AG69: 日本改元昭和 | AI69: 北伐开始 | AL69: 二十世纪 二十年代 | AM69: 丙寅虎年 | AN69: 民国15年 | AO69: 戈达德博士发射首枚液体燃料火箭 闪电引爆新泽西州丹麦湖的军火库，损失8500万美元，死亡30 人 佛罗里达和亚拉巴马州飓风，死亡243 人 蒋介石发动北伐 托洛茨基被逐出苏共政治局 劳力士防水表 杰克·登普西负于吉恩·滕尼，让出拳王名号 | AP69: 书籍： 阿加莎·克里斯蒂《罗杰疑案》，此书是其成名作 威尔·杜兰特《哲学的故事》，售出了 200 万册 海明威《太阳照常升起》 安妮塔·卢斯《绅士爱美人》 影视： 琼·克劳馥在《漂亮女士》中出道 葛丽泰·嘉宝主演《激流》 弗里茨·朗导演经典作品《大都会》 约翰·巴里摩尔出演首部有声歌舞电影《唐璜》 巴斯特·基顿导演《将军号》 弗朗西斯·X·布什曼主演《宾虚》 瓦伦蒂诺的葬礼触发曼哈顿群体歇斯底里事件，会场被前来寻求纪念品的人洗劫 流行歌曲： 《Are You Lonesome Tonight》 《Bye, Bye, Blackbird》 《When the Red, Red Robin (Comes Bob, Bob, Bobbin' Along)》 《Tip Toe Through the Tulips》 百老汇舞台： 梅·韦斯特的《性》轰动 大卫·贝拉斯科创作《Lu Lu Belle》 总统： 卡尔文·柯立芝（共和党） | AQ69: 遥控电唱机 面包机 防水玻璃纸 电传打字机 盖革计数器 纯维生素C 彩色电影胶片 透明胶带 音乐汽车喇叭 闪光灯 速冻食品 球形潜水舱 回旋加速器 折叠式雨伞 电动剃须刀 车载收音机 玛氏巧克力棒 变焦镜头 大富翁桌游 商业洗衣店 畅销平装书 里氏震级 磁带录音机 大众汽车 超市推车 带温控器的电熨斗 速溶咖啡 尼龙 圆珠笔 黄热病疫苗 雷达 汽车自动变速箱 充气救生衣 人工授精 青霉素 军用吉普车 原子裂变 火箭筒 凝固汽油弹 水肺 麦角酸二乙酰胺 神经毒气 原子弹 特百惠 计算机 静电复印法 比基尼泳衣 浓缩咖啡机 宝丽来相机 拼字盘 实心电吉他 尼龙扣 晶体管 黑胶唱片 有线电视 电视显像管 汽车自动点火装置 信用卡 复印机 宽荧幕电影 动力转向器 三色停车灯 人行红绿灯 晶体管助听器 氢弹 录像带 DNA双螺旋结构 麻疹疫苗 按动圆珠笔 硅晶体管 核导弹 空对空导弹 迪士尼乐园 特氟龙 卡丁车 地对空核导弹 沙宾疫苗 通讯卫星 呼啦圈 安全带 人工肾脏 避孕药 气象卫星 便携晶体管收音机 安定 砷化镓半导体激光器 三维全息技术 合成器 香烟健康警示 凯夫拉纤维 子午胎 IBM文字处理机 杜比A型降噪器 滑雪板 喇叭裤 绕月载人火箭 人工心脏移植 波音747喷气式客机 互联网 条形码 软盘 帆板 热裤 液晶显示 便携电子计算器 电视游戏 DNA重组技术 电子游戏机 超级计算机 光纤 试管婴儿 魔方 索尼Walkman 杜比C型降噪器 艾滋病毒 强效可卡因 温室效应 CD 暗物质 暗能量 太阳能飞行器 甲型H1N1 流感 希格斯玻色子 引力波 | AR69: 电气地铁 圣代冰淇淋 实用水电站 手电 电影摄影机 收音机 霍乱疫苗 啤酒瓶盖 柴油发动机 双向电报 实用的胶卷 块麦片 电报 可口可乐 X射线 卷烟机发明 电影放映机 排球 印名片机 福特车 潜望镜 油印蜡纸发明 阴极射线管 商品阿司匹林 凯洛格牌玉米片 手电筒 钋 镭 摇控器 α粒子 β粒子 打字机 柯达布朗尼相机 齐柏林飞艇 人类血型 跨大西洋电报 汽轮机游船 现代柏油路 铝罐奶粉 爆米花 泰迪熊 卡鲁索电唱机 便宜的肥皂和烹饪用油 飞机 荧光灯 邮戳机 摩托车发动机 热水瓶 农业轨道机械 木棉安全带 电动汽车喇叭 化学泡沫灭火器 狭义相对论 自动点唱机 量产舰艇舷外发动机 动画 电动洗衣机 家用洗洁精 立式吸尘器 饮用纸杯 双层公交车 无线电测向仪 电煎锅 质子和电子 玻璃纸 战壕风衣 汽车自动起动器 麦片 氯气毒气 防毒面具 拉链 机械雨刮器 广义相对论 芥子气 量产拖拉机 电子钟 黄油枪 降落伞 广播电台播音 茶包 罗夏墨迹测验 机器人 胰岛素 实用邮戳机 滑水 百日咳疫苗 纸制鸡蛋托 面巾纸 商用飞机农药喷撒 液体燃料火箭 劳力士防水表 | AS69: 液体燃料火箭 劳力士防水表 | AT69: 1926 | BH69: 塔吉克斯坦 | BI69: 杜尚别* | BJ69: 戈尔诺-巴达赫尚自治州 | BK69: 哈特隆州 | BL69: 卡拉库尔州 | BM69: 库利亚布州 | BN69: 列宁纳巴德州 | BO69: 索格特州 | BP69: 塔吉克斯坦共和国直属区
D70: 武器值 | E70: =SUM(人物卡!BS85:BT89) -> 0 | G70: 武器数 | H70: =COUNTA(人物卡!BA85:BJ89) -> 5 | K70: 1 | L70: =IF(人物卡!BA85="",0,1) -> 0 | M70: =IF(L70=0,0,IF(人物卡!BK85="未取名！",1,0)) -> 0 | N70: =IF(L70=0,0,IF(人物卡!BS85="",1,0)) -> 0 | O70: =IF(O69=0,"手无寸铁！","拥有"&O69&"种防身手段") -> 手无寸铁！ | X70: 聆听 | AE70: 1927 | AF70: 咆哮的二十年代（美国） | AI70: 南昌起义 | AJ70: 秋收起义 | AL70: 二十世纪 二十年代 | AM70: 丁卯兔年 | AN70: 民国16年 | AO70: 查尔斯·A·林德伯格单人从纽约直飞巴黎 爵士乐歌手首次主演有声电影 首个遥控电唱机 面包机 萨科与万泽蒂被处决，直到1977 年才恢复名誉 美国体育专栏作家保罗·加利科组织了首场金手套业余拳击赛 | AP70: 书籍： 辛克莱·刘易斯《埃尔默·甘特利》 弗吉尼亚·伍尔芙《到灯塔去》 威尔 · 罗杰斯《自学成才的外交官致总统先生的信》、《俄罗斯没有泳衣》 影视： 朗·钱尼出演《午夜伦敦》 塞西尔·德米尔制作《万王之王》 葛丽泰·嘉宝主演《灵与肉》和约翰·吉尔伯特共演《爱情》 乔生主演首部完整有声电影《爵士歌王》 威廉·福克斯发明幕维通新闻电影机克拉拉·鲍因为电影《攀上枝头》中的形象而成为“It girl” 流行歌曲： 《Lucky Lindy》 《My Blue Heaven》 《Swonderful》 《Side by Side》 《Ain't She Sweet》 《Me and My Shadow》 百老汇舞台： 《演艺船》公演超过 500 场，创下纪录 百老汇人气登顶，全年共举行 268 场首演 总统： 卡尔文·柯立芝（共和党） | AQ70: 防水玻璃纸 电传打字机 盖革计数器 纯维生素C 彩色电影胶片 透明胶带 音乐汽车喇叭 闪光灯 速冻食品 球形潜水舱 回旋加速器 折叠式雨伞 电动剃须刀 车载收音机 玛氏巧克力棒 变焦镜头 大富翁桌游 商业洗衣店 畅销平装书 里氏震级 磁带录音机 大众汽车 超市推车 带温控器的电熨斗 速溶咖啡 尼龙 圆珠笔 黄热病疫苗 雷达 汽车自动变速箱 充气救生衣 人工授精 青霉素 军用吉普车 原子裂变 火箭筒 凝固汽油弹 水肺 麦角酸二乙酰胺 神经毒气 原子弹 特百惠 计算机 静电复印法 比基尼泳衣 浓缩咖啡机 宝丽来相机 拼字盘 实心电吉他 尼龙扣 晶体管 黑胶唱片 有线电视 电视显像管 汽车自动点火装置 信用卡 复印机 宽荧幕电影 动力转向器 三色停车灯 人行红绿灯 晶体管助听器 氢弹 录像带 DNA双螺旋结构 麻疹疫苗 按动圆珠笔 硅晶体管 核导弹 空对空导弹 迪士尼乐园 特氟龙 卡丁车 地对空核导弹 沙宾疫苗 通讯卫星 呼啦圈 安全带 人工肾脏 避孕药 气象卫星 便携晶体管收音机 安定 砷化镓半导体激光器 三维全息技术 合成器 香烟健康警示 凯夫拉纤维 子午胎 IBM文字处理机 杜比A型降噪器 滑雪板 喇叭裤 绕月载人火箭 人工心脏移植 波音747喷气式客机 互联网 条形码 软盘 帆板 热裤 液晶显示 便携电子计算器 电视游戏 DNA重组技术 电子游戏机 超级计算机 光纤 试管婴儿 魔方 索尼Walkman 杜比C型降噪器 艾滋病毒 强效可卡因 温室效应 CD 暗物质 暗能量 太阳能飞行器 甲型H1N1 流感 希格斯玻色子 引力波 | AR70: 电气地铁 圣代冰淇淋 实用水电站 手电 电影摄影机 收音机 霍乱疫苗 啤酒瓶盖 柴油发动机 双向电报 实用的胶卷 块麦片 电报 可口可乐 X射线 卷烟机发明 电影放映机 排球 印名片机 福特车 潜望镜 油印蜡纸发明 阴极射线管 商品阿司匹林 凯洛格牌玉米片 手电筒 钋 镭 摇控器 α粒子 β粒子 打字机 柯达布朗尼相机 齐柏林飞艇 人类血型 跨大西洋电报 汽轮机游船 现代柏油路 铝罐奶粉 爆米花 泰迪熊 卡鲁索电唱机 便宜的肥皂和烹饪用油 飞机 荧光灯 邮戳机 摩托车发动机 热水瓶 农业轨道机械 木棉安全带 电动汽车喇叭 化学泡沫灭火器 狭义相对论 自动点唱机 量产舰艇舷外发动机 动画 电动洗衣机 家用洗洁精 立式吸尘器 饮用纸杯 双层公交车 无线电测向仪 电煎锅 质子和电子 玻璃纸 战壕风衣 汽车自动起动器 麦片 氯气毒气 防毒面具 拉链 机械雨刮器 广义相对论 芥子气 量产拖拉机 电子钟 黄油枪 降落伞 广播电台播音 茶包 罗夏墨迹测验 机器人 胰岛素 实用邮戳机 滑水 百日咳疫苗 纸制鸡蛋托 面巾纸 商用飞机农药喷撒 液体燃料火箭 劳力士防水表 遥控电唱机 面包机 | AS70: 遥控电唱机 面包机 | AT70: 1927 | BH70: 乌兹别克斯坦 | BI70: 塔什干* | BJ70: 安集延州 | BK70: 布哈拉州 | BL70: 费尔干纳州 | BM70: 卡什卡达里亚州 | BN70: 卡拉卡尔帕克斯坦共和国 | BO70: 纳曼干州 | BP70: 纳沃伊州 | BQ70: 萨马尔罕州 | BR70: 苏尔汉河州 | BS70: 锡尔河州 | BT70: 花拉子模州 | BU70: 吉扎克州
D71: 弹药值 | E71: =SUM(人物卡!BS91:BT95) -> 0 | G71: 弹药数 | H71: =COUNTA(人物卡!BA91:BJ95) -> 0 | K71: 2 | L71: =IF(人物卡!BA86="",0,1) -> 0 | M71: =IF(L71=0,0,IF(人物卡!BK86="未取名！",1,0)) -> 0 | N71: =IF(L71=0,0,IF(人物卡!BS86="",1,0)) -> 0 | X71: 侦查 | AE71: 1928 | AF71: 咆哮的二十年代（美国） | AG71: 阿姆斯特丹奥运会 | AI71: 井冈山会师 | AL71: 二十世纪 二十年代 | AM71: 戊辰龙年 | AN71: 民国17年 | AO71: 电视实验 南佛罗里达州飓风，死亡1836 人 伯德探险队驶往南极 电传打字机投入使用 防水赛璐玢发明 盖革计数器 纯维生素C | AP71: 书籍： 阿道司·赫胥黎《针锋相对》 D·H·劳伦斯《查泰莱夫人的情人》被广泛禁止发行 桑顿·怀尔德《圣路易·莱之桥》荣获普利策奖 影视： 琼·克劳馥主演《我们跳舞的姑娘们》 查理·卓别林出演《马戏团》 维克多·麦克劳伦出演《港口女郎》 米老鼠在《威利号汽船》中登场 克拉拉·鲍出演《红发女郎》、《三个周末》、《那个舰队》 霍华德·休斯导演《两个阿拉伯骑士》 流行歌曲： 《I Can't Give You Anything But Love》 《You ' re the C ream in My Coffee》 《Makin' Whoopee》 《I Wanna Be Loved by You》贝蒂娃娃角色形象脱胎于此曲 百老汇舞台： 专栏作家本·赫克特创作《头版》，大受欢迎 马克斯兄弟主演《动物饼干》 梅·韦斯特登场《Diamond Lil》 伯特·拉尔《Hold Everything》 总统： 卡尔文·柯立芝（共和党） | AQ71: 彩色电影胶片 透明胶带 音乐汽车喇叭 闪光灯 速冻食品 球形潜水舱 回旋加速器 折叠式雨伞 电动剃须刀 车载收音机 玛氏巧克力棒 变焦镜头 大富翁桌游 商业洗衣店 畅销平装书 里氏震级 磁带录音机 大众汽车 超市推车 带温控器的电熨斗 速溶咖啡 尼龙 圆珠笔 黄热病疫苗 雷达 汽车自动变速箱 充气救生衣 人工授精 青霉素 军用吉普车 原子裂变 火箭筒 凝固汽油弹 水肺 麦角酸二乙酰胺 神经毒气 原子弹 特百惠 计算机 静电复印法 比基尼泳衣 浓缩咖啡机 宝丽来相机 拼字盘 实心电吉他 尼龙扣 晶体管 黑胶唱片 有线电视 电视显像管 汽车自动点火装置 信用卡 复印机 宽荧幕电影 动力转向器 三色停车灯 人行红绿灯 晶体管助听器 氢弹 录像带 DNA双螺旋结构 麻疹疫苗 按动圆珠笔 硅晶体管 核导弹 空对空导弹 迪士尼乐园 特氟龙 卡丁车 地对空核导弹 沙宾疫苗 通讯卫星 呼啦圈 安全带 人工肾脏 避孕药 气象卫星 便携晶体管收音机 安定 砷化镓半导体激光器 三维全息技术 合成器 香烟健康警示 凯夫拉纤维 子午胎 IBM文字处理机 杜比A型降噪器 滑雪板 喇叭裤 绕月载人火箭 人工心脏移植 波音747喷气式客机 互联网 条形码 软盘 帆板 热裤 液晶显示 便携电子计算器 电视游戏 DNA重组技术 电子游戏机 超级计算机 光纤 试管婴儿 魔方 索尼Walkman 杜比C型降噪器 艾滋病毒 强效可卡因 温室效应 CD 暗物质 暗能量 太阳能飞行器 甲型H1N1 流感 希格斯玻色子 引力波 | AR71: 电气地铁 圣代冰淇淋 实用水电站 手电 电影摄影机 收音机 霍乱疫苗 啤酒瓶盖 柴油发动机 双向电报 实用的胶卷 块麦片 电报 可口可乐 X射线 卷烟机发明 电影放映机 排球 印名片机 福特车 潜望镜 油印蜡纸发明 阴极射线管 商品阿司匹林 凯洛格牌玉米片 手电筒 钋 镭 摇控器 α粒子 β粒子 打字机 柯达布朗尼相机 齐柏林飞艇 人类血型 跨大西洋电报 汽轮机游船 现代柏油路 铝罐奶粉 爆米花 泰迪熊 卡鲁索电唱机 便宜的肥皂和烹饪用油 飞机 荧光灯 邮戳机 摩托车发动机 热水瓶 农业轨道机械 木棉安全带 电动汽车喇叭 化学泡沫灭火器 狭义相对论 自动点唱机 量产舰艇舷外发动机 动画 电动洗衣机 家用洗洁精 立式吸尘器 饮用纸杯 双层公交车 无线电测向仪 电煎锅 质子和电子 玻璃纸 战壕风衣 汽车自动起动器 麦片 氯气毒气 防毒面具 拉链 机械雨刮器 广义相对论 芥子气 量产拖拉机 电子钟 黄油枪 降落伞 广播电台播音 茶包 罗夏墨迹测验 机器人 胰岛素 实用邮戳机 滑水 百日咳疫苗 纸制鸡蛋托 面巾纸 商用飞机农药喷撒 液体燃料火箭 劳力士防水表 遥控电唱机 面包机 防水玻璃纸 电传打字机 盖革计数器 纯维生素C | AS71: 防水玻璃纸 电传打字机 盖革计数器 纯维生素C | AT71: 1928 | BH71: 土库曼斯坦 | BI71: 阿什哈巴德* | BJ71: 阿哈尔州 | BK71: 巴尔坎州 | BL71: 达绍古兹州 | BM71: 列巴普州 | BN71: 马雷州 | BO71: 马纳特州
K72: 3 | L72: =IF(人物卡!BA87="",0,1) -> 0 | M72: =IF(L72=0,0,IF(人物卡!BK87="未取名！",1,0)) -> 0 | N72: =IF(L72=0,0,IF(人物卡!BS87="",1,0)) -> 0 | X72: 追踪 | AA72: =人物卡!BE25&人物卡!BQ25 -> 会计5 | AC72: =人物卡!CA25&人物卡!CM25 -> 锁匠1 | AE72: 1929 | AF72: 咆哮的二十年代（美国） | AG72: 经济大危机 | AI72: —— | AL72: 二十世纪 二十年代 | AM72: 己巳蛇年 | AN72: 民国18年 | AO72: 10 月24 日华尔街股灾 齐柏林伯爵号飞艇环游世界 苏联客轮伏尔加号在黑海被一战残余水雷击中，死亡31 人 16 毫米彩色电影胶片发明 透明胶带 音乐汽车喇叭 | AP72: 书籍： 赫尔曼·黑塞《荒原狼》英译版发行 辛克莱·刘易斯《道兹沃斯》 海明威《永别了，武器》 托马斯·沃尔夫《天使望故乡》 埃里希·玛利亚·雷马克《西线无战事》回忆圣诞停火 威廉·福克纳《喧哗与骚动》 达希尔·哈米特《丹恩家的诅咒》 罗伯特·雷普利《信不信由你！》 影视： 加里·库珀主演《维吉尼亚人》 葛丽泰·嘉宝出演《野兰花》 马克斯兄弟出演《可可豆》 罗纳德·考尔曼出演《名媛双胞案》 道格拉斯·范朋克出演《铁面人》 莱昂纳尔·巴里摩尔出演《神秘岛》 阿尔弗雷德·希区柯克导演《讹诈》 路易斯·布努埃尔《一条安达鲁狗》 流行歌曲： 《Pu t tin ' On th e Ri t z》 《Ain ' t Misbehavin'》 《Star Dust》 《雨中曲》(Singin' in the Rain) 《Wi th a Song in My Heart》 《Wedding Bells Are Breaking Up That Old Gang of Mine》 百老汇舞台： 诺 埃 尔· 科 沃 德 创 作 音 乐 剧《Bittersweet》 碧莉·伯克在《Happy Husbands》中登场 总统： 卡尔文·柯立芝（共和党） 赫伯特·胡佛（共和党） | AQ72: 闪光灯 速冻食品 球形潜水舱 回旋加速器 折叠式雨伞 电动剃须刀 车载收音机 玛氏巧克力棒 变焦镜头 大富翁桌游 商业洗衣店 畅销平装书 里氏震级 磁带录音机 大众汽车 超市推车 带温控器的电熨斗 速溶咖啡 尼龙 圆珠笔 黄热病疫苗 雷达 汽车自动变速箱 充气救生衣 人工授精 青霉素 军用吉普车 原子裂变 火箭筒 凝固汽油弹 水肺 麦角酸二乙酰胺 神经毒气 原子弹 特百惠 计算机 静电复印法 比基尼泳衣 浓缩咖啡机 宝丽来相机 拼字盘 实心电吉他 尼龙扣 晶体管 黑胶唱片 有线电视 电视显像管 汽车自动点火装置 信用卡 复印机 宽荧幕电影 动力转向器 三色停车灯 人行红绿灯 晶体管助听器 氢弹 录像带 DNA双螺旋结构 麻疹疫苗 按动圆珠笔 硅晶体管 核导弹 空对空导弹 迪士尼乐园 特氟龙 卡丁车 地对空核导弹 沙宾疫苗 通讯卫星 呼啦圈 安全带 人工肾脏 避孕药 气象卫星 便携晶体管收音机 安定 砷化镓半导体激光器 三维全息技术 合成器 香烟健康警示 凯夫拉纤维 子午胎 IBM文字处理机 杜比A型降噪器 滑雪板 喇叭裤 绕月载人火箭 人工心脏移植 波音747喷气式客机 互联网 条形码 软盘 帆板 热裤 液晶显示 便携电子计算器 电视游戏 DNA重组技术 电子游戏机 超级计算机 光纤 试管婴儿 魔方 索尼Walkman 杜比C型降噪器 艾滋病毒 强效可卡因 温室效应 CD 暗物质 暗能量 太阳能飞行器 甲型H1N1 流感 希格斯玻色子 引力波 | AR72: 电气地铁 圣代冰淇淋 实用水电站 手电 电影摄影机 收音机 霍乱疫苗 啤酒瓶盖 柴油发动机 双向电报 实用的胶卷 块麦片 电报 可口可乐 X射线 卷烟机发明 电影放映机 排球 印名片机 福特车 潜望镜 油印蜡纸发明 阴极射线管 商品阿司匹林 凯洛格牌玉米片 手电筒 钋 镭 摇控器 α粒子 β粒子 打字机 柯达布朗尼相机 齐柏林飞艇 人类血型 跨大西洋电报 汽轮机游船 现代柏油路 铝罐奶粉 爆米花 泰迪熊 卡鲁索电唱机 便宜的肥皂和烹饪用油 飞机 荧光灯 邮戳机 摩托车发动机 热水瓶 农业轨道机械 木棉安全带 电动汽车喇叭 化学泡沫灭火器 狭义相对论 自动点唱机 量产舰艇舷外发动机 动画 电动洗衣机 家用洗洁精 立式吸尘器 饮用纸杯 双层公交车 无线电测向仪 电煎锅 质子和电子 玻璃纸 战壕风衣 汽车自动起动器 麦片 氯气毒气 防毒面具 拉链 机械雨刮器 广义相对论 芥子气 量产拖拉机 电子钟 黄油枪 降落伞 广播电台播音 茶包 罗夏墨迹测验 机器人 胰岛素 实用邮戳机 滑水 百日咳疫苗 纸制鸡蛋托 面巾纸 商用飞机农药喷撒 液体燃料火箭 劳力士防水表 遥控电唱机 面包机 防水玻璃纸 电传打字机 盖革计数器 纯维生素C 彩色电影胶片 透明胶带 音乐汽车喇叭 | AS72: 彩色电影胶片 透明胶带 音乐汽车喇叭 | AT72: 1929
D73: 总值 | E73: =SUM(E69:E71) -> 0 | G73: 总数 | H73: =SUM(H69:H71) -> 5 | K73: 4 | L73: =IF(人物卡!BA88="",0,1) -> 0 | M73: =IF(L73=0,0,IF(人物卡!BK88="未取名！",1,0)) -> 0 | N73: =IF(L73=0,0,IF(人物卡!BS88="",1,0)) -> 0 | X73: 导航 | AA73: =人物卡!BE26&人物卡!BQ26 -> 法律5 | AC73: =人物卡!CA26&人物卡!CM26 -> 乔装5 | AE73: 1930 | AF73: —— | AI73: —— | AL73: 二十世纪 三十年代 | AM73: 庚午牛年 | AN73: 民国19年 | AO73: 技术官僚运动达到高潮 闪光灯取代镁粉 速冻食品上市 球形潜水舱 回旋加速器 发现冥王星 折叠式雨伞 美国公债161.8亿美元 美国人口1.228 亿 | AP73: 影视： 葛丽泰·嘉宝出演威利斯·奥布莱恩导演的《安娜·克莉丝蒂》 马克斯兄弟出演《疯狂的动物》 约瑟夫·冯·斯登堡导演、玛琳·黛德丽出演《蓝天使》 霍华德·休斯制作《地狱天使》 沃尔特·休斯顿出演《林肯传》 约翰·巴里摩尔在《白鲸记》当中饰演亚哈船长 朗 · 钱尼重拍自自己早先的经典默片《三个邪恶的人》 约翰·巴里摩尔《白鲸记》 流行歌曲： 《I Got Rhythm》 《Embraceable You》 《On the Sunny Side of the Street》 百老汇舞台： 艾索尔·摩曼主演戈什温的《疯狂女郎》 范妮·布莱斯出演《Sweet and Low》 总统： 赫伯特·胡佛（共和党） | AQ73: 电动剃须刀 车载收音机 玛氏巧克力棒 变焦镜头 大富翁桌游 商业洗衣店 畅销平装书 里氏震级 磁带录音机 大众汽车 超市推车 带温控器的电熨斗 速溶咖啡 尼龙 圆珠笔 黄热病疫苗 雷达 汽车自动变速箱 充气救生衣 人工授精 青霉素 军用吉普车 原子裂变 火箭筒 凝固汽油弹 水肺 麦角酸二乙酰胺 神经毒气 原子弹 特百惠 计算机 静电复印法 比基尼泳衣 浓缩咖啡机 宝丽来相机 拼字盘 实心电吉他 尼龙扣 晶体管 黑胶唱片 有线电视 电视显像管 汽车自动点火装置 信用卡 复印机 宽荧幕电影 动力转向器 三色停车灯 人行红绿灯 晶体管助听器 氢弹 录像带 DNA双螺旋结构 麻疹疫苗 按动圆珠笔 硅晶体管 核导弹 空对空导弹 迪士尼乐园 特氟龙 卡丁车 地对空核导弹 沙宾疫苗 通讯卫星 呼啦圈 安全带 人工肾脏 避孕药 气象卫星 便携晶体管收音机 安定 砷化镓半导体激光器 三维全息技术 合成器 香烟健康警示 凯夫拉纤维 子午胎 IBM文字处理机 杜比A型降噪器 滑雪板 喇叭裤 绕月载人火箭 人工心脏移植 波音747喷气式客机 互联网 条形码 软盘 帆板 热裤 液晶显示 便携电子计算器 电视游戏 DNA重组技术 电子游戏机 超级计算机 光纤 试管婴儿 魔方 索尼Walkman 杜比C型降噪器 艾滋病毒 强效可卡因 温室效应 CD 暗物质 暗能量 太阳能飞行器 甲型H1N1 流感 希格斯玻色子 引力波 | AR73: 电气地铁 圣代冰淇淋 实用水电站 手电 电影摄影机 收音机 霍乱疫苗 啤酒瓶盖 柴油发动机 双向电报 实用的胶卷 块麦片 电报 可口可乐 X射线 卷烟机发明 电影放映机 排球 印名片机 福特车 潜望镜 油印蜡纸发明 阴极射线管 商品阿司匹林 凯洛格牌玉米片 手电筒 钋 镭 摇控器 α粒子 β粒子 打字机 柯达布朗尼相机 齐柏林飞艇 人类血型 跨大西洋电报 汽轮机游船 现代柏油路 铝罐奶粉 爆米花 泰迪熊 卡鲁索电唱机 便宜的肥皂和烹饪用油 飞机 荧光灯 邮戳机 摩托车发动机 热水瓶 农业轨道机械 木棉安全带 电动汽车喇叭 化学泡沫灭火器 狭义相对论 自动点唱机 量产舰艇舷外发动机 动画 电动洗衣机 家用洗洁精 立式吸尘器 饮用纸杯 双层公交车 无线电测向仪 电煎锅 质子和电子 玻璃纸 战壕风衣 汽车自动起动器 麦片 氯气毒气 防毒面具 拉链 机械雨刮器 广义相对论 芥子气 量产拖拉机 电子钟 黄油枪 降落伞 广播电台播音 茶包 罗夏墨迹测验 机器人 胰岛素 实用邮戳机 滑水 百日咳疫苗 纸制鸡蛋托 面巾纸 商用飞机农药喷撒 液体燃料火箭 劳力士防水表 遥控电唱机 面包机 防水玻璃纸 电传打字机 盖革计数器 纯维生素C 彩色电影胶片 透明胶带 音乐汽车喇叭 闪光灯 速冻食品 球形潜水舱 回旋加速器 折叠式雨伞 | AS73: 闪光灯 速冻食品 球形潜水舱 回旋加速器 折叠式雨伞 | AT73: 1930 | BH73: ——欧洲——
K74: 5 | L74: =IF(人物卡!BA89="",0,1) -> 0 | M74: =IF(L74=0,0,IF(人物卡!BK89="未取名！",1,0)) -> 0 | N74: =IF(L74=0,0,IF(人物卡!BS89="",1,0)) -> 0 | X74: 心理学 | AA74: =人物卡!BE27&人物卡!BQ27 -> 历史5 | AC74: =人物卡!CA27&人物卡!CM27 -> 妙手10 | AE74: 1931 | AF74: —— | AI74: 九一八事变 | AJ74: 富蕴地震 | AL74: 二十世纪 三十年代 | AM74: 辛未羊年 | AN74: 民国20年 | AO74: 德国富豪赞助纳粹建设 英国海军因弗戈登兵变 帝国大厦正式开放 阿尔·卡彭入狱 电动剃须刀 乔治·华盛顿大桥（3500英尺) 竣工 | AP74: 影视： 路易斯·布努埃尔《黄金年代》 约翰·巴里摩尔《斯文加利》 威尔 · 罗杰斯《康涅狄格的美国佬》 总统： 赫伯特·胡佛（共和党） | AQ74: 车载收音机 玛氏巧克力棒 变焦镜头 大富翁桌游 商业洗衣店 畅销平装书 里氏震级 磁带录音机 大众汽车 超市推车 带温控器的电熨斗 速溶咖啡 尼龙 圆珠笔 黄热病疫苗 雷达 汽车自动变速箱 充气救生衣 人工授精 青霉素 军用吉普车 原子裂变 火箭筒 凝固汽油弹 水肺 麦角酸二乙酰胺 神经毒气 原子弹 特百惠 计算机 静电复印法 比基尼泳衣 浓缩咖啡机 宝丽来相机 拼字盘 实心电吉他 尼龙扣 晶体管 黑胶唱片 有线电视 电视显像管 汽车自动点火装置 信用卡 复印机 宽荧幕电影 动力转向器 三色停车灯 人行红绿灯 晶体管助听器 氢弹 录像带 DNA双螺旋结构 麻疹疫苗 按动圆珠笔 硅晶体管 核导弹 空对空导弹 迪士尼乐园 特氟龙 卡丁车 地对空核导弹 沙宾疫苗 通讯卫星 呼啦圈 安全带 人工肾脏 避孕药 气象卫星 便携晶体管收音机 安定 砷化镓半导体激光器 三维全息技术 合成器 香烟健康警示 凯夫拉纤维 子午胎 IBM文字处理机 杜比A型降噪器 滑雪板 喇叭裤 绕月载人火箭 人工心脏移植 波音747喷气式客机 互联网 条形码 软盘 帆板 热裤 液晶显示 便携电子计算器 电视游戏 DNA重组技术 电子游戏机 超级计算机 光纤 试管婴儿 魔方 索尼Walkman 杜比C型降噪器 艾滋病毒 强效可卡因 温室效应 CD 暗物质 暗能量 太阳能飞行器 甲型H1N1 流感 希格斯玻色子 引力波 | AR74: 电气地铁 圣代冰淇淋 实用水电站 手电 电影摄影机 收音机 霍乱疫苗 啤酒瓶盖 柴油发动机 双向电报 实用的胶卷 块麦片 电报 可口可乐 X射线 卷烟机发明 电影放映机 排球 印名片机 福特车 潜望镜 油印蜡纸发明 阴极射线管 商品阿司匹林 凯洛格牌玉米片 手电筒 钋 镭 摇控器 α粒子 β粒子 打字机 柯达布朗尼相机 齐柏林飞艇 人类血型 跨大西洋电报 汽轮机游船 现代柏油路 铝罐奶粉 爆米花 泰迪熊 卡鲁索电唱机 便宜的肥皂和烹饪用油 飞机 荧光灯 邮戳机 摩托车发动机 热水瓶 农业轨道机械 木棉安全带 电动汽车喇叭 化学泡沫灭火器 狭义相对论 自动点唱机 量产舰艇舷外发动机 动画 电动洗衣机 家用洗洁精 立式吸尘器 饮用纸杯 双层公交车 无线电测向仪 电煎锅 质子和电子 玻璃纸 战壕风衣 汽车自动起动器 麦片 氯气毒气 防毒面具 拉链 机械雨刮器 广义相对论 芥子气 量产拖拉机 电子钟 黄油枪 降落伞 广播电台播音 茶包 罗夏墨迹测验 机器人 胰岛素 实用邮戳机 滑水 百日咳疫苗 纸制鸡蛋托 面巾纸 商用飞机农药喷撒 液体燃料火箭 劳力士防水表 遥控电唱机 面包机 防水玻璃纸 电传打字机 盖革计数器 纯维生素C 彩色电影胶片 透明胶带 音乐汽车喇叭 闪光灯 速冻食品 球形潜水舱 回旋加速器 折叠式雨伞 电动剃须刀 | AS74: 电动剃须刀 | AT74: 1931 | BH74: *北欧*
D75: =IF(G67>0,"本次任务携带"&G67&J67,"零钱不足！请合理分配！") -> 本次任务携带0.6美元 | L75: 携带 | M75: 名 | N75: 值 | X75: 取悦 | AA75: =人物卡!BE28&人物卡!BQ28 -> 人类学1 | AC75: =人物卡!CA28&人物卡!CM28 -> 潜行20 | AE75: 1932 | AF75: 洛杉矶奥运会 | AG75: 伪满洲国成立 | AI75: 上海事变 | AL75: 二十世纪 三十年代 | AM75: 壬申猴年 | AN75: 民国21年 | AO75: 甘地被捕 英国潜艇[7] 在英吉利海峡沉没 罗斯福以压倒优势获得总统竞选 墨索里尼抽干彭甸沼泽 林德伯格绑架案 首个车载收音机 首个盖洛普民意调查 玛氏巧克力棒 变焦镜头发明 Zippo 打火机引进 | AP75: 总统： 赫伯特·胡佛（共和党） | AQ75: 大富翁桌游 商业洗衣店 畅销平装书 里氏震级 磁带录音机 大众汽车 超市推车 带温控器的电熨斗 速溶咖啡 尼龙 圆珠笔 黄热病疫苗 雷达 汽车自动变速箱 充气救生衣 人工授精 青霉素 军用吉普车 原子裂变 火箭筒 凝固汽油弹 水肺 麦角酸二乙酰胺 神经毒气 原子弹 特百惠 计算机 静电复印法 比基尼泳衣 浓缩咖啡机 宝丽来相机 拼字盘 实心电吉他 尼龙扣 晶体管 黑胶唱片 有线电视 电视显像管 汽车自动点火装置 信用卡 复印机 宽荧幕电影 动力转向器 三色停车灯 人行红绿灯 晶体管助听器 氢弹 录像带 DNA双螺旋结构 麻疹疫苗 按动圆珠笔 硅晶体管 核导弹 空对空导弹 迪士尼乐园 特氟龙 卡丁车 地对空核导弹 沙宾疫苗 通讯卫星 呼啦圈 安全带 人工肾脏 避孕药 气象卫星 便携晶体管收音机 安定 砷化镓半导体激光器 三维全息技术 合成器 香烟健康警示 凯夫拉纤维 子午胎 IBM文字处理机 杜比A型降噪器 滑雪板 喇叭裤 绕月载人火箭 人工心脏移植 波音747喷气式客机 互联网 条形码 软盘 帆板 热裤 液晶显示 便携电子计算器 电视游戏 DNA重组技术 电子游戏机 超级计算机 光纤 试管婴儿 魔方 索尼Walkman 杜比C型降噪器 艾滋病毒 强效可卡因 温室效应 CD 暗物质 暗能量 太阳能飞行器 甲型H1N1 流感 希格斯玻色子 引力波 | AR75: 电气地铁 圣代冰淇淋 实用水电站 手电 电影摄影机 收音机 霍乱疫苗 啤酒瓶盖 柴油发动机 双向电报 实用的胶卷 块麦片 电报 可口可乐 X射线 卷烟机发明 电影放映机 排球 印名片机 福特车 潜望镜 油印蜡纸发明 阴极射线管 商品阿司匹林 凯洛格牌玉米片 手电筒 钋 镭 摇控器 α粒子 β粒子 打字机 柯达布朗尼相机 齐柏林飞艇 人类血型 跨大西洋电报 汽轮机游船 现代柏油路 铝罐奶粉 爆米花 泰迪熊 卡鲁索电唱机 便宜的肥皂和烹饪用油 飞机 荧光灯 邮戳机 摩托车发动机 热水瓶 农业轨道机械 木棉安全带 电动汽车喇叭 化学泡沫灭火器 狭义相对论 自动点唱机 量产舰艇舷外发动机 动画 电动洗衣机 家用洗洁精 立式吸尘器 饮用纸杯 双层公交车 无线电测向仪 电煎锅 质子和电子 玻璃纸 战壕风衣 汽车自动起动器 麦片 氯气毒气 防毒面具 拉链 机械雨刮器 广义相对论 芥子气 量产拖拉机 电子钟 黄油枪 降落伞 广播电台播音 茶包 罗夏墨迹测验 机器人 胰岛素 实用邮戳机 滑水 百日咳疫苗 纸制鸡蛋托 面巾纸 商用飞机农药喷撒 液体燃料火箭 劳力士防水表 遥控电唱机 面包机 防水玻璃纸 电传打字机 盖革计数器 纯维生素C 彩色电影胶片 透明胶带 音乐汽车喇叭 闪光灯 速冻食品 球形潜水舱 回旋加速器 折叠式雨伞 电动剃须刀 车载收音机 玛氏巧克力棒 变焦镜头 | AS75: 车载收音机 玛氏巧克力棒 变焦镜头 | AT75: 1932 | BH75: 芬兰 | BI75: 赫尔辛基* | BJ75: 奥卢省 | BK75: 拉普兰省 | BL75: 北博滕省 | BM75: 南博滕省 | BN75: 东芬兰省 | BO75: 西芬兰省 | BP75: 西南芬兰省 | BQ75: 凯努省 | BR75: 中央芬兰省 | BS75: 奥卢市
